{
    "orig": {
        "aktenzeichen": "HRB 8687",
        "amtsgericht": "Kleve",
        "event_date": "2014-05-02",
        "event_type": "Veränderungen",
        "federal_state": "nw",
        "full_text": "Amtsgericht Kleve Aktenzeichen: HRB 8687 \nBekannt gemacht am: 02.05.2014 20:00 Uhr\n\n\n\n\nIn () gesetzte Angaben der Anschrift und des Geschäftszweiges erfolgen ohne Gewähr.\nVeränderungen\n02.05.2014\n\nHRB 8687:Protex GmbH, Emmerich am Rhein, Stadtweide 17, 46446 Emmerich am Rhein.Nicht mehr Geschäftsführer: Bolster, Bernardus Johannes, Druten/Niederlande, *08.08.1965. Bestellt als Geschäftsführer: Koeze, Benjamin, Zutphen / Niederlande, *09.03.1954, einzelvertretungsberechtigt mit der Befugnis im Namen der Gesellschaft mit sich im eigenen Namen oder als Vertreter eines Dritten Rechtsgeschäfte abzuschließen.",
        "gesellschafter": null,
        "inhaber": null,
        "name": "HRB 8687:Protex GmbH",
        "notice_id": "1031920",
        "posted_on": "2014-05-02",
        "rechtsform": null,
        "sitz": null,
        "url": "https://www.handelsregisterbekanntmachungen.de/en/skripte/hrb.php?rb_id=1031920&land_abk=nw"
    },
    "parsed": {
        "officers": [
            {
                "class": "DismissedManagingDirector",
                "payload": {
                    "city": "Druten/Niederlande",
                    "dismissed": true,
                    "dob": "1965-08-08",
                    "lastname": "Bolster",
                    "name": "Bernardus Johannes"
                },
                "text": " Bolster, Bernardus Johannes, Druten/Niederlande, *08.08.1965."
            },
            {
                "class": "AppointedManagingDirector",
                "payload": {
                    "city": "Zutphen / Niederlande",
                    "dob": "1954-03-09",
                    "flag": "einzelvertretungsberechtigt mit der Befugnis im Namen der Gesellschaft mit sich im eigenen Namen oder als Vertreter eines Dritten Rechtsgeschäfte abzuschließen",
                    "lastname": "Koeze",
                    "name": "Benjamin"
                },
                "text": " Koeze, Benjamin, Zutphen / Niederlande, *09.03.1954, einzelvertretungsberechtigt mit der Befugnis im Namen der Gesellschaft mit sich im eigenen Namen oder als Vertreter eines Dritten Rechtsgeschäfte abzuschließen."
            }
        ]
    }
}