{
    "orig": {
        "aktenzeichen": "HRB 86599",
        "amtsgericht": "München",
        "event_date": "2017-03-13",
        "event_type": "Veränderungen",
        "federal_state": "by",
        "full_text": "Amtsgericht München Aktenzeichen: HRB 86599 \nBekannt gemacht am: 14.03.2017 02:06 Uhr\n\n\n\n\nIn ( ) gesetzte Angaben der Anschrift und des Geschäftszweiges erfolgen ohne Gewähr:\nVeränderungen\n13.03.2017\n\nHRB 86599: NOBLE HOUSE DECOR + DESIGN Handelsgesellschaft mbH, München, Barerstr. 71, 80799 München. Die Gesellschaft wird durch den/die Liquidator/en vertreten. Geändert, nun: Liquidator: Koschella, Edeltraud Lucie, Designerin, München. Durch rechtskräftigen Beschluss des Amtsgerichts München (Az. 1509 IN 2350, 1509 IN 2848/16) vom 06.02.2017 ist die Eröffnung des Insolvenzverfahrens über das Vermögen der Gesellschaft mangels Masse abgelehnt. Die Gesellschaft ist aufgelöst. Von Amts wegen eingetragen nach § 65 GmbHG.",
        "gesellschafter": null,
        "inhaber": null,
        "name": "HRB 86599: NOBLE HOUSE DECOR + DESIGN Handelsgesellschaft mbH",
        "notice_id": "1056278",
        "posted_on": "2017-03-14",
        "rechtsform": null,
        "sitz": null,
        "url": "https://www.handelsregisterbekanntmachungen.de/en/skripte/hrb.php?rb_id=1056278&land_abk=by"
    },
    "parsed": {
        "flags": [
            {
                "flag": "CompanyClosed",
                "text": "Die\\ Gesellschaft\\ ist\\ aufgel\\öst\\."
            }
        ],
        "officers": [
            {
                "class": "Liquidator",
                "payload": {
                    "city": "München",
                    "lastname": ": Koschella",
                    "name": "Edeltraud Lucie",
                    "position": "Designerin"
                },
                "text": ": Koschella, Edeltraud Lucie, Designerin, München."
            }
        ]
    }
}