{
    "orig": {
        "aktenzeichen": "HRB 61822",
        "amtsgericht": "Köln",
        "event_date": "2015-06-11",
        "event_type": "Veränderungen",
        "federal_state": "nw",
        "full_text": "Amtsgericht Köln Aktenzeichen: HRB 61822 \nBekannt gemacht am: 11.06.2015 20:02 Uhr\n\n\n\n\nIn () gesetzte Angaben der Anschrift und des Geschäftszweiges erfolgen ohne Gewähr.\nVeränderungen\n11.06.2015\n\nHRB 61822: Erste Madaus Beteiligungsgesellschaft mbH, Köln, Colonia Allee 15, 51067 Köln. Nicht mehr Geschäftsführer: Dr. Rovati, Luca, Köln, *22.08.1961. Bestellt als Geschäftsführer: Faghfouri, Esfandiar, Buseck, *19.03.1962; Weiß, Rainer, Linden, *27.11.1962; Österlund, Marten, Älvsjö / Schweden, *10.12.1957, jeweils mit der Befugnis im Namen der Gesellschaft mit sich im eigenen Namen oder als Vertreter eines Dritten Rechtsgeschäfte abzuschließen.",
        "gesellschafter": null,
        "inhaber": null,
        "name": "HRB 61822: Erste Madaus Beteiligungsgesellschaft mbH",
        "notice_id": "1166613",
        "posted_on": "2015-06-11",
        "rechtsform": null,
        "sitz": null,
        "url": "https://www.handelsregisterbekanntmachungen.de/en/skripte/hrb.php?rb_id=1166613&land_abk=nw"
    },
    "parsed": {
        "officers": [
            {
                "class": "DismissedManagingDirector",
                "payload": {
                    "city": "Köln",
                    "dismissed": true,
                    "dob": "1961-08-22",
                    "lastname": "Rovati",
                    "name": "Luca",
                    "prof_title": "doctor"
                },
                "text": " Doctor Rovati, Luca, Köln, *22.08.1961."
            },
            {
                "class": "AppointedManagingDirector",
                "payload": {
                    "city": "Buseck",
                    "dob": "1962-03-19",
                    "lastname": "Faghfouri",
                    "name": "Esfandiar"
                },
                "text": " Faghfouri, Esfandiar, Buseck, *19.03.1962"
            },
            {
                "class": "AppointedManagingDirector",
                "payload": {
                    "city": "Linden",
                    "dob": "1962-11-27",
                    "lastname": "Weiß",
                    "name": "Rainer"
                },
                "text": " Weiß, Rainer, Linden, *27.11.1962"
            },
            {
                "class": "AppointedManagingDirector",
                "payload": {
                    "city": "Älvsjö / Schweden",
                    "dob": "1957-12-10",
                    "flag": "jeweils mit der Befugnis im Namen der Gesellschaft mit sich im eigenen Namen oder als Vertreter eines Dritten Rechtsgeschäfte abzuschließen",
                    "lastname": "Österlund",
                    "name": "Marten"
                },
                "text": " Österlund, Marten, Älvsjö / Schweden, *10.12.1957, jeweils mit der Befugnis im Namen der Gesellschaft mit sich im eigenen Namen oder als Vertreter eines Dritten Rechtsgeschäfte abzuschließen."
            }
        ]
    }
}