{
    "orig": {
        "aktenzeichen": "HRB 77733",
        "amtsgericht": "Düsseldorf",
        "event_date": "2016-12-27",
        "event_type": "Veränderungen",
        "federal_state": "nw",
        "full_text": "Amtsgericht Düsseldorf Aktenzeichen: HRB 77733 \nBekannt gemacht am: 27.12.2016 20:03 Uhr\n\n\n\n\nIn () gesetzte Angaben der Anschrift und des Geschäftszweiges erfolgen ohne Gewähr.\nVeränderungen\n27.12.2016\n\nHRB 77733: Diamant 152. (Einhundertzweiundfünfzigste) GmbH, Düsseldorf, c/o VRB Vorratsgesellschaften GmbH, Friedrichstraße 133, 10117 Berlin. Die Gesellschafterversammlung vom 19.12.2016 hat den Gesellschaftsvertrag insgesamt neu gefasst und dabei insbesondere die Firma, den Sitz -redaktionell-, die Dauer der Gesellschaft, Geschäftsjahr -redaktionell-, den Gegenstand, das Stammkapital -redaktionell- und die allgemeine Vertretungsregelung -redaktionell- geändert. Neue Firma: PCC Germany Holdings GmbH. Änderung zur Geschäftsanschrift: c/o Noerr LLP, Speditionstr. 1, 40221 Düsseldorf. Neuer Unternehmensgegenstand: Das Halten von Beteiligungen an einer Gesellschaft oder mehreren anderen Gesellschaften, insbesondere an Gesellschaften mit beschränkter Haftung. Nicht mehr Geschäftsführer: Vieth, Julia, Berlin, *01.10.1969. Bestellt als Geschäftsführer: Beyer, Ruth, Lake Oswego / Oregon / Vereinigte Staaten, *25.09.1955, einzelvertretungsberechtigt mit der Befugnis im Namen der Gesellschaft mit sich im eigenen Namen oder als Vertreter eines Dritten Rechtsgeschäfte abzuschließen.",
        "gesellschafter": null,
        "inhaber": null,
        "name": "HRB 77733: Diamant 152. (Einhundertzweiundfünfzigste) GmbH",
        "notice_id": "1359724",
        "posted_on": "2016-12-27",
        "rechtsform": null,
        "sitz": null,
        "url": "https://www.handelsregisterbekanntmachungen.de/en/skripte/hrb.php?rb_id=1359724&land_abk=nw"
    },
    "parsed": {
        "labels": [
            {
                "label": "address",
                "text": " c/o Noerr LLP, Speditionstr."
            }
        ],
        "officers": [
            {
                "class": "DismissedManagingDirector",
                "payload": {
                    "city": "Berlin",
                    "dismissed": true,
                    "dob": "1969-01-10",
                    "lastname": "Vieth",
                    "name": "Julia"
                },
                "text": " Vieth, Julia, Berlin, *01.10.1969."
            },
            {
                "class": "AppointedManagingDirector",
                "payload": {
                    "city": "Lake Oswego / Oregon / Vereinigte Staaten",
                    "dob": "1955-09-25",
                    "flag": "einzelvertretungsberechtigt mit der Befugnis im Namen der Gesellschaft mit sich im eigenen Namen oder als Vertreter eines Dritten Rechtsgeschäfte abzuschließen",
                    "lastname": "Beyer",
                    "name": "Ruth"
                },
                "text": " Beyer, Ruth, Lake Oswego / Oregon / Vereinigte Staaten, *25.09.1955, einzelvertretungsberechtigt mit der Befugnis im Namen der Gesellschaft mit sich im eigenen Namen oder als Vertreter eines Dritten Rechtsgeschäfte abzuschließen."
            }
        ]
    }
}