{
    "orig": {
        "aktenzeichen": "HRB 8272",
        "amtsgericht": "Coesfeld",
        "event_date": "2017-06-12",
        "event_type": "Veränderungen",
        "federal_state": "nw",
        "full_text": "Amtsgericht Coesfeld Aktenzeichen: HRB 8272 \nBekannt gemacht am: 12.06.2017 20:02 Uhr\n\n\n\n\nIn () gesetzte Angaben der Anschrift und des Geschäftszweiges erfolgen ohne Gewähr.\nVeränderungen\n12.06.2017\n\nHRB 8272: Auto Krabbe GmbH, Bocholt, Münsterstraße 145 - 149, 46397 Bocholt. Die Gesellschafterversammlung hat am 29.05.2017 eine vollständige Neufassung des Gesellschaftsvertrages beschlossen und insbesondere, das Stammkapital (DEM 300.000) auf Euro umzustellen, es von dann EUR 153.387,57 um EUR 612,43 auf EUR 154.000 zu erhöhen und den Gesellschaftsvertrag in § 3 zu ändern. Neues Stammkapital: 154.000,00 EUR. Vertretungsbefugnis erweiter bzgl. Geschäftsführer: Krabbe, Hans-Hardy, Bocholt, *10.11.1975, einzelvertretungsberechtigt mit der Befugnis im Namen der Gesellschaft mit sich im eigenen Namen oder als Vertreter eines Dritten Rechtsgeschäfte abzuschließen. Nicht mehr Geschäftsführer: Krabbe, Hans, Bocholt, *24.09.1939. Vertretungsregelung erweitert bzgl. Geschäftsführer: Krabbe, Daniela, Bocholt, *13.04.1972, einzelvertretungsberechtigt mit der Befugnis im Namen der Gesellschaft mit sich im eigenen Namen oder als Vertreter eines Dritten Rechtsgeschäfte abzuschließen.",
        "gesellschafter": null,
        "inhaber": null,
        "name": "HRB 8272: Auto Krabbe GmbH",
        "notice_id": "1418965",
        "posted_on": "2017-06-12",
        "rechtsform": null,
        "sitz": null,
        "url": "https://www.handelsregisterbekanntmachungen.de/en/skripte/hrb.php?rb_id=1418965&land_abk=nw"
    },
    "parsed": {
        "officers": [
            {
                "class": "ManagingDirector",
                "payload": {
                    "city": "Bocholt",
                    "dob": "1975-10-11",
                    "flag": "einzelvertretungsberechtigt mit der Befugnis im Namen der Gesellschaft mit sich im eigenen Namen oder als Vertreter eines Dritten Rechtsgeschäfte abzuschließen",
                    "lastname": "Krabbe",
                    "name": "Hans-Hardy"
                },
                "text": " Krabbe, Hans-Hardy, Bocholt, *10.11.1975, einzelvertretungsberechtigt mit der Befugnis im Namen der Gesellschaft mit sich im eigenen Namen oder als Vertreter eines Dritten Rechtsgeschäfte abzuschließen."
            },
            {
                "class": "DismissedManagingDirector",
                "payload": {
                    "city": "Bocholt",
                    "dismissed": true,
                    "dob": "1939-09-24",
                    "lastname": "Krabbe",
                    "name": "Hans"
                },
                "text": " Krabbe, Hans, Bocholt, *24.09.1939."
            },
            {
                "class": "ManagingDirector",
                "payload": {
                    "city": "Bocholt",
                    "dob": "1972-04-13",
                    "flag": "einzelvertretungsberechtigt mit der Befugnis im Namen der Gesellschaft mit sich im eigenen Namen oder als Vertreter eines Dritten Rechtsgeschäfte abzuschließen",
                    "lastname": "Krabbe",
                    "name": "Daniela"
                },
                "text": " Krabbe, Daniela, Bocholt, *13.04.1972, einzelvertretungsberechtigt mit der Befugnis im Namen der Gesellschaft mit sich im eigenen Namen oder als Vertreter eines Dritten Rechtsgeschäfte abzuschließen."
            }
        ]
    }
}