{
    "orig": {
        "aktenzeichen": "HRB 3676",
        "amtsgericht": "Recklinghausen",
        "event_date": "2006-07-07",
        "event_type": "Veränderungen",
        "federal_state": "nw",
        "full_text": "Amtsgericht Recklinghausen Aktenzeichen: HRB 3676 \nBekannt gemacht am: 28.07.2006 11:39 Uhr\n\n\n\n\nDie in () gesetzten Angaben der Geschäftsanschrift und des Unternehmensgegenstandes erfolgen ohne Gewähr.\nVeränderungen\n07.07.2006\n\nREGIO Wohnungs- und Landgesellschaft mbH, Herten (An der Becke 9, 45527 Hattingen). Nicht mehr Geschäftsführer: Wien, Wolfgang, Herten, *17.03.1957. Neu bestellt als Geschäftsführer: Tetik, Mete, Herten, *20.09.1975, einzelvertretungsberechtigt mit der Befugnis im Namen der Gesellschaft mit sich im eigenen Namen oder als Vertreter eines Dritten Rechtsgeschäfte abzuschließen.",
        "gesellschafter": null,
        "inhaber": null,
        "name": "REGIO Wohnungs- und Landgesellschaft mbH",
        "notice_id": "147339",
        "posted_on": "2006-07-28",
        "rechtsform": null,
        "sitz": null,
        "url": "https://www.handelsregisterbekanntmachungen.de/en/skripte/hrb.php?rb_id=147339&land_abk=nw"
    },
    "parsed": {
        "officers": [
            {
                "class": "DismissedManagingDirector",
                "payload": {
                    "city": "Herten",
                    "dismissed": true,
                    "dob": "1957-03-17",
                    "lastname": "Wien",
                    "name": "Wolfgang"
                },
                "text": " Wien, Wolfgang, Herten, *17.03.1957."
            },
            {
                "class": "AppointedManagingDirector",
                "payload": {
                    "city": "Herten",
                    "dob": "1975-09-20",
                    "flag": "einzelvertretungsberechtigt mit der Befugnis im Namen der Gesellschaft mit sich im eigenen Namen oder als Vertreter eines Dritten Rechtsgeschäfte abzuschließen",
                    "lastname": "Tetik",
                    "name": "Mete"
                },
                "text": " Tetik, Mete, Herten, *20.09.1975, einzelvertretungsberechtigt mit der Befugnis im Namen der Gesellschaft mit sich im eigenen Namen oder als Vertreter eines Dritten Rechtsgeschäfte abzuschließen."
            }
        ]
    }
}