{
    "orig": {
        "aktenzeichen": "HRB 9646 B",
        "amtsgericht": "Charlottenburg (Berlin)",
        "event_date": "2010-11-02",
        "event_type": "Veränderungen",
        "federal_state": "be",
        "full_text": "Amtsgericht Charlottenburg (Berlin) Aktenzeichen: HRB 9646 B \nBekannt gemacht am: 03.11.2010 12:00 Uhr\n\n\n\n\nIn () gesetzte Angaben der Anschrift und des Geschäftszweiges erfolgen ohne Gewähr.\nVeränderungen\n02.11.2010\n\nFeuerungsbau Carl Roschmann GmbH, Berlin, Lorenzstr. 7, 12209 Berlin. Vertretungsregelung: Die Gesellschaft hat einen oder mehrere Liquidatoren. Sind mehrere Liquidatoren bestellt, so vertritt jeder von ihnen die Gesellschaft allein, es sei denn, dass die Gesellschafterversammlung beschließt, dass ein oder mehrere Liquidatoren die Gesellschaft jeweils gemeinschaftlich mit einem anderen Liquidator oder einem Prokuristen die Gesellschaft vertritt. Änderung zu Nr. 1:; Liquidator:; Gärtner, Peter, *28.09.1942, Berlin, Techniker Rechtsverhaeltnis: Durch Beschluss der Gesellschafterversammlung vom 04.05.2010 ist die Gesellschaft aufgelöst..",
        "gesellschafter": null,
        "inhaber": null,
        "name": "Feuerungsbau Carl Roschmann GmbH",
        "notice_id": "148113",
        "posted_on": "2010-11-03",
        "rechtsform": null,
        "sitz": null,
        "url": "https://www.handelsregisterbekanntmachungen.de/en/skripte/hrb.php?rb_id=148113&land_abk=be"
    },
    "parsed": {
        "officers": [
            {
                "class": "Liquidator",
                "payload": {
                    "city": "Berlin",
                    "dob": "1942-09-28",
                    "flag": "Techniker Rechtsverhaeltnis: Durch Beschluss der Gesellschafterversammlung vom 04.05.2010 ist die Gesellschaft aufgelöst",
                    "lastname": "Gärtner",
                    "name": "Peter"
                },
                "text": " Gärtner, Peter, *28.09.1942, Berlin, Techniker Rechtsverhaeltnis: Durch Beschluss der Gesellschafterversammlung vom 04.05.2010 ist die Gesellschaft aufgelöst.."
            }
        ]
    }
}