{
    "orig": {
        "aktenzeichen": "hra 5794",
        "amtsgericht": "lemgo",
        "event_date": "2018-04-30",
        "event_type": "neueintragungen",
        "federal_state": "nw",
        "full_text": "amtsgericht lemgo aktenzeichen: hra 5794 \nbekannt gemacht am: 30.04.2018 20:00 uhr\n\n\n\n\nin () gesetzte angaben der anschrift und des geschäftszweiges erfolgen ohne gewähr.\nneueintragungen\n30.04.2018\n\nhra 5794: grünewälder-damenmoden angela grünewälder e.kfr. inhaber: angela grünewälder, lage, lange straße 67, 32791 lage. einzelkaufmann. geschäftsanschrift: lange straße 67, 32791 lage. inhaber: grünewälder, angela, lage, *27.02.1952. die niederlassung ist von bielefeld (bisher amtsgericht bielefeld hra 12374) nach lage verlegt. zweigniederlassung errichtet unter firma: grünewälder-damenmoden angela grünewälder e.kfr. zweigniederlassung bielefeld inhaber: angela grünewälder, 33602 bielefeld, geschäftsanschrift: gehrenberg 17, 33602 bielefeld.",
        "gesellschafter": null,
        "inhaber": null,
        "name": "hra 5794: grünewälder-damenmoden angela grünewälder e.kfr. inhaber: angela grünewälder",
        "notice_id": "1532943",
        "posted_on": "2018-04-30",
        "rechtsform": "einzelkaufmann",
        "sitz": null,
        "url": "https://www.handelsregisterbekanntmachungen.de/en/skripte/hrb.php?rb_id=1532943&land_abk=nw"
    },
    "parsed": {
        "addresses": [
            {
                "kls": "Address",
                "text": "lange straße 67, 32791 lage"
            },
            {
                "kls": "Address",
                "text": "gehrenberg 17, 33602 bielefeld"
            }
        ],
        "errors": [
            {
                "kls": "ParsingError",
                "text": "Cannot parse a Person from ., error text was a person without DOB, number of chunks: 1"
            },
            {
                "kls": "ParsingError",
                "text": "Cannot parse a Owner from  angela grünewälder, 33602 bielefeld, geschäftsanschrift: gehrenberg 17, 33602 bielefeld., error text was Digits in name: 33602 bielefeld"
            }
        ],
        "flags": [
            {
                "flag": "Sole trader",
                "text": "Einzelkaufmann"
            }
        ],
        "officers": [
            {
                "class": "Owner",
                "payload": {
                    "city": "32791 lage",
                    "lastname": "angela grünewälder",
                    "name": "lage",
                    "position": "lange straße 67"
                },
                "text": " angela grünewälder, lage, lange straße 67, 32791 lage."
            },
            {
                "class": "Owner",
                "payload": {
                    "city": "lage",
                    "dob": "1952-02-27",
                    "lastname": "grünewälder",
                    "name": "angela"
                },
                "text": " grünewälder, angela, lage, *27.02.1952. die niederlassung ist von bielefeld (bisher amtsgericht bielefeld hra 12374) nach lage verlegt."
            }
        ]
    }
}