{
    "orig": {
        "aktenzeichen": "hrb 86197",
        "amtsgericht": "frankfurt am main",
        "event_date": "2010-09-27",
        "event_type": "veränderungen",
        "federal_state": "he",
        "full_text": "amtsgericht frankfurt am main aktenzeichen: hrb 86197 \nbekannt gemacht am: 04.10.2010 12:00 uhr\n\n\n\n\nveröffentlichungen des amtsgerichts frankfurt am main\r\r\rin () gesetzte angaben der anschrift und des geschäftszweiges erfolgen ohne gewähr.\nveränderungen\n27.09.2010\n\nloft tonstudios frankfurt gmbh, frankfurt am main, klaus-groth-straße 44, 60320 frankfurt am main.allgemeine vertretungsregelung geändert, nun: ist nur ein liquidator bestellt, so vertritt er die gesellschaft allein. sind mehrere liquidatoren bestellt, so wird die gesellschaft durch zwei liquidatoren oder durch einen liquidator gemeinsam mit einem prokuristen vertreten. geändert, nun: liquidator: liebethal, andreas, frankfurt am main, *28.08.1959; szymczyk, marian, butzbach-wiesental, *30.10.1954, jeweils einzelvertretungsberechtigt; mit der befugnis, im namen der gesellschaft mit sich im eigenen namen oder als vertreter eines dritten rechtsgeschäfte abzuschließen. die gesellschaft ist aufgelöst.",
        "gesellschafter": null,
        "inhaber": null,
        "name": "loft tonstudios frankfurt gmbh",
        "notice_id": "199799",
        "posted_on": "2010-10-04",
        "rechtsform": null,
        "sitz": null,
        "url": "https://www.handelsregisterbekanntmachungen.de/en/skripte/hrb.php?rb_id=199799&land_abk=he"
    },
    "parsed": {
        "flags": [
            {
                "flag": "with the power to enter into legal transactions on behalf of the Company with itself or as a representative of a third party",
                "text": "mit\\ der\\ Befugnis\\,\\ im\\ Namen\\ der\\ Gesellschaft\\ mit\\ sich\\ im\\ eigenen\\ Namen\\ oder\\ als\\ Vertreter\\ eines\\ Dritten\\ Rechtsgesch\\äfte\\ abzuschlie\\ßen\\."
            },
            {
                "flag": "CompanyClosed",
                "text": "Die\\ Gesellschaft\\ ist\\ aufgel\\öst\\."
            }
        ],
        "officers": [
            {
                "class": "Liquidator",
                "payload": {
                    "city": "frankfurt am main",
                    "dob": "1959-08-28",
                    "lastname": ": liebethal",
                    "name": "andreas"
                },
                "text": ": liebethal, andreas, frankfurt am main, *28.08.1959"
            },
            {
                "class": "Liquidator",
                "payload": {
                    "city": "butzbach-wiesental",
                    "dob": "1954-10-30",
                    "flag": "jeweils einzelvertretungsberechtigt",
                    "lastname": "szymczyk",
                    "name": "marian"
                },
                "text": " szymczyk, marian, butzbach-wiesental, *30.10.1954, jeweils einzelvertretungsberechtigt"
            },
            {
                "class": "Liquidator",
                "payload": {
                    "lastname": "mit der befugnis",
                    "name": "im namen der gesellschaft mit sich im eigenen namen oder als vertreter eines dritten rechtsgeschäfte abzuschließen"
                },
                "text": " mit der befugnis, im namen der gesellschaft mit sich im eigenen namen oder als vertreter eines dritten rechtsgeschäfte abzuschließen."
            }
        ]
    }
}