{
    "orig": {
        "aktenzeichen": "HRB 720872",
        "amtsgericht": "Stuttgart",
        "event_date": "2010-09-09",
        "event_type": "Veränderungen",
        "federal_state": "bw",
        "full_text": "Amtsgericht Stuttgart Aktenzeichen: HRB 720872 \nBekannt gemacht am: 13.09.2010 12:00 Uhr\n\n\n\n\nIn () gesetzte Angaben der Anschrift und des Geschäftszweiges erfolgen ohne Gewähr.\nVeränderungen\n09.09.2010\n\nalles werbung. gmbh Jens Nill, Stuttgart, Lindenspürstraße 22, 70176 Stuttgart.Ist nur ein Geschäftsführer bestellt, vertritt er allein. Sind mehrere Geschäftsführer bestellt, vertreten zwei gemeinsam oder ein Geschäftsführer mit einem Prokuristen. Die allgemeine Vertretungsregelung der Geschäftsführer gilt bei den Liquidatoren nicht automatisch fort. Gemäß § 384 FamFG von Amts wegen eingetragen. Nicht mehr Geschäftsführer, nunmehr Liquidator: Nill, Jens, Stuttgart, *20.03.1967, Gemäß § 384 FamFG von Amts wegen vermerkt : Die bisher eingetragene konkrete Vertretungsregelung des Geschäftsführers gilt nicht automatisch auch für den Liquidator. Durch rechtskräftigen Beschluss des Amtsgerichts Stuttgart vom 01.09.2010 (5 IN 632/10) wurde die Eröffnung des Insolvenzverfahrens über das Vermögen der Gesellschaft mangels einer den Kosten des Verfahrens entsprechenden Masse abgewiesen. Die Gesellschaft ist hierdurch aufgelöst. Gemäß § 60 Abs. 1 GmbHG i.V. § 65 Abs. 1 GmbHG von Amts wegen eingetragen.",
        "gesellschafter": null,
        "inhaber": null,
        "name": "alles werbung. gmbh Jens Nill",
        "notice_id": "207333",
        "posted_on": "2010-09-13",
        "rechtsform": null,
        "sitz": null,
        "url": "https://www.handelsregisterbekanntmachungen.de/en/skripte/hrb.php?rb_id=207333&land_abk=bw"
    },
    "parsed": {
        "officers": [
            {
                "class": "Liquidator",
                "payload": {
                    "city": "Stuttgart",
                    "dob": "1967-03-20",
                    "flag": "Gemäß § 384 FamFG von Amts wegen vermerkt : Die bisher eingetragene konkrete Vertretungsregelung des Geschäftsführers gilt nicht automatisch auch für den Liquidator",
                    "lastname": "Nill",
                    "name": "Jens"
                },
                "text": " Nill, Jens, Stuttgart, *20.03.1967, Gemäß § 384 FamFG von Amts wegen vermerkt : Die bisher eingetragene konkrete Vertretungsregelung des Geschäftsführers gilt nicht automatisch auch für den Liquidator."
            }
        ]
    }
}