{
    "orig": {
        "aktenzeichen": "hra 12128",
        "amtsgericht": "leipzig",
        "event_date": "2016-05-27",
        "event_type": "veränderungen",
        "federal_state": "sn",
        "full_text": "amtsgericht leipzig aktenzeichen: hra 12128 \nbekannt gemacht am: 27.05.2016 18:30 uhr\n\n\n\n\ndie in () gesetzten angaben der geschäftsanschrift und des unternehmensgegenstandes erfolgen ohne gewähr.\nveränderungen\n27.05.2016\n\nhra 12128: handel und transport jope & sohn ohg, leipzig, werkstraße 9, 04249 leipzig. (vermietung von gewerberäumen und lagerflächen, erbringung diverser dienstleistungen im projektmanagement, grundstückssicherung, maklertätigkeit und beratungsleistungen). geändert, nun: einzelkaufmann. die firma ist geändert. neue firma: jope & sohn e.k. ausgeschieden: persönlich haftender gesellschafter: jope, volker, kaufmann, leipzig. nunmehr inhaber: jope, daniel, leipzig, *07.10.1971.",
        "gesellschafter": null,
        "inhaber": null,
        "name": "hra 12128: handel und transport jope & sohn ohg",
        "notice_id": "212849",
        "posted_on": "2016-05-27",
        "rechtsform": "einzelkaufmann",
        "sitz": null,
        "url": "https://www.handelsregisterbekanntmachungen.de/en/skripte/hrb.php?rb_id=212849&land_abk=sn"
    },
    "parsed": {
        "flags": [
            {
                "flag": "Sole trader",
                "text": "Einzelkaufmann"
            }
        ],
        "officers": [
            {
                "class": "RetiredPersonalPartner",
                "payload": {
                    "city": "leipzig",
                    "dismissed": true,
                    "lastname": "jope",
                    "name": "volker",
                    "position": "kaufmann"
                },
                "text": " jope, volker, kaufmann, leipzig."
            },
            {
                "class": "Owner",
                "payload": {
                    "city": "leipzig",
                    "dob": "1971-07-10",
                    "lastname": "jope",
                    "name": "daniel"
                },
                "text": " jope, daniel, leipzig, *07.10.1971."
            }
        ]
    }
}