{
    "orig": {
        "aktenzeichen": "hrb 6951",
        "amtsgericht": "montabaur",
        "event_date": "2017-01-02",
        "event_type": "veränderungen",
        "federal_state": "rp",
        "full_text": "amtsgericht montabaur aktenzeichen: hrb 6951 \nbekannt gemacht am: 02.01.2017 20:06 uhr\n\n\n\n\ndie in () gesetzten angaben der anschrift und des geschäftszweiges erfolgen ohne gewähr.\nveränderungen\n02.01.2017\n\nhrb 6951: foto - parfümerie ewald gmbh, wirges, bahnhofstraße 33, 56422 wirges. geändert, nun: ist nur ein liquidator bestellt, so vertritt er die gesellschaft allein. sind mehrere liquidatoren bestellt, so wird die gesellschaft durch die liquidatoren gemeinsam vertreten. bestellt als liquidator: ewald, heinz, wirges, *23.08.1950, einzelvertretungsberechtigt mit der befugnis im namen der gesellschaft mit sich im eigenen namen oder als vertreter eines dritten rechtsgeschäfte abzuschließen. die gesellschaft ist aufgelöst.",
        "gesellschafter": null,
        "inhaber": null,
        "name": "hrb 6951: foto - parfümerie ewald gmbh",
        "notice_id": "213954",
        "posted_on": "2017-01-02",
        "rechtsform": null,
        "sitz": null,
        "url": "https://www.handelsregisterbekanntmachungen.de/en/skripte/hrb.php?rb_id=213954&land_abk=rp"
    },
    "parsed": {
        "officers": [
            {
                "class": "Liquidator",
                "payload": {
                    "city": "wirges",
                    "dob": "1950-08-23",
                    "flag": "einzelvertretungsberechtigt mit der befugnis im namen der gesellschaft mit sich im eigenen namen oder als vertreter eines dritten rechtsgeschäfte abzuschließen",
                    "lastname": "ewald",
                    "name": "heinz"
                },
                "text": " ewald , heinz , wirges , * 23.08.1950 , einzelvertretungsberechtigt mit der befugnis im namen der gesellschaft mit sich im eigenen namen oder als vertreter eines dritten rechtsgeschäfte abzuschließen ."
            }
        ]
    }
}