{
    "orig": {
        "aktenzeichen": "HRB 6902",
        "amtsgericht": "Koblenz",
        "event_date": "2018-02-16",
        "event_type": "Veränderungen",
        "federal_state": "rp",
        "full_text": "Amtsgericht Koblenz Aktenzeichen: HRB 6902 \nBekannt gemacht am: 16.02.2018 20:30 Uhr\n\n\n\n\nDie in () gesetzten Angaben der Geschäftsanschrift und des Unternehmensgegenstandes erfolgen ohne Gewähr.\nVeränderungen\n16.02.2018\n\nHRB 6902: BHG Koblenz GmbH, Koblenz, St. Elisabeth-Str. 1, 56073 Koblenz. Nicht mehr Geschäftsführer: Zang, Simone Ingeborg, Trier, *29.05.1965. Bestellt als Geschäftsführer: Kiriakidis, Georgios, Andernach, *20.10.1967, einzelvertretungsberechtigt mit der Befugnis im Namen der Gesellschaft mit sich im eigenen Namen oder als Vertreter eines Dritten Rechtsgeschäfte abzuschließen.",
        "gesellschafter": null,
        "inhaber": null,
        "name": "HRB 6902: BHG Koblenz GmbH",
        "notice_id": "239013",
        "posted_on": "2018-02-16",
        "rechtsform": null,
        "sitz": null,
        "url": "https://www.handelsregisterbekanntmachungen.de/en/skripte/hrb.php?rb_id=239013&land_abk=rp"
    },
    "parsed": {
        "officers": [
            {
                "class": "ManagingDirector",
                "payload": {
                    "city": "Trier",
                    "dob": "1965-05-29",
                    "lastname": "Zang",
                    "name": "Simone Ingeborg"
                },
                "text": " Zang , Simone Ingeborg , Trier , * 29.05.1965 ."
            },
            {
                "class": "ManagingDirector",
                "payload": {
                    "city": "Andernach",
                    "dob": "1967-10-20",
                    "flag": "einzelvertretungsberechtigt mit der Befugnis im Namen der Gesellschaft mit sich im eigenen Namen oder als Vertreter eines Dritten Rechtsgeschäfte abzuschließen",
                    "lastname": "Kiriakidis",
                    "name": "Georgios"
                },
                "text": " Kiriakidis , Georgios , Andernach , * 20.10.1967 , einzelvertretungsberechtigt mit der Befugnis im Namen der Gesellschaft mit sich im eigenen Namen oder als Vertreter eines Dritten Rechtsgeschäfte abzuschließen ."
            }
        ]
    }
}