{
    "orig": {
        "aktenzeichen": "HRB 2948",
        "amtsgericht": "Coesfeld",
        "event_date": "2009-06-29",
        "event_type": "Veränderungen",
        "federal_state": "nw",
        "full_text": "Amtsgericht Coesfeld Aktenzeichen: HRB 2948 \nBekannt gemacht am: 16.07.2009 12:00 Uhr\n\n\n\n\nIn () gesetzte Angaben der Anschrift und des Geschäftszweiges erfolgen ohne Gewähr.\nVeränderungen\n29.06.2009\n\nWorkconsult GmbH Personaldienstleistung, Ahaus, Fleehook 1, 48683 Ahaus.Die Gesellschafterversammlung vom 11.05.2009 hat eine Änderung des Gesellschaftsvertrages in § 1 und mit ihr die Änderung der Firma beschlossen. Neue Firma: SOVEA-Workconsult Zeitarbeit GmbH. Bestellt als Geschäftsführer: Liebenow, Bernd, Ahaus, *29.09.1951, einzelvertretungsberechtigt mit der Befugnis im Namen der Gesellschaft mit sich im eigenen Namen oder als Vertreter eines Dritten Rechtsgeschäfte abzuschließen.",
        "gesellschafter": null,
        "inhaber": null,
        "name": "Workconsult GmbH Personaldienstleistung",
        "notice_id": "451212",
        "posted_on": "2009-07-16",
        "rechtsform": null,
        "sitz": null,
        "url": "https://www.handelsregisterbekanntmachungen.de/en/skripte/hrb.php?rb_id=451212&land_abk=nw"
    },
    "parsed": {
        "officers": [
            {
                "class": "AppointedManagingDirector",
                "payload": {
                    "city": "Ahaus",
                    "dob": "1951-09-29",
                    "flag": "einzelvertretungsberechtigt mit der Befugnis im Namen der Gesellschaft mit sich im eigenen Namen oder als Vertreter eines Dritten Rechtsgeschäfte abzuschließen",
                    "lastname": "Liebenow",
                    "name": "Bernd"
                },
                "text": " Liebenow, Bernd, Ahaus, *29.09.1951, einzelvertretungsberechtigt mit der Befugnis im Namen der Gesellschaft mit sich im eigenen Namen oder als Vertreter eines Dritten Rechtsgeschäfte abzuschließen."
            }
        ]
    }
}