{
    "orig": {
        "aktenzeichen": "HRB 1675",
        "amtsgericht": "Kleve",
        "event_date": "2010-02-04",
        "event_type": "Veränderungen",
        "federal_state": "nw",
        "full_text": "Amtsgericht Kleve Aktenzeichen: HRB 1675 \nBekannt gemacht am: 05.02.2010 22:00 Uhr\n\n\n\n\nIn () gesetzte Angaben der Anschrift und des Geschäftszweiges erfolgen ohne Gewähr.\nVeränderungen\n04.02.2010\n\nARCH-BAU, Bauträgergesellschaft mit beschränkter Haftung, Goch, Hervorster Straße 56, 47574 Goch.Durch Beschluss der Gesellschafterversammlung vom 01.02.2010 ist die Gesellschaft aufgelöst. Die Gesellschaft hat einen oder mehrere Abwickler. Ist nur ein Abwickler bestellt, so vertritt er die Gesellschaft allein. Sind mehrere Abwickler bestellt, so wird die Gesellschaft durch zwei Abwickler gemeinsam vertreten. Durch Beschluss der Gesellschafterversammlung kann einem oder mehreren Abwicklern die Befugnis erteilt werden, die Gesellschaft stets einzeln zu vertreten. Jeder Abwickler kann durch Gesellschafterbeschluss von den Beschränkungen des § 181 BGB befreit werden. Nicht mehr Geschäftsführer: Willinghöfer, Beate, Krankenschwester, Goch. Bestellt als Abwickler: Willinghöfer, Beate, Goch, *05.01.1961, einzelvertretungsberechtigt mit der Befugnis im Namen der Gesellschaft mit sich im eigenen Namen oder als Vertreter eines Dritten Rechtsgeschäfte abzuschließen. Geschäftsanschrift: Hervorster Straße 56, 47574 Goch.",
        "gesellschafter": null,
        "inhaber": null,
        "name": "ARCH-BAU",
        "notice_id": "520671",
        "posted_on": "2010-02-05",
        "rechtsform": null,
        "sitz": null,
        "url": "https://www.handelsregisterbekanntmachungen.de/en/skripte/hrb.php?rb_id=520671&land_abk=nw"
    },
    "parsed": {
        "addresses": [
            {
                "kls": "Address",
                "text": "Hervorster Straße 56, 47574 Goch"
            }
        ],
        "officers": [
            {
                "class": "DismissedManagingDirector",
                "payload": {
                    "city": "Goch",
                    "dismissed": true,
                    "lastname": "Willinghöfer",
                    "name": "Beate",
                    "position": "Krankenschwester"
                },
                "text": " Willinghöfer, Beate, Krankenschwester, Goch."
            }
        ]
    }
}