{
    "orig": {
        "aktenzeichen": "HRB 98768",
        "amtsgericht": "München",
        "event_date": "2012-03-27",
        "event_type": "Veränderungen",
        "federal_state": "by",
        "full_text": "Amtsgericht München Aktenzeichen: HRB 98768   \nBekannt gemacht am: 28.03.2012 12:00 Uhr\n\n\n\n\nIn ( ) gesetzte Angaben der Anschrift und des Geschäftszweiges erfolgen ohne Gewähr.\nVeränderungen\n27.03.2012\n\nFerragamo, Deutschland, GmbH, München, Maximilianstraße 29, 80539 München. Ausgeschieden: Geschäftsführer: Anichini, Giuseppe, Florenz, *13.04.1936; Barzaghi, Massimo, Firenze/Italien, *18.08.1956; Dr. Rosi Belliere, Luciano, San Casciano Val di Pesa, Italien, *25.09.1946. Bestellt: Geschäftsführer: Pedani, Raffaela, Florenz/Italien, *28.04.1955; Piccirelli, Piero, La Varenne Saint Hilaire/Italien, *25.09.1971; van Campen, Marcus, Den Haag/Niederlande, *29.09.1944, jeweils mit der Befugnis, im Namen der Gesellschaft mit sich im eigenen Namen oder als Vertreter eines Dritten Rechtsgeschäfte abzuschließen.",
        "gesellschafter": null,
        "inhaber": null,
        "name": "Ferragamo",
        "notice_id": "586928",
        "posted_on": "2012-03-28",
        "rechtsform": null,
        "sitz": null,
        "url": "https://www.handelsregisterbekanntmachungen.de/en/skripte/hrb.php?rb_id=586928&land_abk=by"
    },
    "parsed": {
        "flags": [
            {
                "flag": "with the power to enter into legal transactions on behalf of the Company with itself or as a representative of a third party",
                "text": "mit\\ der\\ Befugnis\\,\\ im\\ Namen\\ der\\ Gesellschaft\\ mit\\ sich\\ im\\ eigenen\\ Namen\\ oder\\ als\\ Vertreter\\ eines\\ Dritten\\ Rechtsgesch\\äfte\\ abzuschlie\\ßen\\."
            }
        ],
        "officers": [
            {
                "class": "RetiredManagingDirector",
                "payload": {
                    "city": "Florenz",
                    "dismissed": true,
                    "dob": "1936-04-13",
                    "lastname": "Anichini",
                    "name": "Giuseppe"
                },
                "text": " Anichini, Giuseppe, Florenz, *13.04.1936"
            },
            {
                "class": "RetiredManagingDirector",
                "payload": {
                    "city": "Firenze/Italien",
                    "dismissed": true,
                    "dob": "1956-08-18",
                    "lastname": "Barzaghi",
                    "name": "Massimo"
                },
                "text": " Barzaghi, Massimo, Firenze/Italien, *18.08.1956"
            },
            {
                "class": "RetiredManagingDirector",
                "payload": {
                    "city": "Italien",
                    "dismissed": true,
                    "dob": "1946-09-25",
                    "lastname": "Rosi Belliere",
                    "name": "Luciano",
                    "position": "San Casciano Val di Pesa",
                    "prof_title": "doctor"
                },
                "text": " Doctor Rosi Belliere, Luciano, San Casciano Val di Pesa, Italien, *25.09.1946."
            },
            {
                "class": "AppointedManagingDirector",
                "payload": {
                    "city": "Florenz/Italien",
                    "dob": "1955-04-28",
                    "lastname": "Pedani",
                    "name": "Raffaela"
                },
                "text": " Pedani, Raffaela, Florenz/Italien, *28.04.1955"
            },
            {
                "class": "AppointedManagingDirector",
                "payload": {
                    "city": "La Varenne Saint Hilaire/Italien",
                    "dob": "1971-09-25",
                    "lastname": "Piccirelli",
                    "name": "Piero"
                },
                "text": " Piccirelli, Piero, La Varenne Saint Hilaire/Italien, *25.09.1971"
            },
            {
                "class": "AppointedManagingDirector",
                "payload": {
                    "city": "Den Haag/Niederlande",
                    "dob": "1944-09-29",
                    "flag": "jeweils mit der Befugnis im Namen der Gesellschaft mit sich im eigenen Namen oder als Vertreter eines Dritten Rechtsgeschäfte abzuschließen",
                    "lastname": "van Campen",
                    "name": "Marcus"
                },
                "text": " van Campen, Marcus, Den Haag/Niederlande, *29.09.1944, jeweils mit der Befugnis, im Namen der Gesellschaft mit sich im eigenen Namen oder als Vertreter eines Dritten Rechtsgeschäfte abzuschließen."
            }
        ]
    }
}