{
    "orig": {
        "aktenzeichen": "PR 1060",
        "amtsgericht": "Essen",
        "event_date": "2012-02-13",
        "event_type": "Veränderungen",
        "federal_state": "nw",
        "full_text": "Amtsgericht Essen Aktenzeichen: PR 1060   \nBekannt gemacht am: 17.02.2012 12:00 Uhr\n\n\n\n\nIn () gesetzte Angaben der Anschrift und des Geschäftszweiges erfolgen ohne Gewähr.\nVeränderungen\n13.02.2012\n\nSpektrum Szymiczek, Schweer & Partner Steuerberatungsgesellschaft, Hamm, Hamm (Brüderstr. 70, 59065 Hamm). Die Partnerschaft ist aufgelöst. Die Liquidatoren vertreten gemeinsam. Bestellt zum Liquidator: Dipl.-Finanzwirtin Schweer, Anne, Steuerberaterin, Ahlen, *30.10.1968; Szymiczek, Paul Werner, Steuerberater, Hamm, *21.10.1947; Szymiczek, Marco, Steuerberater, Hamm, *27.08.1973. Infolge Wohnortänderung: Partner: Szymiczek, Marco, Steuerberater, Hamm, *27.08.1973.",
        "gesellschafter": null,
        "inhaber": null,
        "name": "Spektrum Szymiczek",
        "notice_id": "766583",
        "posted_on": "2012-02-17",
        "rechtsform": null,
        "sitz": null,
        "url": "https://www.handelsregisterbekanntmachungen.de/en/skripte/hrb.php?rb_id=766583&land_abk=nw"
    },
    "parsed": {
        "officers": [
            {
                "class": "Liquidator",
                "payload": {
                    "city": "Ahlen",
                    "dob": "1968-10-30",
                    "lastname": "Dipl.-Finanzwirtin Schweer",
                    "name": "Anne",
                    "position": "Steuerberaterin"
                },
                "text": " Dipl.-Finanzwirtin Schweer, Anne, Steuerberaterin, Ahlen, *30.10.1968"
            }
        ]
    }
}