{
    "orig": {
        "aktenzeichen": "HRA 630146",
        "amtsgericht": "Ulm",
        "event_date": "2008-08-01",
        "event_type": "Veränderungen",
        "federal_state": "bw",
        "full_text": "Amtsgericht Ulm Aktenzeichen: HRA 630146 \nBekannt gemacht am: 12.08.2008 12:00 Uhr\n\n\n\n\nDie in () gesetzten Angaben der Geschäftsanschrift und des Unternehmensgegenstandes erfolgen ohne Gewähr.\nVeränderungen\n01.08.2008\n\nNeue Apotheke Rüdiger Przybilla e.K., Friedrichshafen (Ailinger Strasse 14, 88046 Friedrichshafen). Nun: Einzelkauffrau. Firma geändert; nun: Neue Apotheke Sylvia Klimek e.K. Nicht mehr Inhaber: Przybilla, Rüdiger, Apotheker, Friedrichshafen. Neuer Inhaber: Klimek, Sylvia, Friedrichshafen, *15.03.1966. Das Handelsgeschäft ist mit dem Recht zur Fortführung der Firma übergegangen auf Klimek, Sylvia, Friedrichshafen, *15.03.1966.",
        "gesellschafter": null,
        "inhaber": null,
        "name": "Neue Apotheke Rüdiger Przybilla e.K.",
        "notice_id": "85943",
        "posted_on": "2008-08-12",
        "rechtsform": null,
        "sitz": null,
        "url": "https://www.handelsregisterbekanntmachungen.de/en/skripte/hrb.php?rb_id=85943&land_abk=bw"
    },
    "parsed": {
        "officers": [
            {
                "class": "NotLongerOwner",
                "payload": {
                    "city": "Friedrichshafen",
                    "dismissed": true,
                    "lastname": "Przybilla",
                    "name": "Rüdiger",
                    "position": "Apotheker"
                },
                "text": " Przybilla, Rüdiger, Apotheker, Friedrichshafen."
            },
            {
                "class": "Owner",
                "payload": {
                    "city": "Friedrichshafen",
                    "dob": "1966-03-15",
                    "lastname": "Klimek",
                    "name": "Sylvia"
                },
                "text": " Klimek, Sylvia, Friedrichshafen, *15.03.1966."
            }
        ]
    }
}