{
    "orig": {
        "aktenzeichen": "HRA 18064",
        "amtsgericht": "Wuppertal",
        "event_date": "2014-01-13",
        "event_type": "Veränderungen",
        "federal_state": "nw",
        "full_text": "Amtsgericht Wuppertal Aktenzeichen: HRA 18064 \nBekannt gemacht am: 13.01.2014 19:59 Uhr\n\n\n\n\nIn () gesetzte Angaben der Anschrift und des Geschäftszweiges erfolgen ohne Gewähr.\nVeränderungen\n13.01.2014\n\nHRA 18064:Schein Orthopädie Service KG, Remscheid, Hildegardstr. 5, 42897 Remscheid.Ausgeschieden als Persönlich haftender Gesellschafter: Schein, Ulrike, Remscheid, *10.02.1944; Schein Verwaltungs-GmbH, Remscheid (Amtsgericht Wuppertal HRB 16868). Nunmehr eingetreten als Persönlich haftender Gesellschafter: Schein, Arnd, Remscheid, *28.11.1971, mit der Befugnis im Namen der Gesellschaft mit sich im eigenen Namen oder als Vertreter eines Dritten Rechtsgeschäfte abzuschließen.",
        "gesellschafter": null,
        "inhaber": null,
        "name": "HRA 18064:Schein Orthopädie Service KG",
        "notice_id": "992683",
        "posted_on": "2014-01-13",
        "rechtsform": null,
        "sitz": null,
        "url": "https://www.handelsregisterbekanntmachungen.de/en/skripte/hrb.php?rb_id=992683&land_abk=nw"
    },
    "parsed": {
        "officers": [
            {
                "class": "RetiredPersonalPartner",
                "payload": {
                    "city": "Remscheid",
                    "dismissed": true,
                    "dob": "1944-10-02",
                    "lastname": "Schein",
                    "name": "Ulrike"
                },
                "text": " Schein, Ulrike, Remscheid, *10.02.1944"
            },
            {
                "class": "PersonalPartner",
                "payload": {
                    "city": "Remscheid",
                    "dob": "1971-11-28",
                    "flag": "mit der Befugnis im Namen der Gesellschaft mit sich im eigenen Namen oder als Vertreter eines Dritten Rechtsgeschäfte abzuschließen",
                    "lastname": "Schein",
                    "name": "Arnd"
                },
                "text": " Schein, Arnd, Remscheid, *28.11.1971, mit der Befugnis im Namen der Gesellschaft mit sich im eigenen Namen oder als Vertreter eines Dritten Rechtsgeschäfte abzuschließen."
            }
        ]
    }
}