{
    "orig": {
        "aktenzeichen": "HRB 6301",
        "amtsgericht": "Essen",
        "event_date": "2014-01-22",
        "event_type": "Veränderungen",
        "federal_state": "nw",
        "full_text": "Amtsgericht Essen Aktenzeichen: HRB 6301 \nBekannt gemacht am: 22.01.2014 20:00 Uhr\n\n\n\n\nIn () gesetzte Angaben der Anschrift und des Geschäftszweiges erfolgen ohne Gewähr.\nVeränderungen\n22.01.2014\n\nHRB 6301:Kozica - Reisen GmbH, Essen, Meybuschhof 46 a, 45327 Essen.Die Gesellschafterversammlung hat am 17.12.2013 beschlossen, den Gesellschaftsvertrag in §§ 6 und 10 zu ändern. Nicht mehr Geschäftsführer: Kozica, Brigitte, Kauffrau, Essen. Geschäftsführer: Kozica, Mark, Essen, *19.01.1977, einzelvertretungsberechtigt mit der Befugnis im Namen der Gesellschaft mit sich im eigenen Namen oder als Vertreter eines Dritten Rechtsgeschäfte abzuschließen.",
        "gesellschafter": null,
        "inhaber": null,
        "name": "HRB 6301:Kozica - Reisen GmbH",
        "notice_id": "997141",
        "posted_on": "2014-01-22",
        "rechtsform": null,
        "sitz": null,
        "url": "https://www.handelsregisterbekanntmachungen.de/en/skripte/hrb.php?rb_id=997141&land_abk=nw"
    },
    "parsed": {
        "officers": [
            {
                "class": "DismissedManagingDirector",
                "payload": {
                    "city": "Essen",
                    "dismissed": true,
                    "lastname": "Kozica",
                    "name": "Brigitte",
                    "position": "Kauffrau"
                },
                "text": " Kozica, Brigitte, Kauffrau, Essen."
            },
            {
                "class": "ManagingDirector",
                "payload": {
                    "city": "Essen",
                    "dob": "1977-01-19",
                    "flag": "einzelvertretungsberechtigt mit der Befugnis im Namen der Gesellschaft mit sich im eigenen Namen oder als Vertreter eines Dritten Rechtsgeschäfte abzuschließen",
                    "lastname": "Kozica",
                    "name": "Mark"
                },
                "text": " Kozica, Mark, Essen, *19.01.1977, einzelvertretungsberechtigt mit der Befugnis im Namen der Gesellschaft mit sich im eigenen Namen oder als Vertreter eines Dritten Rechtsgeschäfte abzuschließen."
            }
        ]
    }
}