{
    "orig": {
        "aktenzeichen": "HRB 119266",
        "amtsgericht": "München",
        "event_date": "2006-05-24",
        "event_type": "Veränderungen",
        "federal_state": "by",
        "full_text": "Amtsgericht München Aktenzeichen: HRB 119266 \nBekannt gemacht am: 31.05.2006 09:42 Uhr\n\n\n\n\nDie in ( ) gesetzten Angaben der Geschäftsanschrift und des Geschäftszweiges erfolgen ohne Gewähr.\nVeränderungen\n24.05.2006\n\nINNOVATIVHAUS GmbH, München (Wackersberger Str. 35 A, 81371 München). Die Gesellschaft wird durch den/die Liquidator/en vertreten. Geändert, nun: Liquidator: Seyfried, Alfred, Bauingenieur, München. Durch rechtskräftigen Beschluss des Amtsgerichts München (Az. 1542 IN 176/06, 1542 IN 603/06) vom 03.04.2006 ist die Eröffnung des Insolvenzverfahrens über das Vermögen der Gesellschaft mangels Masse abgelehnt. Die Gesellschaft ist aufgelöst. Von Amts wegen eingetragen gemäß § 65 GmbHG.",
        "gesellschafter": null,
        "inhaber": null,
        "name": "INNOVATIVHAUS GmbH",
        "notice_id": "100300",
        "posted_on": "2006-05-31",
        "rechtsform": null,
        "sitz": null,
        "url": "https://www.handelsregisterbekanntmachungen.de/en/skripte/hrb.php?rb_id=100300&land_abk=by"
    },
    "parsed": {
        "flags": [
            {
                "flag": "CompanyClosed",
                "text": "Die\\ Gesellschaft\\ ist\\ aufgel\\öst\\."
            }
        ],
        "officers": [
            {
                "class": "Liquidator",
                "payload": {
                    "city": "München",
                    "lastname": "Seyfried",
                    "name": "Alfred",
                    "position": "Bauingenieur"
                },
                "text": ": Seyfried, Alfred, Bauingenieur, München."
            }
        ]
    }
}