{
    "orig": {
        "aktenzeichen": "HRB 13707",
        "amtsgericht": "Duisburg",
        "event_date": "2014-02-12",
        "event_type": "Veränderungen",
        "federal_state": "nw",
        "full_text": "Amtsgericht Duisburg Aktenzeichen: HRB 13707 \nBekannt gemacht am: 12.02.2014 20:00 Uhr\n\n\n\n\nIn () gesetzte Angaben der Anschrift und des Geschäftszweiges erfolgen ohne Gewähr.\nVeränderungen\n12.02.2014\n\nHRB 13707:Wohnpark GmbH Königshardt, Oberhausen, Im Lipperfeld 35, 46047 Oberhausen.Ist nur ein Liquidator berufen, so vertritt dieser die Gesellschaft allein. Sind mehrere Liquidatoren bestellt, so wird die Gesellschaft von ihnen gemeinsam vertreten. Nicht mehr Geschäftsführer: Bangel, Franz Josef, Mülheim an der Ruhr, *27.12.1950. Geändert, nunmehr Liquidator: Koch, Heinz, Oberhausen, *13.04.1947, mit der Befugnis im Namen der Gesellschaft mit sich im eigenen Namen oder als Vertreter eines Dritten Rechtsgeschäfte abzuschließen. Die Gesellschaft ist aufgelöst.",
        "gesellschafter": null,
        "inhaber": null,
        "name": "HRB 13707:Wohnpark GmbH Königshardt",
        "notice_id": "1005677",
        "posted_on": "2014-02-12",
        "rechtsform": null,
        "sitz": null,
        "url": "https://www.handelsregisterbekanntmachungen.de/en/skripte/hrb.php?rb_id=1005677&land_abk=nw"
    },
    "parsed": {
        "flags": [
            {
                "flag": "CompanyClosed",
                "text": "Die\\ Gesellschaft\\ ist\\ aufgel\\öst\\."
            }
        ],
        "officers": [
            {
                "class": "DismissedManagingDirector",
                "payload": {
                    "city": "Mülheim an der Ruhr",
                    "dismissed": true,
                    "dob": "1950-12-27",
                    "lastname": "Bangel",
                    "name": "Franz Josef"
                },
                "text": " Bangel, Franz Josef, Mülheim an der Ruhr, *27.12.1950."
            },
            {
                "class": "Liquidator",
                "payload": {
                    "city": "Oberhausen",
                    "dob": "1947-04-13",
                    "flag": "mit der Befugnis im Namen der Gesellschaft mit sich im eigenen Namen oder als Vertreter eines Dritten Rechtsgeschäfte abzuschließen",
                    "lastname": "Koch",
                    "name": "Heinz"
                },
                "text": " Koch, Heinz, Oberhausen, *13.04.1947, mit der Befugnis im Namen der Gesellschaft mit sich im eigenen Namen oder als Vertreter eines Dritten Rechtsgeschäfte abzuschließen."
            }
        ]
    }
}