{
    "orig": {
        "aktenzeichen": "HRB 3282",
        "amtsgericht": "Coesfeld",
        "event_date": "2014-02-14",
        "event_type": "Veränderungen",
        "federal_state": "nw",
        "full_text": "Amtsgericht Coesfeld Aktenzeichen: HRB 3282 \nBekannt gemacht am: 14.02.2014 19:58 Uhr\n\n\n\n\nIn () gesetzte Angaben der Anschrift und des Geschäftszweiges erfolgen ohne Gewähr.\nVeränderungen\n14.02.2014\n\nHRB 3282:Gebrüder Wechsel Gesellschaft mit beschränkter Haftung, Heek, Bahnhofstraße 23, 48619 Heek.Nicht mehr Geschäftsführer: Wechsel, Robert, Heek, *25.02.1975. Unter Änderung des Wohnortes: Nicht mehr Geschäftsführer: Wechsel, Waldemar, Metelen, *29.07.1970. Wohnort geändert bezüglich Geschäftsführer: Wechsel, Sergej, Heek, *05.01.1972, einzelvertretungsberechtigt mit der Befugnis im Namen der Gesellschaft mit sich im eigenen Namen oder als Vertreter eines Dritten Rechtsgeschäfte abzuschließen.",
        "gesellschafter": null,
        "inhaber": null,
        "name": "HRB 3282:Gebrüder Wechsel Gesellschaft mit beschränkter Haftung",
        "notice_id": "1006604",
        "posted_on": "2014-02-14",
        "rechtsform": null,
        "sitz": null,
        "url": "https://www.handelsregisterbekanntmachungen.de/en/skripte/hrb.php?rb_id=1006604&land_abk=nw"
    },
    "parsed": {
        "officers": [
            {
                "class": "DismissedManagingDirector",
                "payload": {
                    "city": "Heek",
                    "dismissed": true,
                    "dob": "1975-02-25",
                    "lastname": "Wechsel",
                    "name": "Robert"
                },
                "text": " Wechsel, Robert, Heek, *25.02.1975."
            },
            {
                "class": "DismissedManagingDirector",
                "payload": {
                    "city": "Metelen",
                    "dismissed": true,
                    "dob": "1970-07-29",
                    "lastname": "Wechsel",
                    "name": "Waldemar"
                },
                "text": " Wechsel, Waldemar, Metelen, *29.07.1970."
            },
            {
                "class": "ManagingDirector",
                "payload": {
                    "city": "Heek",
                    "dob": "1972-05-01",
                    "flag": "einzelvertretungsberechtigt mit der Befugnis im Namen der Gesellschaft mit sich im eigenen Namen oder als Vertreter eines Dritten Rechtsgeschäfte abzuschließen",
                    "lastname": "Wechsel",
                    "name": "Sergej"
                },
                "text": " Wechsel, Sergej, Heek, *05.01.1972, einzelvertretungsberechtigt mit der Befugnis im Namen der Gesellschaft mit sich im eigenen Namen oder als Vertreter eines Dritten Rechtsgeschäfte abzuschließen."
            }
        ]
    }
}