{
    "orig": {
        "aktenzeichen": "HRB 36141",
        "amtsgericht": "Köln",
        "event_date": "2014-02-14",
        "event_type": "Veränderungen",
        "federal_state": "nw",
        "full_text": "Amtsgericht Köln Aktenzeichen: HRB 36141 \nBekannt gemacht am: 14.02.2014 19:57 Uhr\n\n\n\n\nIn () gesetzte Angaben der Anschrift und des Geschäftszweiges erfolgen ohne Gewähr.\nVeränderungen\n14.02.2014\n\nHRB 36141:PROLOGUE Consulting GmbH, Köln, Media Park 8, 50670 Köln.Die Gesellschafterversammlung vom 27.12.2013 hat eine Änderung des Gesellschaftsvertrages in § 10 (Wettbewerbsverbot) beschlossen. Nicht mehr Geschäftsführer: Bröhl, Hans-Josef, Rösrath, *25.12.1947. Bestellt als Geschäftsführer: Merkel, Patrick, Hong Kong (SAR), *01.03.1977, einzelvertretungsberechtigt mit der Befugnis im Namen der Gesellschaft mit sich im eigenen Namen oder als Vertreter eines Dritten Rechtsgeschäfte abzuschließen. Nach Änderung der Vertretungsbefugnis nunmehr Geschäftsführer: Schürnpeck, Sven, Hamburg, *10.01.1964, einzelvertretungsberechtigt mit der Befugnis im Namen der Gesellschaft mit sich im eigenen Namen oder als Vertreter eines Dritten Rechtsgeschäfte abzuschließen.",
        "gesellschafter": null,
        "inhaber": null,
        "name": "HRB 36141:PROLOGUE Consulting GmbH",
        "notice_id": "1006353",
        "posted_on": "2014-02-14",
        "rechtsform": null,
        "sitz": null,
        "url": "https://www.handelsregisterbekanntmachungen.de/en/skripte/hrb.php?rb_id=1006353&land_abk=nw"
    },
    "parsed": {
        "officers": [
            {
                "class": "DismissedManagingDirector",
                "payload": {
                    "city": "Rösrath",
                    "dismissed": true,
                    "dob": "1947-12-25",
                    "lastname": "Bröhl",
                    "name": "Hans-Josef"
                },
                "text": " Bröhl, Hans-Josef, Rösrath, *25.12.1947."
            },
            {
                "class": "AppointedManagingDirector",
                "payload": {
                    "city": "Hong Kong (SAR)",
                    "dob": "1977-01-03",
                    "flag": "einzelvertretungsberechtigt mit der Befugnis im Namen der Gesellschaft mit sich im eigenen Namen oder als Vertreter eines Dritten Rechtsgeschäfte abzuschließen",
                    "lastname": "Merkel",
                    "name": "Patrick"
                },
                "text": " Merkel, Patrick, Hong Kong (SAR), *01.03.1977, einzelvertretungsberechtigt mit der Befugnis im Namen der Gesellschaft mit sich im eigenen Namen oder als Vertreter eines Dritten Rechtsgeschäfte abzuschließen."
            },
            {
                "class": "ManagingDirector",
                "payload": {
                    "city": "Hamburg",
                    "dob": "1964-10-01",
                    "flag": "einzelvertretungsberechtigt mit der Befugnis im Namen der Gesellschaft mit sich im eigenen Namen oder als Vertreter eines Dritten Rechtsgeschäfte abzuschließen",
                    "lastname": "Schürnpeck",
                    "name": "Sven"
                },
                "text": " Schürnpeck, Sven, Hamburg, *10.01.1964, einzelvertretungsberechtigt mit der Befugnis im Namen der Gesellschaft mit sich im eigenen Namen oder als Vertreter eines Dritten Rechtsgeschäfte abzuschließen."
            }
        ]
    }
}