{
    "orig": {
        "aktenzeichen": "HRB 3463",
        "amtsgericht": "Bonn",
        "event_date": "2014-02-25",
        "event_type": "Veränderungen",
        "federal_state": "nw",
        "full_text": "Amtsgericht Bonn Aktenzeichen: HRB 3463 \nBekannt gemacht am: 25.02.2014 19:59 Uhr\n\n\n\n\nIn () gesetzte Angaben der Anschrift und des Geschäftszweiges erfolgen ohne Gewähr.\nVeränderungen\n25.02.2014\n\nHRB 3463:Eggers-Scholz GmbH Sanitär-Heizung, Bonn, Dorotheenstr. 17, 53111 Bonn.Nach Änderung der konreten Vertretungsregelung Geschäftsführer: Scholz, Ulrike Waltraut, Troisdorf, *19.07.1966, einzelvertretungsberechtigt mit der Befugnis im Namen der Gesellschaft mit sich im eigenen Namen oder als Vertreter eines Dritten Rechtsgeschäfte abzuschließen. Nach Änderung der konkreten Vertretungsregelung Geschäftsführer: Scholz, Frank, Troisdorf, *07.10.1969, einzelvertretungsberechtigt mit der Befugnis im Namen der Gesellschaft mit sich im eigenen Namen oder als Vertreter eines Dritten Rechtsgeschäfte abzuschließen.",
        "gesellschafter": null,
        "inhaber": null,
        "name": "HRB 3463:Eggers-Scholz GmbH Sanitär-Heizung",
        "notice_id": "1010257",
        "posted_on": "2014-02-25",
        "rechtsform": null,
        "sitz": null,
        "url": "https://www.handelsregisterbekanntmachungen.de/en/skripte/hrb.php?rb_id=1010257&land_abk=nw"
    },
    "parsed": {
        "officers": [
            {
                "class": "ManagingDirector",
                "payload": {
                    "city": "Troisdorf",
                    "dob": "1966-07-19",
                    "flag": "einzelvertretungsberechtigt mit der Befugnis im Namen der Gesellschaft mit sich im eigenen Namen oder als Vertreter eines Dritten Rechtsgeschäfte abzuschließen",
                    "lastname": "Scholz",
                    "name": "Ulrike Waltraut"
                },
                "text": " Scholz , Ulrike Waltraut , Troisdorf , * 19.07.1966 , einzelvertretungsberechtigt mit der Befugnis im Namen der Gesellschaft mit sich im eigenen Namen oder als Vertreter eines Dritten Rechtsgeschäfte abzuschließen ."
            },
            {
                "class": "ManagingDirector",
                "payload": {
                    "city": "Troisdorf",
                    "dob": "1969-07-10",
                    "flag": "einzelvertretungsberechtigt mit der Befugnis im Namen der Gesellschaft mit sich im eigenen Namen oder als Vertreter eines Dritten Rechtsgeschäfte abzuschließen",
                    "lastname": "Scholz",
                    "name": "Frank"
                },
                "text": " Scholz , Frank , Troisdorf , * 07.10.1969 , einzelvertretungsberechtigt mit der Befugnis im Namen der Gesellschaft mit sich im eigenen Namen oder als Vertreter eines Dritten Rechtsgeschäfte abzuschließen ."
            }
        ]
    }
}