{
    "orig": {
        "aktenzeichen": "HRB 13671",
        "amtsgericht": "Bonn",
        "event_date": "2014-03-07",
        "event_type": "Veränderungen",
        "federal_state": "nw",
        "full_text": "Amtsgericht Bonn Aktenzeichen: HRB 13671 \nBekannt gemacht am: 07.03.2014 19:57 Uhr\n\n\n\n\nIn () gesetzte Angaben der Anschrift und des Geschäftszweiges erfolgen ohne Gewähr.\nVeränderungen\n07.03.2014\n\nHRB 13671:Raths am Bürgerhaus GmbH, Rheinbach, Am Bürgerhaus 5, 53359 Rheinbach.Änderung zur Geschäftsanschrift: Weimarer Str. 15, 53359 Rheinbach. Ist nur ein Liquidator bestellt, so vertritt er die Gesellschaft allein. Sind mehrere Liquidatoren bestellt, so wird die Gesellschaft durch die Liquidatoren gemeinsam vertreten. Nicht mehr Geschäftsführer, nunmehr Liquidator: Raths, Heinz Bernd, Rheinbach, *19.09.1948, mit der Befugnis im Namen der Gesellschaft mit sich im eigenen Namen oder als Vertreter eines Dritten Rechtsgeschäfte abzuschließen. Die Gesellschaft ist aufgelöst.",
        "gesellschafter": null,
        "inhaber": null,
        "name": "HRB 13671:Raths am Bürgerhaus GmbH",
        "notice_id": "1013404",
        "posted_on": "2014-03-07",
        "rechtsform": null,
        "sitz": null,
        "url": "https://www.handelsregisterbekanntmachungen.de/en/skripte/hrb.php?rb_id=1013404&land_abk=nw"
    },
    "parsed": {
        "flags": [
            {
                "flag": "ignore_for_now",
                "text": "Die\\ Gesellschaft\\ ist\\ aufgel\\öst\\."
            }
        ],
        "labels": [
            {
                "label": "address",
                "text": " Weimarer Str."
            }
        ],
        "officers": [
            {
                "class": "Liquidator",
                "payload": {
                    "city": "Rheinbach",
                    "dob": "1948-09-19",
                    "flag": "mit der Befugnis im Namen der Gesellschaft mit sich im eigenen Namen oder als Vertreter eines Dritten Rechtsgeschäfte abzuschließen",
                    "lastname": "Raths",
                    "name": "Heinz Bernd"
                },
                "text": " Raths, Heinz Bernd, Rheinbach, *19.09.1948, mit der Befugnis im Namen der Gesellschaft mit sich im eigenen Namen oder als Vertreter eines Dritten Rechtsgeschäfte abzuschließen."
            }
        ]
    }
}