{
    "orig": {
        "aktenzeichen": "HRB 2934",
        "amtsgericht": "Duisburg",
        "event_date": "2014-04-02",
        "event_type": "Veränderungen",
        "federal_state": "nw",
        "full_text": "Amtsgericht Duisburg Aktenzeichen: HRB 2934 \nBekannt gemacht am: 02.04.2014 19:57 Uhr\n\n\n\n\nIn () gesetzte Angaben der Anschrift und des Geschäftszweiges erfolgen ohne Gewähr.\nVeränderungen\n02.04.2014\n\nHRB 2934:Gerhard Giegel Malerbetriebe Gesellschaft mit beschrankter Haftung, Duisburg, Wanheimerstr. 96 - 98, 47053 Duisburg.Änderung zur Geschäftsanschrift: Ruhrorter Str. 84 a, 47059 Duisburg. Nach Änderung der Vertretungsbefugnis weiterhin Geschäftsführer: Müller, Horst, Moers, *09.03.1963, einzelvertretungsberechtigt mit der Befugnis im Namen der Gesellschaft mit sich im eigenen Namen oder als Vertreter eines Dritten Rechtsgeschäfte abzuschließen.",
        "gesellschafter": null,
        "inhaber": null,
        "name": "HRB 2934:Gerhard Giegel Malerbetriebe Gesellschaft mit beschrankter Haftung",
        "notice_id": "1022372",
        "posted_on": "2014-04-02",
        "rechtsform": null,
        "sitz": null,
        "url": "https://www.handelsregisterbekanntmachungen.de/en/skripte/hrb.php?rb_id=1022372&land_abk=nw"
    },
    "parsed": {
        "labels": [
            {
                "label": "address",
                "text": " Ruhrorter Str."
            }
        ],
        "officers": [
            {
                "class": "ManagingDirector",
                "payload": {
                    "city": "Moers",
                    "dob": "1963-03-09",
                    "flag": "einzelvertretungsberechtigt mit der Befugnis im Namen der Gesellschaft mit sich im eigenen Namen oder als Vertreter eines Dritten Rechtsgeschäfte abzuschließen",
                    "lastname": "Müller",
                    "name": "Horst"
                },
                "text": " Müller, Horst, Moers, *09.03.1963, einzelvertretungsberechtigt mit der Befugnis im Namen der Gesellschaft mit sich im eigenen Namen oder als Vertreter eines Dritten Rechtsgeschäfte abzuschließen."
            }
        ]
    }
}