{
    "orig": {
        "aktenzeichen": "HRB 11345",
        "amtsgericht": "Siegburg",
        "event_date": "2014-04-16",
        "event_type": "Veränderungen",
        "federal_state": "nw",
        "full_text": "Amtsgericht Siegburg Aktenzeichen: HRB 11345 \nBekannt gemacht am: 16.04.2014 20:10 Uhr\n\n\n\n\nIn () gesetzte Angaben der Anschrift und des Geschäftszweiges erfolgen ohne Gewähr.\nVeränderungen\n16.04.2014\n\nHRB 11345:VaroTrans GmbH, Troisdorf, Lütticher Straße 12, 53842 Troisdorf.Neuer Geschäftsführer: Banevicius, Giedrius, Bonn, *13.08.1973, einzelvertretungsberechtigt mit der Befugnis im Namen der Gesellschaft mit sich im eigenen Namen oder als Vertreter eines Dritten Rechtsgeschäfte abzuschließen. Nicht mehr Geschäftsführer: Reich, Dimitri, Essen, *09.01.1978; Sarmina, Natalja, Bonn, *24.04.1980.",
        "gesellschafter": null,
        "inhaber": null,
        "name": "HRB 11345:VaroTrans GmbH",
        "notice_id": "1027926",
        "posted_on": "2014-04-16",
        "rechtsform": null,
        "sitz": null,
        "url": "https://www.handelsregisterbekanntmachungen.de/en/skripte/hrb.php?rb_id=1027926&land_abk=nw"
    },
    "parsed": {
        "officers": [
            {
                "class": "ManagingDirector",
                "payload": {
                    "city": "Bonn",
                    "dob": "1973-08-13",
                    "flag": "einzelvertretungsberechtigt mit der Befugnis im Namen der Gesellschaft mit sich im eigenen Namen oder als Vertreter eines Dritten Rechtsgeschäfte abzuschließen",
                    "lastname": "Banevicius",
                    "name": "Giedrius"
                },
                "text": " Banevicius, Giedrius, Bonn, *13.08.1973, einzelvertretungsberechtigt mit der Befugnis im Namen der Gesellschaft mit sich im eigenen Namen oder als Vertreter eines Dritten Rechtsgeschäfte abzuschließen."
            },
            {
                "class": "DismissedManagingDirector",
                "payload": {
                    "city": "Essen",
                    "dismissed": true,
                    "dob": "1978-01-09",
                    "lastname": "Reich",
                    "name": "Dimitri"
                },
                "text": " Reich, Dimitri, Essen, *09.01.1978"
            },
            {
                "class": "DismissedManagingDirector",
                "payload": {
                    "city": "Bonn",
                    "dismissed": true,
                    "dob": "1980-04-24",
                    "lastname": "Sarmina",
                    "name": "Natalja"
                },
                "text": " Sarmina, Natalja, Bonn, *24.04.1980."
            }
        ]
    }
}