{
    "orig": {
        "aktenzeichen": "HRA 2657",
        "amtsgericht": "Düren",
        "event_date": "2014-06-06",
        "event_type": "Veränderungen",
        "federal_state": "nw",
        "full_text": "Amtsgericht Düren Aktenzeichen: HRA 2657 \nBekannt gemacht am: 06.06.2014 20:01 Uhr\n\n\n\n\nIn () gesetzte Angaben der Anschrift und des Geschäftszweiges erfolgen ohne Gewähr.\nVeränderungen\n06.06.2014\n\nHRA 2657:Getränkesupermarkt Akbas KG, Jülich, Aachener Str. 3, 52428 Jülich.Rechtsform geändert, jetzt: Einzelkaufmann. Getränkesupermarkt Akbas e.K. nunmehr Inhaber: Akbas, Bülent, Mönchengladbach, *28.09.1968. Prokura erloschen: Toeller, Alexandra, Duisburg, *08.06.1968. Die Gesellschaft ist aufgelöst und ohne Liquidation beendet. Das Unternehmen wird in der Rechtsform des Einzelkaufmanns fortgeführt.",
        "gesellschafter": null,
        "inhaber": null,
        "name": "HRA 2657:Getränkesupermarkt Akbas KG",
        "notice_id": "1042986",
        "posted_on": "2014-06-06",
        "rechtsform": "Einzelkaufmann",
        "sitz": null,
        "url": "https://www.handelsregisterbekanntmachungen.de/en/skripte/hrb.php?rb_id=1042986&land_abk=nw"
    },
    "parsed": {
        "flags": [
            {
                "flag": "Sole trader",
                "text": "Einzelkaufmann"
            },
            {
                "flag": "Sole trader",
                "text": "Einzelkaufmann"
            }
        ],
        "officers": [
            {
                "class": "Owner",
                "payload": {
                    "city": "Mönchengladbach",
                    "dob": "1968-09-28",
                    "lastname": "Akbas",
                    "name": "Bülent"
                },
                "text": " Akbas, Bülent, Mönchengladbach, *28.09.1968."
            },
            {
                "class": "ProcurationCancelled",
                "payload": {
                    "city": "Duisburg",
                    "dismissed": true,
                    "dob": "1968-08-06",
                    "lastname": "Toeller",
                    "name": "Alexandra"
                },
                "text": " Toeller, Alexandra, Duisburg, *08.06.1968."
            }
        ]
    }
}