{
    "orig": {
        "aktenzeichen": "HRB 14219",
        "amtsgericht": "Münster",
        "event_date": "2014-06-24",
        "event_type": "Veränderungen",
        "federal_state": "nw",
        "full_text": "Amtsgericht Münster Aktenzeichen: HRB 14219 \nBekannt gemacht am: 24.06.2014 20:01 Uhr\n\n\n\n\nIn () gesetzte Angaben der Anschrift und des Geschäftszweiges erfolgen ohne Gewähr.\nVeränderungen\n24.06.2014\n\nHRB 14219:Citibote Briefdienstleistungs GmbH, Münster, Ostmarkstraße 92, 48145 Münster.Bestellt zum Geschäftsführer: Özözen, Ahmet, Münster, *17.03.1976, einzelvertretungsberechtigt mit der Befugnis im Namen der Gesellschaft mit sich im eigenen Namen oder als Vertreter eines Dritten Rechtsgeschäfte abzuschließen. Nicht mehr Geschäftsführer: Korthues, Nadine, Nottuln, *13.08.1983; Röttger, Hermann, Metelen, *12.10.1954.",
        "gesellschafter": null,
        "inhaber": null,
        "name": "HRB 14219:Citibote Briefdienstleistungs GmbH",
        "notice_id": "1047362",
        "posted_on": "2014-06-24",
        "rechtsform": null,
        "sitz": null,
        "url": "https://www.handelsregisterbekanntmachungen.de/en/skripte/hrb.php?rb_id=1047362&land_abk=nw"
    },
    "parsed": {
        "officers": [
            {
                "class": "ManagingDirector",
                "payload": {
                    "city": "Münster",
                    "dob": "1976-03-17",
                    "flag": "einzelvertretungsberechtigt mit der Befugnis im Namen der Gesellschaft mit sich im eigenen Namen oder als Vertreter eines Dritten Rechtsgeschäfte abzuschließen",
                    "lastname": "Özözen",
                    "name": "Ahmet"
                },
                "text": " Özözen, Ahmet, Münster, *17.03.1976, einzelvertretungsberechtigt mit der Befugnis im Namen der Gesellschaft mit sich im eigenen Namen oder als Vertreter eines Dritten Rechtsgeschäfte abzuschließen."
            },
            {
                "class": "DismissedManagingDirector",
                "payload": {
                    "city": "Nottuln",
                    "dismissed": true,
                    "dob": "1983-08-13",
                    "lastname": "Korthues",
                    "name": "Nadine"
                },
                "text": " Korthues, Nadine, Nottuln, *13.08.1983"
            }
        ]
    }
}