{
    "orig": {
        "aktenzeichen": "HRB 59299",
        "amtsgericht": "Düsseldorf",
        "event_date": "2014-07-09",
        "event_type": "Veränderungen",
        "federal_state": "nw",
        "full_text": "Amtsgericht Düsseldorf Aktenzeichen: HRB 59299 \nBekannt gemacht am: 09.07.2014 20:01 Uhr\n\n\n\n\nIn () gesetzte Angaben der Anschrift und des Geschäftszweiges erfolgen ohne Gewähr.\nVeränderungen\n09.07.2014\n\nHRB 59299:SMH Sparkasse Mannesmann Hoffmeister Projektentwicklung Verwaltungsgesellschaft mbH, Düsseldorf, Peter-Müller-Straße 10, 40468 Düsseldorf.Nicht mehr Geschäftsführer: Fleischer, Andreas, Düsseldorf, *05.02.1973. Nach Änderung des Wohnorts Geschäftsführer: Van der Beken, Philippe Marie L., Bonheiden / Belgien, *01.10.1975, mit der Befugnis im Namen der Gesellschaft mit sich im eigenen Namen oder als Vertreter eines Dritten Rechtsgeschäfte abzuschließen.",
        "gesellschafter": null,
        "inhaber": null,
        "name": "HRB 59299:SMH Sparkasse Mannesmann Hoffmeister Projektentwicklung Verwaltungsgesellschaft mbH",
        "notice_id": "1052794",
        "posted_on": "2014-07-09",
        "rechtsform": null,
        "sitz": null,
        "url": "https://www.handelsregisterbekanntmachungen.de/en/skripte/hrb.php?rb_id=1052794&land_abk=nw"
    },
    "parsed": {
        "officers": [
            {
                "class": "DismissedManagingDirector",
                "payload": {
                    "city": "Düsseldorf",
                    "dismissed": true,
                    "dob": "1973-05-02",
                    "lastname": "Fleischer",
                    "name": "Andreas"
                },
                "text": " Fleischer, Andreas, Düsseldorf, *05.02.1973."
            },
            {
                "class": "ManagingDirector",
                "payload": {
                    "city": "Bonheiden / Belgien",
                    "dob": "1975-01-10",
                    "flag": "mit der Befugnis im Namen der Gesellschaft mit sich im eigenen Namen oder als Vertreter eines Dritten Rechtsgeschäfte abzuschließen",
                    "lastname": "Van der Beken",
                    "name": "Philippe Marie L"
                },
                "text": " Van der Beken, Philippe Marie L., Bonheiden / Belgien, *01.10.1975, mit der Befugnis im Namen der Gesellschaft mit sich im eigenen Namen oder als Vertreter eines Dritten Rechtsgeschäfte abzuschließen."
            }
        ]
    }
}