{
    "orig": {
        "aktenzeichen": "HRB 6811",
        "amtsgericht": "Aachen",
        "event_date": "2014-09-10",
        "event_type": "Veränderungen",
        "federal_state": "nw",
        "full_text": "Amtsgericht Aachen Aktenzeichen: HRB 6811 \nBekannt gemacht am: 10.09.2014 20:02 Uhr\n\n\n\n\nIn () gesetzte Angaben der Anschrift und des Geschäftszweiges erfolgen ohne Gewähr.\nVeränderungen\n10.09.2014\n\nHRB 6811:Universal Trends GmbH, Aachen, St.-Jobser-Straße 47, 52146 Würselen.Nicht mehr Geschäftsführer: Abt, Marcus Thomas, Aachen, *01.06.1966. Bestellt als Geschäftsführer: Ruland, Arthur, Dörrenbach, *23.02.1951, mit der Befugnis im Namen der Gesellschaft mit sich im eigenen Namen oder als Vertreter eines Dritten Rechtsgeschäfte abzuschließen. Einzelprokura: Abt, Marcus Thomas, Aachen, *01.06.1966.",
        "gesellschafter": null,
        "inhaber": null,
        "name": "HRB 6811:Universal Trends GmbH",
        "notice_id": "1074182",
        "posted_on": "2014-09-10",
        "rechtsform": null,
        "sitz": null,
        "url": "https://www.handelsregisterbekanntmachungen.de/en/skripte/hrb.php?rb_id=1074182&land_abk=nw"
    },
    "parsed": {
        "officers": [
            {
                "class": "DismissedManagingDirector",
                "payload": {
                    "city": "Aachen",
                    "dismissed": true,
                    "dob": "1966-01-06",
                    "lastname": "Abt",
                    "name": "Marcus Thomas"
                },
                "text": " Abt, Marcus Thomas, Aachen, *01.06.1966."
            },
            {
                "class": "AppointedManagingDirector",
                "payload": {
                    "city": "Dörrenbach",
                    "dob": "1951-02-23",
                    "flag": "mit der Befugnis im Namen der Gesellschaft mit sich im eigenen Namen oder als Vertreter eines Dritten Rechtsgeschäfte abzuschließen",
                    "lastname": "Ruland",
                    "name": "Arthur"
                },
                "text": " Ruland, Arthur, Dörrenbach, *23.02.1951, mit der Befugnis im Namen der Gesellschaft mit sich im eigenen Namen oder als Vertreter eines Dritten Rechtsgeschäfte abzuschließen."
            },
            {
                "class": "SingleProcuration",
                "payload": {
                    "city": "Aachen",
                    "dob": "1966-01-06",
                    "lastname": "Abt",
                    "name": "Marcus Thomas"
                },
                "text": " Abt, Marcus Thomas, Aachen, *01.06.1966."
            }
        ]
    }
}