{
    "orig": {
        "aktenzeichen": "HRB 9912",
        "amtsgericht": "Bad Oeynhausen",
        "event_date": "2014-09-18",
        "event_type": "Veränderungen",
        "federal_state": "nw",
        "full_text": "Amtsgericht Bad Oeynhausen Aktenzeichen: HRB 9912 \nBekannt gemacht am: 18.09.2014 20:01 Uhr\n\n\n\n\nIn () gesetzte Angaben der Anschrift und des Geschäftszweiges erfolgen ohne Gewähr.\nVeränderungen\n18.09.2014\n\nHRB 9912:Overmeer Schifffahrt & Transport GmbH, Pr. Oldendorf, Getmolder Str. 26, 32361 Preußisch Oldendorf.Nach Änderung der konkreten Vertretungsbefugnis weiterhin: Geschäftsführer: Meeusen, Stefanus Pieter, Oudewater / Niederlande, *25.01.1977, einzelvertretungsberechtigt mit der Befugnis im Namen der Gesellschaft mit sich im eigenen Namen oder als Vertreter eines Dritten Rechtsgeschäfte abzuschließen. Die Gesellschaft ist als übertragender Rechtsträger nach Maßgabe des Verschmelzungsvertrages vom 26.08.2014 sowie der Zustimmungsbeschlüsse ihrer Gesellschafterversammlung vom 26.08.2014 und der Gesellschafterversammlung des übernehmenden Rechtsträgers vom 26.08.2014 mit der Niederländische Partikuliere Rheinfahrt-Centrale Gesellschaft mit beschränkter Haftung mit Sitz in Duisburg (Amtsgericht Duisburg HRB 357) verschmolzen. Die Verschmelzung wird erst wirksam mit Eintragung auf dem Registerblatt des übernehmenden Rechtsträgers. Als nicht eingetragen wird bekannt gemacht: Den Gläubigern der an der Verschmelzung beteiligten Rechtsträger ist, wenn sie binnen sechs Monaten nach dem Tag, an dem die Eintragung der Verschmelzung in das Register des Sitzes derjenigen Rechtsträger deren Gläubiger sie sind, nach § 19 Absatz 3 UmwG als bekanntgemacht gilt, ihren Anspruch nach Grund und Höhe schriftlich anmelden, Sicherheit zu leisten, soweit sie nicht Befriedigung verlangen können. Dieses Recht steht den Gläubigern jedoch nur zu, wenn sie glaubhaft machen, dass durch die Verschmelzung die Erfüllung ihrer Forderung gefährdet wird.",
        "gesellschafter": null,
        "inhaber": null,
        "name": "HRB 9912:Overmeer Schifffahrt & Transport GmbH",
        "notice_id": "1076678",
        "posted_on": "2014-09-18",
        "rechtsform": null,
        "sitz": null,
        "url": "https://www.handelsregisterbekanntmachungen.de/en/skripte/hrb.php?rb_id=1076678&land_abk=nw"
    },
    "parsed": {
        "officers": [
            {
                "class": "ManagingDirector",
                "payload": {
                    "city": "Oudewater / Niederlande",
                    "dob": "1977-01-25",
                    "flag": "einzelvertretungsberechtigt mit der Befugnis im Namen der Gesellschaft mit sich im eigenen Namen oder als Vertreter eines Dritten Rechtsgeschäfte abzuschließen",
                    "lastname": "Meeusen",
                    "name": "Stefanus Pieter"
                },
                "text": " Meeusen , Stefanus Pieter , Oudewater / Niederlande , * 25.01.1977 , einzelvertretungsberechtigt mit der Befugnis im Namen der Gesellschaft mit sich im eigenen Namen oder als Vertreter eines Dritten Rechtsgeschäfte abzuschließen ."
            }
        ]
    }
}