{
    "orig": {
        "aktenzeichen": "HRB 16586",
        "amtsgericht": "Neuss",
        "event_date": "2014-10-02",
        "event_type": "Veränderungen",
        "federal_state": "nw",
        "full_text": "Amtsgericht Neuss Aktenzeichen: HRB 16586 \nBekannt gemacht am: 02.10.2014 20:02 Uhr\n\n\n\n\nIn () gesetzte Angaben der Anschrift und des Geschäftszweiges erfolgen ohne Gewähr.\nVeränderungen\n02.10.2014\n\nHRB 16586:Hummel Betriebsgesellschaft Dreizehn GmbH, Neuss, Duisburger Straße 6, 41460 Neuss.Nicht mehr Geschäftsführer: Moonen, Antonius Johannes Joseph - genannt Ton -, Tilburg/Niederlande / Niederlande, *30.08.1958. Bestellt als Geschäftsführer: Goedvolk, Peter Jacob, Rhoon / Niederlande, *09.02.1957, mit der Befugnis im Namen der Gesellschaft mit sich im eigenen Namen oder als Vertreter eines Dritten Rechtsgeschäfte abzuschließen.",
        "gesellschafter": null,
        "inhaber": null,
        "name": "HRB 16586:Hummel Betriebsgesellschaft Dreizehn GmbH",
        "notice_id": "1081341",
        "posted_on": "2014-10-02",
        "rechtsform": null,
        "sitz": null,
        "url": "https://www.handelsregisterbekanntmachungen.de/en/skripte/hrb.php?rb_id=1081341&land_abk=nw"
    },
    "parsed": {
        "officers": [
            {
                "class": "DismissedManagingDirector",
                "payload": {
                    "city": "Tilburg/Niederlande / Niederlande",
                    "dismissed": true,
                    "dob": "1958-08-30",
                    "lastname": "Moonen",
                    "name": "Antonius Johannes Joseph - genannt Ton -"
                },
                "text": " Moonen, Antonius Johannes Joseph - genannt Ton -, Tilburg/Niederlande / Niederlande, *30.08.1958."
            },
            {
                "class": "AppointedManagingDirector",
                "payload": {
                    "city": "Rhoon / Niederlande",
                    "dob": "1957-02-09",
                    "flag": "mit der Befugnis im Namen der Gesellschaft mit sich im eigenen Namen oder als Vertreter eines Dritten Rechtsgeschäfte abzuschließen",
                    "lastname": "Goedvolk",
                    "name": "Peter Jacob"
                },
                "text": " Goedvolk, Peter Jacob, Rhoon / Niederlande, *09.02.1957, mit der Befugnis im Namen der Gesellschaft mit sich im eigenen Namen oder als Vertreter eines Dritten Rechtsgeschäfte abzuschließen."
            }
        ]
    }
}