{
    "orig": {
        "aktenzeichen": "HRB 10507",
        "amtsgericht": "Köln",
        "event_date": "2014-10-14",
        "event_type": "Veränderungen",
        "federal_state": "nw",
        "full_text": "Amtsgericht Köln Aktenzeichen: HRB 10507 \nBekannt gemacht am: 14.10.2014 20:00 Uhr\n\n\n\n\nIn () gesetzte Angaben der Anschrift und des Geschäftszweiges erfolgen ohne Gewähr.\nVeränderungen\n14.10.2014\n\nHRB 10507:Rasch GmbH, Köln, Mathias-Brüggen-Str. 9, 50827 Köln.Die Gesellschafterversammlung vom 08.08./20.08.2014 hat beschlossen, das Stammkapital auf Euro umzustellen, es von dann EUR 28.121,05 um EUR 28.138,95 auf EUR 56.260,00 zu erhöhen und den Gesellschaftsvertrag in § 3 (Stammkapital, Stammeinlagen) vollständig neuzufassen. Desweiteren wurde der Gesellschaftsvertrag in § 5 Abs. 3 (Gesellschafterbeschlüsse) neugefasst; § 9 (Erbfolge) wurde ersatzlos gestrichen und die nachfolgenden Paragraphen in ihrer Numerierung angepasst. Die früheren § 10, jetzt 9 (Einziehung von Geschäftsanteilen) und § 11, jetzt 10 (Entgelt) des Gesellschaftsvertrages wurden geändert. 56.260,00 EUR. Bestellt als Geschäftsführer: Buchalik, Robert, Düsseldorf, *08.07.1952, einzelvertretungsberechtigt mit der Befugnis im Namen der Gesellschaft mit sich im eigenen Namen oder als Vertreter eines Dritten Rechtsgeschäfte abzuschließen.",
        "gesellschafter": null,
        "inhaber": null,
        "name": "HRB 10507:Rasch GmbH",
        "notice_id": "1084521",
        "posted_on": "2014-10-14",
        "rechtsform": null,
        "sitz": null,
        "url": "https://www.handelsregisterbekanntmachungen.de/en/skripte/hrb.php?rb_id=1084521&land_abk=nw"
    },
    "parsed": {
        "officers": [
            {
                "class": "ManagingDirector",
                "payload": {
                    "city": "Düsseldorf",
                    "dob": "1952-08-07",
                    "flag": "einzelvertretungsberechtigt mit der Befugnis im Namen der Gesellschaft mit sich im eigenen Namen oder als Vertreter eines Dritten Rechtsgeschäfte abzuschließen",
                    "lastname": "Buchalik",
                    "name": "Robert"
                },
                "text": " Buchalik , Robert , Düsseldorf , * 08.07.1952 , einzelvertretungsberechtigt mit der Befugnis im Namen der Gesellschaft mit sich im eigenen Namen oder als Vertreter eines Dritten Rechtsgeschäfte abzuschließen ."
            }
        ]
    }
}