{
    "orig": {
        "aktenzeichen": "HRB 21641",
        "amtsgericht": "Düsseldorf",
        "event_date": "2014-10-22",
        "event_type": "Veränderungen",
        "federal_state": "nw",
        "full_text": "Amtsgericht Düsseldorf Aktenzeichen: HRB 21641 \nBekannt gemacht am: 22.10.2014 20:05 Uhr\n\n\n\n\nIn () gesetzte Angaben der Anschrift und des Geschäftszweiges erfolgen ohne Gewähr.\nVeränderungen\n22.10.2014\n\nHRB 21641: Duferco Deutschland GmbH, Ratingen, Eutelis-Platz 2, 40878 Ratingen. Nicht mehr Geschäftsführer: Melamed, Marko, Lugano/Schweiz, *13.04.1948. Bestellt als Geschäftsführer: Pryor, Martin Thomas, Oberägeri / Schweiz, *20.12.1952, einzelvertretungsberechtigt mit der Befugnis im Namen der Gesellschaft mit sich im eigenen Namen oder als Vertreter eines Dritten Rechtsgeschäfte abzuschließen.",
        "gesellschafter": null,
        "inhaber": null,
        "name": "HRB 21641: Duferco Deutschland GmbH",
        "notice_id": "1086831",
        "posted_on": "2014-10-22",
        "rechtsform": null,
        "sitz": null,
        "url": "https://www.handelsregisterbekanntmachungen.de/en/skripte/hrb.php?rb_id=1086831&land_abk=nw"
    },
    "parsed": {
        "officers": [
            {
                "class": "DismissedManagingDirector",
                "payload": {
                    "city": "Lugano/Schweiz",
                    "dismissed": true,
                    "dob": "1948-04-13",
                    "lastname": "Melamed",
                    "name": "Marko"
                },
                "text": " Melamed, Marko, Lugano/Schweiz, *13.04.1948."
            },
            {
                "class": "AppointedManagingDirector",
                "payload": {
                    "city": "Oberägeri / Schweiz",
                    "dob": "1952-12-20",
                    "flag": "einzelvertretungsberechtigt mit der Befugnis im Namen der Gesellschaft mit sich im eigenen Namen oder als Vertreter eines Dritten Rechtsgeschäfte abzuschließen",
                    "lastname": "Pryor",
                    "name": "Martin Thomas"
                },
                "text": " Pryor, Martin Thomas, Oberägeri / Schweiz, *20.12.1952, einzelvertretungsberechtigt mit der Befugnis im Namen der Gesellschaft mit sich im eigenen Namen oder als Vertreter eines Dritten Rechtsgeschäfte abzuschließen."
            }
        ]
    }
}