{
    "orig": {
        "aktenzeichen": "HRB 1247",
        "amtsgericht": "Siegburg",
        "event_date": "2014-10-23",
        "event_type": "Veränderungen",
        "federal_state": "nw",
        "full_text": "Amtsgericht Siegburg Aktenzeichen: HRB 1247 \nBekannt gemacht am: 23.10.2014 20:00 Uhr\n\n\n\n\nIn () gesetzte Angaben der Anschrift und des Geschäftszweiges erfolgen ohne Gewähr.\nVeränderungen\n23.10.2014\n\nHRB 1247: Buchdruckerei Peter Meier GmbH, Hennef, Reisertstraße 14, 53773 Hennef. Änderung zur Geschäftsanschrift: Bonner Straße 25 B, 53773 Hennef. Die Gesellschaft ist durch Gesellschafterbeschluss vom 14.10.2014 mit sofortiger Wirkung aufgelöst. Ist nur ein Liquidator bestellt, so vertritt er die Gesellschaft allein. Sind mehrere Liquidatoren bestellt, so wird die Gesellschaft durch zwei Liquidatoren oder durch einen Liquidator gemeinsam mit einem Prokuristen vertreten. Nicht mehr Geschäftsführer, nunmehr Liquidator: Hundenborn, Christa, Hennef, *18.11.1951, einzelvertretungsberechtigt mit der Befugnis im Namen der Gesellschaft mit sich im eigenen Namen oder als Vertreter eines Dritten Rechtsgeschäfte abzuschließen.",
        "gesellschafter": null,
        "inhaber": null,
        "name": "HRB 1247: Buchdruckerei Peter Meier GmbH",
        "notice_id": "1087336",
        "posted_on": "2014-10-23",
        "rechtsform": null,
        "sitz": null,
        "url": "https://www.handelsregisterbekanntmachungen.de/en/skripte/hrb.php?rb_id=1087336&land_abk=nw"
    },
    "parsed": {
        "addresses": [
            {
                "kls": "Address",
                "text": "Bonner Straße 25 B, 53773 Hennef"
            }
        ],
        "officers": [
            {
                "class": "Liquidator",
                "payload": {
                    "city": "Hennef",
                    "dob": "1951-11-18",
                    "flag": "einzelvertretungsberechtigt mit der Befugnis im Namen der Gesellschaft mit sich im eigenen Namen oder als Vertreter eines Dritten Rechtsgeschäfte abzuschließen",
                    "lastname": "Hundenborn",
                    "name": "Christa"
                },
                "text": " Hundenborn, Christa, Hennef, *18.11.1951, einzelvertretungsberechtigt mit der Befugnis im Namen der Gesellschaft mit sich im eigenen Namen oder als Vertreter eines Dritten Rechtsgeschäfte abzuschließen."
            }
        ]
    }
}