{
    "orig": {
        "aktenzeichen": "HRB 64560",
        "amtsgericht": "Düsseldorf",
        "event_date": "2014-10-27",
        "event_type": "Veränderungen",
        "federal_state": "nw",
        "full_text": "Amtsgericht Düsseldorf Aktenzeichen: HRB 64560 \nBekannt gemacht am: 27.10.2014 20:00 Uhr\n\n\n\n\nIn () gesetzte Angaben der Anschrift und des Geschäftszweiges erfolgen ohne Gewähr.\nVeränderungen\n27.10.2014\n\nHRB 64560: EnDC Development GmbH, Langenfeld, Solinger Straße 41, 40764 Langenfeld. Die Gesellschafterversammlung vom 21.10.2014 hat eine Änderung des Gesellschaftsvertrages in § 1 Abs. 1 und damit der Firma beschlossen. Neue Firma: GeTeC Gebäude Technologie Center GmbH. Nicht mehr Geschäftsführer: Prüter, Dirk, Bad Neuenahr-Ahrweiler, *28.10.1970. Bestellt als Geschäftsführer: Zetzmann, Sascha Paul, Monheim, *06.07.1971, einzelvertretungsberechtigt mit der Befugnis im Namen der Gesellschaft mit sich im eigenen Namen oder als Vertreter eines Dritten Rechtsgeschäfte abzuschließen.",
        "gesellschafter": null,
        "inhaber": null,
        "name": "HRB 64560: EnDC Development GmbH",
        "notice_id": "1088293",
        "posted_on": "2014-10-27",
        "rechtsform": null,
        "sitz": null,
        "url": "https://www.handelsregisterbekanntmachungen.de/en/skripte/hrb.php?rb_id=1088293&land_abk=nw"
    },
    "parsed": {
        "officers": [
            {
                "class": "DismissedManagingDirector",
                "payload": {
                    "city": "Bad Neuenahr-Ahrweiler",
                    "dismissed": true,
                    "dob": "1970-10-28",
                    "lastname": "Prüter",
                    "name": "Dirk"
                },
                "text": " Prüter, Dirk, Bad Neuenahr-Ahrweiler, *28.10.1970."
            },
            {
                "class": "AppointedManagingDirector",
                "payload": {
                    "city": "Monheim",
                    "dob": "1971-07-06",
                    "flag": "einzelvertretungsberechtigt mit der Befugnis im Namen der Gesellschaft mit sich im eigenen Namen oder als Vertreter eines Dritten Rechtsgeschäfte abzuschließen",
                    "lastname": "Zetzmann",
                    "name": "Sascha Paul"
                },
                "text": " Zetzmann, Sascha Paul, Monheim, *06.07.1971, einzelvertretungsberechtigt mit der Befugnis im Namen der Gesellschaft mit sich im eigenen Namen oder als Vertreter eines Dritten Rechtsgeschäfte abzuschließen."
            }
        ]
    }
}