{
    "orig": {
        "aktenzeichen": "HRB 5135",
        "amtsgericht": "Hagen",
        "event_date": "2014-10-30",
        "event_type": "Veränderungen",
        "federal_state": "nw",
        "full_text": "Amtsgericht Hagen Aktenzeichen: HRB 5135 \nBekannt gemacht am: 30.10.2014 20:01 Uhr\n\n\n\n\nIn () gesetzte Angaben der Anschrift und des Geschäftszweiges erfolgen ohne Gewähr.\nVeränderungen\n30.10.2014\n\nHRB 5135: Dipl.-Ing. Heinz Geisler everplay-Allwettersportbeläge GmbH, Wetter (Ruhr), Am Hilligloh 2, 58300 Wetter. Nicht mehr Geschäftsführer: Geisler, Ingrid, Sprockhövel, *28.11.1947. Bestellt zum Geschäftsführer: Karaca, Islam, Dortmund, *01.04.1970, einzelvertretungsberechtigt mit der Befugnis im Namen der Gesellschaft mit sich im eigenen Namen oder als Vertreter eines Dritten Rechtsgeschäfte abzuschließen.",
        "gesellschafter": null,
        "inhaber": null,
        "name": "HRB 5135: Dipl.-Ing. Heinz Geisler everplay-Allwettersportbeläge GmbH",
        "notice_id": "1089732",
        "posted_on": "2014-10-30",
        "rechtsform": null,
        "sitz": null,
        "url": "https://www.handelsregisterbekanntmachungen.de/en/skripte/hrb.php?rb_id=1089732&land_abk=nw"
    },
    "parsed": {
        "officers": [
            {
                "class": "DismissedManagingDirector",
                "payload": {
                    "city": "Sprockhövel",
                    "dismissed": true,
                    "dob": "1947-11-28",
                    "lastname": "Geisler",
                    "name": "Ingrid"
                },
                "text": " Geisler, Ingrid, Sprockhövel, *28.11.1947."
            },
            {
                "class": "ManagingDirector",
                "payload": {
                    "city": "Dortmund",
                    "dob": "1970-04-01",
                    "flag": "einzelvertretungsberechtigt mit der Befugnis im Namen der Gesellschaft mit sich im eigenen Namen oder als Vertreter eines Dritten Rechtsgeschäfte abzuschließen",
                    "lastname": "Karaca",
                    "name": "Islam"
                },
                "text": " Karaca, Islam, Dortmund, *01.04.1970, einzelvertretungsberechtigt mit der Befugnis im Namen der Gesellschaft mit sich im eigenen Namen oder als Vertreter eines Dritten Rechtsgeschäfte abzuschließen."
            }
        ]
    }
}