{
    "orig": {
        "aktenzeichen": "HRB 44581",
        "amtsgericht": "Hamburg",
        "event_date": "2010-05-28",
        "event_type": "Veränderungen",
        "federal_state": "hh",
        "full_text": "Amtsgericht Hamburg Aktenzeichen: HRB 44581 \nBekannt gemacht am: 31.05.2010 12:00 Uhr\n\n\n\n\nIn () gesetzte Angaben der Anschrift und des Geschäftszweiges erfolgen ohne Gewähr.\nVeränderungen\n28.05.2010\n\nPRODUCTA DIRECT Service für Druck und Werbemittel- Produktion GmbH, Hamburg, Borsteler Chaussee 51, 22453 Hamburg.Die Gesellschafterversammlung vom 30.04.2010 hat die Änderung des Gesellschaftsvertrages in den §§ 1 Abs. 1 (Firma), 2 (Gegenstand) und 6 sowie die ersatzlose Aufhebung der §§ 7 und 7a beschlossen. Die bisherigen §§ 8 und 9 sind nunmehr §§ 7 und 8. Neue Firma: RAPP Strategy GmbH. Geschäftsanschrift: Grüner Deich 1, 20097 Hamburg. Neuer Unternehmensgegenstand: die Beratung bei und die Entwicklung von datengetriebenen Marketinglösungen mit einem Schwerpunkt auf der direkten Beziehung zu Kunden. Vorname berichtigt, nun Geschäftsführer: Schilling, Phillip, Hamburg, *21.03.1968, vertretungsberechtigt gemeinsam mit einem anderen Geschäftsführer oder einem Prokuristen. Gesamtprokura gemeinsam mit einem Geschäftsführer: Feltin, Gernot, Berlin, *06.03.1967.",
        "gesellschafter": null,
        "inhaber": null,
        "name": "PRODUCTA DIRECT Service für Druck und Werbemittel- Produktion GmbH",
        "notice_id": "111272",
        "posted_on": "2010-05-31",
        "rechtsform": null,
        "sitz": null,
        "url": "https://www.handelsregisterbekanntmachungen.de/en/skripte/hrb.php?rb_id=111272&land_abk=hh"
    },
    "parsed": {
        "labels": [
            {
                "label": "address",
                "text": " Grüner Deich 1, 20097 Hamburg."
            }
        ],
        "officers": [
            {
                "class": "ManagingDirector",
                "payload": {
                    "city": "Hamburg",
                    "dob": "1968-03-21",
                    "flag": "vertretungsberechtigt gemeinsam mit einem anderen Geschäftsführer oder einem Prokuristen",
                    "lastname": "Schilling",
                    "name": "Phillip"
                },
                "text": " Schilling, Phillip, Hamburg, *21.03.1968, vertretungsberechtigt gemeinsam mit einem anderen Geschäftsführer oder einem Prokuristen."
            },
            {
                "class": "ManagingDirector",
                "payload": {
                    "city": "Berlin",
                    "dob": "1967-06-03",
                    "lastname": "Feltin",
                    "name": "Gernot"
                },
                "text": " Feltin, Gernot, Berlin, *06.03.1967."
            }
        ]
    }
}