{
    "orig": {
        "aktenzeichen": "HRB 18396",
        "amtsgericht": "Bonn",
        "event_date": "2015-01-08",
        "event_type": "Veränderungen",
        "federal_state": "nw",
        "full_text": "Amtsgericht Bonn Aktenzeichen: HRB 18396 \nBekannt gemacht am: 08.01.2015 20:01 Uhr\n\n\n\n\nIn () gesetzte Angaben der Anschrift und des Geschäftszweiges erfolgen ohne Gewähr.\nVeränderungen\n08.01.2015\n\nHRB 18396: TKKGe - Therapiezentrum für Kommunikationsstörungen KölnBonn Gemeinnützige GmbH, Bonn, Venner Straße 20, 53177 Bonn. Die Gesellschafterversammlung vom 29.12.2014 hat eine Änderung des Gesellschaftsvertrages in § 6 (Vertretung der Gesellschaft) Abs.1 beschlossen. Die Gesellschaft hat mindestens zwei Geschäftsführer. Alle Geschäftsführer vertreten die Gesellschaft gemeinsam. Bestellt zum Geschäftsführer: Konitz, Achim, Bonn, *14.11.1962; Sammet, Christiane, Bonn, *25.06.1965, jeweils einzelvertretungsberechtigt.",
        "gesellschafter": null,
        "inhaber": null,
        "name": "HRB 18396: TKKGe - Therapiezentrum für Kommunikationsstörungen KölnBonn Gemeinnützige GmbH",
        "notice_id": "1113563",
        "posted_on": "2015-01-08",
        "rechtsform": null,
        "sitz": null,
        "url": "https://www.handelsregisterbekanntmachungen.de/en/skripte/hrb.php?rb_id=1113563&land_abk=nw"
    },
    "parsed": {
        "officers": [
            {
                "class": "ManagingDirector",
                "payload": {
                    "city": "Bonn",
                    "dob": "1962-11-14",
                    "lastname": "Konitz",
                    "name": "Achim"
                },
                "text": " Konitz, Achim, Bonn, *14.11.1962"
            },
            {
                "class": "ManagingDirector",
                "payload": {
                    "city": "Bonn",
                    "dob": "1965-06-25",
                    "flag": "jeweils einzelvertretungsberechtigt",
                    "lastname": "Sammet",
                    "name": "Christiane"
                },
                "text": " Sammet, Christiane, Bonn, *25.06.1965, jeweils einzelvertretungsberechtigt."
            }
        ]
    }
}