{
    "orig": {
        "aktenzeichen": "HRA 1529",
        "amtsgericht": "Memmingen",
        "event_date": "2006-08-02",
        "event_type": "Veränderungen",
        "federal_state": "by",
        "full_text": "Amtsgericht Memmingen Aktenzeichen: HRA 1529 \nBekannt gemacht am: 03.08.2006 07:06 Uhr\n\n\n\n\nDie in ( ) gesetzten Angaben zur Geschäftsanschrift und des Geschäftszweiges erfogen ohne Gewähr.\nVeränderungen\n02.08.2006\n\nMichael Zink, Burgau (Siemensstr. 9, 89331 Burgau). Firma geändert, nun: Walter Zink Nachfolger e.K. Die Inhaber handeln in Gesamthandsgemeinschaft. Inhaber in Erbengemeinschaft: Zink, Peter Walter, Burgau-Kleinanhausen, *22.12.1965; Zink, Gabriele Maria, Schleswig, *22.10.1967; Zink, Walter Erich, Schmerikon (Schweiz), *02.09.1972; Zink-Muthig, Christine, Fürth-Ronhof, *06.10.1964. Nicht mehr Inhaber: Zink, Walter, Maschinenbauingenieur, Burgau.",
        "gesellschafter": null,
        "inhaber": null,
        "name": "Michael Zink",
        "notice_id": "112057",
        "posted_on": "2006-08-03",
        "rechtsform": null,
        "sitz": null,
        "url": "https://www.handelsregisterbekanntmachungen.de/en/skripte/hrb.php?rb_id=112057&land_abk=by"
    },
    "parsed": {
        "officers": [
            {
                "class": "NotLongerOwner",
                "payload": {
                    "city": "Burgau",
                    "dismissed": true,
                    "lastname": "Zink",
                    "name": "Walter",
                    "position": "Maschinenbauingenieur"
                },
                "text": " Zink, Walter, Maschinenbauingenieur, Burgau."
            }
        ]
    }
}