{
    "orig": {
        "aktenzeichen": "HRB 16411",
        "amtsgericht": "Moenchengladbach",
        "event_date": "2015-02-03",
        "event_type": "Neueintragungen",
        "federal_state": "nw",
        "full_text": "Amtsgericht Moenchengladbach Aktenzeichen: HRB 16411 \nBekannt gemacht am: 03.02.2015 20:01 Uhr\n\n\n\n\nIn () gesetzte Angaben der Anschrift und des Geschäftszweiges erfolgen ohne Gewähr.\nNeueintragungen\n03.02.2015\n\nHRB 16411: Krosch & Hönings Verwaltungs GmbH, Niederkrüchten, An der Beek 255, 41372 Niederkrüchten. Gesellschaft mit beschränkter Haftung. Gesellschaftsvertrag vom 14.01.2009, geändert am 16.12.2014. Die Gesellschafterversammlung vom 16.12.2014 hat die Änderung des Gesellschaftsvertrages in § 1 Ziffer 2 (Sitz) und mit ihr die Sitzverlegung von Brüggen (bisher Amtsgericht Krefeld HR B 12275) nach Niederkrüchten beschlossen. Geschäftsanschrift: An der Beek 255, 41372 Niederkrüchten. Gegenstand: der Erwerb und die Verwaltung von Beteiligungen sowie die Übernahme der persönlichen Haftung und der Geschäftsführung bei Handelsgesellschaften, insbesondere die Beteiligung als persönlich haftender geschäftsführender Gesellschafter an der Kommanditgesellschaft unter der Firma Krosch & Hönings GmbH & Co. KG, welche den Handel und die Reparatur von Flurförderzeugen zum Gegenstand hat. Stammkapital: 25.000,00 EUR. Allgemeine Vertretungsregelung: Die Gesellschaft hat einen oder mehrere Geschäftsführer. Ist nur ein Geschäftsführer vorhanden, so vertritt dieser die Gesellschaft allein. Sind mehrere Geschäftsführer bestellt, so wird die Gesellschaft durch zwei Geschäftsführer gemeinschaftlich oder durch einen Geschäftsführer zusammen mit einem Prokuristen vertreten. Durch Beschluss der Gesellschafterversammlung kann einzelnen oder mehreren Geschäftsführern Einzelvertretungsbefugnis sowie Befreiung von den Beschränkungen des § 181 BGB erteilt werden. Geschäftsführer: Hönings, Wolfgang, Neuss, *20.07.1953; Krosch, Rafael, Solingen, *06.10.1964, jeweils einzelvertretungsberechtigt mit der Befugnis im Namen der Gesellschaft mit sich im eigenen Namen oder als Vertreter eines Dritten Rechtsgeschäfte abzuschließen.",
        "gesellschafter": null,
        "inhaber": null,
        "name": "HRB 16411: Krosch & Hönings Verwaltungs GmbH",
        "notice_id": "1124287",
        "posted_on": "2015-02-03",
        "rechtsform": null,
        "sitz": null,
        "url": "https://www.handelsregisterbekanntmachungen.de/en/skripte/hrb.php?rb_id=1124287&land_abk=nw"
    },
    "parsed": {
        "addresses": [
            {
                "kls": "Address",
                "text": "An der Beek 255, 41372 Niederkrüchten"
            }
        ],
        "flags": [
            {
                "flag": "Company with limited liability.",
                "text": "Gesellschaft\\ mit\\ beschr\\änkter\\ Haftung\\."
            }
        ],
        "notices": [
            {
                "court": "Krefeld",
                "from": "Brüggen",
                "hrb": "HR B 12275",
                "registration": "predecessor",
                "registration_conflict": true,
                "text": " von Brüggen (bisher Amtsgericht Krefeld HR B 12275) nach Niederkrüchten beschlossen.",
                "to": "Niederkrüchten",
                "used_regex": "court_regex, from_hrb_to_regex"
            }
        ],
        "officers": [
            {
                "class": "ManagingDirector",
                "payload": {
                    "city": "Neuss",
                    "dob": "1953-07-20",
                    "lastname": "Hönings",
                    "name": "Wolfgang"
                },
                "text": " Hönings, Wolfgang, Neuss, *20.07.1953"
            },
            {
                "class": "ManagingDirector",
                "payload": {
                    "city": "Solingen",
                    "dob": "1964-10-06",
                    "flag": "jeweils einzelvertretungsberechtigt mit der Befugnis im Namen der Gesellschaft mit sich im eigenen Namen oder als Vertreter eines Dritten Rechtsgeschäfte abzuschließen",
                    "lastname": "Krosch",
                    "name": "Rafael"
                },
                "text": " Krosch, Rafael, Solingen, *06.10.1964, jeweils einzelvertretungsberechtigt mit der Befugnis im Namen der Gesellschaft mit sich im eigenen Namen oder als Vertreter eines Dritten Rechtsgeschäfte abzuschließen."
            }
        ]
    }
}