{
    "orig": {
        "aktenzeichen": "HRB 15657",
        "amtsgericht": "Moenchengladbach",
        "event_date": "2015-03-05",
        "event_type": "Veränderungen",
        "federal_state": "nw",
        "full_text": "Amtsgericht Moenchengladbach Aktenzeichen: HRB 15657 \nBekannt gemacht am: 05.03.2015 20:02 Uhr\n\n\n\n\nIn () gesetzte Angaben der Anschrift und des Geschäftszweiges erfolgen ohne Gewähr.\nVeränderungen\n05.03.2015\n\nHRB 15657: L+F Mönchengladbach GmbH, Mönchengladbach, Ungermannsweg 19, 41169 Mönchengladbach. Die Gesellschafterversammlung vom 19.01.2015 hat die Änderung der Firma und des Unternehmensgegenstandes sowie die Änderung des Gesellschaftsvertrages in § 1 Abs. 1 (Firma) und in § 2 Abs. 1 (Gegenstand des Unternehmens) beschlossen. Neue Firma: purino Dienstleistungen GmbH. Neuer Unternehmensgegenstand: die Übernahme von Verwaltungs- und Beratungsdienstleistungen für Restaurantbetriebe. Nicht mehr Geschäftsführer: Kabashi, Sabit, Mönchengladbach, *16.03.1971. Bestellt als Geschäftsführer: Klix, Frank Martin, Viersen, *26.06.1961, einzelvertretungsberechtigt mit der Befugnis im Namen der Gesellschaft mit sich im eigenen Namen oder als Vertreter eines Dritten Rechtsgeschäfte abzuschließen.",
        "gesellschafter": null,
        "inhaber": null,
        "name": "HRB 15657: L+F Mönchengladbach GmbH",
        "notice_id": "1135258",
        "posted_on": "2015-03-05",
        "rechtsform": null,
        "sitz": null,
        "url": "https://www.handelsregisterbekanntmachungen.de/en/skripte/hrb.php?rb_id=1135258&land_abk=nw"
    },
    "parsed": {
        "officers": [
            {
                "class": "DismissedManagingDirector",
                "payload": {
                    "city": "Mönchengladbach",
                    "dismissed": true,
                    "dob": "1971-03-16",
                    "lastname": "Kabashi",
                    "name": "Sabit"
                },
                "text": " Kabashi, Sabit, Mönchengladbach, *16.03.1971."
            },
            {
                "class": "AppointedManagingDirector",
                "payload": {
                    "city": "Viersen",
                    "dob": "1961-06-26",
                    "flag": "einzelvertretungsberechtigt mit der Befugnis im Namen der Gesellschaft mit sich im eigenen Namen oder als Vertreter eines Dritten Rechtsgeschäfte abzuschließen",
                    "lastname": "Klix",
                    "name": "Frank Martin"
                },
                "text": " Klix, Frank Martin, Viersen, *26.06.1961, einzelvertretungsberechtigt mit der Befugnis im Namen der Gesellschaft mit sich im eigenen Namen oder als Vertreter eines Dritten Rechtsgeschäfte abzuschließen."
            }
        ]
    }
}