{
    "orig": {
        "aktenzeichen": "HRB 4082",
        "amtsgericht": "Bad Kreuznach",
        "event_date": "2006-05-04",
        "event_type": "Veränderungen",
        "federal_state": "rp",
        "full_text": "Amtsgericht Bad Kreuznach Aktenzeichen: HRB 4082 \nBekannt gemacht am: 06.06.2006 07:05 Uhr\n\n\n\n\nDie in () gesetzten Angaben der Geschäftsanschrift und des Unternehmensgegenstandes erfolgen ohne Gewähr.\nVeränderungen\n04.05.2006\n\nEM Anlagenbau Verwaltungsgesellschaft mit beschränkter Haftung, Buch (Kirchweg 8, 56290 Buch). Nicht mehr Geschäftsführer: Engel, Hermann, Armsheim, *20.06.1955. Bestellt als Geschäftsführer: Nick, Robert, Buch-Mörz, *01.10.1962, einzelvertretungsberechtigt mit der Befugnis im Namen der Gesellschaft mit sich im eigenen Namen oder als Vertreter eines Dritten Rechtsgeschäfte abzuschließen.",
        "gesellschafter": null,
        "inhaber": null,
        "name": "EM Anlagenbau Verwaltungsgesellschaft mit beschränkter Haftung",
        "notice_id": "11389",
        "posted_on": "2006-06-06",
        "rechtsform": null,
        "sitz": null,
        "url": "https://www.handelsregisterbekanntmachungen.de/en/skripte/hrb.php?rb_id=11389&land_abk=rp"
    },
    "parsed": {
        "officers": [
            {
                "class": "DismissedManagingDirector",
                "payload": {
                    "city": "Armsheim",
                    "dismissed": true,
                    "dob": "1955-06-20",
                    "lastname": "Engel",
                    "name": "Hermann"
                },
                "text": " Engel, Hermann, Armsheim, *20.06.1955."
            },
            {
                "class": "AppointedManagingDirector",
                "payload": {
                    "city": "Buch-Mörz",
                    "dob": "1962-10-01",
                    "flag": "einzelvertretungsberechtigt mit der Befugnis im Namen der Gesellschaft mit sich im eigenen Namen oder als Vertreter eines Dritten Rechtsgeschäfte abzuschließen",
                    "lastname": "Nick",
                    "name": "Robert"
                },
                "text": " Nick, Robert, Buch-Mörz, *01.10.1962, einzelvertretungsberechtigt mit der Befugnis im Namen der Gesellschaft mit sich im eigenen Namen oder als Vertreter eines Dritten Rechtsgeschäfte abzuschließen."
            }
        ]
    }
}