{
    "orig": {
        "aktenzeichen": "HRB 8888",
        "amtsgericht": "Moenchengladbach",
        "event_date": "2015-03-23",
        "event_type": "Veränderungen",
        "federal_state": "nw",
        "full_text": "Amtsgericht Moenchengladbach Aktenzeichen: HRB 8888 \nBekannt gemacht am: 23.03.2015 20:00 Uhr\n\n\n\n\nIn () gesetzte Angaben der Anschrift und des Geschäftszweiges erfolgen ohne Gewähr.\nVeränderungen\n23.03.2015\n\nHRB 8888: Hans Wortmann Verwaltung GmbH, Erkelenz, Aachener Straße 75, 41812 Erkelenz. Nicht mehr Geschäftsführer: Wortmann, Johannes, Geilenkirchen, *14.02.1965. Bestellt als Geschäftsführer: Wortmann, Kornelia, Erkelenz, *12.09.1963, einzelvertretungsberechtigt mit der Befugnis im Namen der Gesellschaft mit sich im eigenen Namen oder als Vertreter eines Dritten Rechtsgeschäfte abzuschließen.",
        "gesellschafter": null,
        "inhaber": null,
        "name": "HRB 8888: Hans Wortmann Verwaltung GmbH",
        "notice_id": "1141283",
        "posted_on": "2015-03-23",
        "rechtsform": null,
        "sitz": null,
        "url": "https://www.handelsregisterbekanntmachungen.de/en/skripte/hrb.php?rb_id=1141283&land_abk=nw"
    },
    "parsed": {
        "officers": [
            {
                "class": "DismissedManagingDirector",
                "payload": {
                    "city": "Geilenkirchen",
                    "dismissed": true,
                    "dob": "1965-02-14",
                    "lastname": "Wortmann",
                    "name": "Johannes"
                },
                "text": " Wortmann, Johannes, Geilenkirchen, *14.02.1965."
            },
            {
                "class": "AppointedManagingDirector",
                "payload": {
                    "city": "Erkelenz",
                    "dob": "1963-12-09",
                    "flag": "einzelvertretungsberechtigt mit der Befugnis im Namen der Gesellschaft mit sich im eigenen Namen oder als Vertreter eines Dritten Rechtsgeschäfte abzuschließen",
                    "lastname": "Wortmann",
                    "name": "Kornelia"
                },
                "text": " Wortmann, Kornelia, Erkelenz, *12.09.1963, einzelvertretungsberechtigt mit der Befugnis im Namen der Gesellschaft mit sich im eigenen Namen oder als Vertreter eines Dritten Rechtsgeschäfte abzuschließen."
            }
        ]
    }
}