{
    "orig": {
        "aktenzeichen": "HRB 14749",
        "amtsgericht": "Krefeld",
        "event_date": "2015-05-28",
        "event_type": "Veränderungen",
        "federal_state": "nw",
        "full_text": "Amtsgericht Krefeld Aktenzeichen: HRB 14749 \nBekannt gemacht am: 28.05.2015 20:01 Uhr\n\n\n\n\nIn () gesetzte Angaben der Anschrift und des Geschäftszweiges erfolgen ohne Gewähr.\nVeränderungen\n28.05.2015\n\nHRB 14749: Cityguide Deutschland GmbH, Krefeld, Dießemer Bruch 167, 47805 Krefeld. Nicht mehr Geschäftsführer: Kant, Matthias Andreas Leonhard, Pfäffikon / Schweiz, *20.01.1967. Bestellt als Geschäftsführer: Schulz, Sascha, Krefeld, *10.10.1971, mit der Befugnis im Namen der Gesellschaft mit sich im eigenen Namen oder als Vertreter eines Dritten Rechtsgeschäfte abzuschließen. Prokura erloschen: Gerteis, Urs, Richterswil, *28.02.1953; Steffens, Melanie, Duisburg, *07.07.1988. Einzelprokura: Stiemert, Christina, Velbert, *28.01.1957.",
        "gesellschafter": null,
        "inhaber": null,
        "name": "HRB 14749: Cityguide Deutschland GmbH",
        "notice_id": "1162288",
        "posted_on": "2015-05-28",
        "rechtsform": null,
        "sitz": null,
        "url": "https://www.handelsregisterbekanntmachungen.de/en/skripte/hrb.php?rb_id=1162288&land_abk=nw"
    },
    "parsed": {
        "officers": [
            {
                "class": "DismissedManagingDirector",
                "payload": {
                    "city": "Pfäffikon / Schweiz",
                    "dismissed": true,
                    "dob": "1967-01-20",
                    "lastname": "Kant",
                    "name": "Matthias Andreas Leonhard"
                },
                "text": " Kant, Matthias Andreas Leonhard, Pfäffikon / Schweiz, *20.01.1967."
            },
            {
                "class": "AppointedManagingDirector",
                "payload": {
                    "city": "Krefeld",
                    "dob": "1971-10-10",
                    "flag": "mit der Befugnis im Namen der Gesellschaft mit sich im eigenen Namen oder als Vertreter eines Dritten Rechtsgeschäfte abzuschließen",
                    "lastname": "Schulz",
                    "name": "Sascha"
                },
                "text": " Schulz, Sascha, Krefeld, *10.10.1971, mit der Befugnis im Namen der Gesellschaft mit sich im eigenen Namen oder als Vertreter eines Dritten Rechtsgeschäfte abzuschließen."
            },
            {
                "class": "ProcurationCancelled",
                "payload": {
                    "city": "Richterswil",
                    "dismissed": true,
                    "dob": "1953-02-28",
                    "lastname": "Gerteis",
                    "name": "Urs"
                },
                "text": " Gerteis, Urs, Richterswil, *28.02.1953"
            },
            {
                "class": "SingleProcuration",
                "payload": {
                    "city": "Velbert",
                    "dob": "1957-01-28",
                    "lastname": "Stiemert",
                    "name": "Christina"
                },
                "text": " Stiemert, Christina, Velbert, *28.01.1957."
            }
        ]
    }
}