{
    "orig": {
        "aktenzeichen": "HRB 62917",
        "amtsgericht": "Ludwigshafen a.Rhein (Ludwigshafen)",
        "event_date": "2012-03-05",
        "event_type": "Veränderungen",
        "federal_state": "rp",
        "full_text": "Amtsgericht Ludwigshafen a.Rhein (Ludwigshafen) Aktenzeichen: HRB 62917    \nBekannt gemacht am: 09.03.2012 12:00 Uhr\n\n\n\n\nDie in () gesetzten Angaben der Anschrift und des Geschäftszweiges erfolgen ohne Gewähr.\nVeränderungen\n05.03.2012\n\nLU VEGAS GmbH, Ludwigshafen, Ludwigstr. 75-77, 67059 Ludwigshafen. Nicht mehr Geschäftsführer: Dilekci, Mahmut, Frankfurt, *20.08.1954. Bestellt als Geschäftsführer: Özbek Meurer, Necla, Flörsheim, *10.06.1967, einzelvertretungsberechtigt mit der Befugnis im Namen der Gesellschaft mit sich im eigenen Namen oder als Vertreter eines Dritten Rechtsgeschäfte abzuschließen.",
        "gesellschafter": null,
        "inhaber": null,
        "name": "LU VEGAS GmbH",
        "notice_id": "116447",
        "posted_on": "2012-03-09",
        "rechtsform": null,
        "sitz": null,
        "url": "https://www.handelsregisterbekanntmachungen.de/en/skripte/hrb.php?rb_id=116447&land_abk=rp"
    },
    "parsed": {
        "officers": [
            {
                "class": "DismissedManagingDirector",
                "payload": {
                    "city": "Frankfurt",
                    "dismissed": true,
                    "dob": "1954-08-20",
                    "lastname": "Dilekci",
                    "name": "Mahmut"
                },
                "text": " Dilekci, Mahmut, Frankfurt, *20.08.1954."
            },
            {
                "class": "AppointedManagingDirector",
                "payload": {
                    "city": "Flörsheim",
                    "dob": "1967-06-10",
                    "flag": "einzelvertretungsberechtigt mit der Befugnis im Namen der Gesellschaft mit sich im eigenen Namen oder als Vertreter eines Dritten Rechtsgeschäfte abzuschließen",
                    "lastname": "Özbek Meurer",
                    "name": "Necla"
                },
                "text": " Özbek Meurer, Necla, Flörsheim, *10.06.1967, einzelvertretungsberechtigt mit der Befugnis im Namen der Gesellschaft mit sich im eigenen Namen oder als Vertreter eines Dritten Rechtsgeschäfte abzuschließen."
            }
        ]
    }
}