{
    "orig": {
        "aktenzeichen": "HRB 25931",
        "amtsgericht": "Duisburg",
        "event_date": "2015-06-10",
        "event_type": "Veränderungen",
        "federal_state": "nw",
        "full_text": "Amtsgericht Duisburg Aktenzeichen: HRB 25931 \nBekannt gemacht am: 10.06.2015 20:03 Uhr\n\n\n\n\nIn () gesetzte Angaben der Anschrift und des Geschäftszweiges erfolgen ohne Gewähr.\nVeränderungen\n10.06.2015\n\nHRB 25931: RIW-Krankomponenten UG (haftungsbeschränkt), Duisburg, Vinckeweg 15, 47119 Duisburg. Änderung zur Geschäftsanschrift: Stockummer Str. 28, 58453 Witten. Nicht mehr Geschäftsführer: Ducharme, Daniel, Duisburg, *14.04.1964. Bestellt als Geschäftsführer: Gressner, Rolf, Wetter, *16.12.1967, einzelvertretungsberechtigt mit der Befugnis im Namen der Gesellschaft mit sich im eigenen Namen oder als Vertreter eines Dritten Rechtsgeschäfte abzuschließen.",
        "gesellschafter": null,
        "inhaber": null,
        "name": "HRB 25931: RIW-Krankomponenten UG (haftungsbeschränkt)",
        "notice_id": "1166388",
        "posted_on": "2015-06-10",
        "rechtsform": null,
        "sitz": null,
        "url": "https://www.handelsregisterbekanntmachungen.de/en/skripte/hrb.php?rb_id=1166388&land_abk=nw"
    },
    "parsed": {
        "labels": [
            {
                "label": "address",
                "text": " Stockummer Str."
            }
        ],
        "officers": [
            {
                "class": "DismissedManagingDirector",
                "payload": {
                    "city": "Duisburg",
                    "dismissed": true,
                    "dob": "1964-04-14",
                    "lastname": "Ducharme",
                    "name": "Daniel"
                },
                "text": " Ducharme, Daniel, Duisburg, *14.04.1964."
            },
            {
                "class": "AppointedManagingDirector",
                "payload": {
                    "city": "Wetter",
                    "dob": "1967-12-16",
                    "flag": "einzelvertretungsberechtigt mit der Befugnis im Namen der Gesellschaft mit sich im eigenen Namen oder als Vertreter eines Dritten Rechtsgeschäfte abzuschließen",
                    "lastname": "Gressner",
                    "name": "Rolf"
                },
                "text": " Gressner, Rolf, Wetter, *16.12.1967, einzelvertretungsberechtigt mit der Befugnis im Namen der Gesellschaft mit sich im eigenen Namen oder als Vertreter eines Dritten Rechtsgeschäfte abzuschließen."
            }
        ]
    }
}