{
    "orig": {
        "aktenzeichen": "HRA 15009",
        "amtsgericht": "Leipzig",
        "event_date": "2011-09-06",
        "event_type": "Veränderungen",
        "federal_state": "sn",
        "full_text": "Amtsgericht Leipzig Aktenzeichen: HRA 15009   \nBekannt gemacht am: 08.09.2011 12:00 Uhr\n\n\n\n\nDie in () gesetzten Angaben der Geschäftsanschrift und des Unternehmensgegenstandes erfolgen ohne Gewähr.\nVeränderungen\n06.09.2011\n\nWWPF GmbH & Co. KG, Leipzig, Karl-Rothe-Straße 15, 04105 Leipzig. Die Firma ist geändert. Neue Firma: WWPF UG (haftungsbeschränkt) & Co.KG. Änderung Sitz und registerführendes Amtsgericht infolge Sitzverlegung und ausgeschieden: Persönlich haftender Gesellschafter: Traxxis Grundbesitz GmbH, Stuttgart (Amtsgericht Stuttgart HRB 735666). Eingetreten: Persönlich haftender Gesellschafter: PCO Liegenschaften und Beteiligungen Leipzig UG (haftungsbeschränkt), Leipzig (Amtsgericht Leipzig HRB 27425).",
        "gesellschafter": null,
        "inhaber": null,
        "name": "WWPF GmbH & Co. KG",
        "notice_id": "116678",
        "posted_on": "2011-09-08",
        "rechtsform": null,
        "sitz": null,
        "url": "https://www.handelsregisterbekanntmachungen.de/en/skripte/hrb.php?rb_id=116678&land_abk=sn"
    },
    "parsed": {
        "notices": [
            {
                "court": "Stuttgart",
                "hrb": "HRB 735666",
                "registration": null,
                "text": " und ausgeschieden: Persönlich haftender Gesellschafter: Traxxis Grundbesitz GmbH, Stuttgart (Amtsgericht Stuttgart HRB 735666).",
                "used_regex": "court_regex, hrb"
            }
        ],
        "officers": [
            {
                "class": "RetiredPersonalPartner",
                "payload": {
                    "company_name": "Traxxis Grundbesitz GmbH, Stuttgart (Amtsgericht Stuttgart HRB 735666).",
                    "dismissed": true
                },
                "text": " Traxxis Grundbesitz GmbH, Stuttgart (Amtsgericht Stuttgart HRB 735666)."
            },
            {
                "class": "PersonalPartner",
                "payload": {
                    "lastname": "PCO Liegenschaften und Beteiligungen Leipzig UG (haftungsbeschränkt)",
                    "name": "Leipzig (Amtsgericht Leipzig HRB 27425)"
                },
                "text": " PCO Liegenschaften und Beteiligungen Leipzig UG (haftungsbeschränkt), Leipzig (Amtsgericht Leipzig HRB 27425)."
            }
        ]
    }
}