{
    "orig": {
        "aktenzeichen": "HRB 3414",
        "amtsgericht": "Gelsenkirchen",
        "event_date": "2006-03-23",
        "event_type": "Veränderungen",
        "federal_state": "nw",
        "full_text": "Amtsgericht Gelsenkirchen Aktenzeichen: HRB 3414 \nBekannt gemacht am: 28.03.2006 06:55 Uhr\n\n\n\n\nDie in () gesetzten Angaben der Geschäftsanschrift und des Geschäftszweiges erfolgen ohne Gewähr.\nVeränderungen\n23.03.2006\n\nTEKO Lebensmittel Gesellschaft mit beschränkter Haftung, Gelsenkirchen (Bußmannstrasse 18, 45896 Gelsenkirchen). Die Gesellschafterversammlung vom 02.02.2006 hat eine Änderung des Gesellschaftsvertrages in § 3 Ziff. 2 (Stammkapital und Stammeinlage) beschlossen. Nicht mehr Geschäftsführer: Teltrop, Ulrich, Marl, *07.11.1959. Nicht mehr Geschäftsführer: Koppers, Gregor, Marl, *04.07.1966, einzelvertretungsberechtigt mit der Befugnis im Namen der Gesellschaft mit sich im eigenen Namen oder als Vertreter eines Dritten Rechtsgeschäfte abzuschließen.",
        "gesellschafter": null,
        "inhaber": null,
        "name": "TEKO Lebensmittel Gesellschaft mit beschränkter Haftung",
        "notice_id": "117297",
        "posted_on": "2006-03-28",
        "rechtsform": null,
        "sitz": null,
        "url": "https://www.handelsregisterbekanntmachungen.de/en/skripte/hrb.php?rb_id=117297&land_abk=nw"
    },
    "parsed": {
        "officers": [
            {
                "class": "DismissedManagingDirector",
                "payload": {
                    "city": "Marl",
                    "dismissed": true,
                    "dob": "1959-11-07",
                    "lastname": "Teltrop",
                    "name": "Ulrich"
                },
                "text": " Teltrop, Ulrich, Marl, *07.11.1959."
            },
            {
                "class": "DismissedManagingDirector",
                "payload": {
                    "city": "Marl",
                    "dismissed": true,
                    "dob": "1966-07-04",
                    "flag": "einzelvertretungsberechtigt mit der Befugnis im Namen der Gesellschaft mit sich im eigenen Namen oder als Vertreter eines Dritten Rechtsgeschäfte abzuschließen",
                    "lastname": "Koppers",
                    "name": "Gregor"
                },
                "text": " Koppers, Gregor, Marl, *04.07.1966, einzelvertretungsberechtigt mit der Befugnis im Namen der Gesellschaft mit sich im eigenen Namen oder als Vertreter eines Dritten Rechtsgeschäfte abzuschließen."
            }
        ]
    }
}