{
    "orig": {
        "aktenzeichen": "HRB 13538",
        "amtsgericht": "Moenchengladbach",
        "event_date": "2015-07-20",
        "event_type": "Veränderungen",
        "federal_state": "nw",
        "full_text": "Amtsgericht Moenchengladbach Aktenzeichen: HRB 13538 \nBekannt gemacht am: 20.07.2015 20:01 Uhr\n\n\n\n\nIn () gesetzte Angaben der Anschrift und des Geschäftszweiges erfolgen ohne Gewähr.\nVeränderungen\n20.07.2015\n\nHRB 13538: BluTecPlast Com GmbH, Grevenbroich, Kölner Landstraße 103, 41515 Grevenbroich. Die Gesellschaft ist aufgelöst. Ist nur ein Liquidator bestellt, so vertritt er die Gesellschaft allein. Sind mehrere Liquidatoren bestellt, so wird die Gesellschaft durch die Liquidatoren gemeinsam vertreten. Nicht mehr Geschäftsführer nunmehr bestellt als Liquidator: Ribbink, Hendrik Jan Albert, Roermond / Niederlande, *06.09.1964, einzelvertretungsberechtigt mit der Befugnis im Namen der Gesellschaft mit sich im eigenen Namen oder als Vertreter eines Dritten Rechtsgeschäfte abzuschließen.",
        "gesellschafter": null,
        "inhaber": null,
        "name": "HRB 13538: BluTecPlast Com GmbH",
        "notice_id": "1179468",
        "posted_on": "2015-07-20",
        "rechtsform": null,
        "sitz": null,
        "url": "https://www.handelsregisterbekanntmachungen.de/en/skripte/hrb.php?rb_id=1179468&land_abk=nw"
    },
    "parsed": {
        "flags": [
            {
                "flag": "CompanyClosed",
                "text": "Die\\ Gesellschaft\\ ist\\ aufgel\\öst\\."
            }
        ],
        "officers": [
            {
                "class": "Liquidator",
                "payload": {
                    "city": "Roermond / Niederlande",
                    "dob": "1964-06-09",
                    "flag": "einzelvertretungsberechtigt mit der Befugnis im Namen der Gesellschaft mit sich im eigenen Namen oder als Vertreter eines Dritten Rechtsgeschäfte abzuschließen",
                    "lastname": "Ribbink",
                    "name": "Hendrik Jan Albert"
                },
                "text": " Ribbink, Hendrik Jan Albert, Roermond / Niederlande, *06.09.1964, einzelvertretungsberechtigt mit der Befugnis im Namen der Gesellschaft mit sich im eigenen Namen oder als Vertreter eines Dritten Rechtsgeschäfte abzuschließen."
            }
        ]
    }
}