{
    "orig": {
        "aktenzeichen": "HRB 2072",
        "amtsgericht": "Münster",
        "event_date": "2015-08-20",
        "event_type": "Veränderungen",
        "federal_state": "nw",
        "full_text": "Amtsgericht Münster Aktenzeichen: HRB 2072 \nBekannt gemacht am: 20.08.2015 20:03 Uhr\n\n\n\n\nIn () gesetzte Angaben der Anschrift und des Geschäftszweiges erfolgen ohne Gewähr.\nVeränderungen\n20.08.2015\n\nHRB 2072: GBW-Gemeinnütziges Berufsbildungswerk Münster GmbH, Warendorf, Splieterstr. 33, 48231 Warendorf. Die Gesellschafterversammlung vom 14.08.2015 hat eine Änderung des Gesellschaftsvertrages in § 4 (Stammkapital) und § 10 (Geschäftsführung) beschlossen. Nach Änderung der Vertretungsbefugnis Geschäftsführer: Görgens, Klaus-Dieter, Warendorf, *21.06.1957, einzelvertretungsberechtigt mit der Befugnis im Namen der Gesellschaft mit sich im eigenen Namen oder als Vertreter eines Dritten Rechtsgeschäfte abzuschließen. Bestellt zum Geschäftsführer: Görgens, Ellen, Warendorf, *16.08.1958.",
        "gesellschafter": null,
        "inhaber": null,
        "name": "HRB 2072: GBW-Gemeinnütziges Berufsbildungswerk Münster GmbH",
        "notice_id": "1189920",
        "posted_on": "2015-08-20",
        "rechtsform": null,
        "sitz": null,
        "url": "https://www.handelsregisterbekanntmachungen.de/en/skripte/hrb.php?rb_id=1189920&land_abk=nw"
    },
    "parsed": {
        "officers": [
            {
                "class": "ManagingDirector",
                "payload": {
                    "city": "Warendorf",
                    "dob": "1957-06-21",
                    "flag": "einzelvertretungsberechtigt mit der Befugnis im Namen der Gesellschaft mit sich im eigenen Namen oder als Vertreter eines Dritten Rechtsgeschäfte abzuschließen",
                    "lastname": "Görgens",
                    "name": "Klaus-Dieter"
                },
                "text": " Görgens, Klaus-Dieter, Warendorf, *21.06.1957, einzelvertretungsberechtigt mit der Befugnis im Namen der Gesellschaft mit sich im eigenen Namen oder als Vertreter eines Dritten Rechtsgeschäfte abzuschließen."
            },
            {
                "class": "ManagingDirector",
                "payload": {
                    "city": "Warendorf",
                    "dob": "1958-08-16",
                    "lastname": "Görgens",
                    "name": "Ellen"
                },
                "text": " Görgens, Ellen, Warendorf, *16.08.1958."
            }
        ]
    }
}