{
    "orig": {
        "aktenzeichen": "HRB 23100",
        "amtsgericht": "Wuppertal",
        "event_date": "2015-09-07",
        "event_type": "Veränderungen",
        "federal_state": "nw",
        "full_text": "Amtsgericht Wuppertal Aktenzeichen: HRB 23100 \nBekannt gemacht am: 07.09.2015 20:05 Uhr\n\n\n\n\nIn () gesetzte Angaben der Anschrift und des Geschäftszweiges erfolgen ohne Gewähr.\nVeränderungen\n07.09.2015\n\nHRB 23100: Musterknaben GmbH Atelier für Markenkommunikation, Wuppertal, Hofaue 35 - 39, 42103 Wuppertal. Nach Änderung des Wohnortes nunmehr Geschäftsführer: Buddrus, Christian, Mettmann, *22.02.1977, einzelvertretungsberechtigt mit der Befugnis im Namen der Gesellschaft mit sich im eigenen Namen oder als Vertreter eines Dritten Rechtsgeschäfte abzuschließen. Nicht mehr Geschäftsführer: Heidermann, Marc, Wuppertal, *27.02.1975; Popov, Veit André, Wuppertal, *11.01.1977.",
        "gesellschafter": null,
        "inhaber": null,
        "name": "HRB 23100: Musterknaben GmbH Atelier für Markenkommunikation",
        "notice_id": "1196234",
        "posted_on": "2015-09-07",
        "rechtsform": null,
        "sitz": null,
        "url": "https://www.handelsregisterbekanntmachungen.de/en/skripte/hrb.php?rb_id=1196234&land_abk=nw"
    },
    "parsed": {
        "officers": [
            {
                "class": "ManagingDirector",
                "payload": {
                    "city": "Mettmann",
                    "dob": "1977-02-22",
                    "flag": "einzelvertretungsberechtigt mit der Befugnis im Namen der Gesellschaft mit sich im eigenen Namen oder als Vertreter eines Dritten Rechtsgeschäfte abzuschließen",
                    "lastname": "Buddrus",
                    "name": "Christian"
                },
                "text": " Buddrus, Christian, Mettmann, *22.02.1977, einzelvertretungsberechtigt mit der Befugnis im Namen der Gesellschaft mit sich im eigenen Namen oder als Vertreter eines Dritten Rechtsgeschäfte abzuschließen."
            },
            {
                "class": "DismissedManagingDirector",
                "payload": {
                    "city": "Wuppertal",
                    "dismissed": true,
                    "dob": "1975-02-27",
                    "lastname": "Heidermann",
                    "name": "Marc"
                },
                "text": " Heidermann, Marc, Wuppertal, *27.02.1975"
            }
        ]
    }
}