{
    "orig": {
        "aktenzeichen": "HRB 8134",
        "amtsgericht": "Steinfurt",
        "event_date": "2015-09-11",
        "event_type": "Veränderungen",
        "federal_state": "nw",
        "full_text": "Amtsgericht Steinfurt Aktenzeichen: HRB 8134 \nBekannt gemacht am: 11.09.2015 20:03 Uhr\n\n\n\n\nIn () gesetzte Angaben der Anschrift und des Geschäftszweiges erfolgen ohne Gewähr.\nVeränderungen\n11.09.2015\n\nHRB 8134: TankControl Schumacher Steuerberatungsgesellschaft mbH, Horstmar, Schöppinger Str. 22, 48612 Horstmar. Nach Änderung jetzt Geschäftsanschrift: Schöppinger Str. 18, 48612 Horstmar. Nicht mehr Geschäftsführer: Schumacher, Udo, Horstmar, *29.07.1964. Bestellt als Geschäftsführer: Schroll, Michael, Lüdenscheid, *03.07.1975, einzelvertretungsberechtigt mit der Befugnis im Namen der Gesellschaft mit sich im eigenen Namen oder als Vertreter eines Dritten Rechtsgeschäfte abzuschließen.",
        "gesellschafter": null,
        "inhaber": null,
        "name": "HRB 8134: TankControl Schumacher Steuerberatungsgesellschaft mbH",
        "notice_id": "1198070",
        "posted_on": "2015-09-11",
        "rechtsform": null,
        "sitz": null,
        "url": "https://www.handelsregisterbekanntmachungen.de/en/skripte/hrb.php?rb_id=1198070&land_abk=nw"
    },
    "parsed": {
        "labels": [
            {
                "label": "address",
                "text": " Schöppinger Str."
            }
        ],
        "officers": [
            {
                "class": "DismissedManagingDirector",
                "payload": {
                    "city": "Horstmar",
                    "dismissed": true,
                    "dob": "1964-07-29",
                    "lastname": "Schumacher",
                    "name": "Udo"
                },
                "text": " Schumacher, Udo, Horstmar, *29.07.1964."
            },
            {
                "class": "AppointedManagingDirector",
                "payload": {
                    "city": "Lüdenscheid",
                    "dob": "1975-03-07",
                    "flag": "einzelvertretungsberechtigt mit der Befugnis im Namen der Gesellschaft mit sich im eigenen Namen oder als Vertreter eines Dritten Rechtsgeschäfte abzuschließen",
                    "lastname": "Schroll",
                    "name": "Michael"
                },
                "text": " Schroll, Michael, Lüdenscheid, *03.07.1975, einzelvertretungsberechtigt mit der Befugnis im Namen der Gesellschaft mit sich im eigenen Namen oder als Vertreter eines Dritten Rechtsgeschäfte abzuschließen."
            }
        ]
    }
}