{
    "orig": {
        "aktenzeichen": "HRB 10033",
        "amtsgericht": "Bad Oeynhausen",
        "event_date": "2006-04-05",
        "event_type": "Neueintragungen",
        "federal_state": "nw",
        "full_text": "Amtsgericht Bad Oeynhausen Aktenzeichen: HRB 10033 \nBekannt gemacht am: 10.04.2006 16:23 Uhr\n\n\n\n\nDie in () gesetzten Angaben der Geschäftsanschrift und des Unternehmensgegenstandes erfolgen ohne Gewähr.\nNeueintragungen\n05.04.2006\n\nWEDECO Aktiengesellschaft, Herford (Boschstraße 4, 32051 Herford). Aktiengesellschaft. Satzung vom 17.08.1999, mehrfach geändert. Die Hauptversammlung vom 19.12.2005 hat die Änderung der Satzung in § 1 und mit ihr die Sitzverlegung von Düsseldorf (bisher AG Düsseldorf HRB 37870) nach Herford beschlossen. Die Hauptversammlung vom 19.12.2005 hat zudem in Änderung der Satzung die § 4 Abs. 1 S. 1 neugefasst. Das Grundkapital der Gesellschaft ist eingeteilt in 11.095.480 Aktien (Stückaktien). § 4 Abs. 4 und § 4 Abs. 5 der Satzung (Bedingte Kapitalerhöhung) werden aufgehoben. Die bisherigen § 4 Abs. 6 und § 4 Abs. 7 werden Absatz 4 und Absatz 5. Darüber hinaus hat die Hauptversammlung Änderungen der Satzung in § 8 (Geschäftsführung), § 10 (Zusammensetzung, Amtsdauer, Amtsniederlegung), § 13 (Einberufung des Aufsichtsrats), § 4 (Beschlussfassungen des Aufsichtsrats), § 15 (Vergütung des Aufsichtsrats), § 16 (Aufsichtsratsbeschlüsse), § 17 (Ort und Einberufung der Hauptversammlung), § 21 (Vorsitz der Hauptversammlung) und § 24 (Jahresabschluss) beschlossen. Gegenstand: Die Forschung und Entwicklung sowie die Herstellung und der weltweite Vertrieb von Anlagen und Geräten insbesondere zur Aufbereitung von Wasser und Luft mittels ultravioletter Strahlen, Ozon und anderer geeeigneter Verfahren sowie die Erbringung darauf bezogener Dienstleistungen. Grundkapital: 11.095.480,00 EUR. Allgemeine Vertretungsregelung: Ist nur ein Vorstandsmitglied bestellt, so vertritt es die Gesellschaft allein. Sind mehrere Vorstandsmitglieder bestellt, so wird die Gesellschaft durch zwei Vorstandsmitglieder oder durch ein Vorstandsmitglied gemeinsam mit einem Prokuristen vertreten. Vorstand: Dr. Kolch, Andreas Manfred, Herford, *19.04.1965; Marrino, John, Hoboken/New Jersey, USA, *02.11.1966. Vorstandsvorsitzender: Dhawan, Andre, Virgina Water, Surrey / Großbritannien, *03.06.1963, einzelvertretungsberechtigt mit der Befugnis im Namen der Gesellschaft mit sich als Vertreter eines Dritten Rechtsgeschäfte abzuschließen. Gesamtprokura gemeinsam mit einem Vorstandsmitglied oder einem anderen Prokuristen: Dinkloh, Ludwig, Herford, *30.09.1966; Lange, Claudia Nicole, Bielefeld, *09.09.1968; Meese, Wolf, Herford, *21.03.1963; Neitemeier, Dieter, Steinhagen, *29.07.1962. Gesamtprokura gemeinsam mit einem Vorstandsmitglied oder einem anderen Prokuristen mit der Befugnis im Namen der Gesellschaft mit sich als Vertreter eines Dritten Rechtsgeschäfte abzuschließen: Lange, Steffen, Bielefeld, *15.02.1967; Werkmeister, Hans, Kirchlengern, *09.10.1954. Mit der ITT Industries German Holding GmbH in Frankfurt am Main (Amtsgerich Frankfurt am Main, HRB 58196) als herrschendem Unternehmen ist am 12.07.2004 ein Beherrschungsvertrag geschlossen. Ihm hat die Hauptversammlung vom 30.08.2004 zugestimmt. Die Hauptversammlung vom 30.08.2004 hat den Ausschluss der Minderheitsaktionäre im Verfahren gem. §§ 327 a ff. AktG durch die Übertragung ihrer Aktien auf die ITT Industries German Holding GmbH in Frankfurt/M. (Amtsgericht Frankfurt/M., HRB 58196) als Hauptaktionär gegen Gewährung einer Barabfindung von EUR 18,00 je Aktie beschlossen. Der Vorstand besteht aus drei Personen.",
        "gesellschafter": null,
        "inhaber": null,
        "name": "WEDECO Aktiengesellschaft",
        "notice_id": "121089",
        "posted_on": "2006-04-10",
        "rechtsform": null,
        "sitz": null,
        "url": "https://www.handelsregisterbekanntmachungen.de/en/skripte/hrb.php?rb_id=121089&land_abk=nw"
    },
    "parsed": {
        "notices": [
            {
                "court": "Düsseldorf",
                "from": "Düsseldorf",
                "hrb": "HRB 37870",
                "registration": "predecessor",
                "registration_conflict": true,
                "text": " von Düsseldorf (bisher AG Düsseldorf HRB 37870) nach Herford beschlossen.",
                "to": "Herford",
                "used_regex": "court_regex, from_hrb_to_regex"
            }
        ],
        "officers": [
            {
                "class": "CommonProcuration",
                "payload": {
                    "city": "Herford",
                    "dob": "1966-09-30",
                    "lastname": "Dinkloh",
                    "name": "Ludwig"
                },
                "text": " Dinkloh, Ludwig, Herford, *30.09.1966"
            },
            {
                "class": "CommonProcuration",
                "payload": {
                    "city": "Bielefeld",
                    "dob": "1968-09-09",
                    "lastname": "Lange",
                    "name": "Claudia Nicole"
                },
                "text": " Lange, Claudia Nicole, Bielefeld, *09.09.1968"
            },
            {
                "class": "CommonProcuration",
                "payload": {
                    "city": "Herford",
                    "dob": "1963-03-21",
                    "lastname": "Meese",
                    "name": "Wolf"
                },
                "text": " Meese, Wolf, Herford, *21.03.1963"
            },
            {
                "class": "CommonProcuration",
                "payload": {
                    "city": "Steinhagen",
                    "dob": "1962-07-29",
                    "lastname": "Neitemeier",
                    "name": "Dieter"
                },
                "text": " Neitemeier, Dieter, Steinhagen, *29.07.1962."
            }
        ]
    }
}