{
    "orig": {
        "aktenzeichen": "HRB 74368",
        "amtsgericht": "Düsseldorf",
        "event_date": "2015-10-28",
        "event_type": "Veränderungen",
        "federal_state": "nw",
        "full_text": "Amtsgericht Düsseldorf Aktenzeichen: HRB 74368 \nBekannt gemacht am: 28.10.2015 20:05 Uhr\n\n\n\n\nIn () gesetzte Angaben der Anschrift und des Geschäftszweiges erfolgen ohne Gewähr.\nVeränderungen\n28.10.2015\n\nHRB 74368: Unikia Deutschland GmbH, Düsseldorf, Graf-Adolf-Str. 23, c/o optegra GmbH & Co. KG Wirtschaftsprüfungsgesellschaft Steuerberatungsgesellschaft, 40212 Düsseldorf. Die Gesellschafterversammlung vom 13.10.2015 hat eine Änderung des Gesellschaftsvertrages in § 1 Abs. 1.1 und damit der Firma beschlossen. Neue Firma: HELLAND MÖBEL GmbH. Nicht mehr Geschäftsführer: Hjelmbrekke Andreassen, Gaute, Oslo / Norwegen, *18.09.1975. Bestellt als Geschäftsführer: Helland, Joakim, Alesund / Norwegen, *09.10.1978, mit der Befugnis im Namen der Gesellschaft mit sich im eigenen Namen oder als Vertreter eines Dritten Rechtsgeschäfte abzuschließen. Die Gesellschaft wird fortgesetzt.",
        "gesellschafter": null,
        "inhaber": null,
        "name": "HRB 74368: Unikia Deutschland GmbH",
        "notice_id": "1212985",
        "posted_on": "2015-10-28",
        "rechtsform": null,
        "sitz": null,
        "url": "https://www.handelsregisterbekanntmachungen.de/en/skripte/hrb.php?rb_id=1212985&land_abk=nw"
    },
    "parsed": {
        "officers": [
            {
                "class": "DismissedManagingDirector",
                "payload": {
                    "city": "Oslo / Norwegen",
                    "dismissed": true,
                    "dob": "1975-09-18",
                    "lastname": "Hjelmbrekke Andreassen",
                    "name": "Gaute"
                },
                "text": " Hjelmbrekke Andreassen, Gaute, Oslo / Norwegen, *18.09.1975."
            },
            {
                "class": "AppointedManagingDirector",
                "payload": {
                    "city": "Alesund / Norwegen",
                    "dob": "1978-09-10",
                    "flag": "mit der Befugnis im Namen der Gesellschaft mit sich im eigenen Namen oder als Vertreter eines Dritten Rechtsgeschäfte abzuschließen",
                    "lastname": "Helland",
                    "name": "Joakim"
                },
                "text": " Helland, Joakim, Alesund / Norwegen, *09.10.1978, mit der Befugnis im Namen der Gesellschaft mit sich im eigenen Namen oder als Vertreter eines Dritten Rechtsgeschäfte abzuschließen."
            }
        ]
    }
}