{
    "orig": {
        "aktenzeichen": "HRB 15223",
        "amtsgericht": "Krefeld",
        "event_date": "2015-11-03",
        "event_type": "Veränderungen",
        "federal_state": "nw",
        "full_text": "Amtsgericht Krefeld Aktenzeichen: HRB 15223 \nBekannt gemacht am: 03.11.2015 20:04 Uhr\n\n\n\n\nIn () gesetzte Angaben der Anschrift und des Geschäftszweiges erfolgen ohne Gewähr.\nVeränderungen\n03.11.2015\n\nHRB 15223: Niederrhein Immobilien und Bau GmbH, Krefeld, Wallerspfad 16, 47802 Krefeld. Die Gesellschaft hat einen oder mehrere Liquidatoren. Ist nur ein Liquidator vorhanden, so vertritt dieser die Gesellschaft allein. Sind mehrere Liquidatoren bestellt, so wird die Gesellschaft durch zwei Liquidatoren gemeinschaftlich oder durch einen Liquidator zusammen mit einem Prokuristen vertreten. Durch Beschluss der Gesellschafterversammlung kann einzelnen oder mehreren Liquidatoren Einzelvertretungsbefugnis sowie Befreiung von den Beschränkungen des § 181 BGB erteilt werden. Geändert, nunmehr: Liquidator: Tahtaci, Ergün, Krefeld, *07.10.1969, einzelvertretungsberechtigt mit der Befugnis im Namen der Gesellschaft mit sich im eigenen Namen oder als Vertreter eines Dritten Rechtsgeschäfte abzuschließen. Die Gesellschaft ist aufgelöst.",
        "gesellschafter": null,
        "inhaber": null,
        "name": "HRB 15223: Niederrhein Immobilien und Bau GmbH",
        "notice_id": "1214629",
        "posted_on": "2015-11-03",
        "rechtsform": null,
        "sitz": null,
        "url": "https://www.handelsregisterbekanntmachungen.de/en/skripte/hrb.php?rb_id=1214629&land_abk=nw"
    },
    "parsed": {
        "flags": [
            {
                "flag": "CompanyClosed",
                "text": "Die\\ Gesellschaft\\ ist\\ aufgel\\öst\\."
            }
        ],
        "officers": [
            {
                "class": "Liquidator",
                "payload": {
                    "city": "Krefeld",
                    "dob": "1969-10-07",
                    "flag": "einzelvertretungsberechtigt mit der Befugnis im Namen der Gesellschaft mit sich im eigenen Namen oder als Vertreter eines Dritten Rechtsgeschäfte abzuschließen",
                    "lastname": "Tahtaci",
                    "name": "Ergün"
                },
                "text": " Tahtaci, Ergün, Krefeld, *07.10.1969, einzelvertretungsberechtigt mit der Befugnis im Namen der Gesellschaft mit sich im eigenen Namen oder als Vertreter eines Dritten Rechtsgeschäfte abzuschließen."
            }
        ]
    }
}