{
    "orig": {
        "aktenzeichen": "HRB 12658",
        "amtsgericht": "Bonn",
        "event_date": "2016-01-05",
        "event_type": "Veränderungen",
        "federal_state": "nw",
        "full_text": "Amtsgericht Bonn Aktenzeichen: HRB 12658 \nBekannt gemacht am: 05.01.2016 20:04 Uhr\n\n\n\n\nIn () gesetzte Angaben der Anschrift und des Geschäftszweiges erfolgen ohne Gewähr.\nVeränderungen\n05.01.2016\n\nHRB 12658: [deep white] Unternehmens- und Wertekultur GmbH, Bonn, Kurt-Schumacher-Straße 2, 53113 Bonn. Ist nur ein Liquidator bestellt, so vertritt er die Gesellschaft allein. Sind mehrere Liquidatoren bestellt, so wird die Gesellschaft durch die Liquidatoren gemeinsam vertreten. Nicht mehr Geschäftsführer, nunmehr Liquidator: Schönborn, Gregor, Bonn, *17.06.1959, einzelvertretungsberechtigt mit der Befugnis im Namen der Gesellschaft mit sich im eigenen Namen oder als Vertreter eines Dritten Rechtsgeschäfte abzuschließen. Die Gesellschaft ist aufgelöst.",
        "gesellschafter": null,
        "inhaber": null,
        "name": "HRB 12658: [deep white] Unternehmens- und Wertekultur GmbH",
        "notice_id": "1236252",
        "posted_on": "2016-01-05",
        "rechtsform": null,
        "sitz": null,
        "url": "https://www.handelsregisterbekanntmachungen.de/en/skripte/hrb.php?rb_id=1236252&land_abk=nw"
    },
    "parsed": {
        "flags": [
            {
                "flag": "ignore_for_now",
                "text": "Die\\ Gesellschaft\\ ist\\ aufgel\\öst\\."
            }
        ],
        "officers": [
            {
                "class": "Liquidator",
                "payload": {
                    "city": "Bonn",
                    "dob": "1959-06-17",
                    "flag": "einzelvertretungsberechtigt mit der Befugnis im Namen der Gesellschaft mit sich im eigenen Namen oder als Vertreter eines Dritten Rechtsgeschäfte abzuschließen",
                    "lastname": "Schönborn",
                    "name": "Gregor"
                },
                "text": " Schönborn, Gregor, Bonn, *17.06.1959, einzelvertretungsberechtigt mit der Befugnis im Namen der Gesellschaft mit sich im eigenen Namen oder als Vertreter eines Dritten Rechtsgeschäfte abzuschließen."
            }
        ]
    }
}