{
    "orig": {
        "aktenzeichen": "HRB 12841",
        "amtsgericht": "Siegburg",
        "event_date": "2016-01-11",
        "event_type": "Veränderungen",
        "federal_state": "nw",
        "full_text": "Amtsgericht Siegburg Aktenzeichen: HRB 12841 \nBekannt gemacht am: 11.01.2016 20:08 Uhr\n\n\n\n\nIn () gesetzte Angaben der Anschrift und des Geschäftszweiges erfolgen ohne Gewähr.\nVeränderungen\n11.01.2016\n\nHRB 12841: MySnapshot UG (haftungsbeschränkt), Hennef, Pfaffenpfad 1, 51145 Köln. Ist nur ein Liquidator bestellt, so vertritt er die Gesellschaft allein. Sind mehrere Liquidatoren bestellt, so wird die Gesellschaft durch zwei Liquidatoren oder durch einen Liquidator gemeinsam mit einem Prokuristen vertreten. Nicht mehr Geschäftsführer nunmehr bestellt als Liquidator: Proba, Marvin, Sankt Augustin, *04.05.1991; Risch, Matthias, Köln, *01.03.1992, jeweils einzelvertretungsberechtigt. Die Gesellschaft ist aufgelöst.",
        "gesellschafter": null,
        "inhaber": null,
        "name": "HRB 12841: MySnapshot UG (haftungsbeschränkt)",
        "notice_id": "1239665",
        "posted_on": "2016-01-11",
        "rechtsform": null,
        "sitz": null,
        "url": "https://www.handelsregisterbekanntmachungen.de/en/skripte/hrb.php?rb_id=1239665&land_abk=nw"
    },
    "parsed": {
        "flags": [
            {
                "flag": "CompanyClosed",
                "text": "Die\\ Gesellschaft\\ ist\\ aufgel\\öst\\."
            }
        ],
        "officers": [
            {
                "class": "Liquidator",
                "payload": {
                    "city": "Sankt Augustin",
                    "dob": "1991-05-04",
                    "lastname": "Proba",
                    "name": "Marvin"
                },
                "text": " Proba, Marvin, Sankt Augustin, *04.05.1991"
            },
            {
                "class": "Liquidator",
                "payload": {
                    "city": "Köln",
                    "dob": "1992-03-01",
                    "flag": "jeweils einzelvertretungsberechtigt",
                    "lastname": "Risch",
                    "name": "Matthias"
                },
                "text": " Risch, Matthias, Köln, *01.03.1992, jeweils einzelvertretungsberechtigt."
            }
        ]
    }
}