{
    "orig": {
        "aktenzeichen": "HRB 11908",
        "amtsgericht": "Gelsenkirchen",
        "event_date": "2016-01-13",
        "event_type": "Veränderungen",
        "federal_state": "nw",
        "full_text": "Amtsgericht Gelsenkirchen Aktenzeichen: HRB 11908 \nBekannt gemacht am: 13.01.2016 20:06 Uhr\n\n\n\n\nIn () gesetzte Angaben der Anschrift und des Geschäftszweiges erfolgen ohne Gewähr.\nVeränderungen\n13.01.2016\n\nHRB 11908: SAM Verwaltungs GmbH, Marl, Schillerstr. 34, 45768 Marl. Änderung zur Geschäftsanschrift: Glatzer Straße 39, 45768 Marl. Ist nur ein Liquidator bestellt, so vertritt er die Gesellschaft allein. Sind mehrere Liquidatoren bestellt, so wird die Gesellschaft durch zwei Liquidatoren gemeinsam vertreten. Nicht mehr Geschäftsführer, nunmehr bestellt als Liquidator: Blasius, Dirk, Wuppertal, *07.10.1963, mit der Befugnis im Namen der Gesellschaft mit sich im eigenen Namen oder als Vertreter eines Dritten Rechtsgeschäfte abzuschließen. Die Gesellschaft ist aufgelöst.",
        "gesellschafter": null,
        "inhaber": null,
        "name": "HRB 11908: SAM Verwaltungs GmbH",
        "notice_id": "1240780",
        "posted_on": "2016-01-13",
        "rechtsform": null,
        "sitz": null,
        "url": "https://www.handelsregisterbekanntmachungen.de/en/skripte/hrb.php?rb_id=1240780&land_abk=nw"
    },
    "parsed": {
        "flags": [
            {
                "flag": "CompanyClosed",
                "text": "Die\\ Gesellschaft\\ ist\\ aufgel\\öst\\."
            }
        ],
        "labels": [
            {
                "label": "address",
                "text": " Glatzer Straße 39, 45768 Marl."
            }
        ],
        "officers": [
            {
                "class": "Liquidator",
                "payload": {
                    "city": "Wuppertal",
                    "dob": "1963-07-10",
                    "flag": "mit der Befugnis im Namen der Gesellschaft mit sich im eigenen Namen oder als Vertreter eines Dritten Rechtsgeschäfte abzuschließen",
                    "lastname": "Blasius",
                    "name": "Dirk"
                },
                "text": " Blasius, Dirk, Wuppertal, *07.10.1963, mit der Befugnis im Namen der Gesellschaft mit sich im eigenen Namen oder als Vertreter eines Dritten Rechtsgeschäfte abzuschließen."
            }
        ]
    }
}