{
    "orig": {
        "aktenzeichen": "HRB 6080",
        "amtsgericht": "Hagen",
        "event_date": "2016-01-12",
        "event_type": "Veränderungen",
        "federal_state": "nw",
        "full_text": "Amtsgericht Hagen Aktenzeichen: HRB 6080 \nBekannt gemacht am: 12.01.2016 20:07 Uhr\n\n\n\n\nIn () gesetzte Angaben der Anschrift und des Geschäftszweiges erfolgen ohne Gewähr.\nVeränderungen\n12.01.2016\n\nHRB 6080: Peddinghaus Handwerkzeuge Vertriebs GmbH, Schwelm, In der Graslake 35, 58332 Schwelm. Nicht mehr Geschäftsführer: Hölscheid, Axel, Wuppertal, *02.05.1962. Neu bestellt wurden Geschäftsführer: Moulin, Thibaut, Saint Bonnet les Oules / Frankreich, *20.11.1973; Strasmann, Martin, Remscheid, *04.10.1971, jeweils einzelvertretungsberechtigt mit der Befugnis im Namen der Gesellschaft mit sich im eigenen Namen oder als Vertreter eines Dritten Rechtsgeschäfte abzuschließen.",
        "gesellschafter": null,
        "inhaber": null,
        "name": "HRB 6080: Peddinghaus Handwerkzeuge Vertriebs GmbH",
        "notice_id": "1240219",
        "posted_on": "2016-01-12",
        "rechtsform": null,
        "sitz": null,
        "url": "https://www.handelsregisterbekanntmachungen.de/en/skripte/hrb.php?rb_id=1240219&land_abk=nw"
    },
    "parsed": {
        "officers": [
            {
                "class": "DismissedManagingDirector",
                "payload": {
                    "city": "Wuppertal",
                    "dismissed": true,
                    "dob": "1962-05-02",
                    "lastname": "Hölscheid",
                    "name": "Axel"
                },
                "text": " Hölscheid, Axel, Wuppertal, *02.05.1962."
            },
            {
                "class": "ManagingDirector",
                "payload": {
                    "city": "Saint Bonnet les Oules / Frankreich",
                    "dob": "1973-11-20",
                    "lastname": "Moulin",
                    "name": "Thibaut"
                },
                "text": " Moulin, Thibaut, Saint Bonnet les Oules / Frankreich, *20.11.1973"
            },
            {
                "class": "ManagingDirector",
                "payload": {
                    "city": "Remscheid",
                    "dob": "1971-10-04",
                    "flag": "jeweils einzelvertretungsberechtigt mit der Befugnis im Namen der Gesellschaft mit sich im eigenen Namen oder als Vertreter eines Dritten Rechtsgeschäfte abzuschließen",
                    "lastname": "Strasmann",
                    "name": "Martin"
                },
                "text": " Strasmann, Martin, Remscheid, *04.10.1971, jeweils einzelvertretungsberechtigt mit der Befugnis im Namen der Gesellschaft mit sich im eigenen Namen oder als Vertreter eines Dritten Rechtsgeschäfte abzuschließen."
            }
        ]
    }
}