{
    "orig": {
        "aktenzeichen": "HRB 8003",
        "amtsgericht": "Hamm",
        "event_date": "2016-01-22",
        "event_type": "Veränderungen",
        "federal_state": "nw",
        "full_text": "Amtsgericht Hamm Aktenzeichen: HRB 8003 \nBekannt gemacht am: 22.01.2016 20:06 Uhr\n\n\n\n\nIn () gesetzte Angaben der Anschrift und des Geschäftszweiges erfolgen ohne Gewähr.\nVeränderungen\n22.01.2016\n\nHRB 8003: Altem GmbH, Kamen, Lünener Straße 211/212, 59174 Kamen. Die Gesellschafterversammlung vom 07.10.2015 hat die Änderung des Gesellschaftsvertrages in § 4 (Stammkapital, Geschäftsanteile) und mit ihr die Erhöhung des Stammkapitals von 25.000,00 EUR um 2,00 EUR auf 25.002,00 EUR beschlossen. Stammkapital nunmehr: 25.002,00 EUR. Nicht mehr Geschäftsführer: Temur, Hüseyin, Bergkamen, *19.03.1967. Bestellt als Geschäftsführer: Seidenglanz, Jens, Köln, *13.08.1962, einzelvertretungsberechtigt mit der Befugnis im Namen der Gesellschaft mit sich im eigenen Namen oder als Vertreter eines Dritten Rechtsgeschäfte abzuschließen.",
        "gesellschafter": null,
        "inhaber": null,
        "name": "HRB 8003: Altem GmbH",
        "notice_id": "1245032",
        "posted_on": "2016-01-22",
        "rechtsform": null,
        "sitz": null,
        "url": "https://www.handelsregisterbekanntmachungen.de/en/skripte/hrb.php?rb_id=1245032&land_abk=nw"
    },
    "parsed": {
        "officers": [
            {
                "class": "DismissedManagingDirector",
                "payload": {
                    "city": "Bergkamen",
                    "dismissed": true,
                    "dob": "1967-03-19",
                    "lastname": "Temur",
                    "name": "Hüseyin"
                },
                "text": " Temur, Hüseyin, Bergkamen, *19.03.1967."
            },
            {
                "class": "AppointedManagingDirector",
                "payload": {
                    "city": "Köln",
                    "dob": "1962-08-13",
                    "flag": "einzelvertretungsberechtigt mit der Befugnis im Namen der Gesellschaft mit sich im eigenen Namen oder als Vertreter eines Dritten Rechtsgeschäfte abzuschließen",
                    "lastname": "Seidenglanz",
                    "name": "Jens"
                },
                "text": " Seidenglanz, Jens, Köln, *13.08.1962, einzelvertretungsberechtigt mit der Befugnis im Namen der Gesellschaft mit sich im eigenen Namen oder als Vertreter eines Dritten Rechtsgeschäfte abzuschließen."
            }
        ]
    }
}