{
    "orig": {
        "aktenzeichen": "HRB 28211",
        "amtsgericht": "Duisburg",
        "event_date": "2016-01-27",
        "event_type": "Neueintragungen",
        "federal_state": "nw",
        "full_text": "Amtsgericht Duisburg Aktenzeichen: HRB 28211 \nBekannt gemacht am: 27.01.2016 20:08 Uhr\n\n\n\n\nIn () gesetzte Angaben der Anschrift und des Geschäftszweiges erfolgen ohne Gewähr.\nNeueintragungen\n27.01.2016\n\nHRB 28211: BAVARIA Lederveredelung GmbH, Mülheim an der Ruhr, Uhlenhorstweg 18, 45479 Mülheim an der Ruhr. Gesellschaft mit beschränkter Haftung. Gesellschaftsvertrag vom 02.12.1992 mehrfach, zuletzt gemäß Beschluss der Gesellschafterversammlung vom 27.04.2000 geändert. Die Gesellschafterversammlung vom 07.12.2015 hat die Änderung des Gesellschaftsvertrages in § 1 (Firma und Sitz) und mit ihr die Sitzverlegung von Großbottwar (bisher Amtsgericht Stuttgart, HRB 311031) nach Mülheim an der Ruhr beschlossen. Geschäftsanschrift: Uhlenhorstweg 18, 45479 Mülheim an der Ruhr. Gegenstand: Be- und Verarbeitung von Leder aller Art. Stammkapital: 500.000,00 EUR. Allgemeine Vertretungsregelung: Die Gesellschaft hat einen oder mehrere Geschäftsführer. Ist nur ein Geschäftsführer berufen, so vertritt dieser die Gesellschaft allein. Sind mehrere Geschäftsführer bestellt, so wird die Gesellschaft durch zwei Geschäftsführer gemeinsam oder durch einen Geschäftsführer zusammen mit einem Prokuristen vertreten. Durch Gesellschafterbeschluss kann Geschäftsführern die Befugnis erteilt werden, die Gesellschaft einzeln zu vertreten oder im Namen der Gesellschaft mit sich im eigenen Namen oder als Vertreter eines Dritten Rechtsgeschäfte vorzunehmen. Geschäftsführer: Lüke, Heinz-Joachim, Mülheim, *09.11.1964, mit der Befugnis im Namen der Gesellschaft mit sich im eigenen Namen oder als Vertreter eines Dritten Rechtsgeschäfte abzuschließen.",
        "gesellschafter": null,
        "inhaber": null,
        "name": "HRB 28211: BAVARIA Lederveredelung GmbH",
        "notice_id": "1246874",
        "posted_on": "2016-01-27",
        "rechtsform": null,
        "sitz": null,
        "url": "https://www.handelsregisterbekanntmachungen.de/en/skripte/hrb.php?rb_id=1246874&land_abk=nw"
    },
    "parsed": {
        "flags": [
            {
                "flag": "Company with limited liability.",
                "text": "Gesellschaft\\ mit\\ beschr\\änkter\\ Haftung\\."
            }
        ],
        "labels": [
            {
                "label": "address",
                "text": " Uhlenhorstweg 18, 45479 Mülheim an der Ruhr."
            }
        ],
        "notices": [
            {
                "court": "Stuttgart",
                "from": "Großbottwar",
                "hrb": "HRB 311031",
                "registration": "predecessor",
                "text": " von Großbottwar (bisher Amtsgericht Stuttgart, HRB 311031) nach Mülheim an der Ruhr beschlossen.",
                "to": "Mülheim an der Ruhr",
                "used_regex": "court, from_hrb_to_regex"
            }
        ],
        "officers": [
            {
                "class": "ManagingDirector",
                "payload": {
                    "city": "Mülheim",
                    "dob": "1964-09-11",
                    "flag": "mit der Befugnis im Namen der Gesellschaft mit sich im eigenen Namen oder als Vertreter eines Dritten Rechtsgeschäfte abzuschließen",
                    "lastname": "Lüke",
                    "name": "Heinz-Joachim"
                },
                "text": " Lüke, Heinz-Joachim, Mülheim, *09.11.1964, mit der Befugnis im Namen der Gesellschaft mit sich im eigenen Namen oder als Vertreter eines Dritten Rechtsgeschäfte abzuschließen."
            }
        ]
    }
}