{
    "orig": {
        "aktenzeichen": "HRB 24705",
        "amtsgericht": "Wuppertal",
        "event_date": "2016-02-04",
        "event_type": "Veränderungen",
        "federal_state": "nw",
        "full_text": "Amtsgericht Wuppertal Aktenzeichen: HRB 24705 \nBekannt gemacht am: 04.02.2016 20:06 Uhr\n\n\n\n\nIn () gesetzte Angaben der Anschrift und des Geschäftszweiges erfolgen ohne Gewähr.\nVeränderungen\n04.02.2016\n\nHRB 24705: Pachal GmbH, Velbert, Schwanenstraße 48 a, 42551 Velbert. Änderung zur Geschäftsanschrift: Von-Behring-Straße 48, 42549 Velbert. Ist nur ein Liquidator bestellt, so vertritt er die Gesellschaft allein. Sind mehrere Liquidatoren bestellt, so wird die Gesellschaft durch die Liquidatoren gemeinsam vertreten. Nunmehr Liquidator: Pachal, Sylvia, Velbert, *04.03.1964, einzelvertretungsberechtigt mit der Befugnis im Namen der Gesellschaft mit sich im eigenen Namen oder als Vertreter eines Dritten Rechtsgeschäfte abzuschließen. Die Gesellschaft ist aufgelöst.",
        "gesellschafter": null,
        "inhaber": null,
        "name": "HRB 24705: Pachal GmbH",
        "notice_id": "1250200",
        "posted_on": "2016-02-04",
        "rechtsform": null,
        "sitz": null,
        "url": "https://www.handelsregisterbekanntmachungen.de/en/skripte/hrb.php?rb_id=1250200&land_abk=nw"
    },
    "parsed": {
        "flags": [
            {
                "flag": "ignore_for_now",
                "text": "Die\\ Gesellschaft\\ ist\\ aufgel\\öst\\."
            }
        ],
        "labels": [
            {
                "label": "address",
                "text": " Von-Behring-Straße 48, 42549 Velbert."
            }
        ],
        "officers": [
            {
                "class": "Liquidator",
                "payload": {
                    "city": "Velbert",
                    "dob": "1964-04-03",
                    "flag": "einzelvertretungsberechtigt mit der Befugnis im Namen der Gesellschaft mit sich im eigenen Namen oder als Vertreter eines Dritten Rechtsgeschäfte abzuschließen",
                    "lastname": "Pachal",
                    "name": "Sylvia"
                },
                "text": " Pachal, Sylvia, Velbert, *04.03.1964, einzelvertretungsberechtigt mit der Befugnis im Namen der Gesellschaft mit sich im eigenen Namen oder als Vertreter eines Dritten Rechtsgeschäfte abzuschließen."
            }
        ]
    }
}