{
    "orig": {
        "aktenzeichen": "GnR 218 FF",
        "amtsgericht": "Frankfurt/Oder",
        "event_date": "2007-01-24",
        "event_type": "Neueintragungen",
        "federal_state": "br",
        "full_text": "Amtsgericht Frankfurt/Oder Aktenzeichen: GnR 218 FF \nBekannt gemacht am: 14.03.2007 14:48 Uhr\n\n\n\n\nFür die Angaben in (), die den Unternehmensgegenstand und die Anschrift betreffen, keine Gewähr. In das Genossenschaftsregister ist folgendes eingetragen worden.\nNeueintragungen\n24.01.2007\n\nNEUES WOHNEN Wohnungsgenossenschaft eG, Strausberg(Am Försterweg 7, 15344  Strausberg). Gegenstand der Firma: Die Genossenschaft kann Bauten in allen Rechts- und Nutzungsformen bewirtschaften, errichten, erwerben, vermitteln und betreuen. Sie kann alle im Bereich der Wohnungs- und Immobilienwirtschaft, des Städtebaus und der Infrastruktur anfallenden Aufgaben übernehmen. Hierzu gehören Gemeinschaftsanlagen und Folgeeinrichtungen, Läden und Räume für Gewerbebetriebe, soziale, wirtschaftliche und kulturelle Einrichtungen und Dienstleistungen. Beteiligungen sind zulässig. Nachschusspflicht: keine Nachschusspflicht. Vertretungregelung: Der Vorstand besteht aus mindestens zwei Personen. Die Genossenschaft wird durch zwei Vorstandsmitglieder oder durch ein Vorstandsmitglied in Gemeinschaft mit einem Prokuristen vertreten. Vorstand: Vorstand: 1. Dr. Jakubzik, Martina, geb. Fräbel, *17.01.1963, Berlin; Vorstand: 2. Seek, Daniela, geb. Jahnke, *12.02.1965, Hönow Rechtsform: Eingetragene Genossenschaft; Satzung vom: 02.08.2000 zuletzt geändert durch Beschluss vom 28.06.2001 Durch Beschluss der Mitgliederversammlung vom 21.06.2006 ist der Sitz der Genossenschaft von Berlin (AG Charlottenburg, GnR 573 B) nach Strausberg verlegt und die Satzung geändert in § 1 Satz 2 (Firma und Sitz). Bemerkung: Tag der ersten Eintragung: 09.11.2000. Die Mitgliederversammlung vom 21.06.2006 hat die Änderung des Statutes beschlossen: § 1 Satz 2 (Firma und Sitz). Sie hat ihren Sitz in Strausberg.",
        "gesellschafter": null,
        "inhaber": null,
        "name": "NEUES WOHNEN Wohnungsgenossenschaft eG",
        "notice_id": "12573",
        "posted_on": "2007-03-14",
        "rechtsform": null,
        "sitz": null,
        "url": "https://www.handelsregisterbekanntmachungen.de/en/skripte/hrb.php?rb_id=12573&land_abk=br"
    },
    "parsed": {
        "notices": [
            {
                "court": "Charlottenburg",
                "from": "Berlin",
                "hrb": "GnR 573 B",
                "registration": "successor",
                "text": " der Genossenschaft von Berlin (AG Charlottenburg, GnR 573 B) nach Strausberg verlegt und die Satzung geändert in § 1 Satz 2 (Firma und Sitz).",
                "to": "Strausberg",
                "used_regex": "from_regex, hrb_regex, to_regex, court_regex"
            }
        ]
    }
}