{
    "orig": {
        "aktenzeichen": "HRA 8796",
        "amtsgericht": "Bad Oeynhausen",
        "event_date": "2016-02-26",
        "event_type": "Veränderungen",
        "federal_state": "nw",
        "full_text": "Amtsgericht Bad Oeynhausen Aktenzeichen: HRA 8796 \nBekannt gemacht am: 26.02.2016 20:07 Uhr\n\n\n\n\nIn () gesetzte Angaben der Anschrift und des Geschäftszweiges erfolgen ohne Gewähr.\nVeränderungen\n26.02.2016\n\nHRA 8796: DesignHeim KG, Hüllhorst, Mühlenweg 6, 32609 Hüllhorst. Lübbecke. Änderung zur Geschäftsanschrift: Bäckerstraße 26, 32312 Lübbecke. Familienname und Wohnort berichtigt, weiterhin Persönlich haftender Gesellschafter: Wölfing, Sandra, Lübbecke, *31.03.1981, einzelvertretungsberechtigt mit der Befugnis im Namen der Gesellschaft mit sich im eigenen Namen oder als Vertreter eines Dritten Rechtsgeschäfte abzuschließen. Der Sitz ist nach Lübbecke verlegt.",
        "gesellschafter": null,
        "inhaber": null,
        "name": "HRA 8796: DesignHeim KG",
        "notice_id": "1257978",
        "posted_on": "2016-02-26",
        "rechtsform": null,
        "sitz": null,
        "url": "https://www.handelsregisterbekanntmachungen.de/en/skripte/hrb.php?rb_id=1257978&land_abk=nw"
    },
    "parsed": {
        "labels": [
            {
                "label": "address",
                "text": " Bäckerstraße 26, 32312 Lübbecke."
            }
        ],
        "officers": [
            {
                "class": "PersonalPartner",
                "payload": {
                    "city": "Lübbecke",
                    "dob": "1981-03-31",
                    "flag": "einzelvertretungsberechtigt mit der Befugnis im Namen der Gesellschaft mit sich im eigenen Namen oder als Vertreter eines Dritten Rechtsgeschäfte abzuschließen",
                    "lastname": "Wölfing",
                    "name": "Sandra"
                },
                "text": " Wölfing, Sandra, Lübbecke, *31.03.1981, einzelvertretungsberechtigt mit der Befugnis im Namen der Gesellschaft mit sich im eigenen Namen oder als Vertreter eines Dritten Rechtsgeschäfte abzuschließen."
            }
        ]
    }
}