{
    "orig": {
        "aktenzeichen": "HRB 7500",
        "amtsgericht": "Gelsenkirchen",
        "event_date": "2016-04-06",
        "event_type": "Veränderungen",
        "federal_state": "nw",
        "full_text": "Amtsgericht Gelsenkirchen Aktenzeichen: HRB 7500 \nBekannt gemacht am: 06.04.2016 20:11 Uhr\n\n\n\n\nIn () gesetzte Angaben der Anschrift und des Geschäftszweiges erfolgen ohne Gewähr.\nVeränderungen\n06.04.2016\n\nHRB 7500: Indutechnik GmbH, Gladbeck, Am Wiesenbusch 30, 45966 Gladbeck. Nicht mehr Geschäftsführer: Bartosik, Michael, Gladbeck, *06.11.1963. Bestellt zum Geschäftsführer: Kamberi, Kadri, Aachen, *06.06.1954; Kamberi, Valon, Ottobrunn, *31.10.1986, jeweils einzelvertretungsberechtigt mit der Befugnis im Namen der Gesellschaft mit sich im eigenen Namen oder als Vertreter eines Dritten Rechtsgeschäfte abzuschließen.",
        "gesellschafter": null,
        "inhaber": null,
        "name": "HRB 7500: Indutechnik GmbH",
        "notice_id": "1271185",
        "posted_on": "2016-04-06",
        "rechtsform": null,
        "sitz": null,
        "url": "https://www.handelsregisterbekanntmachungen.de/en/skripte/hrb.php?rb_id=1271185&land_abk=nw"
    },
    "parsed": {
        "officers": [
            {
                "class": "DismissedManagingDirector",
                "payload": {
                    "city": "Gladbeck",
                    "dismissed": true,
                    "dob": "1963-11-06",
                    "lastname": "Bartosik",
                    "name": "Michael"
                },
                "text": " Bartosik, Michael, Gladbeck, *06.11.1963."
            },
            {
                "class": "ManagingDirector",
                "payload": {
                    "city": "Aachen",
                    "dob": "1954-06-06",
                    "lastname": "Kamberi",
                    "name": "Kadri"
                },
                "text": " Kamberi, Kadri, Aachen, *06.06.1954"
            },
            {
                "class": "ManagingDirector",
                "payload": {
                    "city": "Ottobrunn",
                    "dob": "1986-10-31",
                    "flag": "jeweils einzelvertretungsberechtigt mit der Befugnis im Namen der Gesellschaft mit sich im eigenen Namen oder als Vertreter eines Dritten Rechtsgeschäfte abzuschließen",
                    "lastname": "Kamberi",
                    "name": "Valon"
                },
                "text": " Kamberi, Valon, Ottobrunn, *31.10.1986, jeweils einzelvertretungsberechtigt mit der Befugnis im Namen der Gesellschaft mit sich im eigenen Namen oder als Vertreter eines Dritten Rechtsgeschäfte abzuschließen."
            }
        ]
    }
}