{
    "orig": {
        "aktenzeichen": "HRB 2004",
        "amtsgericht": "Bad Oeynhausen",
        "event_date": "2016-05-02",
        "event_type": "Veränderungen",
        "federal_state": "nw",
        "full_text": "Amtsgericht Bad Oeynhausen Aktenzeichen: HRB 2004 \nBekannt gemacht am: 02.05.2016 20:10 Uhr\n\n\n\n\nIn () gesetzte Angaben der Anschrift und des Geschäftszweiges erfolgen ohne Gewähr.\nVeränderungen\n02.05.2016\n\nHRB 2004: Helmerding hiw Maschinen GmbH, Bad Oeynhausen, Königstraße 132, 32547 Bad Oeynhausen. Bestellt als Geschäftsführer: Priske, Bernd, Willich, *07.07.1959, einzelvertretungsberechtigt mit der Befugnis im Namen der Gesellschaft mit sich im eigenen Namen oder als Vertreter eines Dritten Rechtsgeschäfte abzuschließen. Nicht mehr Geschäftsführer: Hallinger, Lieselotte, Bad Oeynhausen, *11.07.1944.",
        "gesellschafter": null,
        "inhaber": null,
        "name": "HRB 2004: Helmerding hiw Maschinen GmbH",
        "notice_id": "1280314",
        "posted_on": "2016-05-02",
        "rechtsform": null,
        "sitz": null,
        "url": "https://www.handelsregisterbekanntmachungen.de/en/skripte/hrb.php?rb_id=1280314&land_abk=nw"
    },
    "parsed": {
        "officers": [
            {
                "class": "AppointedManagingDirector",
                "payload": {
                    "city": "Willich",
                    "dob": "1959-07-07",
                    "flag": "einzelvertretungsberechtigt mit der Befugnis im Namen der Gesellschaft mit sich im eigenen Namen oder als Vertreter eines Dritten Rechtsgeschäfte abzuschließen",
                    "lastname": "Priske",
                    "name": "Bernd"
                },
                "text": " Priske, Bernd, Willich, *07.07.1959, einzelvertretungsberechtigt mit der Befugnis im Namen der Gesellschaft mit sich im eigenen Namen oder als Vertreter eines Dritten Rechtsgeschäfte abzuschließen."
            },
            {
                "class": "DismissedManagingDirector",
                "payload": {
                    "city": "Bad Oeynhausen",
                    "dismissed": true,
                    "dob": "1944-11-07",
                    "lastname": "Hallinger",
                    "name": "Lieselotte"
                },
                "text": " Hallinger, Lieselotte, Bad Oeynhausen, *11.07.1944."
            }
        ]
    }
}