{
    "orig": {
        "aktenzeichen": "HRB 8406",
        "amtsgericht": "Siegburg",
        "event_date": "2016-09-19",
        "event_type": "Veränderungen",
        "federal_state": "nw",
        "full_text": "Amtsgericht Siegburg Aktenzeichen: HRB 8406 \nBekannt gemacht am: 19.09.2016 20:17 Uhr\n\n\n\n\nIn () gesetzte Angaben der Anschrift und des Geschäftszweiges erfolgen ohne Gewähr.\nVeränderungen\n19.09.2016\n\nHRB 8406: Azelis Deutschland GmbH, Sankt Augustin, Zum Siegblick 37-45, 53757 Sankt Augustin. Geschäftsführer: Bakker, Thijs, Singapore / Singapur, *06.07.1974; Bertona, Anna, Kapellen / Belgien, *22.04.1967, jeweils mit der Befugnis im Namen der Gesellschaft mit sich im eigenen Namen oder als Vertreter eines Dritten Rechtsgeschäfte abzuschließen. Nicht mehr Geschäftsführer: Hollenhorst, Martin, Wiesbaden, *28.08.1959. Gesamtprokura gemeinsam mit einem Geschäftsführer oder einem anderen Prokuristen: von Deylen, Jörg, Meerbusch, *09.05.1978.",
        "gesellschafter": null,
        "inhaber": null,
        "name": "HRB 8406: Azelis Deutschland GmbH",
        "notice_id": "1326841",
        "posted_on": "2016-09-19",
        "rechtsform": null,
        "sitz": null,
        "url": "https://www.handelsregisterbekanntmachungen.de/en/skripte/hrb.php?rb_id=1326841&land_abk=nw"
    },
    "parsed": {
        "officers": [
            {
                "class": "ManagingDirector",
                "payload": {
                    "city": "Singapore / Singapur",
                    "dob": "1974-07-06",
                    "lastname": "Bakker",
                    "name": "Thijs"
                },
                "text": " Bakker, Thijs, Singapore / Singapur, *06.07.1974"
            },
            {
                "class": "ManagingDirector",
                "payload": {
                    "city": "Kapellen / Belgien",
                    "dob": "1967-04-22",
                    "flag": "jeweils mit der Befugnis im Namen der Gesellschaft mit sich im eigenen Namen oder als Vertreter eines Dritten Rechtsgeschäfte abzuschließen",
                    "lastname": "Bertona",
                    "name": "Anna"
                },
                "text": " Bertona, Anna, Kapellen / Belgien, *22.04.1967, jeweils mit der Befugnis im Namen der Gesellschaft mit sich im eigenen Namen oder als Vertreter eines Dritten Rechtsgeschäfte abzuschließen."
            },
            {
                "class": "DismissedManagingDirector",
                "payload": {
                    "city": "Wiesbaden",
                    "dismissed": true,
                    "dob": "1959-08-28",
                    "lastname": "Hollenhorst",
                    "name": "Martin"
                },
                "text": " Hollenhorst, Martin, Wiesbaden, *28.08.1959."
            },
            {
                "class": "CommonProcuration",
                "payload": {
                    "city": "Meerbusch",
                    "dob": "1978-05-09",
                    "lastname": "von Deylen",
                    "name": "Jörg"
                },
                "text": " von Deylen, Jörg, Meerbusch, *09.05.1978."
            }
        ]
    }
}