{
    "orig": {
        "aktenzeichen": "HRB 23450",
        "amtsgericht": "Düsseldorf",
        "event_date": "2016-09-23",
        "event_type": "Veränderungen",
        "federal_state": "nw",
        "full_text": "Amtsgericht Düsseldorf Aktenzeichen: HRB 23450 \nBekannt gemacht am: 23.09.2016 20:17 Uhr\n\n\n\n\nIn () gesetzte Angaben der Anschrift und des Geschäftszweiges erfolgen ohne Gewähr.\nVeränderungen\n23.09.2016\n\nHRB 23450: JOP Joker Office Products GmbH, Düsseldorf, Faunastraße 17, 40239 Düsseldorf. Die Gesellschaft ist aufgelöst. Ist ein Liquidator bestellt, vertritt er allein. Sind mehrere Liquidatoren bestellt, vertreten diese die Gesellschaft gemeinsam. Nicht mehr Geschäftsführer: Grau, Rita, kaufmännische Angestellte, Leichlingen, *25.05.1961. Bestellt als Liquidator: Bauer, Karl Heinz, Düsseldorf, *05.03.1946, einzelvertretungsberechtigt mit der Befugnis im Namen der Gesellschaft mit sich im eigenen Namen oder als Vertreter eines Dritten Rechtsgeschäfte abzuschließen.",
        "gesellschafter": null,
        "inhaber": null,
        "name": "HRB 23450: JOP Joker Office Products GmbH",
        "notice_id": "1328746",
        "posted_on": "2016-09-23",
        "rechtsform": null,
        "sitz": null,
        "url": "https://www.handelsregisterbekanntmachungen.de/en/skripte/hrb.php?rb_id=1328746&land_abk=nw"
    },
    "parsed": {
        "flags": [
            {
                "flag": "CompanyClosed",
                "text": "Die\\ Gesellschaft\\ ist\\ aufgel\\öst\\."
            }
        ],
        "officers": [
            {
                "class": "DismissedManagingDirector",
                "payload": {
                    "city": "Leichlingen",
                    "dismissed": true,
                    "dob": "1961-05-25",
                    "lastname": "Grau",
                    "name": "Rita",
                    "position": "kaufmännische Angestellte"
                },
                "text": " Grau, Rita, kaufmännische Angestellte, Leichlingen, *25.05.1961."
            },
            {
                "class": "Liquidator",
                "payload": {
                    "city": "Düsseldorf",
                    "dob": "1946-05-03",
                    "flag": "einzelvertretungsberechtigt mit der Befugnis im Namen der Gesellschaft mit sich im eigenen Namen oder als Vertreter eines Dritten Rechtsgeschäfte abzuschließen",
                    "lastname": "Bauer",
                    "name": "Karl Heinz"
                },
                "text": " Bauer, Karl Heinz, Düsseldorf, *05.03.1946, einzelvertretungsberechtigt mit der Befugnis im Namen der Gesellschaft mit sich im eigenen Namen oder als Vertreter eines Dritten Rechtsgeschäfte abzuschließen."
            }
        ]
    }
}