{
    "orig": {
        "aktenzeichen": "HRB 17213",
        "amtsgericht": "Duisburg",
        "event_date": "2006-05-30",
        "event_type": "Veränderungen",
        "federal_state": "nw",
        "full_text": "Amtsgericht Duisburg Aktenzeichen: HRB 17213 \nBekannt gemacht am: 02.06.2006 10:22 Uhr\n\n\n\n\nDie in ( ) gesetzten Angaben der Geschäftsanschrift und des Geschäftszweiges erfolgen ohne Gewähr.\nVeränderungen\n30.05.2006\n\nVVF-Immobilien GmbH, Duisburg (Gneisenaustr. 79, 47057 Duisburg). Die Gesellschafterversammlung vom 31.03.2006 hat eine Änderung des Gesellschaftsvertrages in § 1 Ziffer (1) und mit ihr die Änderung der Firma beschlossen. Neue Firma: UnserMakler GmbH. Neu bestellt zum weiteren Geschäftsführer: Müller, Dieter, Geldern, *02.06.1944, einzelvertretungsberechtigt mit der Befugnis im Namen der Gesellschaft mit sich im eigenen Namen oder als Vertreter eines Dritten Rechtsgeschäfte abzuschließen. Nach Änderung der besonderen Vertretungsbefugnis weiterhin: Geschäftsführer: Müller, Thomas, Duisburg, *02.03.1966, einzelvertretungsberechtigt mit der Befugnis im Namen der Gesellschaft mit sich im eigenen Namen oder als Vertreter eines Dritten Rechtsgeschäfte abzuschließen.",
        "gesellschafter": null,
        "inhaber": null,
        "name": "VVF-Immobilien GmbH",
        "notice_id": "134202",
        "posted_on": "2006-06-02",
        "rechtsform": null,
        "sitz": null,
        "url": "https://www.handelsregisterbekanntmachungen.de/en/skripte/hrb.php?rb_id=134202&land_abk=nw"
    },
    "parsed": {
        "officers": [
            {
                "class": "ManagingDirector",
                "payload": {
                    "city": "Geldern",
                    "dob": "1944-02-06",
                    "flag": "einzelvertretungsberechtigt mit der Befugnis im Namen der Gesellschaft mit sich im eigenen Namen oder als Vertreter eines Dritten Rechtsgeschäfte abzuschließen",
                    "lastname": "Müller",
                    "name": "Dieter"
                },
                "text": " Müller, Dieter, Geldern, *02.06.1944, einzelvertretungsberechtigt mit der Befugnis im Namen der Gesellschaft mit sich im eigenen Namen oder als Vertreter eines Dritten Rechtsgeschäfte abzuschließen."
            },
            {
                "class": "ManagingDirector",
                "payload": {
                    "city": "Duisburg",
                    "dob": "1966-02-03",
                    "flag": "einzelvertretungsberechtigt mit der Befugnis im Namen der Gesellschaft mit sich im eigenen Namen oder als Vertreter eines Dritten Rechtsgeschäfte abzuschließen",
                    "lastname": "Müller",
                    "name": "Thomas"
                },
                "text": " Müller, Thomas, Duisburg, *02.03.1966, einzelvertretungsberechtigt mit der Befugnis im Namen der Gesellschaft mit sich im eigenen Namen oder als Vertreter eines Dritten Rechtsgeschäfte abzuschließen."
            }
        ]
    }
}