{
    "orig": {
        "aktenzeichen": "HRB 77442",
        "amtsgericht": "Köln",
        "event_date": "2016-12-06",
        "event_type": "Veränderungen",
        "federal_state": "nw",
        "full_text": "Amtsgericht Köln Aktenzeichen: HRB 77442 \nBekannt gemacht am: 06.12.2016 20:02 Uhr\n\n\n\n\nIn () gesetzte Angaben der Anschrift und des Geschäftszweiges erfolgen ohne Gewähr.\nVeränderungen\n06.12.2016\n\nHRB 77442: flat-clean GmbH, Köln, Remscheider Strasse 47, 51103 Köln. Änderung zur Geschäftsanschrift: Bertramstr. 2, 51103 Köln. Nicht mehr Geschäftsführer: Rasul, Nabas Abdullah, Köln, *10.06.1969. Bestellt als Geschäftsführer: Abdukadir, Ako, Köln, *01.11.1968, einzelvertretungsberechtigt mit der Befugnis im Namen der Gesellschaft mit sich im eigenen Namen oder als Vertreter eines Dritten Rechtsgeschäfte abzuschließen.",
        "gesellschafter": null,
        "inhaber": null,
        "name": "HRB 77442: flat-clean GmbH",
        "notice_id": "1351903",
        "posted_on": "2016-12-06",
        "rechtsform": null,
        "sitz": null,
        "url": "https://www.handelsregisterbekanntmachungen.de/en/skripte/hrb.php?rb_id=1351903&land_abk=nw"
    },
    "parsed": {
        "labels": [
            {
                "label": "address",
                "text": " Bertramstr."
            }
        ],
        "officers": [
            {
                "class": "DismissedManagingDirector",
                "payload": {
                    "city": "Köln",
                    "dismissed": true,
                    "dob": "1969-06-10",
                    "lastname": "Rasul",
                    "name": "Nabas Abdullah"
                },
                "text": " Rasul, Nabas Abdullah, Köln, *10.06.1969."
            },
            {
                "class": "AppointedManagingDirector",
                "payload": {
                    "city": "Köln",
                    "dob": "1968-11-01",
                    "flag": "einzelvertretungsberechtigt mit der Befugnis im Namen der Gesellschaft mit sich im eigenen Namen oder als Vertreter eines Dritten Rechtsgeschäfte abzuschließen",
                    "lastname": "Abdukadir",
                    "name": "Ako"
                },
                "text": " Abdukadir, Ako, Köln, *01.11.1968, einzelvertretungsberechtigt mit der Befugnis im Namen der Gesellschaft mit sich im eigenen Namen oder als Vertreter eines Dritten Rechtsgeschäfte abzuschließen."
            }
        ]
    }
}