{
    "orig": {
        "aktenzeichen": "HRB 37513",
        "amtsgericht": "Düsseldorf",
        "event_date": "2016-12-09",
        "event_type": "Veränderungen",
        "federal_state": "nw",
        "full_text": "Amtsgericht Düsseldorf Aktenzeichen: HRB 37513 \nBekannt gemacht am: 09.12.2016 20:02 Uhr\n\n\n\n\nIn () gesetzte Angaben der Anschrift und des Geschäftszweiges erfolgen ohne Gewähr.\nVeränderungen\n09.12.2016\n\nHRB 37513: BeKu Automaten & Gastronomie Service GmbH, Düsseldorf, Münsterstraße 336, 40470 Düsseldorf. Änderung zur Geschäftsanschrift: Theuerbach 30, 88630 Pfullendorf. Nicht mehr Geschäftsführer: Korovko, Volodymyr, Wuppertal, *05.07.1963. Bestellt als Geschäftsführer: Moßbrucker, Martin, Pfullendorf, *12.02.1972, einzelvertretungsberechtigt mit der Befugnis im Namen der Gesellschaft mit sich als Vertreter eines Dritten Rechtsgeschäfte abzuschließen.",
        "gesellschafter": null,
        "inhaber": null,
        "name": "HRB 37513: BeKu Automaten & Gastronomie Service GmbH",
        "notice_id": "1353555",
        "posted_on": "2016-12-09",
        "rechtsform": null,
        "sitz": null,
        "url": "https://www.handelsregisterbekanntmachungen.de/en/skripte/hrb.php?rb_id=1353555&land_abk=nw"
    },
    "parsed": {
        "labels": [
            {
                "label": "address",
                "text": " Theuerbach 30, 88630 Pfullendorf."
            }
        ],
        "officers": [
            {
                "class": "DismissedManagingDirector",
                "payload": {
                    "city": "Wuppertal",
                    "dismissed": true,
                    "dob": "1963-05-07",
                    "lastname": "Korovko",
                    "name": "Volodymyr"
                },
                "text": " Korovko, Volodymyr, Wuppertal, *05.07.1963."
            },
            {
                "class": "AppointedManagingDirector",
                "payload": {
                    "city": "Pfullendorf",
                    "dob": "1972-12-02",
                    "flag": "einzelvertretungsberechtigt mit der Befugnis im Namen der Gesellschaft mit sich als Vertreter eines Dritten Rechtsgeschäfte abzuschließen",
                    "lastname": "Moßbrucker",
                    "name": "Martin"
                },
                "text": " Moßbrucker, Martin, Pfullendorf, *12.02.1972, einzelvertretungsberechtigt mit der Befugnis im Namen der Gesellschaft mit sich als Vertreter eines Dritten Rechtsgeschäfte abzuschließen."
            }
        ]
    }
}