{
    "orig": {
        "aktenzeichen": "HRB 4546",
        "amtsgericht": "Köln",
        "event_date": "2006-06-13",
        "event_type": "Veränderungen",
        "federal_state": "nw",
        "full_text": "Amtsgericht Köln Aktenzeichen: HRB 4546 \nBekannt gemacht am: 20.06.2006 10:43 Uhr\n\n\n\n\nDie in () gesetzten Angaben der Geschäftsanschrift und des Geschäftszweiges erfolgen ohne Gewähr.\nVeränderungen\n13.06.2006\n\nEgmont vgs verlagsgesellschaft mbH, Köln (Gertrudenstr. 30 - 36, 50667 Köln). Nicht mehr Geschäftsführer: Schweins, Michael. Bestellt als Geschäftsführer: Firnig, Klaus-Thorsten, Berlin, *02.06.1963. Bestellt als Geschäftsführer: Knau, Frank, Berlin, *09.03.1958, mit der Befugnis im Namen der Gesellschaft mit sich im eigenen Namen oder als Vertreter eines Dritten Rechtsgeschäfte abzuschließen. Gesamtprokura gemeinsam mit einem Geschäftsführer: Allendorf, Matthias, München, *27.01.1961.",
        "gesellschafter": null,
        "inhaber": null,
        "name": "Egmont vgs verlagsgesellschaft mbH",
        "notice_id": "137209",
        "posted_on": "2006-06-20",
        "rechtsform": null,
        "sitz": null,
        "url": "https://www.handelsregisterbekanntmachungen.de/en/skripte/hrb.php?rb_id=137209&land_abk=nw"
    },
    "parsed": {
        "officers": [
            {
                "class": "DismissedManagingDirector",
                "payload": {
                    "dismissed": true,
                    "lastname": "Schweins",
                    "name": "Michael"
                },
                "text": " Schweins, Michael."
            },
            {
                "class": "AppointedManagingDirector",
                "payload": {
                    "city": "Berlin",
                    "dob": "1963-02-06",
                    "lastname": "Firnig",
                    "name": "Klaus-Thorsten"
                },
                "text": " Firnig, Klaus-Thorsten, Berlin, *02.06.1963."
            },
            {
                "class": "AppointedManagingDirector",
                "payload": {
                    "city": "Berlin",
                    "dob": "1958-09-03",
                    "flag": "mit der Befugnis im Namen der Gesellschaft mit sich im eigenen Namen oder als Vertreter eines Dritten Rechtsgeschäfte abzuschließen",
                    "lastname": "Knau",
                    "name": "Frank"
                },
                "text": " Knau, Frank, Berlin, *09.03.1958, mit der Befugnis im Namen der Gesellschaft mit sich im eigenen Namen oder als Vertreter eines Dritten Rechtsgeschäfte abzuschließen."
            },
            {
                "class": "ManagingDirector",
                "payload": {
                    "city": "München",
                    "dob": "1961-01-27",
                    "lastname": "Allendorf",
                    "name": "Matthias"
                },
                "text": " Allendorf, Matthias, München, *27.01.1961."
            }
        ]
    }
}