{
    "orig": {
        "aktenzeichen": "HRB 81427",
        "amtsgericht": "Saarbrücken",
        "event_date": "2007-12-20",
        "event_type": "Veränderungen",
        "federal_state": "sl",
        "full_text": "Amtsgericht Saarbrücken Aktenzeichen: HRB 81427 \nBekannt gemacht am: 02.01.2008 12:00 Uhr\n\n\n\n\nDie in () gesetzten Angaben der Geschäftsanschrift und des Unternehmensgegenstandes erfolgen ohne Gewähr.\nVeränderungen\n20.12.2007\n\nDAM Deutschland GmbH, Nohfelden (Saarbrücker Straße 25, 66625 Nohfelden). Bestellt zum Geschäftsführer: Besnault, David Pierre, Versailles/Frankreich, *25.04.1970, einzelvertretungsberechtigt mit der Befugnis im Namen der Gesellschaft mit sich im eigenen Namen oder als Vertreter eines Dritten Rechtsgeschäfte abzuschließen. Nicht mehr Geschäftsführer: Lebrun, Marc, LePecq/Frankreich, *26.11.1953.",
        "gesellschafter": null,
        "inhaber": null,
        "name": "DAM Deutschland GmbH",
        "notice_id": "13827",
        "posted_on": "2008-01-02",
        "rechtsform": null,
        "sitz": null,
        "url": "https://www.handelsregisterbekanntmachungen.de/en/skripte/hrb.php?rb_id=13827&land_abk=sl"
    },
    "parsed": {
        "officers": [
            {
                "class": "ManagingDirector",
                "payload": {
                    "city": "Versailles/Frankreich",
                    "dob": "1970-04-25",
                    "flag": "einzelvertretungsberechtigt mit der Befugnis im Namen der Gesellschaft mit sich im eigenen Namen oder als Vertreter eines Dritten Rechtsgeschäfte abzuschließen",
                    "lastname": "Besnault",
                    "name": "David Pierre"
                },
                "text": " Besnault, David Pierre, Versailles/Frankreich, *25.04.1970, einzelvertretungsberechtigt mit der Befugnis im Namen der Gesellschaft mit sich im eigenen Namen oder als Vertreter eines Dritten Rechtsgeschäfte abzuschließen."
            },
            {
                "class": "DismissedManagingDirector",
                "payload": {
                    "city": "LePecq/Frankreich",
                    "dismissed": true,
                    "dob": "1953-11-26",
                    "lastname": "Lebrun",
                    "name": "Marc"
                },
                "text": " Lebrun, Marc, LePecq/Frankreich, *26.11.1953."
            }
        ]
    }
}