{
    "orig": {
        "aktenzeichen": "HRB 27832",
        "amtsgericht": "Dresden",
        "event_date": "2012-09-27",
        "event_type": "Veränderungen",
        "federal_state": "sn",
        "full_text": "Amtsgericht Dresden Aktenzeichen: HRB 27832   \nBekannt gemacht am: 04.10.2012 12:00 Uhr\n\n\n\n\nDie in () gesetzten Angaben der Geschäftsanschrift und des  Unternehmensgegenstandes erfolgen ohne Gewähr.\nVeränderungen\n27.09.2012\n\nDoble Lemke GmbH, Wilsdruff, Zschoner Ring 9, 01723 Wilsdruff OT Kesselsdorf. Ausgeschieden: Geschäftsführer: Richey jr., Victor Lee, St. Louis, MO 63119, *10.08.1957. Bestellt: Geschäftsführer: Garretson, Richard, Smithton, IL/USA, *20.12.1958; Stromme, Arvid, Trondheim/Norwegen, *21.05.1964, jeweils einzelvertretungsberechtigt; mit der Befugnis, im Namen der Gesellschaft mit sich als Vertreter eines Dritten Rechtsgeschäfte abzuschließen.",
        "gesellschafter": null,
        "inhaber": null,
        "name": "Doble Lemke GmbH",
        "notice_id": "138588",
        "posted_on": "2012-10-04",
        "rechtsform": null,
        "sitz": null,
        "url": "https://www.handelsregisterbekanntmachungen.de/en/skripte/hrb.php?rb_id=138588&land_abk=sn"
    },
    "parsed": {
        "officers": [
            {
                "class": "RetiredManagingDirector",
                "payload": {
                    "city": "MO 63119",
                    "dismissed": true,
                    "dob": "1957-10-08",
                    "lastname": "Richey jr",
                    "name": "Victor Lee",
                    "position": "St. Louis"
                },
                "text": " Richey jr., Victor Lee, St. Louis, MO 63119, *10.08.1957."
            },
            {
                "class": "AppointedManagingDirector",
                "payload": {
                    "city": "IL/USA",
                    "dob": "1958-12-20",
                    "lastname": "Garretson",
                    "name": "Richard",
                    "position": "Smithton"
                },
                "text": " Garretson, Richard, Smithton, IL/USA, *20.12.1958"
            }
        ]
    }
}