{
    "orig": {
        "aktenzeichen": "HRB 14486",
        "amtsgericht": "Kleve",
        "event_date": "2017-03-03",
        "event_type": "Veränderungen",
        "federal_state": "nw",
        "full_text": "Amtsgericht Kleve Aktenzeichen: HRB 14486 \nBekannt gemacht am: 03.03.2017 20:01 Uhr\n\n\n\n\nIn () gesetzte Angaben der Anschrift und des Geschäftszweiges erfolgen ohne Gewähr.\nVeränderungen\n03.03.2017\n\nHRB 14486: Etteplan Deutschland GmbH, Neukirchen-Vluyn, Weserstraße 4, 47506 Neukirchen-Vluyn. Nicht mehr Geschäftsführer: Ikonen, Petri T., Best / Niederlande, *24.10.1964. Bestellt als Geschäftsführer: Vatn, Tom Mikael, Täby / Schweden, *02.09.1967, einzelvertretungsberechtigt mit der Befugnis im Namen der Gesellschaft mit sich im eigenen Namen oder als Vertreter eines Dritten Rechtsgeschäfte abzuschließen. Gesamtprokura gemeinsam mit einem Geschäftsführer oder einem anderen Prokuristen: Bauer, Michael, Wesel, *17.09.1969.",
        "gesellschafter": null,
        "inhaber": null,
        "name": "HRB 14486: Etteplan Deutschland GmbH",
        "notice_id": "1386560",
        "posted_on": "2017-03-03",
        "rechtsform": null,
        "sitz": null,
        "url": "https://www.handelsregisterbekanntmachungen.de/en/skripte/hrb.php?rb_id=1386560&land_abk=nw"
    },
    "parsed": {
        "officers": [
            {
                "class": "DismissedManagingDirector",
                "payload": {
                    "city": "Best / Niederlande",
                    "dismissed": true,
                    "dob": "1964-10-24",
                    "lastname": "Ikonen",
                    "name": "Petri T"
                },
                "text": " Ikonen, Petri T., Best / Niederlande, *24.10.1964."
            },
            {
                "class": "AppointedManagingDirector",
                "payload": {
                    "city": "Täby / Schweden",
                    "dob": "1967-02-09",
                    "flag": "einzelvertretungsberechtigt mit der Befugnis im Namen der Gesellschaft mit sich im eigenen Namen oder als Vertreter eines Dritten Rechtsgeschäfte abzuschließen",
                    "lastname": "Vatn",
                    "name": "Tom Mikael"
                },
                "text": " Vatn, Tom Mikael, Täby / Schweden, *02.09.1967, einzelvertretungsberechtigt mit der Befugnis im Namen der Gesellschaft mit sich im eigenen Namen oder als Vertreter eines Dritten Rechtsgeschäfte abzuschließen."
            },
            {
                "class": "CommonProcuration",
                "payload": {
                    "city": "Wesel",
                    "dob": "1969-09-17",
                    "lastname": "Bauer",
                    "name": "Michael"
                },
                "text": " Bauer, Michael, Wesel, *17.09.1969."
            }
        ]
    }
}