{
    "orig": {
        "aktenzeichen": "HRA 4336",
        "amtsgericht": "Steinfurt",
        "event_date": "2017-03-22",
        "event_type": "Löschungen",
        "federal_state": "nw",
        "full_text": "Amtsgericht Steinfurt Aktenzeichen: HRA 4336 \nBekannt gemacht am: 22.03.2017 20:00 Uhr\n\n\n\n\nIn () gesetzte Angaben der Anschrift und des Geschäftszweiges erfolgen ohne Gewähr.\nLöschungen\n22.03.2017\n\nHRA 4336: NFT Automatisierungssysteme OHG, Ibbenbüren, Ignatz-Wiemeler-Str. 16, 49477 Ibbenbüren. Ausgeschieden als Persönlich haftender Gesellschafter: Hacks, Frank, Hasbergen, *03.10.1966; Lühn, Klaus, Spelle, *29.04.1968. Eingetreten als Persönlich haftender Gesellschafter: Haacks, Monika, Georgsmarienhütte, *18.06.1968, mit der Befugnis im Namen der Gesellschaft mit sich im eigenen Namen oder als Vertreter eines Dritten Rechtsgeschäfte abzuschließen. Die Gesellschaft ist aufgelöst und ohne Liquidation erloschen.",
        "gesellschafter": null,
        "inhaber": null,
        "name": "HRA 4336: NFT Automatisierungssysteme OHG",
        "notice_id": "1393434",
        "posted_on": "2017-03-22",
        "rechtsform": null,
        "sitz": null,
        "url": "https://www.handelsregisterbekanntmachungen.de/en/skripte/hrb.php?rb_id=1393434&land_abk=nw"
    },
    "parsed": {
        "officers": [
            {
                "class": "RetiredPersonalPartner",
                "payload": {
                    "city": "Hasbergen",
                    "dismissed": true,
                    "dob": "1966-10-03",
                    "lastname": "Hacks",
                    "name": "Frank"
                },
                "text": " Hacks, Frank, Hasbergen, *03.10.1966"
            },
            {
                "class": "RetiredPersonalPartner",
                "payload": {
                    "city": "Spelle",
                    "dismissed": true,
                    "dob": "1968-04-29",
                    "lastname": "Lühn",
                    "name": "Klaus"
                },
                "text": " Lühn, Klaus, Spelle, *29.04.1968."
            },
            {
                "class": "PersonalPartner",
                "payload": {
                    "city": "Georgsmarienhütte",
                    "dob": "1968-06-18",
                    "flag": "mit der Befugnis im Namen der Gesellschaft mit sich im eigenen Namen oder als Vertreter eines Dritten Rechtsgeschäfte abzuschließen",
                    "lastname": "Haacks",
                    "name": "Monika"
                },
                "text": " Haacks, Monika, Georgsmarienhütte, *18.06.1968, mit der Befugnis im Namen der Gesellschaft mit sich im eigenen Namen oder als Vertreter eines Dritten Rechtsgeschäfte abzuschließen."
            }
        ]
    }
}