{
    "orig": {
        "aktenzeichen": "HRB 26784",
        "amtsgericht": "Essen",
        "event_date": "2017-05-03",
        "event_type": "Veränderungen",
        "federal_state": "nw",
        "full_text": "Amtsgericht Essen Aktenzeichen: HRB 26784 \nBekannt gemacht am: 03.05.2017 20:01 Uhr\n\n\n\n\nIn () gesetzte Angaben der Anschrift und des Geschäftszweiges erfolgen ohne Gewähr.\nVeränderungen\n03.05.2017\n\nHRB 26784: WTS - Wärmetauscher Service Rohreinwalztechnik GmbH, Essen, Nordlandring 10, 45357 Essen. Bestellt zum Geschäftsführer: Könnings, Manfred, Essen, *06.04.1965. Nach Wohnortänderung (bisher: Oberhausen) nunmehr Geschäftsführer: Ochmann, Peter, Essen, *10.09.1957, mit der Befugnis im Namen der Gesellschaft mit sich im eigenen Namen oder als Vertreter eines Dritten Rechtsgeschäfte abzuschließen.",
        "gesellschafter": null,
        "inhaber": null,
        "name": "HRB 26784: WTS - Wärmetauscher Service Rohreinwalztechnik GmbH",
        "notice_id": "1406955",
        "posted_on": "2017-05-03",
        "rechtsform": null,
        "sitz": null,
        "url": "https://www.handelsregisterbekanntmachungen.de/en/skripte/hrb.php?rb_id=1406955&land_abk=nw"
    },
    "parsed": {
        "officers": [
            {
                "class": "ManagingDirector",
                "payload": {
                    "city": "Essen",
                    "dob": "1965-06-04",
                    "lastname": "Könnings",
                    "name": "Manfred"
                },
                "text": " Könnings, Manfred, Essen, *06.04.1965."
            },
            {
                "class": "ManagingDirector",
                "payload": {
                    "city": "Essen",
                    "dob": "1957-10-09",
                    "flag": "mit der Befugnis im Namen der Gesellschaft mit sich im eigenen Namen oder als Vertreter eines Dritten Rechtsgeschäfte abzuschließen",
                    "lastname": "Ochmann",
                    "name": "Peter"
                },
                "text": " Ochmann, Peter, Essen, *10.09.1957, mit der Befugnis im Namen der Gesellschaft mit sich im eigenen Namen oder als Vertreter eines Dritten Rechtsgeschäfte abzuschließen."
            }
        ]
    }
}