{
    "orig": {
        "aktenzeichen": "HRB 19292",
        "amtsgericht": "Essen",
        "event_date": "2017-05-03",
        "event_type": "Veränderungen",
        "federal_state": "nw",
        "full_text": "Amtsgericht Essen Aktenzeichen: HRB 19292 \nBekannt gemacht am: 03.05.2017 20:01 Uhr\n\n\n\n\nIn () gesetzte Angaben der Anschrift und des Geschäftszweiges erfolgen ohne Gewähr.\nVeränderungen\n03.05.2017\n\nHRB 19292: Pro Life Gesellschaft für Notfall- und Gesundheitsschulungen mbH, Essen, Kettwiger Str. 3, 45127 Essen. Bestellt zum Geschäftsführer: Bredenbröker, Katharina, Essen, *14.08.1988, einzelvertretungsberechtigt mit der Befugnis im Namen der Gesellschaft mit sich im eigenen Namen oder als Vertreter eines Dritten Rechtsgeschäfte abzuschließen. Prokura erloschen: Schemberg, Katharina, Bochum, *14.08.1988.",
        "gesellschafter": null,
        "inhaber": null,
        "name": "HRB 19292: Pro Life Gesellschaft für Notfall- und Gesundheitsschulungen mbH",
        "notice_id": "1406786",
        "posted_on": "2017-05-03",
        "rechtsform": null,
        "sitz": null,
        "url": "https://www.handelsregisterbekanntmachungen.de/en/skripte/hrb.php?rb_id=1406786&land_abk=nw"
    },
    "parsed": {
        "officers": [
            {
                "class": "ManagingDirector",
                "payload": {
                    "city": "Essen",
                    "dob": "1988-08-14",
                    "flag": "einzelvertretungsberechtigt mit der Befugnis im Namen der Gesellschaft mit sich im eigenen Namen oder als Vertreter eines Dritten Rechtsgeschäfte abzuschließen",
                    "lastname": "Bredenbröker",
                    "name": "Katharina"
                },
                "text": " Bredenbröker, Katharina, Essen, *14.08.1988, einzelvertretungsberechtigt mit der Befugnis im Namen der Gesellschaft mit sich im eigenen Namen oder als Vertreter eines Dritten Rechtsgeschäfte abzuschließen."
            },
            {
                "class": "ProcurationCancelled",
                "payload": {
                    "city": "Bochum",
                    "dismissed": true,
                    "dob": "1988-08-14",
                    "lastname": "Schemberg",
                    "name": "Katharina"
                },
                "text": " Schemberg, Katharina, Bochum, *14.08.1988."
            }
        ]
    }
}