{
    "orig": {
        "aktenzeichen": "HRB 12639",
        "amtsgericht": "Moenchengladbach",
        "event_date": "2017-05-04",
        "event_type": "Veränderungen",
        "federal_state": "nw",
        "full_text": "Amtsgericht Moenchengladbach Aktenzeichen: HRB 12639 \nBekannt gemacht am: 04.05.2017 20:01 Uhr\n\n\n\n\nIn () gesetzte Angaben der Anschrift und des Geschäftszweiges erfolgen ohne Gewähr.\nVeränderungen\n04.05.2017\n\nHRB 12639: Glitretind GmbH, Mönchengladbach, Hopfengarten 22, 41189 Mönchengladbach. Änderung zur Geschäftsanschrift: Prinzregentenstraße 48, c/o Heuking Kühn Lüer Wojtek, 80538 München. Ist ein Liquidator bestellt, vertritt er allein. Sind mehrere Liquidatoren bestellt, vertreten diese die Gesellschaft gemeinsam. Nicht mehr Geschäftsführer: Corneliussen, Susanne, Mönchengladbach, *09.01.1988. Bestellt als Liquidator: Becker, Fabian, München, *16.12.1984, mit der Befugnis im Namen der Gesellschaft mit sich im eigenen Namen oder als Vertreter eines Dritten Rechtsgeschäfte abzuschließen. Die Gesellschaft ist aufgelöst.",
        "gesellschafter": null,
        "inhaber": null,
        "name": "HRB 12639: Glitretind GmbH",
        "notice_id": "1407332",
        "posted_on": "2017-05-04",
        "rechtsform": null,
        "sitz": null,
        "url": "https://www.handelsregisterbekanntmachungen.de/en/skripte/hrb.php?rb_id=1407332&land_abk=nw"
    },
    "parsed": {
        "addresses": [
            {
                "kls": "Address",
                "text": "Prinzregentenstraße 48, c/o Heuking Kühn Lüer Wojtek, 80538 München"
            }
        ],
        "flags": [
            {
                "flag": "CompanyClosed",
                "text": "Die\\ Gesellschaft\\ ist\\ aufgel\\öst\\."
            }
        ],
        "officers": [
            {
                "class": "DismissedManagingDirector",
                "payload": {
                    "city": "Mönchengladbach",
                    "dismissed": true,
                    "dob": "1988-01-09",
                    "lastname": "Corneliussen",
                    "name": "Susanne"
                },
                "text": " Corneliussen, Susanne, Mönchengladbach, *09.01.1988."
            },
            {
                "class": "Liquidator",
                "payload": {
                    "city": "München",
                    "dob": "1984-12-16",
                    "flag": "mit der Befugnis im Namen der Gesellschaft mit sich im eigenen Namen oder als Vertreter eines Dritten Rechtsgeschäfte abzuschließen",
                    "lastname": "Becker",
                    "name": "Fabian"
                },
                "text": " Becker, Fabian, München, *16.12.1984, mit der Befugnis im Namen der Gesellschaft mit sich im eigenen Namen oder als Vertreter eines Dritten Rechtsgeschäfte abzuschließen."
            }
        ]
    }
}