{
    "orig": {
        "aktenzeichen": "HRA 24503",
        "amtsgericht": "Wuppertal",
        "event_date": "2017-05-09",
        "event_type": "Veränderungen",
        "federal_state": "nw",
        "full_text": "Amtsgericht Wuppertal Aktenzeichen: HRA 24503 \nBekannt gemacht am: 09.05.2017 20:02 Uhr\n\n\n\n\nIn () gesetzte Angaben der Anschrift und des Geschäftszweiges erfolgen ohne Gewähr.\nVeränderungen\n09.05.2017\n\nHRA 24503: Multicomsystem OHG, Erkrath, Steinhof 29, 40699 Erkrath. Ausgeschieden als Persönlich haftender Gesellschafter: Goßen, Bernhard, Düsseldorf, *31.03.1951. Eingetreten als Persönlich haftender Gesellschafter: Goßen, Nadine, Hilden, *28.12.1980, mit der Befugnis im Namen der Gesellschaft mit sich im eigenen Namen oder als Vertreter eines Dritten Rechtsgeschäfte abzuschließen. Einzelprokura: Goßen, Bernhard, Hilden, *31.03.1951.",
        "gesellschafter": null,
        "inhaber": null,
        "name": "HRA 24503: Multicomsystem OHG",
        "notice_id": "1408852",
        "posted_on": "2017-05-09",
        "rechtsform": null,
        "sitz": null,
        "url": "https://www.handelsregisterbekanntmachungen.de/en/skripte/hrb.php?rb_id=1408852&land_abk=nw"
    },
    "parsed": {
        "officers": [
            {
                "class": "RetiredPersonalPartner",
                "payload": {
                    "city": "Düsseldorf",
                    "dismissed": true,
                    "dob": "1951-03-31",
                    "lastname": "Goßen",
                    "name": "Bernhard"
                },
                "text": " Goßen, Bernhard, Düsseldorf, *31.03.1951."
            },
            {
                "class": "PersonalPartner",
                "payload": {
                    "city": "Hilden",
                    "dob": "1980-12-28",
                    "flag": "mit der Befugnis im Namen der Gesellschaft mit sich im eigenen Namen oder als Vertreter eines Dritten Rechtsgeschäfte abzuschließen",
                    "lastname": "Goßen",
                    "name": "Nadine"
                },
                "text": " Goßen, Nadine, Hilden, *28.12.1980, mit der Befugnis im Namen der Gesellschaft mit sich im eigenen Namen oder als Vertreter eines Dritten Rechtsgeschäfte abzuschließen."
            },
            {
                "class": "SingleProcuration",
                "payload": {
                    "city": "Hilden",
                    "dob": "1951-03-31",
                    "lastname": "Goßen",
                    "name": "Bernhard"
                },
                "text": " Goßen, Bernhard, Hilden, *31.03.1951."
            }
        ]
    }
}