{
    "orig": {
        "aktenzeichen": "HRB 25372",
        "amtsgericht": "Essen",
        "event_date": "2017-06-26",
        "event_type": "Veränderungen",
        "federal_state": "nw",
        "full_text": "Amtsgericht Essen Aktenzeichen: HRB 25372 \nBekannt gemacht am: 26.06.2017 20:00 Uhr\n\n\n\n\nIn () gesetzte Angaben der Anschrift und des Geschäftszweiges erfolgen ohne Gewähr.\nVeränderungen\n26.06.2017\n\nHRB 25372: MIR Im- und Export GmbH, Essen, Viehofer Straße 20, 45127 Essen. Die Gesellschafterversammlung hat am 21.06.2017 beschlossen, die Firma und den Gegenstand des Unternehmens sowie entsprechend den Gesellschaftsvertrag in §§ 1 (Firma und Sitz) und 2 (Gegenstand des Unternehmens) zu ändern. Neue Firma: Restaurant Habanna Club GmbH. Nach Änderung nunmehr: Geschäftsanschrift: Zweigertstr. 55, 45130 Essen. Neuer Unternehmensgegenstand: Der Betrieb von Gaststätten. Nicht mehr Geschäftsführer: Aldaoud, Hoschang, Essen, *19.10.1978. Bestellt zum Geschäftsführer: Haj Sulayman, Medya, Herne, *05.08.1975, mit der Befugnis im Namen der Gesellschaft mit sich im eigenen Namen oder als Vertreter eines Dritten Rechtsgeschäfte abzuschließen.",
        "gesellschafter": null,
        "inhaber": null,
        "name": "HRB 25372: MIR Im- und Export GmbH",
        "notice_id": "1422980",
        "posted_on": "2017-06-26",
        "rechtsform": null,
        "sitz": null,
        "url": "https://www.handelsregisterbekanntmachungen.de/en/skripte/hrb.php?rb_id=1422980&land_abk=nw"
    },
    "parsed": {
        "labels": [
            {
                "label": "address",
                "text": " Zweigertstr."
            }
        ],
        "officers": [
            {
                "class": "DismissedManagingDirector",
                "payload": {
                    "city": "Essen",
                    "dismissed": true,
                    "dob": "1978-10-19",
                    "lastname": "Aldaoud",
                    "name": "Hoschang"
                },
                "text": " Aldaoud, Hoschang, Essen, *19.10.1978."
            },
            {
                "class": "ManagingDirector",
                "payload": {
                    "city": "Herne",
                    "dob": "1975-08-05",
                    "flag": "mit der Befugnis im Namen der Gesellschaft mit sich im eigenen Namen oder als Vertreter eines Dritten Rechtsgeschäfte abzuschließen",
                    "lastname": "Haj Sulayman",
                    "name": "Medya"
                },
                "text": " Haj Sulayman, Medya, Herne, *05.08.1975, mit der Befugnis im Namen der Gesellschaft mit sich im eigenen Namen oder als Vertreter eines Dritten Rechtsgeschäfte abzuschließen."
            }
        ]
    }
}