{
    "orig": {
        "aktenzeichen": "HRB 35647",
        "amtsgericht": "Hamburg",
        "event_date": "2011-07-06",
        "event_type": "Veränderungen",
        "federal_state": "hh",
        "full_text": "Amtsgericht Hamburg Aktenzeichen: HRB 35647 \nBekannt gemacht am: 07.07.2011 12:00 Uhr\n\n\n\n\nIn () gesetzte Angaben der Anschrift und des Geschäftszweiges erfolgen ohne Gewähr.\nVeränderungen\n06.07.2011\n\nSENATOR Verwaltungsgesellschaft m.b.H., Hamburg, Bramfelder Chaussee 41, 22177 Hamburg. Die Gesellschafterversammlung vom 26.05.2011 hat die Änderung des Gesellschaftsvertrages in § 2 (Gegenstand des Unternehmens) beschlossen. Geschäftsanschrift: Bramfelder Chaussee 41, 22177 Hamburg. Neuer Unternehmensgegenstand: die Verwaltung von eigenem und fremdem Vermögen sowie alle damit im Zusammenhang stehenden Geschäfte mit Ausnahme einer Tätigkeit gemäß § 34c GewO oder sonstiger erlaubnispflichtiger Tätigkeiten; die Erbringung von Dienstleistungen jeglicher Art im Bürowesen, einschließlich Organisation, Werbung, Marketing und Unternehmensberatung, mit Ausnahme erlaubnispflichtiger Beratung; die Vertretung von Handelsfirmen und von Im- und Exporteuren sowie der Handel mit Waren aller Art, mit Ausnahme erlaubnispflichtiger Waren; die Erbringung von Vermittlungs- und Maklertätigkeiten. Ausgeschieden Geschäftsführer: Lux, Helmar, Kaufmann, Hamburg. Einzelprokura: Dosch, Karen, Hamburg, *04.10.1971. Prokura erloschen Lux, Christiane, Hamburg, *13.12.1947.",
        "gesellschafter": null,
        "inhaber": null,
        "name": "SENATOR Verwaltungsgesellschaft m.b.H.",
        "notice_id": "144128",
        "posted_on": "2011-07-07",
        "rechtsform": null,
        "sitz": null,
        "url": "https://www.handelsregisterbekanntmachungen.de/en/skripte/hrb.php?rb_id=144128&land_abk=hh"
    },
    "parsed": {
        "labels": [
            {
                "label": "address",
                "text": " Bramfelder Chaussee 41, 22177 Hamburg."
            }
        ],
        "officers": [
            {
                "class": "RetiredManagingDirector",
                "payload": {
                    "city": "Hamburg",
                    "dismissed": true,
                    "lastname": "Lux",
                    "name": "Helmar",
                    "position": "Kaufmann"
                },
                "text": " Lux, Helmar, Kaufmann, Hamburg."
            },
            {
                "class": "SingleProcuration",
                "payload": {
                    "city": "Hamburg",
                    "dob": "1971-04-10",
                    "lastname": "Dosch",
                    "name": "Karen"
                },
                "text": " Dosch, Karen, Hamburg, *04.10.1971."
            }
        ]
    }
}