{
    "orig": {
        "aktenzeichen": "HRB 71673",
        "amtsgericht": "Düsseldorf",
        "event_date": "2017-08-16",
        "event_type": "Veränderungen",
        "federal_state": "nw",
        "full_text": "Amtsgericht Düsseldorf Aktenzeichen: HRB 71673 \nBekannt gemacht am: 16.08.2017 20:02 Uhr\n\n\n\n\nIn () gesetzte Angaben der Anschrift und des Geschäftszweiges erfolgen ohne Gewähr.\nVeränderungen\n16.08.2017\n\nHRB 71673: SIGNA Investment AG, Düsseldorf, Benrather Str. 18-20, 40213 Düsseldorf. Nach Änderung der besonderen Vertretungsbefugnis Vorstand: Tölle, Frank, Düsseldorf, *09.07.1963, mit der Befugnis im Namen der Gesellschaft mit sich als Vertreter eines Dritten Rechtsgeschäfte abzuschließen. Bestellt als Vorstand: Kusdil, Oguz, Dachau, *21.09.1979, mit der Befugnis im Namen der Gesellschaft mit sich als Vertreter eines Dritten Rechtsgeschäfte abzuschließen.",
        "gesellschafter": null,
        "inhaber": null,
        "name": "HRB 71673: SIGNA Investment AG",
        "notice_id": "1442318",
        "posted_on": "2017-08-16",
        "rechtsform": null,
        "sitz": null,
        "url": "https://www.handelsregisterbekanntmachungen.de/en/skripte/hrb.php?rb_id=1442318&land_abk=nw"
    },
    "parsed": {
        "officers": [
            {
                "class": "Person",
                "payload": {
                    "city": "Dachau",
                    "dob": "1979-09-21",
                    "flag": "mit der Befugnis im Namen der Gesellschaft mit sich als Vertreter eines Dritten Rechtsgeschäfte abzuschließen",
                    "lastname": "Kusdil",
                    "name": "Oguz"
                },
                "text": ": Kusdil, Oguz, Dachau, *21.09.1979, mit der Befugnis im Namen der Gesellschaft mit sich als Vertreter eines Dritten Rechtsgeschäfte abzuschließen."
            }
        ]
    }
}