{
    "orig": {
        "aktenzeichen": "HRB 91239",
        "amtsgericht": "Köln",
        "event_date": "2017-08-21",
        "event_type": "Veränderungen",
        "federal_state": "nw",
        "full_text": "Amtsgericht Köln Aktenzeichen: HRB 91239 \nBekannt gemacht am: 21.08.2017 20:02 Uhr\n\n\n\n\nIn () gesetzte Angaben der Anschrift und des Geschäftszweiges erfolgen ohne Gewähr.\nVeränderungen\n21.08.2017\n\nHRB 91239: de-trust.de-Vorratsgesellschaft-257 GmbH, Köln, c/o DE-Trust GmbH, Koblenzer Straße 65, 53173 Bonn. Die Gesellschafterversammlung hat am 18.07.2017 beschlossen, die Firma und entsprechend den Gesellschaftsvertrag in § 1 Ziffer 1 zu ändern, den Gegenstand des Unternehmens und entsprechend den Gesellschaftsvertrag in § 2 Ziffer 1 zu ändern, sowie den Gesellschaftsvertrag in § 4 Ziffer 1 S. 2 (Stammkapital, Stammeinlage) zu ändern. § 5 Ziffer 6 (Geschäftsführung) wurde gestrichen. Neue Firma: Hipo Market GmbH. Änderung zur Geschäftsanschrift: Wittener Straße 38, 42277 Wuppertal. Neuer Unternehmensgegenstand: die Verwaltung eigenen Vermögens, Handel mit IT-Systemen, Großhandel von EDV-Geräten, Hardware und Zubehör. Nicht mehr Geschäftsführer: Schenk, Jan-Michael, Bonn, *04.05.1983. Bestellt als Geschäftsführer: Orlovskis, Normunds, Wuppertal, *05.11.1988, einzelvertretungsberechtigt mit der Befugnis im Namen der Gesellschaft mit sich im eigenen Namen oder als Vertreter eines Dritten Rechtsgeschäfte abzuschließen.",
        "gesellschafter": null,
        "inhaber": null,
        "name": "HRB 91239: de-trust.de-Vorratsgesellschaft-257 GmbH",
        "notice_id": "1443615",
        "posted_on": "2017-08-21",
        "rechtsform": null,
        "sitz": null,
        "url": "https://www.handelsregisterbekanntmachungen.de/en/skripte/hrb.php?rb_id=1443615&land_abk=nw"
    },
    "parsed": {
        "addresses": [
            {
                "kls": "Address",
                "text": "Wittener Straße 38, 42277 Wuppertal"
            }
        ],
        "officers": [
            {
                "class": "DismissedManagingDirector",
                "payload": {
                    "city": "Bonn",
                    "dismissed": true,
                    "dob": "1983-05-04",
                    "lastname": "Schenk",
                    "name": "Jan-Michael"
                },
                "text": " Schenk, Jan-Michael, Bonn, *04.05.1983."
            },
            {
                "class": "AppointedManagingDirector",
                "payload": {
                    "city": "Wuppertal",
                    "dob": "1988-11-05",
                    "flag": "einzelvertretungsberechtigt mit der Befugnis im Namen der Gesellschaft mit sich im eigenen Namen oder als Vertreter eines Dritten Rechtsgeschäfte abzuschließen",
                    "lastname": "Orlovskis",
                    "name": "Normunds"
                },
                "text": " Orlovskis, Normunds, Wuppertal, *05.11.1988, einzelvertretungsberechtigt mit der Befugnis im Namen der Gesellschaft mit sich im eigenen Namen oder als Vertreter eines Dritten Rechtsgeschäfte abzuschließen."
            }
        ]
    }
}