{
    "orig": {
        "aktenzeichen": "HRB 4017",
        "amtsgericht": "Steinfurt",
        "event_date": "2017-09-25",
        "event_type": "Veränderungen",
        "federal_state": "nw",
        "full_text": "Amtsgericht Steinfurt Aktenzeichen: HRB 4017 \nBekannt gemacht am: 25.09.2017 20:01 Uhr\n\n\n\n\nIn () gesetzte Angaben der Anschrift und des Geschäftszweiges erfolgen ohne Gewähr.\nVeränderungen\n25.09.2017\n\nHRB 4017: LOS Einkaufs- und Beteiligungs-Verwaltungs-GmbH, Emsdetten, Hollefeldstraße 46, 48282 Emsdetten. Nicht mehr Geschäftsführer: Lüke, Michael, Emsdetten, *16.12.1955; Ortmeier, Thomas, Emsdetten, *01.02.1959. Bestellt als Geschäftsführer: Ortmeier, Jörg, Emsdetten, *13.03.1975, einzelvertretungsberechtigt mit der Befugnis im Namen der Gesellschaft mit sich als Vertreter eines Dritten Rechtsgeschäfte abzuschließen.",
        "gesellschafter": null,
        "inhaber": null,
        "name": "HRB 4017: LOS Einkaufs- und Beteiligungs-Verwaltungs-GmbH",
        "notice_id": "1455682",
        "posted_on": "2017-09-25",
        "rechtsform": null,
        "sitz": null,
        "url": "https://www.handelsregisterbekanntmachungen.de/en/skripte/hrb.php?rb_id=1455682&land_abk=nw"
    },
    "parsed": {
        "officers": [
            {
                "class": "DismissedManagingDirector",
                "payload": {
                    "city": "Emsdetten",
                    "dismissed": true,
                    "dob": "1955-12-16",
                    "lastname": "Lüke",
                    "name": "Michael"
                },
                "text": " Lüke, Michael, Emsdetten, *16.12.1955"
            },
            {
                "class": "AppointedManagingDirector",
                "payload": {
                    "city": "Emsdetten",
                    "dob": "1975-03-13",
                    "flag": "einzelvertretungsberechtigt mit der Befugnis im Namen der Gesellschaft mit sich als Vertreter eines Dritten Rechtsgeschäfte abzuschließen",
                    "lastname": "Ortmeier",
                    "name": "Jörg"
                },
                "text": " Ortmeier, Jörg, Emsdetten, *13.03.1975, einzelvertretungsberechtigt mit der Befugnis im Namen der Gesellschaft mit sich als Vertreter eines Dritten Rechtsgeschäfte abzuschließen."
            }
        ]
    }
}