{
    "orig": {
        "aktenzeichen": "HRB 16005",
        "amtsgericht": "Aachen",
        "event_date": "2017-09-29",
        "event_type": "Veränderungen",
        "federal_state": "nw",
        "full_text": "Amtsgericht Aachen Aktenzeichen: HRB 16005 \nBekannt gemacht am: 29.09.2017 20:01 Uhr\n\n\n\n\nIn () gesetzte Angaben der Anschrift und des Geschäftszweiges erfolgen ohne Gewähr.\nVeränderungen\n29.09.2017\n\nHRB 16005: \"Dentes\"-Dental-Labor GmbH, Aachen, Schildstraße 12-14, 52062 Aachen. Änderung zur Geschäftsanschrift: Friedrich-Franz-Straße 13, 12103 Berlin. Nicht mehr Geschäftsführer: Heigl, Andre, Aachen, *11.10.1958. Bestellt als Geschäftsführer: Bülowius, Gerti, Fürstenwalde, *02.06.1961, einzelvertretungsberechtigt mit der Befugnis im Namen der Gesellschaft mit sich im eigenen Namen oder als Vertreter eines Dritten Rechtsgeschäfte abzuschließen.",
        "gesellschafter": null,
        "inhaber": null,
        "name": "HRB 16005: \"Dentes\"-Dental-Labor GmbH",
        "notice_id": "1457470",
        "posted_on": "2017-09-29",
        "rechtsform": null,
        "sitz": null,
        "url": "https://www.handelsregisterbekanntmachungen.de/en/skripte/hrb.php?rb_id=1457470&land_abk=nw"
    },
    "parsed": {
        "addresses": [
            {
                "kls": "Address",
                "text": "Friedrich-Franz-Straße 13, 12103 Berlin"
            }
        ],
        "officers": [
            {
                "class": "DismissedManagingDirector",
                "payload": {
                    "city": "Aachen",
                    "dismissed": true,
                    "dob": "1958-10-11",
                    "lastname": "Heigl",
                    "name": "Andre"
                },
                "text": " Heigl, Andre, Aachen, *11.10.1958."
            },
            {
                "class": "AppointedManagingDirector",
                "payload": {
                    "city": "Fürstenwalde",
                    "dob": "1961-06-02",
                    "flag": "einzelvertretungsberechtigt mit der Befugnis im Namen der Gesellschaft mit sich im eigenen Namen oder als Vertreter eines Dritten Rechtsgeschäfte abzuschließen",
                    "lastname": "Bülowius",
                    "name": "Gerti"
                },
                "text": " Bülowius, Gerti, Fürstenwalde, *02.06.1961, einzelvertretungsberechtigt mit der Befugnis im Namen der Gesellschaft mit sich im eigenen Namen oder als Vertreter eines Dritten Rechtsgeschäfte abzuschließen."
            }
        ]
    }
}