{
    "orig": {
        "aktenzeichen": "HRB 77511",
        "amtsgericht": "Düsseldorf",
        "event_date": "2017-11-15",
        "event_type": "Veränderungen",
        "federal_state": "nw",
        "full_text": "Amtsgericht Düsseldorf Aktenzeichen: HRB 77511 \nBekannt gemacht am: 15.11.2017 20:01 Uhr\n\n\n\n\nIn () gesetzte Angaben der Anschrift und des Geschäftszweiges erfolgen ohne Gewähr.\nVeränderungen\n15.11.2017\n\nHRB 77511: DERZMANN Elektrotechnik UG (haftungsbeschränkt), Düsseldorf, Heesenstraße 14 h, 40549 Düsseldorf. Die Gesellschafterversammlung vom 06.11.2017 hat eine Änderung des Gesellschaftsvertrages in § 1 Abs. 1 und damit der Firma beschlossen, ferner wurde das Stammkapital um 23.000,00 Euro auf 25.000,00 Euro erhöht und somit § 3 geändert. Neue Firma: DERZMANN Elektrotechnik GmbH. Neues Stammkapital: 25.000,00 EUR. Nach Änderung der Vertretungsbefugnis nunmehr: Geschäftsführer: Shao, Hanfeng, Düsseldorf, *25.10.1981, einzelvertretungsberechtigt mit der Befugnis im Namen der Gesellschaft mit sich im eigenen Namen oder als Vertreter eines Dritten Rechtsgeschäfte abzuschließen.",
        "gesellschafter": null,
        "inhaber": null,
        "name": "HRB 77511: DERZMANN Elektrotechnik UG (haftungsbeschränkt)",
        "notice_id": "1471625",
        "posted_on": "2017-11-15",
        "rechtsform": null,
        "sitz": null,
        "url": "https://www.handelsregisterbekanntmachungen.de/en/skripte/hrb.php?rb_id=1471625&land_abk=nw"
    },
    "parsed": {
        "officers": [
            {
                "class": "ManagingDirector",
                "payload": {
                    "city": "Düsseldorf",
                    "dob": "1981-10-25",
                    "flag": "einzelvertretungsberechtigt mit der Befugnis im Namen der Gesellschaft mit sich im eigenen Namen oder als Vertreter eines Dritten Rechtsgeschäfte abzuschließen",
                    "lastname": "Shao",
                    "name": "Hanfeng"
                },
                "text": " Shao, Hanfeng, Düsseldorf, *25.10.1981, einzelvertretungsberechtigt mit der Befugnis im Namen der Gesellschaft mit sich im eigenen Namen oder als Vertreter eines Dritten Rechtsgeschäfte abzuschließen."
            }
        ]
    }
}