{
    "orig": {
        "aktenzeichen": "HRB 14547",
        "amtsgericht": "Wuppertal",
        "event_date": "2017-12-08",
        "event_type": "Veränderungen",
        "federal_state": "nw",
        "full_text": "Amtsgericht Wuppertal Aktenzeichen: HRB 14547 \nBekannt gemacht am: 08.12.2017 20:07 Uhr\n\n\n\n\nIn () gesetzte Angaben der Anschrift und des Geschäftszweiges erfolgen ohne Gewähr.\nVeränderungen\n08.12.2017\n\nHRB 14547: Eurostar International GmbH, Wuppertal, Werth 93, 42275 Wuppertal. Ist nur ein Liquidator bestellt, so vertritt er die Gesellschaft allein. Sind mehrere Liquidatoren bestellt, so wird die Gesellschaft durch zwei Liquidatoren gemeinsam vertreten. Nunmehr bestellt als Liquidator: Palagashvili, Aharon, Wuppertal, *23.12.1954, mit der Befugnis im Namen der Gesellschaft mit sich im eigenen Namen oder als Vertreter eines Dritten Rechtsgeschäfte abzuschließen. Die Gesellschaft ist aufgelöst.",
        "gesellschafter": null,
        "inhaber": null,
        "name": "HRB 14547: Eurostar International GmbH",
        "notice_id": "1480178",
        "posted_on": "2017-12-08",
        "rechtsform": null,
        "sitz": null,
        "url": "https://www.handelsregisterbekanntmachungen.de/en/skripte/hrb.php?rb_id=1480178&land_abk=nw"
    },
    "parsed": {
        "flags": [
            {
                "flag": "ignore_for_now",
                "text": "Die\\ Gesellschaft\\ ist\\ aufgel\\öst\\."
            }
        ],
        "officers": [
            {
                "class": "Liquidator",
                "payload": {
                    "city": "Wuppertal",
                    "dob": "1954-12-23",
                    "flag": "mit der Befugnis im Namen der Gesellschaft mit sich im eigenen Namen oder als Vertreter eines Dritten Rechtsgeschäfte abzuschließen",
                    "lastname": "Palagashvili",
                    "name": "Aharon"
                },
                "text": " Palagashvili, Aharon, Wuppertal, *23.12.1954, mit der Befugnis im Namen der Gesellschaft mit sich im eigenen Namen oder als Vertreter eines Dritten Rechtsgeschäfte abzuschließen."
            }
        ]
    }
}