{
    "orig": {
        "aktenzeichen": "HRB 92894",
        "amtsgericht": "Köln",
        "event_date": "2017-12-22",
        "event_type": "Veränderungen",
        "federal_state": "nw",
        "full_text": "Amtsgericht Köln Aktenzeichen: HRB 92894 \nBekannt gemacht am: 22.12.2017 20:01 Uhr\n\n\n\n\nIn () gesetzte Angaben der Anschrift und des Geschäftszweiges erfolgen ohne Gewähr.\nVeränderungen\n22.12.2017\n\nHRB 92894: MAURITIUS 165. Vermögensverwaltungs GmbH, Bergisch Gladbach, Schloßstraße 23, 51429 Bergisch Gladbach. Die Gesellschafterversammlung vom 19.12.2017 hat eine Änderung des Gesellschaftsvertrages in § 1 (Firma und Sitz) und damit die Änderung der Firma und die Sitzverlegung nach Köln, sowie eine Änderung des Gesellschaftsvertrages in § 2 (Gegenstand des Unternehmens) beschlossen. Neue Firma: UnterhaltungsFlotte TV GmbH. Köln. Geschäftsanschrift: Venloer Straße 2344, 50672 Köln. Neuer Unternehmensgegenstand: die Planung, Produktion, Vermarktung und Auswertung von Bühnenprogrammen (Einzelauftritte und Tourneen) sowie audiovisuellen Produktionen. Hierzu zählen insbesondere Kinofilm- und Fernseh-produktionen, Produktionen für das Internet und soziale Medien (z.B. youtube channel) sowie Bild-, Ton- und Datenträger aller Art. Bestellt als Geschäftsführer: Weihrauch, Constance Anita, Köln, *18.10.1972, einzelvertretungsberechtigt mit der Befugnis im Namen der Gesellschaft mit sich im eigenen Namen oder als Vertreter eines Dritten Rechtsgeschäfte abzuschließen. Nicht mehr Geschäftsführer: Bott, Sandra, Bergisch Gladbach, *25.09.1973.",
        "gesellschafter": null,
        "inhaber": null,
        "name": "HRB 92894: MAURITIUS 165. Vermögensverwaltungs GmbH",
        "notice_id": "1485697",
        "posted_on": "2017-12-22",
        "rechtsform": null,
        "sitz": null,
        "url": "https://www.handelsregisterbekanntmachungen.de/en/skripte/hrb.php?rb_id=1485697&land_abk=nw"
    },
    "parsed": {
        "labels": [
            {
                "label": "address",
                "text": " Venloer Straße 2344, 50672 Köln."
            }
        ],
        "officers": [
            {
                "class": "AppointedManagingDirector",
                "payload": {
                    "city": "Köln",
                    "dob": "1972-10-18",
                    "flag": "einzelvertretungsberechtigt mit der Befugnis im Namen der Gesellschaft mit sich im eigenen Namen oder als Vertreter eines Dritten Rechtsgeschäfte abzuschließen",
                    "lastname": "Weihrauch",
                    "name": "Constance Anita"
                },
                "text": " Weihrauch, Constance Anita, Köln, *18.10.1972, einzelvertretungsberechtigt mit der Befugnis im Namen der Gesellschaft mit sich im eigenen Namen oder als Vertreter eines Dritten Rechtsgeschäfte abzuschließen."
            },
            {
                "class": "DismissedManagingDirector",
                "payload": {
                    "city": "Bergisch Gladbach",
                    "dismissed": true,
                    "dob": "1973-09-25",
                    "lastname": "Bott",
                    "name": "Sandra"
                },
                "text": " Bott, Sandra, Bergisch Gladbach, *25.09.1973."
            }
        ]
    }
}