{
    "orig": {
        "aktenzeichen": "HRB 63061",
        "amtsgericht": "Düsseldorf",
        "event_date": "2018-01-02",
        "event_type": "Veränderungen",
        "federal_state": "nw",
        "full_text": "Amtsgericht Düsseldorf Aktenzeichen: HRB 63061 \nBekannt gemacht am: 02.01.2018 20:03 Uhr\n\n\n\n\nIn () gesetzte Angaben der Anschrift und des Geschäftszweiges erfolgen ohne Gewähr.\nVeränderungen\n02.01.2018\n\nHRB 63061: Mathias Bork Vermögensverwaltung GmbH, Düsseldorf, Klopstockstraße 1, 40237 Düsseldorf. Die Gesellschaft ist aufgelöst. Nicht mehr Geschäftsführer, nunmehr bestellt als Liquidator: Bork, Mathias, Düsseldorf, *29.12.1964, einzelvertretungsberechtigt mit der Befugnis im Namen der Gesellschaft mit sich im eigenen Namen oder als Vertreter eines Dritten Rechtsgeschäfte abzuschließen. Ist nur ein Liquidator bestellt, so vertritt er die Gesellschaft allein. Sind mehrere Liquidatoren bestellt, so wird die Gesellschaft durch zwei Liquidatoren oder durch einen Liquidator gemeinsam mit einem Prokuristen vertreten.",
        "gesellschafter": null,
        "inhaber": null,
        "name": "HRB 63061: Mathias Bork Vermögensverwaltung GmbH",
        "notice_id": "1488225",
        "posted_on": "2018-01-02",
        "rechtsform": null,
        "sitz": null,
        "url": "https://www.handelsregisterbekanntmachungen.de/en/skripte/hrb.php?rb_id=1488225&land_abk=nw"
    },
    "parsed": {
        "flags": [
            {
                "flag": "ignore_for_now",
                "text": "Die\\ Gesellschaft\\ ist\\ aufgel\\öst\\."
            }
        ],
        "officers": [
            {
                "class": "Liquidator",
                "payload": {
                    "city": "Düsseldorf",
                    "dob": "1964-12-29",
                    "flag": "einzelvertretungsberechtigt mit der Befugnis im Namen der Gesellschaft mit sich im eigenen Namen oder als Vertreter eines Dritten Rechtsgeschäfte abzuschließen",
                    "lastname": "Bork",
                    "name": "Mathias"
                },
                "text": " Bork, Mathias, Düsseldorf, *29.12.1964, einzelvertretungsberechtigt mit der Befugnis im Namen der Gesellschaft mit sich im eigenen Namen oder als Vertreter eines Dritten Rechtsgeschäfte abzuschließen."
            }
        ]
    }
}