{
    "orig": {
        "aktenzeichen": "HRB 7190",
        "amtsgericht": "Siegen",
        "event_date": "2018-01-25",
        "event_type": "Veränderungen",
        "federal_state": "nw",
        "full_text": "Amtsgericht Siegen Aktenzeichen: HRB 7190 \nBekannt gemacht am: 25.01.2018 20:05 Uhr\n\n\n\n\nIn () gesetzte Angaben der Anschrift und des Geschäftszweiges erfolgen ohne Gewähr.\nVeränderungen\n25.01.2018\n\nHRB 7190: P.M.P. GmbH, Attendorn, Askay 38, 57439 Attendorn. Die Gesellschafterversammlung vom 20. Oktober 2017 hat die Änderung von § 3 (Stammkapital) und § 7 (Gesellschafterversammlung, Gesellschafterbeschlüsse) des Gesellschaftsvertrags beschlossen. Nicht mehr Geschäftsführer: Menke, Thomas, Finnentrop, *08.08.1973; Menke, Georg, Lennestadt, *04.05.1962. Bestellt als Geschäftsführer: Hecker, Florian, Kirchhundem, *16.07.1987; Jleilati, Daniel Abud, Attendorn, *02.09.1980, jeweils einzelvertretungsberechtigt mit der Befugnis im Namen der Gesellschaft mit sich im eigenen Namen oder als Vertreter eines Dritten Rechtsgeschäfte abzuschließen.",
        "gesellschafter": null,
        "inhaber": null,
        "name": "HRB 7190: P.M.P. GmbH",
        "notice_id": "1499833",
        "posted_on": "2018-01-25",
        "rechtsform": null,
        "sitz": null,
        "url": "https://www.handelsregisterbekanntmachungen.de/en/skripte/hrb.php?rb_id=1499833&land_abk=nw"
    },
    "parsed": {
        "officers": [
            {
                "class": "DismissedManagingDirector",
                "payload": {
                    "city": "Finnentrop",
                    "dismissed": true,
                    "dob": "1973-08-08",
                    "lastname": "Menke",
                    "name": "Thomas"
                },
                "text": " Menke, Thomas, Finnentrop, *08.08.1973"
            },
            {
                "class": "DismissedManagingDirector",
                "payload": {
                    "city": "Lennestadt",
                    "dismissed": true,
                    "dob": "1962-05-04",
                    "lastname": "Menke",
                    "name": "Georg"
                },
                "text": " Menke, Georg, Lennestadt, *04.05.1962."
            },
            {
                "class": "AppointedManagingDirector",
                "payload": {
                    "city": "Kirchhundem",
                    "dob": "1987-07-16",
                    "lastname": "Hecker",
                    "name": "Florian"
                },
                "text": " Hecker, Florian, Kirchhundem, *16.07.1987"
            },
            {
                "class": "AppointedManagingDirector",
                "payload": {
                    "city": "Attendorn",
                    "dob": "1980-09-02",
                    "flag": "jeweils einzelvertretungsberechtigt mit der Befugnis im Namen der Gesellschaft mit sich im eigenen Namen oder als Vertreter eines Dritten Rechtsgeschäfte abzuschließen",
                    "lastname": "Jleilati",
                    "name": "Daniel Abud"
                },
                "text": " Jleilati, Daniel Abud, Attendorn, *02.09.1980, jeweils einzelvertretungsberechtigt mit der Befugnis im Namen der Gesellschaft mit sich im eigenen Namen oder als Vertreter eines Dritten Rechtsgeschäfte abzuschließen."
            }
        ]
    }
}