{
    "orig": {
        "aktenzeichen": "HRB 17026",
        "amtsgericht": "Duisburg",
        "event_date": "2018-03-01",
        "event_type": "Veränderungen",
        "federal_state": "nw",
        "full_text": "Amtsgericht Duisburg Aktenzeichen: HRB 17026 \nBekannt gemacht am: 01.03.2018 20:02 Uhr\n\n\n\n\nIn () gesetzte Angaben der Anschrift und des Geschäftszweiges erfolgen ohne Gewähr.\nVeränderungen\n01.03.2018\n\nHRB 17026: Golf Revier Duisburg GmbH, Oberhausen, Kurfürstenstr. 151, 46147 Oberhausen. Die Gesellschafterversammlung vom 08.02.2018 hat die Änderung des Gesellschaftsvertrages in § 5 (Geschäftsführung und Vertretung) beschlossen. Nicht mehr Geschäftsführer: Schulz, Willi, Duisburg, *09.05.1947. Bestellt als Geschäftsführer: Kochanski, Dirk, Dinslaken, *07.06.1966, einzelvertretungsberechtigt mit der Befugnis im Namen der Gesellschaft mit sich im eigenen Namen oder als Vertreter eines Dritten Rechtsgeschäfte abzuschließen.",
        "gesellschafter": null,
        "inhaber": null,
        "name": "HRB 17026: Golf Revier Duisburg GmbH",
        "notice_id": "1512705",
        "posted_on": "2018-03-01",
        "rechtsform": null,
        "sitz": null,
        "url": "https://www.handelsregisterbekanntmachungen.de/en/skripte/hrb.php?rb_id=1512705&land_abk=nw"
    },
    "parsed": {
        "officers": [
            {
                "class": "DismissedManagingDirector",
                "payload": {
                    "city": "Duisburg",
                    "dismissed": true,
                    "dob": "1947-09-05",
                    "lastname": "Schulz",
                    "name": "Willi"
                },
                "text": " Schulz, Willi, Duisburg, *09.05.1947."
            },
            {
                "class": "AppointedManagingDirector",
                "payload": {
                    "city": "Dinslaken",
                    "dob": "1966-07-06",
                    "flag": "einzelvertretungsberechtigt mit der Befugnis im Namen der Gesellschaft mit sich im eigenen Namen oder als Vertreter eines Dritten Rechtsgeschäfte abzuschließen",
                    "lastname": "Kochanski",
                    "name": "Dirk"
                },
                "text": " Kochanski, Dirk, Dinslaken, *07.06.1966, einzelvertretungsberechtigt mit der Befugnis im Namen der Gesellschaft mit sich im eigenen Namen oder als Vertreter eines Dritten Rechtsgeschäfte abzuschließen."
            }
        ]
    }
}