{
    "orig": {
        "aktenzeichen": "HRB 11775",
        "amtsgericht": "Kaiserslautern",
        "event_date": "2014-01-06",
        "event_type": "Veränderungen",
        "federal_state": "rp",
        "full_text": "Amtsgericht Kaiserslautern Aktenzeichen: HRB 11775   \nBekannt gemacht am: 20.01.2014 12:00 Uhr\n\n\n\n\nDie in () gesetzten Angaben der Anschrift und des Geschäftszweiges erfolgen ohne Gewähr.\nVeränderungen\n06.01.2014\n\nATM Mayer GmbH, Winnweiler, Wichernstr. 16, 67722 Winnweiler. Ist nur ein Liquidator bestellt, so vertritt er die Gesellschaft allein. Sind mehrere Liquidatoren bestellt, so wird die Gesellschaft durch zwei Liquidatoren gemeinsam vertreten. Nicht mehr Geschäftsführer: Mayer, Werner, Maschinenbautechniker, Winnweiler. Bestellt als Liquidator: Mayer, Werner, Winnweiler, *03.04.1944, mit der Befugnis im Namen der Gesellschaft mit sich im eigenen Namen oder als Vertreter eines Dritten Rechtsgeschäfte abzuschließen. Die Gesellschaft ist aufgelöst.",
        "gesellschafter": null,
        "inhaber": null,
        "name": "ATM Mayer GmbH",
        "notice_id": "152082",
        "posted_on": "2014-01-20",
        "rechtsform": null,
        "sitz": null,
        "url": "https://www.handelsregisterbekanntmachungen.de/en/skripte/hrb.php?rb_id=152082&land_abk=rp"
    },
    "parsed": {
        "flags": [
            {
                "flag": "ignore_for_now",
                "text": "Die\\ Gesellschaft\\ ist\\ aufgel\\öst\\."
            }
        ],
        "officers": [
            {
                "class": "DismissedManagingDirector",
                "payload": {
                    "city": "Winnweiler",
                    "dismissed": true,
                    "lastname": "Mayer",
                    "name": "Werner",
                    "position": "Maschinenbautechniker"
                },
                "text": " Mayer, Werner, Maschinenbautechniker, Winnweiler."
            },
            {
                "class": "Liquidator",
                "payload": {
                    "city": "Winnweiler",
                    "dob": "1944-03-04",
                    "flag": "mit der Befugnis im Namen der Gesellschaft mit sich im eigenen Namen oder als Vertreter eines Dritten Rechtsgeschäfte abzuschließen",
                    "lastname": "Mayer",
                    "name": "Werner"
                },
                "text": " Mayer, Werner, Winnweiler, *03.04.1944, mit der Befugnis im Namen der Gesellschaft mit sich im eigenen Namen oder als Vertreter eines Dritten Rechtsgeschäfte abzuschließen."
            }
        ]
    }
}