{
    "orig": {
        "aktenzeichen": "HRB 16192",
        "amtsgericht": "Moenchengladbach",
        "event_date": "2018-04-03",
        "event_type": "Veränderungen",
        "federal_state": "nw",
        "full_text": "Amtsgericht Moenchengladbach Aktenzeichen: HRB 16192 \nBekannt gemacht am: 03.04.2018 20:02 Uhr\n\n\n\n\nIn () gesetzte Angaben der Anschrift und des Geschäftszweiges erfolgen ohne Gewähr.\nVeränderungen\n03.04.2018\n\nHRB 16192: Rafet GmbH, Mönchengladbach, Stresemannstraße 26 - 30, 41236 Mönchengladbach. Die Gesellschaft ist aufgelöst. Die Gesellschaft hat einen oder mehrere Liquidatoren. Ist nur ein Liquidator bestellt, so vertritt dieser die Gesellschaft allein. Sind mehrere Liquidatoren bestellt, so wird die Gesellschaft durch zwei Liquidatoren gemeinschaftlich vertreten. Durch Beschluss der Gesellschafter kann einzelnen, mehreren oder allen Liquidatoren Einzelvertretungsbefugnis sowie Befreiung von den Beschränkungen des § 181 BGB erteilt werden. Nicht mehr Geschäftsführer, nunmehr bestellt als Liquidator: Ab Raouf Rafet, Mohammad Ihsan, Dubai / Vereinigte Arabische Emirate, *15.12.1970, einzelvertretungsberechtigt mit der Befugnis im Namen der Gesellschaft mit sich im eigenen Namen oder als Vertreter eines Dritten Rechtsgeschäfte abzuschließen.",
        "gesellschafter": null,
        "inhaber": null,
        "name": "HRB 16192: Rafet GmbH",
        "notice_id": "1523428",
        "posted_on": "2018-04-03",
        "rechtsform": null,
        "sitz": null,
        "url": "https://www.handelsregisterbekanntmachungen.de/en/skripte/hrb.php?rb_id=1523428&land_abk=nw"
    },
    "parsed": {
        "flags": [
            {
                "flag": "CompanyClosed",
                "text": "Die\\ Gesellschaft\\ ist\\ aufgel\\öst\\."
            }
        ],
        "officers": [
            {
                "class": "Liquidator",
                "payload": {
                    "city": "Dubai / Vereinigte Arabische Emirate",
                    "dob": "1970-12-15",
                    "flag": "einzelvertretungsberechtigt mit der Befugnis im Namen der Gesellschaft mit sich im eigenen Namen oder als Vertreter eines Dritten Rechtsgeschäfte abzuschließen",
                    "lastname": "Ab Raouf Rafet",
                    "name": "Mohammad Ihsan"
                },
                "text": " Ab Raouf Rafet, Mohammad Ihsan, Dubai / Vereinigte Arabische Emirate, *15.12.1970, einzelvertretungsberechtigt mit der Befugnis im Namen der Gesellschaft mit sich im eigenen Namen oder als Vertreter eines Dritten Rechtsgeschäfte abzuschließen."
            }
        ]
    }
}