{
    "orig": {
        "aktenzeichen": "HRA 12374",
        "amtsgericht": "Duisburg",
        "event_date": "2018-04-30",
        "event_type": "Neueintragungen",
        "federal_state": "nw",
        "full_text": "Amtsgericht Duisburg Aktenzeichen: HRA 12374 \nBekannt gemacht am: 30.04.2018 20:02 Uhr\n\n\n\n\nIn () gesetzte Angaben der Anschrift und des Geschäftszweiges erfolgen ohne Gewähr.\nNeueintragungen\n30.04.2018\n\nHRA 12374: LANES e.K., Duisburg, Bismarckstr. 142 a, 47057 Duisburg. (die Beratung und Weiterbildung, insbesondere der Sprachvermittlung und sonstige Bildungsmaßnahmen.). Einzelkaufmann. Geschäftsanschrift: Bismarckstr. 142 a, 47057 Duisburg. Zweigniederlassung unter gleicher Firma errichtet in: 40210 Düsseldorf, Geschäftsanschrift: Graf-Adolf-Str. 41, 40210 Düsseldorf. Inhaber: El Jirari, Youness, Mülheim an der Ruhr, *13.03.1979.",
        "gesellschafter": null,
        "inhaber": null,
        "name": "HRA 12374: LANES e.K.",
        "notice_id": "1533265",
        "posted_on": "2018-04-30",
        "rechtsform": "Einzelkaufmann",
        "sitz": null,
        "url": "https://www.handelsregisterbekanntmachungen.de/en/skripte/hrb.php?rb_id=1533265&land_abk=nw"
    },
    "parsed": {
        "flags": [
            {
                "flag": "Sole trader",
                "text": "Einzelkaufmann"
            }
        ],
        "labels": [
            {
                "label": "address",
                "text": " Bismarckstr."
            },
            {
                "label": "address",
                "text": " Graf-Adolf-Str."
            }
        ],
        "officers": [
            {
                "class": "Owner",
                "payload": {
                    "city": "Mülheim an der Ruhr",
                    "dob": "1979-03-13",
                    "lastname": "El Jirari",
                    "name": "Youness"
                },
                "text": " El Jirari, Youness, Mülheim an der Ruhr, *13.03.1979."
            }
        ]
    }
}