{
    "orig": {
        "aktenzeichen": "HRB 14072",
        "amtsgericht": "Gelsenkirchen",
        "event_date": "2018-05-04",
        "event_type": "Veränderungen",
        "federal_state": "nw",
        "full_text": "Amtsgericht Gelsenkirchen Aktenzeichen: HRB 14072 \nBekannt gemacht am: 04.05.2018 20:01 Uhr\n\n\n\n\nIn () gesetzte Angaben der Anschrift und des Geschäftszweiges erfolgen ohne Gewähr.\nVeränderungen\n04.05.2018\n\nHRB 14072: ComTax Treuhand und Beratungsgesellschaft mbH, Gelsenkirchen, Bismarckstraße 57, 45881 Gelsenkirchen. Bestellt zum Geschäftsführer: Peschel, Jolanta, Wuppertal, *12.05.1975, einzelvertretungsberechtigt mit der Befugnis im Namen der Gesellschaft mit sich im eigenen Namen oder als Vertreter eines Dritten Rechtsgeschäfte abzuschließen. Nicht mehr Geschäftsführer: Knopp, Christian, Rotterdam / Niederlande, *18.09.1968.",
        "gesellschafter": null,
        "inhaber": null,
        "name": "HRB 14072: ComTax Treuhand und Beratungsgesellschaft mbH",
        "notice_id": "1534586",
        "posted_on": "2018-05-04",
        "rechtsform": null,
        "sitz": null,
        "url": "https://www.handelsregisterbekanntmachungen.de/en/skripte/hrb.php?rb_id=1534586&land_abk=nw"
    },
    "parsed": {
        "officers": [
            {
                "class": "ManagingDirector",
                "payload": {
                    "city": "Wuppertal",
                    "dob": "1975-12-05",
                    "flag": "einzelvertretungsberechtigt mit der Befugnis im Namen der Gesellschaft mit sich im eigenen Namen oder als Vertreter eines Dritten Rechtsgeschäfte abzuschließen",
                    "lastname": "Peschel",
                    "name": "Jolanta"
                },
                "text": " Peschel , Jolanta , Wuppertal , * 12.05.1975 , einzelvertretungsberechtigt mit der Befugnis im Namen der Gesellschaft mit sich im eigenen Namen oder als Vertreter eines Dritten Rechtsgeschäfte abzuschließen ."
            },
            {
                "class": "ManagingDirector",
                "payload": {
                    "city": "Rotterdam / Niederlande",
                    "dob": "1968-09-18",
                    "lastname": "Knopp",
                    "name": "Christian"
                },
                "text": " Knopp , Christian , Rotterdam / Niederlande , * 18.09.1968 ."
            }
        ]
    }
}