{
    "orig": {
        "aktenzeichen": "HRB 17079",
        "amtsgericht": "Bochum",
        "event_date": "2018-05-09",
        "event_type": "Veränderungen",
        "federal_state": "nw",
        "full_text": "Amtsgericht Bochum Aktenzeichen: HRB 17079 \nBekannt gemacht am: 09.05.2018 20:02 Uhr\n\n\n\n\nIn () gesetzte Angaben der Anschrift und des Geschäftszweiges erfolgen ohne Gewähr.\nVeränderungen\n09.05.2018\n\nHRB 17079: H.O. Livestock GmbH, Bochum, Berliner Straße 9b, 44866 Bochum. Die Gesellschafterversammlung vom 17.04.2018 hat eine Änderung des Gesellschaftsvertrages in § 1 und mit ihr die Sitzverlegung nach Herne beschlossen. Weiter wurde die Änderung des Gesellschaftsvertrages in § 1 (Firma und Sitz) und mit ihr die Änderung der Firma und § 2 (Gegenstand des Unternehmens) beschlossen. Nach Änderung: Neue Firma: IL-HAN Bau GmbH. Nach Änderung: Herne. Geschäftsanschrift: Westfalenstr. 22, 44651 Herne. Nach Änderung: Neuer Unternehmensgegenstand: ist Verlegen von Estrichen, Fliesen, Parkett, Verputzarbeiten, Raumausstattungen, Gartenlandschaftsarbeiten, Gebäudereinigung, Bautrocknung, Verfugungen, Holz- und Bautenschutz, Pflasterarbeiten, Einbau von genormten Baufertigteilen, Maurerarbeiten und Hausmeisterarbeiten. Die Gesellschaft ist berechtigt, alle Rechtsgeschäfte und Handlungen vorzunehmen, die mit dem vorgenannten Gegenstand des Unternehmens im Zusammenhang stehen oder diesen unmittelbar oder mittelbar fördern. Bestellt als Geschäftsführer: Ilhan, Ensar, Neu-Isenburg, *04.01.1963, einzelvertretungsberechtigt mit der Befugnis im Namen der Gesellschaft mit sich im eigenen Namen oder als Vertreter eines Dritten Rechtsgeschäfte abzuschließen. Nicht mehr Geschäftsführer: Özbek, Ismail, Sarkisla/Sivas / Türkei, *01.03.1985.",
        "gesellschafter": null,
        "inhaber": null,
        "name": "HRB 17079: H.O. Livestock GmbH",
        "notice_id": "1536235",
        "posted_on": "2018-05-09",
        "rechtsform": null,
        "sitz": null,
        "url": "https://www.handelsregisterbekanntmachungen.de/en/skripte/hrb.php?rb_id=1536235&land_abk=nw"
    },
    "parsed": {
        "labels": [
            {
                "label": "address",
                "text": " Westfalenstr."
            }
        ],
        "officers": [
            {
                "class": "AppointedManagingDirector",
                "payload": {
                    "city": "Neu-Isenburg",
                    "dob": "1963-04-01",
                    "flag": "einzelvertretungsberechtigt mit der Befugnis im Namen der Gesellschaft mit sich im eigenen Namen oder als Vertreter eines Dritten Rechtsgeschäfte abzuschließen",
                    "lastname": "Ilhan",
                    "name": "Ensar"
                },
                "text": " Ilhan, Ensar, Neu-Isenburg, *04.01.1963, einzelvertretungsberechtigt mit der Befugnis im Namen der Gesellschaft mit sich im eigenen Namen oder als Vertreter eines Dritten Rechtsgeschäfte abzuschließen."
            },
            {
                "class": "DismissedManagingDirector",
                "payload": {
                    "city": "Sarkisla/Sivas / Türkei",
                    "dismissed": true,
                    "dob": "1985-01-03",
                    "lastname": "Özbek",
                    "name": "Ismail"
                },
                "text": " Özbek, Ismail, Sarkisla/Sivas / Türkei, *01.03.1985."
            }
        ]
    }
}