{
    "orig": {
        "aktenzeichen": "HRB 26300",
        "amtsgericht": "Wuppertal",
        "event_date": "2018-05-15",
        "event_type": "Veränderungen",
        "federal_state": "nw",
        "full_text": "Amtsgericht Wuppertal Aktenzeichen: HRB 26300 \nBekannt gemacht am: 15.05.2018 20:02 Uhr\n\n\n\n\nIn () gesetzte Angaben der Anschrift und des Geschäftszweiges erfolgen ohne Gewähr.\nVeränderungen\n15.05.2018\n\nHRB 26300: WST Wasserstrahltechnik Velbert GmbH, Velbert, Siemensstraße 46, 42551 Velbert. Die Gesellschafterversammlung vom 26.03.2018 hat eine Änderung des Gesellschaftsvertrages in § 1 (Firma, Sitz) Abs. 1 und § 2 (Gegenstand des Unternehmens) Abs. 1 und mit ihr die Änderung der Firma und des Unternehmensgegenstandes beschlossen. Neue Firma: ABBS Montage GmbH. Änderung zur Geschäftsanschrift: Wülfrather Straße 37, 42553 Velbert. Neuer Unternehmensgegenstand: Die Ausführung von Montagearbeiten für das Baunebengewerbe. Nicht mehr Geschäftsführer: Frey, Frank, Heiligenhaus, *10.01.1965. Bestellt als Geschäftsführer: Hübner, Wolfgang Heinz Julius, Velbert, *16.09.1948, einzelvertretungsberechtigt mit der Befugnis im Namen der Gesellschaft mit sich im eigenen Namen oder als Vertreter eines Dritten Rechtsgeschäfte abzuschließen.",
        "gesellschafter": null,
        "inhaber": null,
        "name": "HRB 26300: WST Wasserstrahltechnik Velbert GmbH",
        "notice_id": "1537761",
        "posted_on": "2018-05-15",
        "rechtsform": null,
        "sitz": null,
        "url": "https://www.handelsregisterbekanntmachungen.de/en/skripte/hrb.php?rb_id=1537761&land_abk=nw"
    },
    "parsed": {
        "labels": [
            {
                "label": "address",
                "text": " Wülfrather Straße 37, 42553 Velbert."
            }
        ],
        "officers": [
            {
                "class": "DismissedManagingDirector",
                "payload": {
                    "city": "Heiligenhaus",
                    "dismissed": true,
                    "dob": "1965-10-01",
                    "lastname": "Frey",
                    "name": "Frank"
                },
                "text": " Frey, Frank, Heiligenhaus, *10.01.1965."
            },
            {
                "class": "AppointedManagingDirector",
                "payload": {
                    "city": "Velbert",
                    "dob": "1948-09-16",
                    "flag": "einzelvertretungsberechtigt mit der Befugnis im Namen der Gesellschaft mit sich im eigenen Namen oder als Vertreter eines Dritten Rechtsgeschäfte abzuschließen",
                    "lastname": "Hübner",
                    "name": "Wolfgang Heinz Julius"
                },
                "text": " Hübner, Wolfgang Heinz Julius, Velbert, *16.09.1948, einzelvertretungsberechtigt mit der Befugnis im Namen der Gesellschaft mit sich im eigenen Namen oder als Vertreter eines Dritten Rechtsgeschäfte abzuschließen."
            }
        ]
    }
}