{
    "orig": {
        "aktenzeichen": "HRB 13639",
        "amtsgericht": "Gelsenkirchen",
        "event_date": "2018-05-14",
        "event_type": "Veränderungen",
        "federal_state": "nw",
        "full_text": "Amtsgericht Gelsenkirchen Aktenzeichen: HRB 13639 \nBekannt gemacht am: 14.05.2018 20:02 Uhr\n\n\n\n\nIn () gesetzte Angaben der Anschrift und des Geschäftszweiges erfolgen ohne Gewähr.\nVeränderungen\n14.05.2018\n\nHRB 13639: ELITE Industrieservice GmbH, Marl, Im Gleisbogen 24, 45770 Marl. Die Gesellschafterversammlung vom 18.04.2018 hat eine Änderung des Gesellschaftsvertrages in § 3 (Stammkapital, Stammeinlagen) beschlossen. Bestellt als Geschäftsführer: Beutz, Martina, Marl, *12.01.1965, einzelvertretungsberechtigt mit der Befugnis im Namen der Gesellschaft mit sich im eigenen Namen oder als Vertreter eines Dritten Rechtsgeschäfte abzuschließen. Nicht mehr Geschäftsführer: Beutz, Uwe, Marl, *21.09.1956.",
        "gesellschafter": null,
        "inhaber": null,
        "name": "HRB 13639: ELITE Industrieservice GmbH",
        "notice_id": "1537299",
        "posted_on": "2018-05-14",
        "rechtsform": null,
        "sitz": null,
        "url": "https://www.handelsregisterbekanntmachungen.de/en/skripte/hrb.php?rb_id=1537299&land_abk=nw"
    },
    "parsed": {
        "officers": [
            {
                "class": "AppointedManagingDirector",
                "payload": {
                    "city": "Marl",
                    "dob": "1965-01-12",
                    "flag": "einzelvertretungsberechtigt mit der Befugnis im Namen der Gesellschaft mit sich im eigenen Namen oder als Vertreter eines Dritten Rechtsgeschäfte abzuschließen",
                    "lastname": "Beutz",
                    "name": "Martina"
                },
                "text": " Beutz, Martina, Marl, *12.01.1965, einzelvertretungsberechtigt mit der Befugnis im Namen der Gesellschaft mit sich im eigenen Namen oder als Vertreter eines Dritten Rechtsgeschäfte abzuschließen."
            },
            {
                "class": "DismissedManagingDirector",
                "payload": {
                    "city": "Marl",
                    "dismissed": true,
                    "dob": "1956-09-21",
                    "lastname": "Beutz",
                    "name": "Uwe"
                },
                "text": " Beutz, Uwe, Marl, *21.09.1956."
            }
        ]
    }
}