{
    "orig": {
        "aktenzeichen": "HRB 32259",
        "amtsgericht": "Saarbrücken",
        "event_date": "2008-04-23",
        "event_type": "Veränderungen",
        "federal_state": "sl",
        "full_text": "Amtsgericht Saarbrücken Aktenzeichen: HRB 32259 \nBekannt gemacht am: 30.04.2008 12:00 Uhr\n\n\n\n\nDie in () gesetzten Angaben der Geschäftsanschrift und des Unternehmensgegenstandes erfolgen ohne Gewähr.\nVeränderungen\n23.04.2008\n\nWilli Brill GmbH, St.Ingbert (Geistkircher Straße 4, 66386 St. Ingbert). Die Gesellschafterversammlung hat am 20.03.2008 beschlossen, das Stammkapital (DEM 50.000) auf Euro umzustellen, es von dann EUR 25.564,59 um 435,41 EUR auf 26.000,00 EUR zu erhöhen und den Gesellschaftsvertrag in § 4 (Stammkapital) sowie in den §§ 8 (Gesellschaftsversammlung), 10 (Einziehung von Geschäftsanteilen), 11 (Erbfolge), 12 (Bewertung von Geschäftsanteilen), 18 (Veröffentlichungen) zu ändern. Bestellt als Geschäftsführer: Brill, Rosemarie, Bexbach, *16.02.1966, einzelvertretungsberechtigt mit der Befugnis im Namen der Gesellschaft mit sich in eigenem Namen oder als Vertreter eines Dritten Rechtsgeschäfte abzuschließen.",
        "gesellschafter": null,
        "inhaber": null,
        "name": "Willi Brill GmbH",
        "notice_id": "15408",
        "posted_on": "2008-04-30",
        "rechtsform": null,
        "sitz": null,
        "url": "https://www.handelsregisterbekanntmachungen.de/en/skripte/hrb.php?rb_id=15408&land_abk=sl"
    },
    "parsed": {
        "officers": [
            {
                "class": "AppointedManagingDirector",
                "payload": {
                    "city": "Bexbach",
                    "dob": "1966-02-16",
                    "flag": "einzelvertretungsberechtigt mit der Befugnis im Namen der Gesellschaft mit sich in eigenem Namen oder als Vertreter eines Dritten Rechtsgeschäfte abzuschließen",
                    "lastname": "Brill",
                    "name": "Rosemarie"
                },
                "text": " Brill, Rosemarie, Bexbach, *16.02.1966, einzelvertretungsberechtigt mit der Befugnis im Namen der Gesellschaft mit sich in eigenem Namen oder als Vertreter eines Dritten Rechtsgeschäfte abzuschließen."
            }
        ]
    }
}