{
    "orig": {
        "aktenzeichen": "HRB 10651",
        "amtsgericht": "Saarbrücken",
        "event_date": "2008-06-06",
        "event_type": "Veränderungen",
        "federal_state": "sl",
        "full_text": "Amtsgericht Saarbrücken Aktenzeichen: HRB 10651 \nBekannt gemacht am: 11.06.2008 12:00 Uhr\n\n\n\n\nDie in () gesetzten Angaben der Geschäftsanschrift und des Unternehmensgegenstandes erfolgen ohne Gewähr.\nVeränderungen\n06.06.2008\n\nSAAR - Hochdruck Rohrleitungs- und Tiefbau GmbH, Saarbrücken (Bertha-von-Suttner-Straße 3, 66123 Saarbrücken)Die Gesellschaft ist infolge Eröffnung des Insolvenzverfahrens (Amtsgericht Saarbrücken Az.: 61 IN 24/08) kraft Gesetzes aufgelöst. Gemäß § 65 Abs. 1 GmbHG von Amts wegen eingetragen.Von Amts wegen eingetragen gemäß § 144 c FGG: Prokura erloschen: Daschner, Markus, Alsting/Frankreich, *30.07.1965; Gräff, Gerd-Peter, Diplom-Ingenieur, Saarbrücken, *05.08.1947; Körber, Jürgen, Diplom-Ingenieur, Nalbach, *13.04.1962. Von Amts wegen eingetragen gemäß 144 c FGG: Schmidt, Wolfgang, Saarbrücken, *23.03.1945.",
        "gesellschafter": null,
        "inhaber": null,
        "name": "SAAR - Hochdruck Rohrleitungs- und Tiefbau GmbH",
        "notice_id": "15851",
        "posted_on": "2008-06-11",
        "rechtsform": null,
        "sitz": null,
        "url": "https://www.handelsregisterbekanntmachungen.de/en/skripte/hrb.php?rb_id=15851&land_abk=sl"
    },
    "parsed": {
        "officers": [
            {
                "class": "ProcurationCancelled",
                "payload": {
                    "city": "Alsting/Frankreich",
                    "dismissed": true,
                    "dob": "1965-07-30",
                    "lastname": "Daschner",
                    "name": "Markus"
                },
                "text": " Daschner, Markus, Alsting/Frankreich, *30.07.1965"
            },
            {
                "class": "ProcurationCancelled",
                "payload": {
                    "city": "Saarbrücken",
                    "dismissed": true,
                    "dob": "1947-08-05",
                    "lastname": "Gräff",
                    "name": "Gerd-Peter",
                    "position": "Diplom-Ingenieur"
                },
                "text": " Gräff, Gerd-Peter, Diplom-Ingenieur, Saarbrücken, *05.08.1947"
            },
            {
                "class": "ProcurationCancelled",
                "payload": {
                    "city": "Nalbach",
                    "dismissed": true,
                    "dob": "1962-04-13",
                    "lastname": "Körber",
                    "name": "Jürgen",
                    "position": "Diplom-Ingenieur"
                },
                "text": " Körber, Jürgen, Diplom-Ingenieur, Nalbach, *13.04.1962."
            }
        ]
    }
}