{
    "orig": {
        "aktenzeichen": "HRB 55125",
        "amtsgericht": "Köln",
        "event_date": "2006-09-06",
        "event_type": "Veränderungen",
        "federal_state": "nw",
        "full_text": "Amtsgericht Köln Aktenzeichen: HRB 55125 \nBekannt gemacht am: 12.09.2006 13:49 Uhr\n\n\n\n\nDie in () gesetzten Angaben der Geschäftsanschrift und des Geschäftszweiges erfolgen ohne Gewähr.\nVeränderungen\n06.09.2006\n\nFRESH FOOD GmbH, Köln (Pasteurstr. 1a, 50735 Köln). Die Gesellschafterversammlung vom 21.06.2006 hat eine Änderung des Gesellschaftsvertrages in. § 2 und mit ihr die Änderung des Unternehmensgegenstandes, § 4 und mit ihr die Erhöhung des Stammkapitals um 25.000,00 EUR beschlossen. Neuer Unternehmensgegenstand: der Einzel- und Großhandel mit Waren aller Art, die keiner gesetzlichen Genehmigung bedürfen, sowie der Groß- und Einzelhandel mit Lebensmitteln, Getränken, Gastronomiebedarf, Tabakwaren sowie Waren aller Art. 50.000,00 EUR. Nicht mehr Geschäftsführer: Güven, Nurten, Köln, *28.11.1978. Bestellt als Geschäftsführer: Dogrusözlü, Mahmut, Essen, *26.01.1971, einzelvertretungsberechtigt mit der Befugnis im Namen der Gesellschaft mit sich im eigenen Namen oder als Vertreter eines Dritten Rechtsgeschäfte abzuschließen.",
        "gesellschafter": null,
        "inhaber": null,
        "name": "FRESH FOOD GmbH",
        "notice_id": "159006",
        "posted_on": "2006-09-12",
        "rechtsform": null,
        "sitz": null,
        "url": "https://www.handelsregisterbekanntmachungen.de/en/skripte/hrb.php?rb_id=159006&land_abk=nw"
    },
    "parsed": {
        "officers": [
            {
                "class": "DismissedManagingDirector",
                "payload": {
                    "city": "Köln",
                    "dismissed": true,
                    "dob": "1978-11-28",
                    "lastname": "Güven",
                    "name": "Nurten"
                },
                "text": " Güven, Nurten, Köln, *28.11.1978."
            },
            {
                "class": "AppointedManagingDirector",
                "payload": {
                    "city": "Essen",
                    "dob": "1971-01-26",
                    "flag": "einzelvertretungsberechtigt mit der Befugnis im Namen der Gesellschaft mit sich im eigenen Namen oder als Vertreter eines Dritten Rechtsgeschäfte abzuschließen",
                    "lastname": "Dogrusözlü",
                    "name": "Mahmut"
                },
                "text": " Dogrusözlü, Mahmut, Essen, *26.01.1971, einzelvertretungsberechtigt mit der Befugnis im Namen der Gesellschaft mit sich im eigenen Namen oder als Vertreter eines Dritten Rechtsgeschäfte abzuschließen."
            }
        ]
    }
}