{
    "orig": {
        "aktenzeichen": "HRB 3070",
        "amtsgericht": "Kleve",
        "event_date": "2006-09-13",
        "event_type": "Veränderungen",
        "federal_state": "nw",
        "full_text": "Amtsgericht Kleve Aktenzeichen: HRB 3070 \nBekannt gemacht am: 15.09.2006 06:40 Uhr\n\n\n\n\nDie in () gesetzten Angaben der Geschäftsanschrift und des Unternehmensgegenstandes erfolgen ohne Gewähr.\nVeränderungen\n13.09.2006\n\nAppenzeller-Bauträger GmbH, Rees (Lindenallee 21, 46459 Rees). Die Gesellschafterversammlung hat am 01.09.2006 beschlossen, das Stammkapital (DEM 50000,00) auf Euro umzustellen, es von dann EUR 25.564,59 um EUR 435,41 auf EUR 26.000,00 zu erhöhen und den Gesellschaftsvertrag in § 3 (Stammkapital) zu ändern. Geschäftsführer: Appenzeller, Thomas, Rees, *26.10.1965, einzelvertretungsberechtigt mit der Befugnis im Namen der Gesellschaft mit sich im eigenen Namen oder als Vertreter eines Dritten Rechtsgeschäfte abzuschließen.",
        "gesellschafter": null,
        "inhaber": null,
        "name": "Appenzeller-Bauträger GmbH",
        "notice_id": "160033",
        "posted_on": "2006-09-15",
        "rechtsform": null,
        "sitz": null,
        "url": "https://www.handelsregisterbekanntmachungen.de/en/skripte/hrb.php?rb_id=160033&land_abk=nw"
    },
    "parsed": {
        "officers": [
            {
                "class": "ManagingDirector",
                "payload": {
                    "city": "Rees",
                    "dob": "1965-10-26",
                    "flag": "einzelvertretungsberechtigt mit der Befugnis im Namen der Gesellschaft mit sich im eigenen Namen oder als Vertreter eines Dritten Rechtsgeschäfte abzuschließen",
                    "lastname": "Appenzeller",
                    "name": "Thomas"
                },
                "text": " Appenzeller, Thomas, Rees, *26.10.1965, einzelvertretungsberechtigt mit der Befugnis im Namen der Gesellschaft mit sich im eigenen Namen oder als Vertreter eines Dritten Rechtsgeschäfte abzuschließen."
            }
        ]
    }
}