{
    "orig": {
        "aktenzeichen": "HRA 42220",
        "amtsgericht": "Mainz",
        "event_date": "2014-06-20",
        "event_type": "Neueintragungen",
        "federal_state": "rp",
        "full_text": "Amtsgericht Mainz Aktenzeichen: HRA 42220 \nBekannt gemacht am: 20.06.2014 20:05 Uhr\n\n\n\n\nDie in () gesetzten Angaben der Anschrift und des Geschäftszweiges erfolgen ohne Gewähr.\nNeueintragungen\n20.06.2014\n\nHRA 42220:Falanga & Schleicher Immobilien oHG, Mainz, Dekan-Laist-Straße 54, 55129 Mainz.(Gegenstand des Unternehmens sind der Erwerb, die Veräußerung, die Vermietung und Verpachtung, die Verwaltung, die Projektierung, der Nachweis und die Vermittlung von Grundstücken und grundstücksgleichen Rechten. Die Gesellschaft ist berechtigt, alle Geschäfte vorzunehmen, die dem genannten Zweck unmittelbar oder mittelbar förderlich sein können. Die Gesellschaft darf andere Unternehmen gleicher oder ähnlicher Art übernehmen, vertreten und sich an solchen Unternehmen beteiligen. Sie darf auch Zweigniederlassungen im In- und Ausland errichten.). Offene Handelsgesellschaft. Geschäftsanschrift: Dekan-Laist-Straße 54, 55129 Mainz. Allgemeine Vertretungsregelung: Jeder persönlich haftende Gesellschafter vertritt einzeln. Persönlich haftender Gesellschafter: Falanga, Giancarlo Gerardo, Mainz, *23.01.1970; Schleicher, Jan Alexander, Mainz-Kastel, *15.11.1966, jeweils mit der Befugnis im Namen der Gesellschaft mit sich im eigenen Namen oder als Vertreter eines Dritten Rechtsgeschäfte abzuschließen.",
        "gesellschafter": null,
        "inhaber": null,
        "name": "HRA 42220:Falanga & Schleicher Immobilien oHG",
        "notice_id": "161547",
        "posted_on": "2014-06-20",
        "rechtsform": null,
        "sitz": null,
        "url": "https://www.handelsregisterbekanntmachungen.de/en/skripte/hrb.php?rb_id=161547&land_abk=rp"
    },
    "parsed": {
        "labels": [
            {
                "label": "address",
                "text": " Dekan-Laist-Straße 54, 55129 Mainz."
            }
        ],
        "officers": [
            {
                "class": "PersonalPartner",
                "payload": {
                    "city": "Mainz",
                    "dob": "1970-01-23",
                    "lastname": "Falanga",
                    "name": "Giancarlo Gerardo"
                },
                "text": " Falanga, Giancarlo Gerardo, Mainz, *23.01.1970"
            },
            {
                "class": "PersonalPartner",
                "payload": {
                    "city": "Mainz-Kastel",
                    "dob": "1966-11-15",
                    "flag": "jeweils mit der Befugnis im Namen der Gesellschaft mit sich im eigenen Namen oder als Vertreter eines Dritten Rechtsgeschäfte abzuschließen",
                    "lastname": "Schleicher",
                    "name": "Jan Alexander"
                },
                "text": " Schleicher, Jan Alexander, Mainz-Kastel, *15.11.1966, jeweils mit der Befugnis im Namen der Gesellschaft mit sich im eigenen Namen oder als Vertreter eines Dritten Rechtsgeschäfte abzuschließen."
            }
        ]
    }
}