{
    "orig": {
        "aktenzeichen": "HRB 52599",
        "amtsgericht": "Ludwigshafen a.Rhein (Ludwigshafen)",
        "event_date": "2014-09-30",
        "event_type": "Veränderungen",
        "federal_state": "rp",
        "full_text": "Amtsgericht Ludwigshafen a.Rhein (Ludwigshafen) Aktenzeichen: HRB 52599 \nBekannt gemacht am: 30.09.2014 20:05 Uhr\n\n\n\n\nDie in () gesetzten Angaben der Anschrift und des Geschäftszweiges erfolgen ohne Gewähr.\nVeränderungen\n30.09.2014\n\nHRB 52599:Jürgen Gruber Baubetreuung GmbH, Otterstadt, Zanderstr. 2, 67166 Otterstadt.Ist nur ein Liquidator bestellt, so vertritt er die Gesellschaft allein. Sind mehrere Liquidatoren bestellt, so wird die Gesellschaft durch zwei Liquidatoren oder durch einen Liquidator gemeinsam mit einem Prokuristen vertreten. Bestellt als Liquidator: Gruber, Jürgen, Otterstadt, *02.10.1950, einzelvertretungsberechtigt mit der Befugnis im Namen der Gesellschaft mit sich im eigenen Namen oder als Vertreter eines Dritten Rechtsgeschäfte abzuschließen. Die Gesellschaft ist aufgelöst.",
        "gesellschafter": null,
        "inhaber": null,
        "name": "HRB 52599:Jürgen Gruber Baubetreuung GmbH",
        "notice_id": "167102",
        "posted_on": "2014-09-30",
        "rechtsform": null,
        "sitz": null,
        "url": "https://www.handelsregisterbekanntmachungen.de/en/skripte/hrb.php?rb_id=167102&land_abk=rp"
    },
    "parsed": {
        "flags": [
            {
                "flag": "CompanyClosed",
                "text": "Die\\ Gesellschaft\\ ist\\ aufgel\\öst\\."
            }
        ],
        "officers": [
            {
                "class": "Liquidator",
                "payload": {
                    "city": "Otterstadt",
                    "dob": "1950-02-10",
                    "flag": "einzelvertretungsberechtigt mit der Befugnis im Namen der Gesellschaft mit sich im eigenen Namen oder als Vertreter eines Dritten Rechtsgeschäfte abzuschließen",
                    "lastname": "Gruber",
                    "name": "Jürgen"
                },
                "text": " Gruber, Jürgen, Otterstadt, *02.10.1950, einzelvertretungsberechtigt mit der Befugnis im Namen der Gesellschaft mit sich im eigenen Namen oder als Vertreter eines Dritten Rechtsgeschäfte abzuschließen."
            }
        ]
    }
}