{
    "orig": {
        "aktenzeichen": "HRB 103566",
        "amtsgericht": "Hamburg",
        "event_date": "2012-04-25",
        "event_type": "Veränderungen",
        "federal_state": "hh",
        "full_text": "Amtsgericht Hamburg Aktenzeichen: HRB 103566   \nBekannt gemacht am: 26.04.2012 12:00 Uhr\n\n\n\n\nIn () gesetzte Angaben der Anschrift und des Geschäftszweiges erfolgen ohne Gewähr.\nVeränderungen\n25.04.2012\n\nGrabarz Verwaltungsgesellschaft mbH, Hamburg, Alter Wall 55, 20457 Hamburg. Geschäftsanschrift: Alter Wall 55, 20457 Hamburg. Bestellt Geschäftsführer: Patzschke, Reinhard, Hamburg, *05.02.1968, vertretungsberechtigt gemäß allgemeiner Vertretungsregelung; mit der Befugnis, im Namen der Gesellschaft mit sich im eigenen Namen oder als Vertreter eines Dritten Rechtsgeschäfte abzuschließen. Geändert, nun Geschäftsführer: Eickhoff, Thomas, Hamburg, *24.02.1960; Grabarz, Andreas, Wedel, *04.07.1957; Heuel, Ralf, Hamburg, *23.04.1967; Jezuita, Annemarie, Hamburg, *18.07.1956, jeweils vertretungsberechtigt gemeinsam mit einem anderen Geschäftsführer oder einem Prokuristen. mit der Befugnis, im Namen der Gesellschaft mit sich im eigenen Namen oder als Vertreter eines Dritten Rechtsgeschäfte abzuschließen.",
        "gesellschafter": null,
        "inhaber": null,
        "name": "Grabarz Verwaltungsgesellschaft mbH",
        "notice_id": "169662",
        "posted_on": "2012-04-26",
        "rechtsform": null,
        "sitz": null,
        "url": "https://www.handelsregisterbekanntmachungen.de/en/skripte/hrb.php?rb_id=169662&land_abk=hh"
    },
    "parsed": {
        "errors": [
            {
                "kls": "ParsingError",
                "text": "Cannot parse a AppointedManagingDirector from  mit der Befugnis, im Namen der Gesellschaft mit sich im eigenen Namen oder als Vertreter eines Dritten Rechtsgeschäfte abzuschließen., error text was Name is too long: im Namen der Gesellschaft mit sich im eigenen Namen oder als Vertreter eines Dritten Rechtsgeschäfte abzuschließen"
            }
        ],
        "flags": [
            {
                "flag": "with the power to enter into legal transactions on behalf of the Company with itself or as a representative of a third party",
                "text": "mit\\ der\\ Befugnis\\,\\ im\\ Namen\\ der\\ Gesellschaft\\ mit\\ sich\\ im\\ eigenen\\ Namen\\ oder\\ als\\ Vertreter\\ eines\\ Dritten\\ Rechtsgesch\\äfte\\ abzuschlie\\ßen\\."
            },
            {
                "flag": "with the power to enter into legal transactions on behalf of the Company with itself or as a representative of a third party",
                "text": "mit\\ der\\ Befugnis\\,\\ im\\ Namen\\ der\\ Gesellschaft\\ mit\\ sich\\ im\\ eigenen\\ Namen\\ oder\\ als\\ Vertreter\\ eines\\ Dritten\\ Rechtsgesch\\äfte\\ abzuschlie\\ßen\\."
            }
        ],
        "labels": [
            {
                "label": "address",
                "text": " Alter Wall 55, 20457 Hamburg."
            }
        ],
        "officers": [
            {
                "class": "AppointedManagingDirector",
                "payload": {
                    "city": "Hamburg",
                    "dob": "1968-02-05",
                    "flag": "vertretungsberechtigt gemäß allgemeiner Vertretungsregelung",
                    "lastname": "Patzschke",
                    "name": "Reinhard"
                },
                "text": " Patzschke, Reinhard, Hamburg, *05.02.1968, vertretungsberechtigt gemäß allgemeiner Vertretungsregelung"
            },
            {
                "class": "ManagingDirector",
                "payload": {
                    "city": "Hamburg",
                    "dob": "1960-02-24",
                    "lastname": "Eickhoff",
                    "name": "Thomas"
                },
                "text": " Eickhoff, Thomas, Hamburg, *24.02.1960"
            },
            {
                "class": "ManagingDirector",
                "payload": {
                    "city": "Wedel",
                    "dob": "1957-07-04",
                    "lastname": "Grabarz",
                    "name": "Andreas"
                },
                "text": " Grabarz, Andreas, Wedel, *04.07.1957"
            },
            {
                "class": "ManagingDirector",
                "payload": {
                    "city": "Hamburg",
                    "dob": "1967-04-23",
                    "lastname": "Heuel",
                    "name": "Ralf"
                },
                "text": " Heuel, Ralf, Hamburg, *23.04.1967"
            },
            {
                "class": "ManagingDirector",
                "payload": {
                    "city": "Hamburg",
                    "dob": "1956-07-18",
                    "flag": "jeweils vertretungsberechtigt gemeinsam mit einem anderen Geschäftsführer oder einem Prokuristen",
                    "lastname": "Jezuita",
                    "name": "Annemarie"
                },
                "text": " Jezuita, Annemarie, Hamburg, *18.07.1956, jeweils vertretungsberechtigt gemeinsam mit einem anderen Geschäftsführer oder einem Prokuristen."
            }
        ]
    }
}