{
    "orig": {
        "aktenzeichen": "HRB 9672",
        "amtsgericht": "Coesfeld",
        "event_date": "2006-10-26",
        "event_type": "Veränderungen",
        "federal_state": "nw",
        "full_text": "Amtsgericht Coesfeld Aktenzeichen: HRB 9672 \nBekannt gemacht am: 27.10.2006 06:58 Uhr\n\n\n\n\nDie in () gesetzten Angaben der Geschäftsanschrift und des Unternehmensgegenstandes erfolgen ohne Gewähr.\nVeränderungen\n26.10.2006\n\nRTM Kunststofftechnik GmbH, Vreden (Hakenbree 14, 48691 Vreden). Nicht mehr Geschäftsführer: Kaiser, Robert, Vreden, *01.06.1970. Bestellt zum Geschäftsführer: Kaiser-Timmermans, Theresa-Marie, Eibergen/Niederlande, *29.10.1970; van Aperlo, Wijnand, Nunspeet/Niederlande, *22.04.1965, jeweils einzelvertretungsberechtigt mit der Befugnis im Namen der Gesellschaft mit sich im eigenen Namen oder als Vertreter eines Dritten Rechtsgeschäfte abzuschließen.",
        "gesellschafter": null,
        "inhaber": null,
        "name": "RTM Kunststofftechnik GmbH",
        "notice_id": "170627",
        "posted_on": "2006-10-27",
        "rechtsform": null,
        "sitz": null,
        "url": "https://www.handelsregisterbekanntmachungen.de/en/skripte/hrb.php?rb_id=170627&land_abk=nw"
    },
    "parsed": {
        "officers": [
            {
                "class": "DismissedManagingDirector",
                "payload": {
                    "city": "Vreden",
                    "dismissed": true,
                    "dob": "1970-06-01",
                    "lastname": "Kaiser",
                    "name": "Robert"
                },
                "text": " Kaiser, Robert, Vreden, *01.06.1970."
            },
            {
                "class": "ManagingDirector",
                "payload": {
                    "city": "Eibergen/Niederlande",
                    "dob": "1970-10-29",
                    "lastname": "Kaiser-Timmermans",
                    "name": "Theresa-Marie"
                },
                "text": " Kaiser-Timmermans, Theresa-Marie, Eibergen/Niederlande, *29.10.1970"
            },
            {
                "class": "ManagingDirector",
                "payload": {
                    "city": "Nunspeet/Niederlande",
                    "dob": "1965-04-22",
                    "flag": "jeweils einzelvertretungsberechtigt mit der Befugnis im Namen der Gesellschaft mit sich im eigenen Namen oder als Vertreter eines Dritten Rechtsgeschäfte abzuschließen",
                    "lastname": "van Aperlo",
                    "name": "Wijnand"
                },
                "text": " van Aperlo, Wijnand, Nunspeet/Niederlande, *22.04.1965, jeweils einzelvertretungsberechtigt mit der Befugnis im Namen der Gesellschaft mit sich im eigenen Namen oder als Vertreter eines Dritten Rechtsgeschäfte abzuschließen."
            }
        ]
    }
}