{
    "orig": {
        "aktenzeichen": "HRA 3696",
        "amtsgericht": "Wittlich",
        "event_date": "2014-12-16",
        "event_type": "Veränderungen",
        "federal_state": "rp",
        "full_text": "Amtsgericht Wittlich Aktenzeichen: HRA 3696 \nBekannt gemacht am: 16.12.2014 20:05 Uhr\n\n\n\n\nDie in () gesetzten Angaben der Anschrift und des Geschäftszweiges erfolgen ohne Gewähr.\nVeränderungen\n16.12.2014\n\nHRA 3696:Autohaus Klaus Steffgen e.Kfm., Schweich, In den Schlimmfuhren 1, 54338 Schweich.Geändert, nun: Neue Firma: Autohaus Klaus Steffgen e.Kfm., Inh. Frank Oster. Der Inhaber handelt allein. Nicht mehr Inhaber: Steffgen, Klaus, Kaufmann und Kfz.-Meister, Schweich. Nunmehr Inhaber: Oster, Frank, Fell, *07.05.1971. Der Übergang der in dem Betriebe des Geschäfts begründeten Verbindlichkeiten und Forderungen ist beim Erwerb des Geschäfts durch den neuen Inhaber ausgeschlossen.",
        "gesellschafter": null,
        "inhaber": null,
        "name": "HRA 3696:Autohaus Klaus Steffgen e.Kfm.",
        "notice_id": "171485",
        "posted_on": "2014-12-16",
        "rechtsform": null,
        "sitz": null,
        "url": "https://www.handelsregisterbekanntmachungen.de/en/skripte/hrb.php?rb_id=171485&land_abk=rp"
    },
    "parsed": {
        "flags": [
            {
                "flag": "The owner is acting alone",
                "text": "Der\\ Inhaber\\ handelt\\ allein"
            }
        ],
        "officers": [
            {
                "class": "NotLongerOwner",
                "payload": {
                    "city": "Schweich",
                    "dismissed": true,
                    "lastname": "Steffgen",
                    "name": "Klaus",
                    "position": "Kaufmann und Kfz.-Meister"
                },
                "text": " Steffgen, Klaus, Kaufmann und Kfz.-Meister, Schweich."
            },
            {
                "class": "Owner",
                "payload": {
                    "city": "Fell",
                    "dob": "1971-07-05",
                    "lastname": "Oster",
                    "name": "Frank"
                },
                "text": " Oster, Frank, Fell, *07.05.1971."
            }
        ]
    }
}