{
    "orig": {
        "aktenzeichen": "HRA 104917",
        "amtsgericht": "Stuttgart",
        "event_date": "2007-04-03",
        "event_type": "Veränderungen",
        "federal_state": "bw",
        "full_text": "Amtsgericht Stuttgart Aktenzeichen: HRA 104917 \nBekannt gemacht am: 10.04.2007 07:15 Uhr\n\n\n\n\nDie in () gesetzten Angaben der Geschäftsanschrift und des Unternehmensgegenstandes erfolgen ohne Gewähr.\nVeränderungen\n03.04.2007\n\nMix Markt 03 OHG, Heilbronn (Sinsheimer Str. 7-11, 74080 Heilbronn). Ausgeschieden als Persönlich haftender Gesellschafter: Mirali, Ruben, Karlsruhe, *19.10.1950; Surikow, Dimitri, Karlsruhe, *30.08.1980. Eingetreten als Persönlich haftender Gesellschafter: Kronewald, Viktor, Bad Mergentheim, *16.06.1962, vertretungsberechtigt gemeinsam mit einem anderen persönlich haftenden Gesellschafter.",
        "gesellschafter": null,
        "inhaber": null,
        "name": "Mix Markt 03 OHG",
        "notice_id": "17260",
        "posted_on": "2007-04-10",
        "rechtsform": null,
        "sitz": null,
        "url": "https://www.handelsregisterbekanntmachungen.de/en/skripte/hrb.php?rb_id=17260&land_abk=bw"
    },
    "parsed": {
        "officers": [
            {
                "class": "RetiredPersonalPartner",
                "payload": {
                    "city": "Karlsruhe",
                    "dismissed": true,
                    "dob": "1950-10-19",
                    "lastname": "Mirali",
                    "name": "Ruben"
                },
                "text": " Mirali, Ruben, Karlsruhe, *19.10.1950"
            },
            {
                "class": "RetiredPersonalPartner",
                "payload": {
                    "city": "Karlsruhe",
                    "dismissed": true,
                    "dob": "1980-08-30",
                    "lastname": "Surikow",
                    "name": "Dimitri"
                },
                "text": " Surikow, Dimitri, Karlsruhe, *30.08.1980."
            },
            {
                "class": "PersonalPartner",
                "payload": {
                    "city": "Bad Mergentheim",
                    "dob": "1962-06-16",
                    "flag": "vertretungsberechtigt gemeinsam mit einem anderen persönlich haftenden Gesellschafter",
                    "lastname": "Kronewald",
                    "name": "Viktor"
                },
                "text": " Kronewald, Viktor, Bad Mergentheim, *16.06.1962, vertretungsberechtigt gemeinsam mit einem anderen persönlich haftenden Gesellschafter."
            }
        ]
    }
}