{
    "orig": {
        "aktenzeichen": "HRB 8008",
        "amtsgericht": "Mainz",
        "event_date": "2015-03-06",
        "event_type": "Veränderungen",
        "federal_state": "rp",
        "full_text": "Amtsgericht Mainz Aktenzeichen: HRB 8008 \nBekannt gemacht am: 06.03.2015 20:05 Uhr\n\n\n\n\nDie in () gesetzten Angaben der Anschrift und des Geschäftszweiges erfolgen ohne Gewähr.\nVeränderungen\n06.03.2015\n\nHRB 8008:Parfümerie Ackermann GmbH, Mainz, Breite Straße 26, 55124 Mainz.Die Gesellschafterversammlung vom 24.02.2015 hat eine Änderung des Gesellschaftsvertrages in § 1 (Firma, Sitz) und mit ihr die Sitzverlegung nach Ober-Olm beschlossen. Neuer Sitz: Ober-Olm. Geschäftsanschrift: Gutenbergstraße 22 a, 55270 Ober-Olm. Die Gesellschaft ist aufgelöst. Ist nur ein Liquidator bestellt, so vertritt er die Gesellschaft allein. Sind mehrere Liquidatoren bestellt, so wird die Gesellschaft durch die Liquidatoren gemeinsam vertreten. Nicht mehr Geschäftsführer, jetzt bestellt als Liquidator: Ackermann, Günter, Ober-Olm, *11.07.1932, mit der Befugnis im Namen der Gesellschaft mit sich im eigenen Namen oder als Vertreter eines Dritten Rechtsgeschäfte abzuschließen.",
        "gesellschafter": null,
        "inhaber": null,
        "name": "HRB 8008:Parfümerie Ackermann GmbH",
        "notice_id": "176922",
        "posted_on": "2015-03-06",
        "rechtsform": null,
        "sitz": null,
        "url": "https://www.handelsregisterbekanntmachungen.de/en/skripte/hrb.php?rb_id=176922&land_abk=rp"
    },
    "parsed": {
        "addresses": [
            {
                "kls": "Address",
                "text": "Gutenbergstraße 22 a, 55270 Ober-Olm"
            }
        ],
        "flags": [
            {
                "flag": "CompanyClosed",
                "text": "Die\\ Gesellschaft\\ ist\\ aufgel\\öst\\."
            }
        ],
        "notices": [
            {
                "court": null,
                "registration": null,
                "text": " nach Ober-Olm beschlossen.",
                "to": "Ober-Olm",
                "used_regex": "to_regex"
            }
        ],
        "officers": [
            {
                "class": "Liquidator",
                "payload": {
                    "city": "Ober-Olm",
                    "dob": "1932-07-11",
                    "flag": "mit der Befugnis im Namen der Gesellschaft mit sich im eigenen Namen oder als Vertreter eines Dritten Rechtsgeschäfte abzuschließen",
                    "lastname": "Ackermann",
                    "name": "Günter"
                },
                "text": " Ackermann, Günter, Ober-Olm, *11.07.1932, mit der Befugnis im Namen der Gesellschaft mit sich im eigenen Namen oder als Vertreter eines Dritten Rechtsgeschäfte abzuschließen."
            }
        ]
    }
}