{
    "orig": {
        "aktenzeichen": "HRA 38149 B",
        "amtsgericht": "Charlottenburg (Berlin)",
        "event_date": "2006-06-21",
        "event_type": "Neueintragungen",
        "federal_state": "be",
        "full_text": "Amtsgericht Charlottenburg (Berlin) Aktenzeichen: HRA 38149 B  \nBekannt gemacht am: 28.06.2006 06:42 Uhr\n\n\n\n\nFür die Angaben in (), die den Unternehmensgegenstand und die Anschrift betreffen, keine Gewähr. In das Handelsregister ist folgendes eingetragen worden.\nNeueintragungen\n21.06.2006\n\nEU-VISION GmbH & Co. KG, Berlin(Brunnenstr. 36, 10115  Berlin). Firma: EU-VISION GmbH & Co. KG Sitz: Berlin Vertretungsregelung: Jeder persönlich haftende Gesellschafter vertritt die Gesellschaft allein. Die persönlich haftenden Gesellschafter dürfen Rechtsgeschäfte mit sich selbst oder mit sich als Vertreter Dritter abschließen. Inhaber: Persönlich haftender Gesellschafter:; PHOENIX Verwaltungs GmbH, Bielefeld (Amtsgericht Bielefeld, HRB 38569) Rechtsform: Kommanditgesellschaft; Der Sitz der Gesellschaft ist von Bielefeld (Amtsgericht Bielefeld, HRA 14941) nach Berlin verlegt..",
        "gesellschafter": "; PHOENIX Verwaltungs GmbH, Bielefeld (Amtsgericht Bielefeld, HRB 38569)",
        "inhaber": "Persönlich haftender",
        "name": "EU-VISION GmbH & Co. KG",
        "notice_id": "17793",
        "posted_on": "2006-06-28",
        "rechtsform": "Kommanditgesellschaft; Der Sitz der Gesellschaft ist von Bielefeld (Amtsgericht Bielefeld, HRA 14941) nach Berlin verlegt..",
        "sitz": "Berlin Vertretungsregelung: Jeder persönlich haftende Gesellschafter vertritt die Gesellschaft allein. Die persönlich haftenden Gesellschafter dürfen Rechtsgeschäfte mit sich selbst oder mit sich als Vertreter Dritter abschließen.",
        "url": "https://www.handelsregisterbekanntmachungen.de/en/skripte/hrb.php?rb_id=17793&land_abk=be"
    },
    "parsed": {
        "notices": [
            {
                "court": "Bielefeld",
                "from": "Bielefeld",
                "hrb": "HRA 14941",
                "registration": "predecessor",
                "registration_fuzzy": true,
                "text": " der Gesellschaft ist von Bielefeld (Amtsgericht Bielefeld, HRA 14941) nach Berlin verlegt..",
                "to": "Berlin",
                "used_regex": "from_regex, hrb_regex, to_regex, court_regex"
            }
        ],
        "officers": [
            {
                "class": "PersonalPartner",
                "payload": {
                    "company_name": "PHOENIX Verwaltungs GmbH, Bielefeld (Amtsgericht Bielefeld, HRB 38569) Rechtsform: Kommanditgesellschaft"
                },
                "text": " PHOENIX Verwaltungs GmbH, Bielefeld (Amtsgericht Bielefeld, HRB 38569) Rechtsform: Kommanditgesellschaft"
            }
        ]
    }
}