{
    "orig": {
        "aktenzeichen": "HRB 9834",
        "amtsgericht": "Chemnitz",
        "event_date": "2006-02-23",
        "event_type": "Veränderungen",
        "federal_state": "sn",
        "full_text": "Amtsgericht Chemnitz Aktenzeichen: HRB 9834 \nBekannt gemacht am: 02.03.2006 10:06 Uhr\n\n\n\n\nDie in () gesetzten Angaben der Geschäftsanschrift und des  Unternehmensgegenstandes erfolgen ohne Gewähr.\nVeränderungen\n23.02.2006\n\nBestattungshaus Zietenstraße GmbH, Chemnitz (Zietenstr. 10, 09130 Chemnitz). Ausgeschieden: Geschäftsführer: Christ, Klaus, Langenfeld, *06.03.1962; Elsner, Hartmut Fritz, Köln, *20.09.1945; Richter, Gunter, Angestellter, Chemnitz. Bestellt: Geschäftsführer: Schumacher, Peter Klaus, Köln, *23.07.1950, einzelvertretungsberechtigt; mit der Befugnis im Namen der Gesellschaft mit sich im eigenen Namen oder als Vertreter eines Dritten Rechtsgeschäfte abzuschließen.",
        "gesellschafter": null,
        "inhaber": null,
        "name": "Bestattungshaus Zietenstraße GmbH",
        "notice_id": "18316",
        "posted_on": "2006-03-02",
        "rechtsform": null,
        "sitz": null,
        "url": "https://www.handelsregisterbekanntmachungen.de/en/skripte/hrb.php?rb_id=18316&land_abk=sn"
    },
    "parsed": {
        "errors": [
            {
                "kls": "ParsingError",
                "text": "Cannot parse a AppointedManagingDirector from  mit der Befugnis im Namen der Gesellschaft mit sich im eigenen Namen oder als Vertreter eines Dritten Rechtsgeschäfte abzuschließen., error text was a person without DOB, number of chunks: 1"
            }
        ],
        "officers": [
            {
                "class": "RetiredManagingDirector",
                "payload": {
                    "city": "Langenfeld",
                    "dismissed": true,
                    "dob": "1962-03-06",
                    "lastname": "Christ",
                    "name": "Klaus"
                },
                "text": " Christ, Klaus, Langenfeld, *06.03.1962"
            },
            {
                "class": "RetiredManagingDirector",
                "payload": {
                    "city": "Köln",
                    "dismissed": true,
                    "dob": "1945-09-20",
                    "lastname": "Elsner",
                    "name": "Hartmut Fritz"
                },
                "text": " Elsner, Hartmut Fritz, Köln, *20.09.1945"
            },
            {
                "class": "RetiredManagingDirector",
                "payload": {
                    "city": "Chemnitz",
                    "dismissed": true,
                    "lastname": "Richter",
                    "name": "Gunter",
                    "position": "Angestellter"
                },
                "text": " Richter, Gunter, Angestellter, Chemnitz."
            },
            {
                "class": "AppointedManagingDirector",
                "payload": {
                    "city": "Köln",
                    "dob": "1950-07-23",
                    "flag": "sole representation",
                    "lastname": "Schumacher",
                    "name": "Peter Klaus"
                },
                "text": " Schumacher, Peter Klaus, Köln, *23.07.1950, einzelvertretungsberechtigt"
            }
        ]
    }
}