{
    "orig": {
        "aktenzeichen": "HRB 100613",
        "amtsgericht": "Tostedt",
        "event_date": "2011-09-22",
        "event_type": "Veränderungen",
        "federal_state": "ni",
        "full_text": "Amtsgericht Tostedt Aktenzeichen: HRB 100613   \nBekannt gemacht am: 23.09.2011 12:00 Uhr\n\n\n\n\nDie in () gesetzten Angaben der Geschäftsanschrift und des Unternehmensgegenstandes erfolgen ohne Gewähr.\nVeränderungen\n22.09.2011\n\nMS \"Apollo Condor\" Verwaltungs GmbH, Wischhafen, Fährstraße 10 A, 21737 Wischhafen. Ist nur ein Liquidator bestellt, so vertritt er die Gesellschaft allein. Sind mehrere Liquidatoren bestellt, so wird die Gesellschaft durch zwei Liquidatoren gemeinsam vertreten. Geändert, nun: Liquidator: Lührs, Gido, Wischhafen, *19.09.1943; Lührs, Andreas, Stade, *11.01.1967, jeweils vertretungsberechtigt gemeinsam mit einem anderen Liquidator; mit der Befugnis, im Namen der Gesellschaft mit sich im eigenen Namen oder als Vertreter eines Dritten Rechtsgeschäfte abzuschließen. Die Gesellschaft ist aufgelöst.",
        "gesellschafter": null,
        "inhaber": null,
        "name": "MS \"Apollo Condor\" Verwaltungs GmbH",
        "notice_id": "184485",
        "posted_on": "2011-09-23",
        "rechtsform": null,
        "sitz": null,
        "url": "https://www.handelsregisterbekanntmachungen.de/en/skripte/hrb.php?rb_id=184485&land_abk=ni"
    },
    "parsed": {
        "flags": [
            {
                "flag": "with the power to enter into legal transactions on behalf of the Company with itself or as a representative of a third party",
                "text": "mit\\ der\\ Befugnis\\,\\ im\\ Namen\\ der\\ Gesellschaft\\ mit\\ sich\\ im\\ eigenen\\ Namen\\ oder\\ als\\ Vertreter\\ eines\\ Dritten\\ Rechtsgesch\\äfte\\ abzuschlie\\ßen\\."
            },
            {
                "flag": "CompanyClosed",
                "text": "Die\\ Gesellschaft\\ ist\\ aufgel\\öst\\."
            }
        ],
        "officers": [
            {
                "class": "Liquidator",
                "payload": {
                    "city": "Wischhafen",
                    "dob": "1943-09-19",
                    "lastname": ": Lührs",
                    "name": "Gido"
                },
                "text": ": Lührs, Gido, Wischhafen, *19.09.1943"
            },
            {
                "class": "Liquidator",
                "payload": {
                    "city": "Stade",
                    "dob": "1967-01-11",
                    "flag": "jeweils vertretungsberechtigt gemeinsam mit einem anderen Liquidator",
                    "lastname": "Lührs",
                    "name": "Andreas"
                },
                "text": " Lührs, Andreas, Stade, *11.01.1967, jeweils vertretungsberechtigt gemeinsam mit einem anderen Liquidator"
            },
            {
                "class": "Liquidator",
                "payload": {
                    "lastname": "mit der Befugnis",
                    "name": "im Namen der Gesellschaft mit sich im eigenen Namen oder als Vertreter eines Dritten Rechtsgeschäfte abzuschließen"
                },
                "text": " mit der Befugnis, im Namen der Gesellschaft mit sich im eigenen Namen oder als Vertreter eines Dritten Rechtsgeschäfte abzuschließen."
            }
        ]
    }
}