{
    "orig": {
        "aktenzeichen": "HRA 4632 KI",
        "amtsgericht": "Kiel",
        "event_date": "2016-02-10",
        "event_type": "Veränderungen",
        "federal_state": "sh",
        "full_text": "Amtsgericht Kiel Aktenzeichen: HRA 4632 KI \nBekannt gemacht am: 09.03.2016 10:12 Uhr\n\n\n\n\nIn () gesetzte Angaben der Anschrift und des Unternehmensgegenstandes erfolgen ohne Gewähr:\nVeränderungen\n10.02.2016\n\nHRA 4632 KI: Rendsburger Druck und Verlagshaus GmbH & Co. KG, Osterrönfeld, Nikolaus-Otto-Str. 12, 24783 Osterrönfeld. Name der Firma: Rendsburger Druck und Verlagshaus GmbH & Co. KG; Inhaber: Persönlich haftender Gesellschafter: 3.\nRD Druck Verwaltung GmbH, Osterrönfeld\n(Amtsgericht Kiel, HRB 16990 KI); Nicht mehr Persönlich haftender Gesellschafter: 1. Boger, Torsten; Nicht mehr Persönlich haftender Gesellschafter: 2. Delfs, Reiner; Prokura: 1.\nRieper, Andreas, *31.08.1969, Aukrug; Einzelprokura; Rechtsform: nunmehr: Kommanditgesellschaft; Die Firma ist geändert.",
        "gesellschafter": null,
        "inhaber": null,
        "name": "Rieper",
        "notice_id": "185861",
        "posted_on": "2016-03-09",
        "rechtsform": null,
        "sitz": null,
        "url": "https://www.handelsregisterbekanntmachungen.de/en/skripte/hrb.php?rb_id=185861&land_abk=sh"
    },
    "parsed": {
        "flags": [
            {
                "flag": "Single procuration",
                "text": "Einzelprokura"
            }
        ],
        "officers": [
            {
                "class": "PersonalPartner",
                "payload": {
                    "company_name": " RD Druck Verwaltung GmbH, Osterrönfeld (Amtsgericht Kiel, HRB 16990 KI)"
                },
                "text": " RD Druck Verwaltung GmbH, Osterrönfeld (Amtsgericht Kiel, HRB 16990 KI)"
            },
            {
                "class": "PersonalPartner",
                "payload": {
                    "lastname": "Boger",
                    "name": "Torsten"
                },
                "text": " Boger, Torsten"
            },
            {
                "class": "PersonalPartner",
                "payload": {
                    "lastname": "Delfs",
                    "name": "Reiner"
                },
                "text": " Delfs, Reiner"
            },
            {
                "class": "Procuration",
                "payload": {
                    "city": "Aukrug",
                    "dob": "1969-08-31",
                    "lastname": "Rieper",
                    "name": "Andreas"
                },
                "text": " Rieper, Andreas, *31.08.1969, Aukrug"
            }
        ]
    }
}