{
    "orig": {
        "aktenzeichen": "HRB 31530",
        "amtsgericht": "Landau",
        "event_date": "2015-09-21",
        "event_type": "Veränderungen",
        "federal_state": "rp",
        "full_text": "Amtsgericht Landau Aktenzeichen: HRB 31530 \nBekannt gemacht am: 21.09.2015 20:05 Uhr\n\n\n\n\nDie in () gesetzten Angaben der Anschrift und des Geschäftszweiges erfolgen ohne Gewähr.\nVeränderungen\n21.09.2015\n\nHRB 31530:ObjektVerwaltung Schuster GmbH, Offenbach / Queich, Interpark 2, 76877 Offenbach / Queich.Die Gesellschafterversammlung vom 12.08.2015 hat die Änderung des Gesellschaftsvertrages in § 4 (Stammkapital) und mit ihr die Erhöhung des Stammkapitals um 1.000,00 EUR auf 26.000,00 EUR zum Zwecke der Aufnahme nach Ausgliederung des Unternehmens, betrieben unter der Firma Objektverwaltung Schuster, Inh. Werner Schuster e.K., Landau in der Pfalz (Amtsgericht Landau in der Pfalz HRA 30536) beschlossen. Geändert, nun: Neues Stammkapital: 26.000,00 EUR. Die Gesellschaft hat nach Maßgabe des Ausgliederungs- und Übernahmevertrages vom 12.08.2015 mit Nachtrag vom 11.09.2015 sowie des Zustimmungsbeschlusses ihrer Gesellschafterversammmlung vom 12.08.2015 mit Nachtrag vom 11.09.2015 das von dem Einzelkaufmann Werner Schuster, Neustadt an der Weinstraße, *15.07.1955 unter der Firma Objektverwaltung Schuster, Inh. Werner Schuster e. K. in Offenbach/Queich (Amtsgericht Landau in der Pfalz, HRA 30536) betriebene Unternehmen als Ganzes im Wege der Umwandlung durch Ausgliederung übernommen. Die Ausgliederung wird erst wirksam mit Eintragung auf dem Registerblatt des übertragenden Rechtsträgers. Diese Eintragung ist am 18.09.2015 erfolgt.Den Gläubigern der an der Ausgliederung beteiligten Gesellschaften ist, wenn sie binnen sechs Monaten nach dem Tag, an dem die Eintragung der Ausgliederung in das Register des Sitzes desjenigen Rechtsträgers, dessen Gläubiger sie sind, nach § 19 Absatz 3 UmwG als bekanntgemacht gilt, ihren Anspruch nach Grund und Höhe schriftlich anmelden, Sicherheit zu leisten, soweit sie nicht Befriedigung verlangen können. Dieses Recht steht den Gläubigern jedoch nur zu, wenn sie glaubhaft machen, dass durch die Ausgliederung die Erfüllung ihrer Forderung gefährdet wird.",
        "gesellschafter": null,
        "inhaber": null,
        "name": "HRB 31530:ObjektVerwaltung Schuster GmbH",
        "notice_id": "187777",
        "posted_on": "2015-09-21",
        "rechtsform": "Einzelkaufmann",
        "sitz": null,
        "url": "https://www.handelsregisterbekanntmachungen.de/en/skripte/hrb.php?rb_id=187777&land_abk=rp"
    },
    "parsed": {
        "flags": [
            {
                "flag": "Sole trader",
                "text": "Einzelkaufmann"
            }
        ],
        "officers": [
            {
                "class": "Person",
                "payload": {
                    "city": "Inh",
                    "dob": "1955-07-15",
                    "lastname": "Werner Schuster",
                    "name": "Neustadt an der Weinstraße"
                },
                "text": " Werner Schuster, Neustadt an der Weinstraße, *15.07.1955 unter der Firma Objektverwaltung Schuster, Inh."
            }
        ]
    }
}