{
    "orig": {
        "aktenzeichen": "HRB 53020",
        "amtsgericht": "Düsseldorf",
        "event_date": "2006-12-22",
        "event_type": "Veränderungen",
        "federal_state": "nw",
        "full_text": "Amtsgericht Düsseldorf Aktenzeichen: HRB 53020 \nBekannt gemacht am: 04.01.2007 13:46 Uhr\n\n\n\n\nDie in () gesetzten Angaben der Geschäftsanschrift und des Geschäftszweiges erfolgen ohne Gewähr.\nVeränderungen\n22.12.2006\n\nBlack Maple Logistics GmbH, Langenfeld (Elisabeth-Selbert-Str. 1a, 40764 Langenfeld). Nicht mehr Geschäftsführer: Hendrickx, Francis Ignace Manu Marie, Knokke/Belgien, *06.04.1971; van Lancker, Jan, Bottelare/Belgien, *22.02.1966. Bestellt als Geschäftsführer: Van der Beken, Philippe, Luxemburg/Luxemburg, *01.10.1975; Huyghe, Paul, Sint-Joost-ten-Node/Belgien, *01.07.1970; Peeters, Daniel, Rijkevorsel/Belgien, *16.04.1968, jeweils vertretungsberechtigt gemeinsam mit einem anderen Geschäftsführer mit der Befugnis im Namen der Gesellschaft mit sich als Vertreter eines Dritten Rechtsgeschäfte abzuschließen.",
        "gesellschafter": null,
        "inhaber": null,
        "name": "Black Maple Logistics GmbH",
        "notice_id": "190222",
        "posted_on": "2007-01-04",
        "rechtsform": null,
        "sitz": null,
        "url": "https://www.handelsregisterbekanntmachungen.de/en/skripte/hrb.php?rb_id=190222&land_abk=nw"
    },
    "parsed": {
        "officers": [
            {
                "class": "DismissedManagingDirector",
                "payload": {
                    "city": "Knokke/Belgien",
                    "dismissed": true,
                    "dob": "1971-04-06",
                    "lastname": "Hendrickx",
                    "name": "Francis Ignace Manu Marie"
                },
                "text": " Hendrickx, Francis Ignace Manu Marie, Knokke/Belgien, *06.04.1971"
            },
            {
                "class": "DismissedManagingDirector",
                "payload": {
                    "city": "Bottelare/Belgien",
                    "dismissed": true,
                    "dob": "1966-02-22",
                    "lastname": "van Lancker",
                    "name": "Jan"
                },
                "text": " van Lancker, Jan, Bottelare/Belgien, *22.02.1966."
            },
            {
                "class": "AppointedManagingDirector",
                "payload": {
                    "city": "Luxemburg/Luxemburg",
                    "dob": "1975-10-01",
                    "lastname": "Van der Beken",
                    "name": "Philippe"
                },
                "text": " Van der Beken, Philippe, Luxemburg/Luxemburg, *01.10.1975"
            },
            {
                "class": "AppointedManagingDirector",
                "payload": {
                    "city": "Sint-Joost-ten-Node/Belgien",
                    "dob": "1970-07-01",
                    "lastname": "Huyghe",
                    "name": "Paul"
                },
                "text": " Huyghe, Paul, Sint-Joost-ten-Node/Belgien, *01.07.1970"
            },
            {
                "class": "AppointedManagingDirector",
                "payload": {
                    "city": "Rijkevorsel/Belgien",
                    "dob": "1968-04-16",
                    "flag": "jeweils vertretungsberechtigt gemeinsam mit einem anderen Geschäftsführer mit der Befugnis im Namen der Gesellschaft mit sich als Vertreter eines Dritten Rechtsgeschäfte abzuschließen",
                    "lastname": "Peeters",
                    "name": "Daniel"
                },
                "text": " Peeters, Daniel, Rijkevorsel/Belgien, *16.04.1968, jeweils vertretungsberechtigt gemeinsam mit einem anderen Geschäftsführer mit der Befugnis im Namen der Gesellschaft mit sich als Vertreter eines Dritten Rechtsgeschäfte abzuschließen."
            }
        ]
    }
}