{
    "orig": {
        "aktenzeichen": "HRB 30476",
        "amtsgericht": "Zweibrücken",
        "event_date": "2016-01-07",
        "event_type": "Veränderungen",
        "federal_state": "rp",
        "full_text": "Amtsgericht Zweibrücken Aktenzeichen: HRB 30476 \nBekannt gemacht am: 07.01.2016 20:05 Uhr\n\n\n\n\nDie in () gesetzten Angaben der Anschrift und des Geschäftszweiges erfolgen ohne Gewähr.\nVeränderungen\n07.01.2016\n\nHRB 30476: G. Schaaf-Lavan GmbH, Pirmasens, Am Rehpfad 9, 66955 Pirmasens. Geändert, nun: Ist nur ein Liquidator bestellt, so vertritt er die Gesellschaft allein. Sind mehrere Liquidatoren bestellt, so wird die Gesellschaft durch zwei Liquidatoren gemeinsam vertreten. Nicht mehr Geschäftsführer; nun bestellt als Liquidator: Schaaf, Kurt, Pirmasens, *27.03.1926, einzelvertretungsberechtigt mit der Befugnis im Namen der Gesellschaft mit sich im eigenen Namen oder als Vertreter eines Dritten Rechtsgeschäfte abzuschließen. Die Gesellschaft ist aufgelöst.",
        "gesellschafter": null,
        "inhaber": null,
        "name": "HRB 30476: G. Schaaf-Lavan GmbH",
        "notice_id": "193630",
        "posted_on": "2016-01-07",
        "rechtsform": null,
        "sitz": null,
        "url": "https://www.handelsregisterbekanntmachungen.de/en/skripte/hrb.php?rb_id=193630&land_abk=rp"
    },
    "parsed": {
        "flags": [
            {
                "flag": "CompanyClosed",
                "text": "Die\\ Gesellschaft\\ ist\\ aufgel\\öst\\."
            }
        ],
        "officers": [
            {
                "class": "Liquidator",
                "payload": {
                    "city": "Pirmasens",
                    "dob": "1926-03-27",
                    "flag": "einzelvertretungsberechtigt mit der Befugnis im Namen der Gesellschaft mit sich im eigenen Namen oder als Vertreter eines Dritten Rechtsgeschäfte abzuschließen",
                    "lastname": "Schaaf",
                    "name": "Kurt"
                },
                "text": " Schaaf, Kurt, Pirmasens, *27.03.1926, einzelvertretungsberechtigt mit der Befugnis im Namen der Gesellschaft mit sich im eigenen Namen oder als Vertreter eines Dritten Rechtsgeschäfte abzuschließen."
            }
        ]
    }
}