{
    "orig": {
        "aktenzeichen": "HRB 10979",
        "amtsgericht": "Bad Kreuznach",
        "event_date": "2016-02-11",
        "event_type": "Veränderungen",
        "federal_state": "rp",
        "full_text": "Amtsgericht Bad Kreuznach Aktenzeichen: HRB 10979 \nBekannt gemacht am: 11.02.2016 20:05 Uhr\n\n\n\n\nDie in () gesetzten Angaben der Anschrift und des Geschäftszweiges erfolgen ohne Gewähr.\nVeränderungen\n11.02.2016\n\nHRB 10979: K.-H. Rumke GmbH, Idar-Oberstein, Am Südhang 6 a, 55743 Idar-Oberstein. Ist nur ein Liquidator bestellt, so vertritt er die Gesellschaft allein. Sind mehrere Liquidatoren bestellt, so wird die Gesellschaft durch die Liquidatoren gemeinsam vertreten. Nicht mehr Geschäftsführer, nunmehr bestellt als Liquidator: Rumke, Karl-Heinz, Idar-Oberstein, *21.12.1954, vertretungsberechtigt gemäß allgemeiner Vertretungsregelung. Die Gesellschaft ist aufgelöst.",
        "gesellschafter": null,
        "inhaber": null,
        "name": "HRB 10979: K.-H. Rumke GmbH",
        "notice_id": "196063",
        "posted_on": "2016-02-11",
        "rechtsform": null,
        "sitz": null,
        "url": "https://www.handelsregisterbekanntmachungen.de/en/skripte/hrb.php?rb_id=196063&land_abk=rp"
    },
    "parsed": {
        "flags": [
            {
                "flag": "CompanyClosed",
                "text": "Die\\ Gesellschaft\\ ist\\ aufgel\\öst\\."
            }
        ],
        "officers": [
            {
                "class": "Liquidator",
                "payload": {
                    "city": "Idar-Oberstein",
                    "dob": "1954-12-21",
                    "flag": "vertretungsberechtigt gemäß allgemeiner Vertretungsregelung",
                    "lastname": "Rumke",
                    "name": "Karl-Heinz"
                },
                "text": " Rumke, Karl-Heinz, Idar-Oberstein, *21.12.1954, vertretungsberechtigt gemäß allgemeiner Vertretungsregelung."
            }
        ]
    }
}