{
    "orig": {
        "aktenzeichen": "HRB 5992",
        "amtsgericht": "Siegen",
        "event_date": "2007-02-07",
        "event_type": "Veränderungen",
        "federal_state": "nw",
        "full_text": "Amtsgericht Siegen Aktenzeichen: HRB 5992 \nBekannt gemacht am: 12.02.2007 08:08 Uhr\n\n\n\n\nDie in () gesetzten Angaben der Geschäftsanschrift und des Unternehmensgegenstandes erfolgen ohne Gewähr.\nVeränderungen\n07.02.2007\n\nHensel Metalltechnik Verwaltungsgesellschaft mbH, Lennestadt (Gustav-Hensel-Straße 6, 57368 Lennestadt). Nicht mehr Geschäftsführer: Siebel, Sigurd, Hilchenbach, *16.09.1943. Bestellt zum Geschäftsführer: Dubberke, Frank, Lennestadt, *17.10.1958, mit der Befugnis im Namen der Gesellschaft mit sich im eigenen Namen Rechtsgeschäfte abzuschließen. Gesamtprokura gemeinsam mit einem Geschäftsführer oder einem anderen Prokuristen: Gerhardt, Rainer, Haiger, *19.04.1969.",
        "gesellschafter": null,
        "inhaber": null,
        "name": "Hensel Metalltechnik Verwaltungsgesellschaft mbH",
        "notice_id": "198493",
        "posted_on": "2007-02-12",
        "rechtsform": null,
        "sitz": null,
        "url": "https://www.handelsregisterbekanntmachungen.de/en/skripte/hrb.php?rb_id=198493&land_abk=nw"
    },
    "parsed": {
        "officers": [
            {
                "class": "DismissedManagingDirector",
                "payload": {
                    "city": "Hilchenbach",
                    "dismissed": true,
                    "dob": "1943-09-16",
                    "lastname": "Siebel",
                    "name": "Sigurd"
                },
                "text": " Siebel, Sigurd, Hilchenbach, *16.09.1943."
            },
            {
                "class": "ManagingDirector",
                "payload": {
                    "city": "Lennestadt",
                    "dob": "1958-10-17",
                    "flag": "mit der Befugnis im Namen der Gesellschaft mit sich im eigenen Namen Rechtsgeschäfte abzuschließen",
                    "lastname": "Dubberke",
                    "name": "Frank"
                },
                "text": " Dubberke, Frank, Lennestadt, *17.10.1958, mit der Befugnis im Namen der Gesellschaft mit sich im eigenen Namen Rechtsgeschäfte abzuschließen."
            },
            {
                "class": "CommonProcuration",
                "payload": {
                    "city": "Haiger",
                    "dob": "1969-04-19",
                    "lastname": "Gerhardt",
                    "name": "Rainer"
                },
                "text": " Gerhardt, Rainer, Haiger, *19.04.1969."
            }
        ]
    }
}