{
    "orig": {
        "aktenzeichen": "HRB 20050",
        "amtsgericht": "Leipzig",
        "event_date": "2015-11-02",
        "event_type": "Veränderungen",
        "federal_state": "sn",
        "full_text": "Amtsgericht Leipzig Aktenzeichen: HRB 20050 \nBekannt gemacht am: 02.11.2015 18:30 Uhr\n\n\n\n\nDie in () gesetzten Angaben der Geschäftsanschrift und des Unternehmensgegenstandes erfolgen ohne Gewähr.\nVeränderungen\n02.11.2015\n\nHRB 20050: EUROPAL Hoch- und Industriebau GmbH, Leipzig, Antonienstraße 1, 04229 Leipzig. Die Gesellschaft wird durch Liquidatoren vertreten. Von Amts wegen eingetragen gemäß § 384 Abs. 2 FamFG. Geschäftsführer: Heintz, Rüdiger, Mönchsroth, *27.11.1941, Amtsbezeichnung und Vertretungsbefugnis sind infolge Auflösung der Gesellschaft unrichtig geworden. Von Amts wegen eingetragen gemäß § 384 Abs. 2 FamFG. Zuvor: einzelvertretungsberechtigt. Das Insolvenzverfahren ist durch Beschluss des Amtsgerichts Leipzig vom 18.09.2015, AZ: 406 IN 1299/06, nach Anzeige der Masseunzulänglichkeit eingestellt.",
        "gesellschafter": null,
        "inhaber": null,
        "name": "HRB 20050: EUROPAL Hoch- und Industriebau GmbH",
        "notice_id": "200709",
        "posted_on": "2015-11-02",
        "rechtsform": null,
        "sitz": null,
        "url": "https://www.handelsregisterbekanntmachungen.de/en/skripte/hrb.php?rb_id=200709&land_abk=sn"
    },
    "parsed": {
        "officers": [
            {
                "class": "ManagingDirector",
                "payload": {
                    "city": "Mönchsroth",
                    "dob": "1941-11-27",
                    "flag": "Amtsbezeichnung und Vertretungsbefugnis sind infolge Auflösung der Gesellschaft unrichtig geworden",
                    "lastname": "Heintz",
                    "name": "Rüdiger"
                },
                "text": " Heintz, Rüdiger, Mönchsroth, *27.11.1941, Amtsbezeichnung und Vertretungsbefugnis sind infolge Auflösung der Gesellschaft unrichtig geworden."
            }
        ]
    }
}