{
    "orig": {
        "aktenzeichen": "HRB 620",
        "amtsgericht": "Bonn",
        "event_date": "2007-02-15",
        "event_type": "Veränderungen",
        "federal_state": "nw",
        "full_text": "Amtsgericht Bonn Aktenzeichen: HRB 620 \nBekannt gemacht am: 20.02.2007 09:41 Uhr\n\n\n\n\nDie in () gesetzten Angaben der Geschäftsanschrift und des Geschäftszweiges erfolgen ohne Gewähr.\nVeränderungen\n15.02.2007\n\nB B A Bonner Büro-Ausstattungs-Gesellschaft mit beschränkter Haftung, Bonn (In den Dauen 6, 53117 Bonn). Die Gesellschafterversammlung hat am 08.01.2007 beschlossen, das Stammkapital (DEM 51.000,00) auf Euro umzustellen, es von dann EUR 26.075,89 um EUR 924,11 auf EUR 27.000,00 zu erhöhen und den Gesellschaftsvertrag in § 3 (Stammkapital) zu ändern. Nicht mehr Geschäftsführer: Knobloch, Bodo, Kaufmann, Bonn.",
        "gesellschafter": null,
        "inhaber": null,
        "name": "B B A Bonner Büro-Ausstattungs-Gesellschaft mit beschränkter Haftung",
        "notice_id": "200962",
        "posted_on": "2007-02-20",
        "rechtsform": null,
        "sitz": null,
        "url": "https://www.handelsregisterbekanntmachungen.de/en/skripte/hrb.php?rb_id=200962&land_abk=nw"
    },
    "parsed": {
        "officers": [
            {
                "class": "DismissedManagingDirector",
                "payload": {
                    "city": "Bonn",
                    "dismissed": true,
                    "lastname": "Knobloch",
                    "name": "Bodo",
                    "position": "Kaufmann"
                },
                "text": " Knobloch, Bodo, Kaufmann, Bonn."
            }
        ]
    }
}