{
    "orig": {
        "aktenzeichen": "HRB 11270",
        "amtsgericht": "Bad Kreuznach",
        "event_date": "2016-06-24",
        "event_type": "Veränderungen",
        "federal_state": "rp",
        "full_text": "Amtsgericht Bad Kreuznach Aktenzeichen: HRB 11270 \nBekannt gemacht am: 24.06.2016 20:06 Uhr\n\n\n\n\nDie in () gesetzten Angaben der Anschrift und des Geschäftszweiges erfolgen ohne Gewähr.\nVeränderungen\n24.06.2016\n\nHRB 11270: Bernhard Lukas GmbH, Idar-Oberstein, Atzenbach 22, 55743 Idar-Oberstein. Bestellt als Geschäftsführer: Berkler, Simon Narayn, Gerach, *03.10.1988, mit der Befugnis im Namen der Gesellschaft mit sich im eigenen Namen oder als Vertreter eines Dritten Rechtsgeschäfte abzuschließen. Nicht mehr Geschäftsführer: Berkler, Wilhelm, Schmittweiler, *16.06.1958. Einzelprokura: Berkler, Wilhelm, Schmittweiler, *16.06.1958.",
        "gesellschafter": null,
        "inhaber": null,
        "name": "HRB 11270: Bernhard Lukas GmbH",
        "notice_id": "203595",
        "posted_on": "2016-06-24",
        "rechtsform": null,
        "sitz": null,
        "url": "https://www.handelsregisterbekanntmachungen.de/en/skripte/hrb.php?rb_id=203595&land_abk=rp"
    },
    "parsed": {
        "officers": [
            {
                "class": "AppointedManagingDirector",
                "payload": {
                    "city": "Gerach",
                    "dob": "1988-03-10",
                    "flag": "mit der Befugnis im Namen der Gesellschaft mit sich im eigenen Namen oder als Vertreter eines Dritten Rechtsgeschäfte abzuschließen",
                    "lastname": "Berkler",
                    "name": "Simon Narayn"
                },
                "text": " Berkler, Simon Narayn, Gerach, *03.10.1988, mit der Befugnis im Namen der Gesellschaft mit sich im eigenen Namen oder als Vertreter eines Dritten Rechtsgeschäfte abzuschließen."
            },
            {
                "class": "DismissedManagingDirector",
                "payload": {
                    "city": "Schmittweiler",
                    "dismissed": true,
                    "dob": "1958-06-16",
                    "lastname": "Berkler",
                    "name": "Wilhelm"
                },
                "text": " Berkler, Wilhelm, Schmittweiler, *16.06.1958."
            },
            {
                "class": "SingleProcuration",
                "payload": {
                    "city": "Schmittweiler",
                    "dob": "1958-06-16",
                    "lastname": "Berkler",
                    "name": "Wilhelm"
                },
                "text": " Berkler, Wilhelm, Schmittweiler, *16.06.1958."
            }
        ]
    }
}