{
    "orig": {
        "aktenzeichen": "HRB 202498",
        "amtsgericht": "Oldenburg",
        "event_date": "2012-03-15",
        "event_type": "Veränderungen",
        "federal_state": "ni",
        "full_text": "Amtsgericht Oldenburg Aktenzeichen: HRB 202498   \nBekannt gemacht am: 16.03.2012 12:00 Uhr\n\n\n\n\nIn () gesetzte Angaben der Anschrift und des Geschäftszweiges erfolgen ohne Gewähr.\nVeränderungen\n15.03.2012\n\nMS \"Anibal\" Verwaltungs-GmbH, Elsfleth, Hafenstraße 4, 26931 Elsfleth. Jeder Liquidator vertritt einzeln. Jeder Liquidator ist befugt, im Namen der Gesellschaft mit sich im eigenen Namen oder als Vertreter eines Dritten Rechtsgeschäfte vorzunehmen. Geändert, nun: Liquidator: Krüger, Bernd Theodor, Bremen, *26.11.1953, vertretungsberechtigt gemäß allgemeiner Vertretungsregelung. Die Gesellschaft ist mit Beschluss der Gesellschafterversammlung vom 09.03.2012 aufgelöst.",
        "gesellschafter": null,
        "inhaber": null,
        "name": "MS \"Anibal\" Verwaltungs-GmbH",
        "notice_id": "205987",
        "posted_on": "2012-03-16",
        "rechtsform": null,
        "sitz": null,
        "url": "https://www.handelsregisterbekanntmachungen.de/en/skripte/hrb.php?rb_id=205987&land_abk=ni"
    },
    "parsed": {
        "officers": [
            {
                "class": "Liquidator",
                "payload": {
                    "city": "Bremen",
                    "dob": "1953-11-26",
                    "flag": "vertretungsberechtigt gemäß allgemeiner Vertretungsregelung",
                    "lastname": "Krüger",
                    "name": "Bernd Theodor"
                },
                "text": ": Krüger, Bernd Theodor, Bremen, *26.11.1953, vertretungsberechtigt gemäß allgemeiner Vertretungsregelung."
            }
        ]
    }
}