{
    "orig": {
        "aktenzeichen": "HRA 9700",
        "amtsgericht": "Dresden",
        "event_date": "2016-01-29",
        "event_type": "Veränderungen",
        "federal_state": "sn",
        "full_text": "Amtsgericht Dresden Aktenzeichen: HRA 9700 \nBekannt gemacht am: 29.01.2016 18:30 Uhr\n\n\n\n\nDie in () gesetzten Angaben der Geschäftsanschrift und des  Unternehmensgegenstandes erfolgen ohne Gewähr.\nVeränderungen\n29.01.2016\n\nHRA 9700: Hörgeräte Dippe e. K., Dresden, Wiener Platz 6, 01069 Dresden. Nunmehr Inhaber: Wüstenhagen, Alexander, Dresden, *31.03.1976. Nicht mehr Inhaber: Dippe, Klaus, Pirna, Graupa, *11.07.1952. Der Übergang der im Betrieb des Geschäfts des früheren Inhabers Klaus Dippe begründeten Forderungen und Verbindlichkeiten auf den neuen Inhaber Alexander Wüstenhagen ist ausgeschlossen.",
        "gesellschafter": null,
        "inhaber": null,
        "name": "HRA 9700: Hörgeräte Dippe e. K.",
        "notice_id": "206207",
        "posted_on": "2016-01-29",
        "rechtsform": null,
        "sitz": null,
        "url": "https://www.handelsregisterbekanntmachungen.de/en/skripte/hrb.php?rb_id=206207&land_abk=sn"
    },
    "parsed": {
        "officers": [
            {
                "class": "Owner",
                "payload": {
                    "city": "Dresden",
                    "dob": "1976-03-31",
                    "lastname": "Wüstenhagen",
                    "name": "Alexander"
                },
                "text": " Wüstenhagen, Alexander, Dresden, *31.03.1976."
            },
            {
                "class": "NotLongerOwner",
                "payload": {
                    "city": "Graupa",
                    "dismissed": true,
                    "dob": "1952-07-11",
                    "lastname": "Dippe",
                    "name": "Klaus",
                    "position": "Pirna"
                },
                "text": " Dippe, Klaus, Pirna, Graupa, *11.07.1952."
            }
        ]
    }
}