{
    "orig": {
        "aktenzeichen": "HRB 31201",
        "amtsgericht": "Zweibrücken",
        "event_date": "2016-10-06",
        "event_type": "Veränderungen",
        "federal_state": "rp",
        "full_text": "Amtsgericht Zweibrücken Aktenzeichen: HRB 31201 \nBekannt gemacht am: 06.10.2016 20:05 Uhr\n\n\n\n\nDie in () gesetzten Angaben der Anschrift und des Geschäftszweiges erfolgen ohne Gewähr.\nVeränderungen\n06.10.2016\n\nHRB 31201: SBN Verwaltungs GmbH, Schönenberg-Kübelberg, Jan-Hutzel-Weg 1, 66901 Schönenberg-Kübelberg. Nicht mehr Geschäftsführer: Hutzel, Wolfgang, Schönenberg-Kübelberg, *30.03.1949. Bestellt als Geschäftsführer: Hutzel, Tim, Homburg, *10.07.1977, einzelvertretungsberechtigt mit der Befugnis im Namen der Gesellschaft mit sich im eigenen Namen oder als Vertreter eines Dritten Rechtsgeschäfte abzuschließen.",
        "gesellschafter": null,
        "inhaber": null,
        "name": "HRB 31201: SBN Verwaltungs GmbH",
        "notice_id": "209288",
        "posted_on": "2016-10-06",
        "rechtsform": null,
        "sitz": null,
        "url": "https://www.handelsregisterbekanntmachungen.de/en/skripte/hrb.php?rb_id=209288&land_abk=rp"
    },
    "parsed": {
        "officers": [
            {
                "class": "DismissedManagingDirector",
                "payload": {
                    "city": "Schönenberg-Kübelberg",
                    "dismissed": true,
                    "dob": "1949-03-30",
                    "lastname": "Hutzel",
                    "name": "Wolfgang"
                },
                "text": " Hutzel, Wolfgang, Schönenberg-Kübelberg, *30.03.1949."
            },
            {
                "class": "AppointedManagingDirector",
                "payload": {
                    "city": "Homburg",
                    "dob": "1977-10-07",
                    "flag": "einzelvertretungsberechtigt mit der Befugnis im Namen der Gesellschaft mit sich im eigenen Namen oder als Vertreter eines Dritten Rechtsgeschäfte abzuschließen",
                    "lastname": "Hutzel",
                    "name": "Tim"
                },
                "text": " Hutzel, Tim, Homburg, *10.07.1977, einzelvertretungsberechtigt mit der Befugnis im Namen der Gesellschaft mit sich im eigenen Namen oder als Vertreter eines Dritten Rechtsgeschäfte abzuschließen."
            }
        ]
    }
}