{
    "orig": {
        "aktenzeichen": "HRB 37656",
        "amtsgericht": "Köln",
        "event_date": "2007-03-19",
        "event_type": "Veränderungen",
        "federal_state": "nw",
        "full_text": "Amtsgericht Köln Aktenzeichen: HRB 37656 \nBekannt gemacht am: 23.03.2007 11:30 Uhr\n\n\n\n\nDie in () gesetzten Angaben der Geschäftsanschrift und des Geschäftszweiges erfolgen ohne Gewähr.\nVeränderungen\n19.03.2007\n\nOpti-Dent Dental -Labor GmbH, Hückeswagen (Wiehagener Straße 65, 42499 Hückeswagen). Nicht mehr Geschäftsführer: Küpper, Norbert Alfons; Westermann, Heidrun. Nach Änderung der Vertretungsbefugns u. des Wohnort nunmehr: Geschäftsführer: Sielmann, Volker-Achim, Hückeswagen, *14.02.1958, einzelvertretungsberechtigt mit der Befugnis im Namen der Gesellschaft mit sich im eigenen Namen oder als Vertreter eines Dritten Rechtsgeschäfte abzuschließen.",
        "gesellschafter": null,
        "inhaber": null,
        "name": "Opti-Dent Dental -Labor GmbH",
        "notice_id": "209948",
        "posted_on": "2007-03-23",
        "rechtsform": null,
        "sitz": null,
        "url": "https://www.handelsregisterbekanntmachungen.de/en/skripte/hrb.php?rb_id=209948&land_abk=nw"
    },
    "parsed": {
        "officers": [
            {
                "class": "DismissedManagingDirector",
                "payload": {
                    "dismissed": true,
                    "lastname": "Küpper",
                    "name": "Norbert Alfons"
                },
                "text": " Küpper, Norbert Alfons"
            },
            {
                "class": "ManagingDirector",
                "payload": {
                    "city": "Hückeswagen",
                    "dob": "1958-02-14",
                    "flag": "einzelvertretungsberechtigt mit der Befugnis im Namen der Gesellschaft mit sich im eigenen Namen oder als Vertreter eines Dritten Rechtsgeschäfte abzuschließen",
                    "lastname": "Sielmann",
                    "name": "Volker-Achim"
                },
                "text": " Sielmann, Volker-Achim, Hückeswagen, *14.02.1958, einzelvertretungsberechtigt mit der Befugnis im Namen der Gesellschaft mit sich im eigenen Namen oder als Vertreter eines Dritten Rechtsgeschäfte abzuschließen."
            }
        ]
    }
}