{
    "orig": {
        "aktenzeichen": "HRB 6688",
        "amtsgericht": "Paderborn",
        "event_date": "2007-03-26",
        "event_type": "Veränderungen",
        "federal_state": "nw",
        "full_text": "Amtsgericht Paderborn Aktenzeichen: HRB 6688 \nBekannt gemacht am: 30.03.2007 13:44 Uhr\n\n\n\n\nDie in () gesetzten Angaben der Geschäftsanschrift und des Unternehmensgegenstandes erfolgen ohne Gewähr.\nVeränderungen\n26.03.2007\n\n\"Bröckling Verwaltungs GmbH\", Hövelhof (Sennestr. 105, 33161 Hövelhof). Die Gesellschafterversammlung hat am 29.12.2006 beschlossen, das Stammkapital (DEM 50.000,00) auf Euro umzustellen, es von dann EUR 25.564,59 um EUR 435,41 auf EUR 26.000,00 zu erhöhen und den Gesellschaftsvertrag in § 3 (Stammkapital) als auch in §§ 6 (Gesellschafterversammlung) und 13 (Bekanntmachungen) zu ändern. 26.000,00 EUR. Nicht mehr Geschäftsführer: Bröckling, Heinrich, Landwirt, Hövelhof. Nicht mehr Geschäftsführer: Bröckling-Maske, Anja, Hövelhof, *24.10.1974, einzelvertretungsberechtigt mit der Befugnis im Namen der Gesellschaft mit sich im eigenen Namen oder als Vertreter eines Dritten Rechtsgeschäfte abzuschließen.",
        "gesellschafter": null,
        "inhaber": null,
        "name": "\"Bröckling Verwaltungs GmbH\"",
        "notice_id": "211886",
        "posted_on": "2007-03-30",
        "rechtsform": null,
        "sitz": null,
        "url": "https://www.handelsregisterbekanntmachungen.de/en/skripte/hrb.php?rb_id=211886&land_abk=nw"
    },
    "parsed": {
        "officers": [
            {
                "class": "DismissedManagingDirector",
                "payload": {
                    "city": "Hövelhof",
                    "dismissed": true,
                    "lastname": "Bröckling",
                    "name": "Heinrich",
                    "position": "Landwirt"
                },
                "text": " Bröckling, Heinrich, Landwirt, Hövelhof."
            },
            {
                "class": "DismissedManagingDirector",
                "payload": {
                    "city": "Hövelhof",
                    "dismissed": true,
                    "dob": "1974-10-24",
                    "flag": "einzelvertretungsberechtigt mit der Befugnis im Namen der Gesellschaft mit sich im eigenen Namen oder als Vertreter eines Dritten Rechtsgeschäfte abzuschließen",
                    "lastname": "Bröckling-Maske",
                    "name": "Anja"
                },
                "text": " Bröckling-Maske, Anja, Hövelhof, *24.10.1974, einzelvertretungsberechtigt mit der Befugnis im Namen der Gesellschaft mit sich im eigenen Namen oder als Vertreter eines Dritten Rechtsgeschäfte abzuschließen."
            }
        ]
    }
}