{
    "orig": {
        "aktenzeichen": "HRA 3280",
        "amtsgericht": "Bad Kreuznach",
        "event_date": "2017-01-05",
        "event_type": "Veränderungen",
        "federal_state": "rp",
        "full_text": "Amtsgericht Bad Kreuznach Aktenzeichen: HRA 3280 \nBekannt gemacht am: 05.01.2017 20:06 Uhr\n\n\n\n\nDie in () gesetzten Angaben der Anschrift und des Geschäftszweiges erfolgen ohne Gewähr.\nVeränderungen\n05.01.2017\n\nHRA 3280: Villa Vinum GmbH & Co. KG, Rümmelsheim, Burg Layen 2, 55452 Rümmelsheim. Ist nur ein Liquidator bestellt, so vertritt er die Gesellschaft allein. Sind mehrere Liquidatoren bestellt, so wird die Gesellschaft durch die Liquidatoren gemeinsam vertreten. Nach Änderung der Vertretungsbefugnis nunmehr Persönlich haftender Gesellschafter: Villa Vinum Verwaltungs GmbH, Rüdesheim/Nahe (AG Bad Kreuznach HRB 4620), von der Vertretung ausgeschlossen. Bestellt als Liquidator: Pieroth, Dieter, Mainz, *28.04.1949, einzelvertretungsberechtigt mit der Befugnis im Namen der Gesellschaft mit sich im eigenen Namen oder als Vertreter eines Dritten Rechtsgeschäfte abzuschließen. Die Gesellschaft ist aufgelöst.",
        "gesellschafter": null,
        "inhaber": null,
        "name": "HRA 3280: Villa Vinum GmbH & Co. KG",
        "notice_id": "214315",
        "posted_on": "2017-01-05",
        "rechtsform": null,
        "sitz": null,
        "url": "https://www.handelsregisterbekanntmachungen.de/en/skripte/hrb.php?rb_id=214315&land_abk=rp"
    },
    "parsed": {
        "flags": [
            {
                "flag": "ignore_for_now",
                "text": "Die\\ Gesellschaft\\ ist\\ aufgel\\öst\\."
            }
        ],
        "officers": [
            {
                "class": "PersonalPartner",
                "payload": {
                    "company_name": " Villa Vinum Verwaltungs GmbH, Rüdesheim/Nahe (AG Bad Kreuznach HRB 4620), von der Vertretung ausgeschlossen."
                },
                "text": " Villa Vinum Verwaltungs GmbH, Rüdesheim/Nahe (AG Bad Kreuznach HRB 4620), von der Vertretung ausgeschlossen."
            },
            {
                "class": "Liquidator",
                "payload": {
                    "city": "Mainz",
                    "dob": "1949-04-28",
                    "flag": "einzelvertretungsberechtigt mit der Befugnis im Namen der Gesellschaft mit sich im eigenen Namen oder als Vertreter eines Dritten Rechtsgeschäfte abzuschließen",
                    "lastname": "Pieroth",
                    "name": "Dieter"
                },
                "text": " Pieroth, Dieter, Mainz, *28.04.1949, einzelvertretungsberechtigt mit der Befugnis im Namen der Gesellschaft mit sich im eigenen Namen oder als Vertreter eines Dritten Rechtsgeschäfte abzuschließen."
            }
        ]
    }
}