{
    "orig": {
        "aktenzeichen": "HRB 31410",
        "amtsgericht": "Kaiserslautern",
        "event_date": "2017-02-17",
        "event_type": "Veränderungen",
        "federal_state": "rp",
        "full_text": "Amtsgericht Kaiserslautern Aktenzeichen: HRB 31410 \nBekannt gemacht am: 17.02.2017 20:06 Uhr\n\n\n\n\nDie in () gesetzten Angaben der Anschrift und des Geschäftszweiges erfolgen ohne Gewähr.\nVeränderungen\n17.02.2017\n\nHRB 31410: Blue Order Technologies GmbH, Kaiserslautern, Europaallee 10, 67657 Kaiserslautern. Nicht mehr Geschäftsführer: Frederick, John W., Fallston, Maryland/USA, *26.10.1963. Bestellt als Geschäftsführer: Agle, Brian, Boxborough / USA - Vereinigte Staaten, *20.10.1962; Melloni, Alessandra Cäcilia, Wynnewood / USA - Vereinigte Staaten, *09.06.1975, jeweils einzelvertretungsberechtigt mit der Befugnis im Namen der Gesellschaft mit sich im eigenen Namen oder als Vertreter eines Dritten Rechtsgeschäfte abzuschließen.",
        "gesellschafter": null,
        "inhaber": null,
        "name": "HRB 31410: Blue Order Technologies GmbH",
        "notice_id": "217285",
        "posted_on": "2017-02-17",
        "rechtsform": null,
        "sitz": null,
        "url": "https://www.handelsregisterbekanntmachungen.de/en/skripte/hrb.php?rb_id=217285&land_abk=rp"
    },
    "parsed": {
        "officers": [
            {
                "class": "DismissedManagingDirector",
                "payload": {
                    "city": "Maryland/USA",
                    "dismissed": true,
                    "dob": "1963-10-26",
                    "lastname": "Frederick",
                    "name": "John W",
                    "position": "Fallston"
                },
                "text": " Frederick, John W., Fallston, Maryland/USA, *26.10.1963."
            },
            {
                "class": "AppointedManagingDirector",
                "payload": {
                    "city": "Boxborough / USA - Vereinigte Staaten",
                    "dob": "1962-10-20",
                    "lastname": "Agle",
                    "name": "Brian"
                },
                "text": " Agle, Brian, Boxborough / USA - Vereinigte Staaten, *20.10.1962"
            }
        ]
    }
}