{
    "orig": {
        "aktenzeichen": "HRB 9421",
        "amtsgericht": "Duisburg",
        "event_date": "2007-04-27",
        "event_type": "Veränderungen",
        "federal_state": "nw",
        "full_text": "Amtsgericht Duisburg Aktenzeichen: HRB 9421 \nBekannt gemacht am: 27.04.2007 13:40 Uhr\n\n\n\n\nDie in ( ) gesetzten Angaben der Geschäftsanschrift und des Geschäftszweiges erfolgen ohne Gewähr.\nVeränderungen\n27.04.2007\n\nSAI Wettannahmen GmbH, Duisburg (Kirchenweg 10, 87743 Egg an der Günz). Nicht mehr Liquidator: Springer, Simon. Bestellt als Geschäftsführer: Brauchle, Horst, München, *09.06.1944, einzelvertretungsberechtigt mit der Befugnis im Namen der Gesellschaft mit sich im eigenen Namen oder als Vertreter eines Dritten Rechtsgeschäfte abzuschließen. Durch Gesellschafterbeschluss vom 15.03.2007 wurde die Fortsetzung der Gesellschaft beschlossen.",
        "gesellschafter": null,
        "inhaber": null,
        "name": "SAI Wettannahmen GmbH",
        "notice_id": "219074",
        "posted_on": "2007-04-27",
        "rechtsform": null,
        "sitz": null,
        "url": "https://www.handelsregisterbekanntmachungen.de/en/skripte/hrb.php?rb_id=219074&land_abk=nw"
    },
    "parsed": {
        "officers": [
            {
                "class": "NotALiquidator",
                "payload": {
                    "dismissed": true,
                    "lastname": "Springer",
                    "name": "Simon"
                },
                "text": ": Springer, Simon."
            },
            {
                "class": "AppointedManagingDirector",
                "payload": {
                    "city": "München",
                    "dob": "1944-06-09",
                    "flag": "einzelvertretungsberechtigt mit der Befugnis im Namen der Gesellschaft mit sich im eigenen Namen oder als Vertreter eines Dritten Rechtsgeschäfte abzuschließen",
                    "lastname": "Brauchle",
                    "name": "Horst"
                },
                "text": " Brauchle, Horst, München, *09.06.1944, einzelvertretungsberechtigt mit der Befugnis im Namen der Gesellschaft mit sich im eigenen Namen oder als Vertreter eines Dritten Rechtsgeschäfte abzuschließen."
            }
        ]
    }
}