{
    "orig": {
        "aktenzeichen": "HRB 99896",
        "amtsgericht": "München",
        "event_date": "2008-01-29",
        "event_type": "Veränderungen",
        "federal_state": "by",
        "full_text": "Amtsgericht München Aktenzeichen: HRB 99896 \nBekannt gemacht am: 30.01.2008 12:00 Uhr\n\n\n\n\nDie in ( ) gesetzten Angaben der Geschäftsanschrift und des Geschäftszweiges erfolgen ohne Gewähr.\nVeränderungen\n29.01.2008\n\nCOSTA Grundstücks-Verwaltungsgesellschaft mbH, München (Ottostraße 3, 80333 München). Ausgeschieden: Liquidator: Eckert, Carsten, München, *01.01.1965. Bestellt: Liquidator: Holderer, Steffen Kurt, Fürstenfeldbruck, *17.09.1963, vertretungsberechtigt gemeinsam mit einem anderen Liquidator oder einem Prokuristen; mit der Befugnis, im Namen der Gesellschaft mit sich im eigenen Namen oder als Vertreter eines Dritten Rechtsgeschäfte abzuschließen.",
        "gesellschafter": null,
        "inhaber": null,
        "name": "COSTA Grundstücks-Verwaltungsgesellschaft mbH",
        "notice_id": "221723",
        "posted_on": "2008-01-30",
        "rechtsform": null,
        "sitz": null,
        "url": "https://www.handelsregisterbekanntmachungen.de/en/skripte/hrb.php?rb_id=221723&land_abk=by"
    },
    "parsed": {
        "flags": [
            {
                "flag": "with the power to enter into legal transactions on behalf of the Company with itself or as a representative of a third party",
                "text": "mit\\ der\\ Befugnis\\,\\ im\\ Namen\\ der\\ Gesellschaft\\ mit\\ sich\\ im\\ eigenen\\ Namen\\ oder\\ als\\ Vertreter\\ eines\\ Dritten\\ Rechtsgesch\\äfte\\ abzuschlie\\ßen\\."
            }
        ],
        "officers": [
            {
                "class": "Liquidator",
                "payload": {
                    "city": "München",
                    "dob": "1965-01-01",
                    "lastname": "Eckert",
                    "name": "Carsten"
                },
                "text": " Eckert, Carsten, München, *01.01.1965."
            },
            {
                "class": "Liquidator",
                "payload": {
                    "city": "Fürstenfeldbruck",
                    "dob": "1963-09-17",
                    "flag": "vertretungsberechtigt gemeinsam mit einem anderen Liquidator oder einem Prokuristen",
                    "lastname": "Holderer",
                    "name": "Steffen Kurt"
                },
                "text": " Holderer, Steffen Kurt, Fürstenfeldbruck, *17.09.1963, vertretungsberechtigt gemeinsam mit einem anderen Liquidator oder einem Prokuristen"
            }
        ]
    }
}