{
    "orig": {
        "aktenzeichen": "HRA 31102",
        "amtsgericht": "Ludwigshafen a.Rhein (Ludwigshafen)",
        "event_date": "2017-07-19",
        "event_type": "Veränderungen",
        "federal_state": "rp",
        "full_text": "Amtsgericht Ludwigshafen a.Rhein (Ludwigshafen) Aktenzeichen: HRA 31102 \nBekannt gemacht am: 19.07.2017 20:06 Uhr\n\n\n\n\nDie in () gesetzten Angaben der Anschrift und des Geschäftszweiges erfolgen ohne Gewähr.\nVeränderungen\n19.07.2017\n\nHRA 31102: Schiffer & Nicklaus KG Großhandels- und Lagerhausgesellschaft, Grünstadt, Verladeplatz1, 67269 Grünstadt. Neue Firma: Schiffer & Nicklaus GmbH & Co. KG. Geschäftsanschrift: Verladeplatz 1, 67269 Grünstadt. Neue Allgemeine Vertretungsregelung: Jeder persönlich haftende Gesellschafter vertritt einzeln. Jeder persönlich haftende Gesellschafter ist befugt, im Namen der Gesellschaft mit sich im eigenen Namen oder als Vertreter eines Dritten Rechtsgeschäfte vorzunehmen. Eingetreten als Persönlich haftender Gesellschafter: Schiffer & Nicklaus Verwaltungs-GmbH, Grünstadt (Amtsgericht Ludwigshafen am Rhein HRB 31029). Ausgeschieden als Persönlich haftender Gesellschafter: Nicklaus, Heinz, Kaufmann, Günstadt, *24.12.1925.",
        "gesellschafter": null,
        "inhaber": null,
        "name": "HRA 31102: Schiffer & Nicklaus KG Großhandels- und Lagerhausgesellschaft",
        "notice_id": "225711",
        "posted_on": "2017-07-19",
        "rechtsform": null,
        "sitz": null,
        "url": "https://www.handelsregisterbekanntmachungen.de/en/skripte/hrb.php?rb_id=225711&land_abk=rp"
    },
    "parsed": {
        "labels": [
            {
                "label": "address",
                "text": " Verladeplatz 1, 67269 Grünstadt."
            }
        ],
        "officers": [
            {
                "class": "PersonalPartner",
                "payload": {
                    "lastname": "Schiffer & Nicklaus Verwaltungs-GmbH",
                    "name": "Grünstadt (Amtsgericht Ludwigshafen am Rhein HRB 31029)"
                },
                "text": " Schiffer & Nicklaus Verwaltungs-GmbH, Grünstadt (Amtsgericht Ludwigshafen am Rhein HRB 31029)."
            },
            {
                "class": "RetiredPersonalPartner",
                "payload": {
                    "city": "Günstadt",
                    "dismissed": true,
                    "dob": "1925-12-24",
                    "lastname": "Nicklaus",
                    "name": "Heinz",
                    "position": "Kaufmann"
                },
                "text": " Nicklaus, Heinz, Kaufmann, Günstadt, *24.12.1925."
            }
        ]
    }
}