{
    "orig": {
        "aktenzeichen": "HRB 6878",
        "amtsgericht": "Montabaur",
        "event_date": "2017-07-19",
        "event_type": "Veränderungen",
        "federal_state": "rp",
        "full_text": "Amtsgericht Montabaur Aktenzeichen: HRB 6878 \nBekannt gemacht am: 19.07.2017 20:06 Uhr\n\n\n\n\nDie in () gesetzten Angaben der Anschrift und des Geschäftszweiges erfolgen ohne Gewähr.\nVeränderungen\n19.07.2017\n\nHRB 6878: KMB sector GmbH, Betzdorf, Friedrichstr. 61, 57518 Betzdorf. Die Gesellschafterversammlung vom 14.03.2017 hat eine Änderung des Gesellschaftsvertrages in § 21 (Auflösung und Liquidation) und in § 1 (Firma, Sitz) und mit ihr die Sitzverlegung nach Molzhain beschlossen. geändert nun: Neuer Sitz: Molzhain. Geschäftsanschrift: Betzdorfer Straße 1a, 57520 Molzhain. Ist nur ein Liquidator bestellt, so vertritt er die Gesellschaft allein. Sind mehrere Liquidatoren bestellt, so wird die Gesellschaft durch die Liquidatoren gemeinsam vertreten. Nicht mehr Geschäftsführer: Härter, Klaus-Martin, Molzhain, *09.11.1966. Nicht mehr Geschäftsführer nun: Liquidator: Frei, Bernward, Molzhain, *12.12.1964, einzelvertretungsberechtigt mit der Befugnis im Namen der Gesellschaft mit sich im eigenen Namen oder als Vertreter eines Dritten Rechtsgeschäfte abzuschließen. Die Gesellschaft ist aufgelöst.",
        "gesellschafter": null,
        "inhaber": null,
        "name": "HRB 6878: KMB sector GmbH",
        "notice_id": "225755",
        "posted_on": "2017-07-19",
        "rechtsform": null,
        "sitz": null,
        "url": "https://www.handelsregisterbekanntmachungen.de/en/skripte/hrb.php?rb_id=225755&land_abk=rp"
    },
    "parsed": {
        "flags": [
            {
                "flag": "CompanyClosed",
                "text": "Die\\ Gesellschaft\\ ist\\ aufgel\\öst\\."
            }
        ],
        "labels": [
            {
                "label": "address",
                "text": " Betzdorfer Straße 1a, 57520 Molzhain."
            }
        ],
        "notices": [
            {
                "court": null,
                "registration": null,
                "text": " nach Molzhain beschlossen.",
                "to": "Molzhain",
                "used_regex": "to_regex"
            }
        ],
        "officers": [
            {
                "class": "DismissedManagingDirector",
                "payload": {
                    "city": "Molzhain",
                    "dismissed": true,
                    "dob": "1966-09-11",
                    "lastname": "Härter",
                    "name": "Klaus-Martin"
                },
                "text": " Härter, Klaus-Martin, Molzhain, *09.11.1966."
            },
            {
                "class": "Liquidator",
                "payload": {
                    "city": "Molzhain",
                    "dob": "1964-12-12",
                    "flag": "einzelvertretungsberechtigt mit der Befugnis im Namen der Gesellschaft mit sich im eigenen Namen oder als Vertreter eines Dritten Rechtsgeschäfte abzuschließen",
                    "lastname": "Frei",
                    "name": "Bernward"
                },
                "text": " Frei, Bernward, Molzhain, *12.12.1964, einzelvertretungsberechtigt mit der Befugnis im Namen der Gesellschaft mit sich im eigenen Namen oder als Vertreter eines Dritten Rechtsgeschäfte abzuschließen."
            }
        ]
    }
}