{
    "orig": {
        "aktenzeichen": "HRB 15451",
        "amtsgericht": "Bonn",
        "event_date": "2007-05-23",
        "event_type": "Neueintragungen",
        "federal_state": "nw",
        "full_text": "Amtsgericht Bonn Aktenzeichen: HRB 15451 \nBekannt gemacht am: 29.05.2007 07:32 Uhr\n\n\n\n\nDie in () gesetzten Angaben der Geschäftsanschrift und des Geschäftszweiges erfolgen ohne Gewähr.\nNeueintragungen\n23.05.2007\n\nNEXIA Deutschland GmbH Wirtschaftsprüfungsgesellschaft, Bonn (Godesberger Allee 125-127, 53175 Bonn). Gesellschaft mit beschränkter Haftung. Gesellschaftsvertrag vom 03.12.1979, mehrfach geändert. Die Gesellschafterversammlung vom 20.02.2007 hat die Änderung des Gesellschaftsvertrages in § 2 (Sitz) und mit ihr die Sitzverlegung von Düsseldorf (bisher Düsseldorf HRB 32023) nach Bonn und in § 15 (Bekanntmachungen) beschlossen. Zweigniederlassung errichtet unter gleicher Firma mit Zusatz: Niederlassung Hamburg, 20095 Hamburg; Niederlassung Stuttgart, 70174 Stuttgart; Niederlassung München, 80335 München; Niederlassung Freiburg, 79102 Freiburg. Gegenstand: die Übernahme der Gesamtberatung von Wirtschaftsgebilden aller Art, soweit sie nach den Bestimmungen des Gesetzes über die Berufsordnung der Wirtschaftsprüfer und/oder diesen entsprechenden ausländischen Bestimmungen für die Tätigkeiten im Ausland zulässig ist. Insbesondere ist Gegenstand der Gesellschaft die Übernahme von Treuhand- und Revisionsgeschäften und sonstiger in das Tätigkeitsgebiet einer Wirtschaftsprüfungsgesellschaft fallender Arbeiten. Stammkapital: 400.000,00 DEM. Allgemeine Vertretungsregelung: Ist nur ein Geschäftsführer bestellt, so vertritt er die Gesellschaft allein. Sind mehrere Geschäftsführer bestellt, so wird die Gesellschaft durch zwei Geschäftsführer oder durch einen Geschäftsführer gemeinsam mit einem Prokuristen vertreten. Nicht mehr Geschäftsführer: Dr. Amonat, Wolfgang, Köln, *24.01.1947; Aufderheide, Rolf, Bünde, *17.12.1958; Rohler, Thomas, Langenfeld, *16.10.1958; Scholz, Reinhard, Isernhagen, *26.07.1954; Stengert, Uwe, Rüsselheim. Nicht mehr Geschäftsführer: Bail, Ulrich, Neunkirchen, *29.11.1958; Brandenburg, Achim, Köln, *04.12.1959; Harms, Christian, Adendorf, *24.01.1958; Heinze, Frank, Tübingen, *07.07.1958; Heun, Horst Volkmar, Bonn, *27.08.1950; Jost, Christian Otto, Bremen, *17.05.1957; Lorenzen, Peter, Lübeck, *25.07.1948; Müller, Burkhard, Marienheide, *21.09.1945; Nettekoven, Norbert, Bornheim, *24.02.1950; Dr. Neu, Norbert, Wachtberg, *17.04.1961; Pütz, Rainer, Gröbenzell, *16.06.1952; Schmidt, Jürgen, Lohmar, *16.02.1954; Seidel, Torsten, Hemmingen, *05.11.1961; Volkmer, Katrin, Berlin, *27.07.1966; Dr. Weyer, Helmut, Freiburg, *10.10.1049; Winkler, Josef, Herford, *22.01.1960, jeweils einzelvertretungsberechtigt mit der Befugnis im Namen der Gesellschaft mit sich im eigenen Namen oder als Vertreter eines Dritten Rechtsgeschäfte abzuschließen. Nicht mehr Geschäftsführer: Klein, Werner, Schwalbach, *07.09.1954; Pohl, Horst-Dieter, Bald Oldesloe, *17.11.1952; Schmitz, Rolf-Dieter, Wiesbaden, *27.07.1955; Weiß, Paul-Bernhard, Bocholt, *24.04.1953, jeweils mit der Befugnis im Namen der Gesellschaft mit sich im eigenen Namen oder als Vertreter eines Dritten Rechtsgeschäfte abzuschließen.",
        "gesellschafter": null,
        "inhaber": null,
        "name": "NEXIA Deutschland GmbH Wirtschaftsprüfungsgesellschaft",
        "notice_id": "225816",
        "posted_on": "2007-05-29",
        "rechtsform": null,
        "sitz": null,
        "url": "https://www.handelsregisterbekanntmachungen.de/en/skripte/hrb.php?rb_id=225816&land_abk=nw"
    },
    "parsed": {
        "flags": [
            {
                "flag": "Company with limited liability.",
                "text": "Gesellschaft\\ mit\\ beschr\\änkter\\ Haftung\\."
            },
            {
                "flag": "If only one managing director is appointed, he represents the company alone.",
                "text": "Ist\\ nur\\ ein\\ Gesch\\äftsf\\ührer\\ bestellt\\,\\ so\\ vertritt\\ er\\ die\\ Gesellschaft\\ allein\\."
            },
            {
                "flag": "If several managing directors are appointed, then the company is represented by two managing directors or by a managing director together with an authorized officer.",
                "text": "Sind\\ mehrere\\ Gesch\\äftsf\\ührer\\ bestellt\\,\\ so\\ wird\\ die\\ Gesellschaft\\ durch\\ zwei\\ Gesch\\äftsf\\ührer\\ oder\\ durch\\ einen\\ Gesch\\äftsf\\ührer\\ gemeinsam\\ mit\\ einem\\ Prokuristen\\ vertreten\\."
            }
        ],
        "notices": [
            {
                "court": null,
                "from": "Düsseldorf",
                "hrb": "HRB 32023",
                "registration": null,
                "text": " von Düsseldorf (bisher Düsseldorf HRB 32023) nach Bonn und in § 15 (Bekanntmachungen) beschlossen.",
                "to": "Bonn",
                "used_regex": "from_hrb_to_regex"
            }
        ],
        "officers": [
            {
                "class": "DismissedManagingDirector",
                "payload": {
                    "city": "Köln",
                    "dismissed": true,
                    "dob": "1947-01-24",
                    "lastname": "Doctor Amonat",
                    "name": "Wolfgang"
                },
                "text": " Doctor Amonat, Wolfgang, Köln, *24.01.1947"
            },
            {
                "class": "DismissedManagingDirector",
                "payload": {
                    "city": "Bünde",
                    "dismissed": true,
                    "dob": "1958-12-17",
                    "lastname": "Aufderheide",
                    "name": "Rolf"
                },
                "text": " Aufderheide, Rolf, Bünde, *17.12.1958"
            },
            {
                "class": "DismissedManagingDirector",
                "payload": {
                    "city": "Langenfeld",
                    "dismissed": true,
                    "dob": "1958-10-16",
                    "lastname": "Rohler",
                    "name": "Thomas"
                },
                "text": " Rohler, Thomas, Langenfeld, *16.10.1958"
            },
            {
                "class": "DismissedManagingDirector",
                "payload": {
                    "city": "Isernhagen",
                    "dismissed": true,
                    "dob": "1954-07-26",
                    "lastname": "Scholz",
                    "name": "Reinhard"
                },
                "text": " Scholz, Reinhard, Isernhagen, *26.07.1954"
            },
            {
                "class": "DismissedManagingDirector",
                "payload": {
                    "city": "Rüsselheim",
                    "dismissed": true,
                    "lastname": "Stengert",
                    "name": "Uwe"
                },
                "text": " Stengert, Uwe, Rüsselheim."
            },
            {
                "class": "DismissedManagingDirector",
                "payload": {
                    "city": "Neunkirchen",
                    "dismissed": true,
                    "dob": "1958-11-29",
                    "lastname": "Bail",
                    "name": "Ulrich"
                },
                "text": " Bail, Ulrich, Neunkirchen, *29.11.1958"
            },
            {
                "class": "DismissedManagingDirector",
                "payload": {
                    "city": "Köln",
                    "dismissed": true,
                    "dob": "1959-12-04",
                    "lastname": "Brandenburg",
                    "name": "Achim"
                },
                "text": " Brandenburg, Achim, Köln, *04.12.1959"
            },
            {
                "class": "DismissedManagingDirector",
                "payload": {
                    "city": "Adendorf",
                    "dismissed": true,
                    "dob": "1958-01-24",
                    "lastname": "Harms",
                    "name": "Christian"
                },
                "text": " Harms, Christian, Adendorf, *24.01.1958"
            },
            {
                "class": "DismissedManagingDirector",
                "payload": {
                    "city": "Tübingen",
                    "dismissed": true,
                    "dob": "1958-07-07",
                    "lastname": "Heinze",
                    "name": "Frank"
                },
                "text": " Heinze, Frank, Tübingen, *07.07.1958"
            },
            {
                "class": "DismissedManagingDirector",
                "payload": {
                    "city": "Bonn",
                    "dismissed": true,
                    "dob": "1950-08-27",
                    "lastname": "Heun",
                    "name": "Horst Volkmar"
                },
                "text": " Heun, Horst Volkmar, Bonn, *27.08.1950"
            },
            {
                "class": "DismissedManagingDirector",
                "payload": {
                    "city": "Bremen",
                    "dismissed": true,
                    "dob": "1957-05-17",
                    "lastname": "Jost",
                    "name": "Christian Otto"
                },
                "text": " Jost, Christian Otto, Bremen, *17.05.1957"
            },
            {
                "class": "DismissedManagingDirector",
                "payload": {
                    "city": "Lübeck",
                    "dismissed": true,
                    "dob": "1948-07-25",
                    "lastname": "Lorenzen",
                    "name": "Peter"
                },
                "text": " Lorenzen, Peter, Lübeck, *25.07.1948"
            },
            {
                "class": "DismissedManagingDirector",
                "payload": {
                    "city": "Marienheide",
                    "dismissed": true,
                    "dob": "1945-09-21",
                    "lastname": "Müller",
                    "name": "Burkhard"
                },
                "text": " Müller, Burkhard, Marienheide, *21.09.1945"
            },
            {
                "class": "DismissedManagingDirector",
                "payload": {
                    "city": "Bornheim",
                    "dismissed": true,
                    "dob": "1950-02-24",
                    "lastname": "Nettekoven",
                    "name": "Norbert"
                },
                "text": " Nettekoven, Norbert, Bornheim, *24.02.1950"
            },
            {
                "class": "DismissedManagingDirector",
                "payload": {
                    "city": "Wachtberg",
                    "dismissed": true,
                    "dob": "1961-04-17",
                    "lastname": "Doctor Neu",
                    "name": "Norbert"
                },
                "text": " Doctor Neu, Norbert, Wachtberg, *17.04.1961"
            },
            {
                "class": "DismissedManagingDirector",
                "payload": {
                    "city": "Gröbenzell",
                    "dismissed": true,
                    "dob": "1952-06-16",
                    "lastname": "Pütz",
                    "name": "Rainer"
                },
                "text": " Pütz, Rainer, Gröbenzell, *16.06.1952"
            },
            {
                "class": "DismissedManagingDirector",
                "payload": {
                    "city": "Lohmar",
                    "dismissed": true,
                    "dob": "1954-02-16",
                    "lastname": "Schmidt",
                    "name": "Jürgen"
                },
                "text": " Schmidt, Jürgen, Lohmar, *16.02.1954"
            },
            {
                "class": "DismissedManagingDirector",
                "payload": {
                    "city": "Hemmingen",
                    "dismissed": true,
                    "dob": "1961-11-05",
                    "lastname": "Seidel",
                    "name": "Torsten"
                },
                "text": " Seidel, Torsten, Hemmingen, *05.11.1961"
            },
            {
                "class": "DismissedManagingDirector",
                "payload": {
                    "city": "Berlin",
                    "dismissed": true,
                    "dob": "1966-07-27",
                    "lastname": "Volkmer",
                    "name": "Katrin"
                },
                "text": " Volkmer, Katrin, Berlin, *27.07.1966"
            },
            {
                "class": "DismissedManagingDirector",
                "payload": {
                    "city": "Freiburg",
                    "dismissed": true,
                    "dob": "1049-10-10",
                    "lastname": "Doctor Weyer",
                    "name": "Helmut"
                },
                "text": " Doctor Weyer, Helmut, Freiburg, *10.10.1049"
            },
            {
                "class": "DismissedManagingDirector",
                "payload": {
                    "city": "Herford",
                    "dismissed": true,
                    "dob": "1960-01-22",
                    "flag": "jeweils einzelvertretungsberechtigt mit der Befugnis im Namen der Gesellschaft mit sich im eigenen Namen oder als Vertreter eines Dritten Rechtsgeschäfte abzuschließen",
                    "lastname": "Winkler",
                    "name": "Josef"
                },
                "text": " Winkler, Josef, Herford, *22.01.1960, jeweils einzelvertretungsberechtigt mit der Befugnis im Namen der Gesellschaft mit sich im eigenen Namen oder als Vertreter eines Dritten Rechtsgeschäfte abzuschließen."
            },
            {
                "class": "DismissedManagingDirector",
                "payload": {
                    "city": "Schwalbach",
                    "dismissed": true,
                    "dob": "1954-09-07",
                    "lastname": "Klein",
                    "name": "Werner"
                },
                "text": " Klein, Werner, Schwalbach, *07.09.1954"
            },
            {
                "class": "DismissedManagingDirector",
                "payload": {
                    "city": "Bald Oldesloe",
                    "dismissed": true,
                    "dob": "1952-11-17",
                    "lastname": "Pohl",
                    "name": "Horst-Dieter"
                },
                "text": " Pohl, Horst-Dieter, Bald Oldesloe, *17.11.1952"
            },
            {
                "class": "DismissedManagingDirector",
                "payload": {
                    "city": "Wiesbaden",
                    "dismissed": true,
                    "dob": "1955-07-27",
                    "lastname": "Schmitz",
                    "name": "Rolf-Dieter"
                },
                "text": " Schmitz, Rolf-Dieter, Wiesbaden, *27.07.1955"
            },
            {
                "class": "DismissedManagingDirector",
                "payload": {
                    "city": "Bocholt",
                    "dismissed": true,
                    "dob": "1953-04-24",
                    "flag": "jeweils mit der Befugnis im Namen der Gesellschaft mit sich im eigenen Namen oder als Vertreter eines Dritten Rechtsgeschäfte abzuschließen",
                    "lastname": "Weiß",
                    "name": "Paul-Bernhard"
                },
                "text": " Weiß, Paul-Bernhard, Bocholt, *24.04.1953, jeweils mit der Befugnis im Namen der Gesellschaft mit sich im eigenen Namen oder als Vertreter eines Dritten Rechtsgeschäfte abzuschließen."
            }
        ]
    }
}