{
    "orig": {
        "aktenzeichen": "HRB 22385",
        "amtsgericht": "Montabaur",
        "event_date": "2017-10-23",
        "event_type": "Veränderungen",
        "federal_state": "rp",
        "full_text": "Amtsgericht Montabaur Aktenzeichen: HRB 22385 \nBekannt gemacht am: 23.10.2017 20:06 Uhr\n\n\n\n\nDie in () gesetzten Angaben der Anschrift und des Geschäftszweiges erfolgen ohne Gewähr.\nVeränderungen\n23.10.2017\n\nHRB 22385: Energie- und Brennstoffpark Krunkel GmbH, Krunkel, Steinackerstraße 54, 53797 Lohmar. Änderung der Geschäftsanschrift: Industriepark 80, 56593 Krunkel. Nicht mehr Geschäftsführer: Krebs, Ludger, Lohmar, *01.03.1962; Schmidt, Peter-Josef, Bürdenbach, *31.07.1962. Bestellt als Geschäftsführer: Sojka, Ralf, Urbach, *09.03.1972; Dr. Sojka, Dirk, Herschbach, *14.04.1978, jeweils einzelvertretungsberechtigt mit der Befugnis im Namen der Gesellschaft mit sich im eigenen Namen oder als Vertreter eines Dritten Rechtsgeschäfte abzuschließen.",
        "gesellschafter": null,
        "inhaber": null,
        "name": "HRB 22385: Energie- und Brennstoffpark Krunkel GmbH",
        "notice_id": "231395",
        "posted_on": "2017-10-23",
        "rechtsform": null,
        "sitz": null,
        "url": "https://www.handelsregisterbekanntmachungen.de/en/skripte/hrb.php?rb_id=231395&land_abk=rp"
    },
    "parsed": {
        "addresses": [
            {
                "kls": "Address",
                "text": "Industriepark 80, 56593 Krunkel"
            }
        ],
        "officers": [
            {
                "class": "DismissedManagingDirector",
                "payload": {
                    "city": "Lohmar",
                    "dismissed": true,
                    "dob": "1962-03-01",
                    "lastname": "Krebs",
                    "name": "Ludger"
                },
                "text": " Krebs, Ludger, Lohmar, *01.03.1962"
            },
            {
                "class": "DismissedManagingDirector",
                "payload": {
                    "city": "Bürdenbach",
                    "dismissed": true,
                    "dob": "1962-07-31",
                    "lastname": "Schmidt",
                    "name": "Peter-Josef"
                },
                "text": " Schmidt, Peter-Josef, Bürdenbach, *31.07.1962."
            },
            {
                "class": "AppointedManagingDirector",
                "payload": {
                    "city": "Urbach",
                    "dob": "1972-03-09",
                    "lastname": "Sojka",
                    "name": "Ralf"
                },
                "text": " Sojka, Ralf, Urbach, *09.03.1972"
            },
            {
                "class": "AppointedManagingDirector",
                "payload": {
                    "city": "Herschbach",
                    "dob": "1978-04-14",
                    "flag": "jeweils einzelvertretungsberechtigt mit der Befugnis im Namen der Gesellschaft mit sich im eigenen Namen oder als Vertreter eines Dritten Rechtsgeschäfte abzuschließen",
                    "lastname": "Sojka",
                    "name": "Dirk",
                    "prof_title": "doctor"
                },
                "text": " Doctor Sojka, Dirk, Herschbach, *14.04.1978, jeweils einzelvertretungsberechtigt mit der Befugnis im Namen der Gesellschaft mit sich im eigenen Namen oder als Vertreter eines Dritten Rechtsgeschäfte abzuschließen."
            }
        ]
    }
}