{
    "orig": {
        "aktenzeichen": "HRB 106228",
        "amtsgericht": "Hamburg",
        "event_date": "2014-04-09",
        "event_type": "Veränderungen",
        "federal_state": "hh",
        "full_text": "Amtsgericht Hamburg Aktenzeichen: HRB 106228 \nBekannt gemacht am: 09.04.2014 10:06 Uhr\n\n\n\n\nIn () gesetzte Angaben der Anschrift und des Geschäftszweiges erfolgen ohne Gewähr.\nVeränderungen\n09.04.2014\n\nHRB 106228:Verwaltung Projektgesellschaft Marco Polo Tower GmbH, Hamburg, Fuhlsbüttler Str. 399, 22309 Hamburg.Geändert, nun Geschäftsführer: Dahler, Björn, Buchholz, *15.08.1958, vertretungsberechtigt gemeinsam mit der weiteren Geschäftsführerin Vera Spörl oder dem Prokuristen Gordon Gorski. Prokura erloschen Tscheu, Matthias, Hamburg, *25.03.1966. Gesamtprokura gemeinsam mit dem Geschäftsführer Björn Dahler mit der Ermächtigung zur Veräußerung und Belastung von Grundstücken: Gorski, Gordon, Berlin, *10.05.1977.",
        "gesellschafter": null,
        "inhaber": null,
        "name": "HRB 106228:Verwaltung Projektgesellschaft Marco Polo Tower GmbH",
        "notice_id": "231309",
        "posted_on": "2014-04-09",
        "rechtsform": null,
        "sitz": null,
        "url": "https://www.handelsregisterbekanntmachungen.de/en/skripte/hrb.php?rb_id=231309&land_abk=hh"
    },
    "parsed": {
        "officers": [
            {
                "class": "ManagingDirector",
                "payload": {
                    "city": "Buchholz",
                    "dob": "1958-08-15",
                    "flag": "vertretungsberechtigt gemeinsam mit der weiteren Geschäftsführerin Vera Spörl oder dem Prokuristen Gordon Gorski",
                    "lastname": "Dahler",
                    "name": "Björn"
                },
                "text": " Dahler, Björn, Buchholz, *15.08.1958, vertretungsberechtigt gemeinsam mit der weiteren Geschäftsführerin Vera Spörl oder dem Prokuristen Gordon Gorski."
            }
        ]
    }
}