{
    "orig": {
        "aktenzeichen": "HRB 15102",
        "amtsgericht": "Dortmund",
        "event_date": "2007-07-19",
        "event_type": "Veränderungen",
        "federal_state": "nw",
        "full_text": "Amtsgericht Dortmund Aktenzeichen: HRB 15102 \nBekannt gemacht am: 20.07.2007 09:36 Uhr\n\n\n\n\nDie in () gesetzten Angaben der Geschäftsanschrift und des Unternehmensgegenstandes erfolgen ohne Gewähr.\nVeränderungen\n19.07.2007\n\nGebrüder Mause Wohnungsbau GmbH, Dortmund (Mangeder Str. 716, 44359 Dortmund). Die Gesellschafterversammlung vom 15.06.2007 hat eine Änderung des Gesellschaftsvertrages in § 1 (Name und Sitz) und mit ihr die Änderung der Firma beschlossen. Neue Firma: SF Wohnungsbau GmbH. Nicht mehr Geschäftsführer: Mause, Jürgen, Dortmund, *24.07.1957; Mause, Thomas, Dortmund, *28.03.1968. Bestellt als Geschäftsführer: Böhmke, Ruthild, Schwelm, *26.10.1944, einzelvertretungsberechtigt mit der Befugnis im Namen der Gesellschaft mit sich im eigenen Namen oder als Vertreter eines Dritten Rechtsgeschäfte abzuschließen.",
        "gesellschafter": null,
        "inhaber": null,
        "name": "Gebrüder Mause Wohnungsbau GmbH",
        "notice_id": "239923",
        "posted_on": "2007-07-20",
        "rechtsform": null,
        "sitz": null,
        "url": "https://www.handelsregisterbekanntmachungen.de/en/skripte/hrb.php?rb_id=239923&land_abk=nw"
    },
    "parsed": {
        "officers": [
            {
                "class": "DismissedManagingDirector",
                "payload": {
                    "city": "Dortmund",
                    "dismissed": true,
                    "dob": "1957-07-24",
                    "lastname": "Mause",
                    "name": "Jürgen"
                },
                "text": " Mause, Jürgen, Dortmund, *24.07.1957"
            },
            {
                "class": "AppointedManagingDirector",
                "payload": {
                    "city": "Schwelm",
                    "dob": "1944-10-26",
                    "flag": "einzelvertretungsberechtigt mit der Befugnis im Namen der Gesellschaft mit sich im eigenen Namen oder als Vertreter eines Dritten Rechtsgeschäfte abzuschließen",
                    "lastname": "Böhmke",
                    "name": "Ruthild"
                },
                "text": " Böhmke, Ruthild, Schwelm, *26.10.1944, einzelvertretungsberechtigt mit der Befugnis im Namen der Gesellschaft mit sich im eigenen Namen oder als Vertreter eines Dritten Rechtsgeschäfte abzuschließen."
            }
        ]
    }
}