{
    "orig": {
        "aktenzeichen": "HRB 45153",
        "amtsgericht": "Mainz",
        "event_date": "2018-06-05",
        "event_type": "Veränderungen",
        "federal_state": "rp",
        "full_text": "Amtsgericht Mainz Aktenzeichen: HRB 45153 \nBekannt gemacht am: 05.06.2018 20:07 Uhr\n\n\n\n\nDie in () gesetzten Angaben der Anschrift und des Geschäftszweiges erfolgen ohne Gewähr.\nVeränderungen\n05.06.2018\n\nHRB 45153: Özgün GmbH, Wörrstadt, Talstraße 9, 55286 Wörrstadt. Die Gesellschafterversammlung vom 14.05.2018 hat eine Änderung des Gesellschaftsvertrages in § 2 (Gegenstand des Unternehmens) und mit ihr die Änderung des Unternehmensgegenstandes beschlossen. geändert, jetzt: Neuer Unternehmensgegenstand: Die Durchführung von Garten- und Landschaftsbauarbeiten, die Durchführung von Kurierdiensten und Transportdienstleistungen im In- und Ausland und die Erbringung damit im Zusammenhang stehender Serviceleistungen sowie der Betrieb eines Gebrauchtwagenhandels. Bestellt als Geschäftsführer: Özdemir, Fuat, Alzey, *25.09.1964, einzelvertretungsberechtigt mit der Befugnis im Namen der Gesellschaft mit sich im eigenen Namen oder als Vertreter eines Dritten Rechtsgeschäfte abzuschließen. Nicht mehr Geschäftsführer: Günesdogdu, Gülbahar, Wörrstadt, *21.05.1983.",
        "gesellschafter": null,
        "inhaber": null,
        "name": "HRB 45153: Özgün GmbH",
        "notice_id": "244732",
        "posted_on": "2018-06-05",
        "rechtsform": null,
        "sitz": null,
        "url": "https://www.handelsregisterbekanntmachungen.de/en/skripte/hrb.php?rb_id=244732&land_abk=rp"
    },
    "parsed": {
        "officers": [
            {
                "class": "ManagingDirector",
                "payload": {
                    "city": "Alzey",
                    "dob": "1964-09-25",
                    "flag": "einzelvertretungsberechtigt mit der Befugnis im Namen der Gesellschaft mit sich im eigenen Namen oder als Vertreter eines Dritten Rechtsgeschäfte abzuschließen",
                    "lastname": "Özdemir",
                    "name": "Fuat"
                },
                "text": " Özdemir , Fuat , Alzey , * 25.09.1964 , einzelvertretungsberechtigt mit der Befugnis im Namen der Gesellschaft mit sich im eigenen Namen oder als Vertreter eines Dritten Rechtsgeschäfte abzuschließen ."
            },
            {
                "class": "ManagingDirector",
                "payload": {
                    "city": "Wörrstadt",
                    "dob": "1983-05-21",
                    "lastname": "Günesdogdu",
                    "name": "Gülbahar"
                },
                "text": " Günesdogdu , Gülbahar , Wörrstadt , * 21.05.1983 ."
            }
        ]
    }
}