{
    "orig": {
        "aktenzeichen": "HRB 124006",
        "amtsgericht": "Hamburg",
        "event_date": "2014-11-24",
        "event_type": "Veränderungen",
        "federal_state": "hh",
        "full_text": "Amtsgericht Hamburg Aktenzeichen: HRB 124006 \nBekannt gemacht am: 24.11.2014 12:02 Uhr\n\n\n\n\nIn () gesetzte Angaben der Anschrift und des Geschäftszweiges erfolgen ohne Gewähr.\nVeränderungen\n24.11.2014\n\nHRB 124006:MHM Hamburg Verwaltung GmbH, Hamburg, Wilhelm-Stein-Weg 12, 22339 Hamburg.Bestellt Geschäftsführer: Abdi Khorsand, Mohammad, Hamburg, *08.05.1967; Nazari Moghaddam, Jahangir, Hamburg, *21.03.1961, jeweils vertretungsberechtigt gemäß allgemeiner Vertretungsregelung; mit der Befugnis, im Namen der Gesellschaft mit sich im eigenen Namen oder als Vertreter eines Dritten Rechtsgeschäfte abzuschließen. Prokura erloschen Abdi Khorsand, Mohammad, Hamburg, *08.05.1967; Nazari Moghaddam, Jahangir, Hamburg, *21.03.1961.",
        "gesellschafter": null,
        "inhaber": null,
        "name": "HRB 124006:MHM Hamburg Verwaltung GmbH",
        "notice_id": "250201",
        "posted_on": "2014-11-24",
        "rechtsform": null,
        "sitz": null,
        "url": "https://www.handelsregisterbekanntmachungen.de/en/skripte/hrb.php?rb_id=250201&land_abk=hh"
    },
    "parsed": {
        "flags": [
            {
                "flag": "with the power to enter into legal transactions on behalf of the Company with itself or as a representative of a third party",
                "text": "mit\\ der\\ Befugnis\\,\\ im\\ Namen\\ der\\ Gesellschaft\\ mit\\ sich\\ im\\ eigenen\\ Namen\\ oder\\ als\\ Vertreter\\ eines\\ Dritten\\ Rechtsgesch\\äfte\\ abzuschlie\\ßen\\."
            }
        ],
        "officers": [
            {
                "class": "AppointedManagingDirector",
                "payload": {
                    "city": "Hamburg",
                    "dob": "1967-05-08",
                    "lastname": "Abdi Khorsand",
                    "name": "Mohammad"
                },
                "text": " Abdi Khorsand, Mohammad, Hamburg, *08.05.1967"
            },
            {
                "class": "AppointedManagingDirector",
                "payload": {
                    "city": "Hamburg",
                    "dob": "1961-03-21",
                    "flag": "jeweils vertretungsberechtigt gemäß allgemeiner Vertretungsregelung",
                    "lastname": "Nazari Moghaddam",
                    "name": "Jahangir"
                },
                "text": " Nazari Moghaddam, Jahangir, Hamburg, *21.03.1961, jeweils vertretungsberechtigt gemäß allgemeiner Vertretungsregelung"
            },
            {
                "class": "AppointedManagingDirector",
                "payload": {
                    "lastname": "mit der Befugnis",
                    "name": "im Namen der Gesellschaft mit sich im eigenen Namen oder als Vertreter eines Dritten Rechtsgeschäfte abzuschließen"
                },
                "text": " mit der Befugnis, im Namen der Gesellschaft mit sich im eigenen Namen oder als Vertreter eines Dritten Rechtsgeschäfte abzuschließen."
            }
        ]
    }
}