{
    "orig": {
        "aktenzeichen": "HRB 20392",
        "amtsgericht": "Hamburg",
        "event_date": "2014-12-10",
        "event_type": "Veränderungen",
        "federal_state": "hh",
        "full_text": "Amtsgericht Hamburg Aktenzeichen: HRB 20392 \nBekannt gemacht am: 10.12.2014 15:08 Uhr\n\n\n\n\nIn () gesetzte Angaben der Anschrift und des Geschäftszweiges erfolgen ohne Gewähr.\nVeränderungen\n10.12.2014\n\nHRB 20392:Creative Media Services GmbH, Hamburg, Hongkongstraße 10, 20457 Hamburg.Bestellt Geschäftsführer: Dunke, Michael, Frankfurt am Main, *27.03.1965, vertretungsberechtigt gemäß allgemeiner Vertretungsregelung. Der mit der Initiative Group GmbH (nach Firmenänderung jetzt: Mediabrands GmbH) mit Sitz in Hamburg (Amtsgericht Hamburg, HRB 64504) am 03.11.2004 abgeschlossene Beherrschungs- und Ergebnisabführungsvertrag ist durch Vertrag vom 09.10.2014 geändert. Die Gesellschafterversammlung vom 10.11.2014 hat der Änderung zugestimmt.",
        "gesellschafter": null,
        "inhaber": null,
        "name": "HRB 20392:Creative Media Services GmbH",
        "notice_id": "251892",
        "posted_on": "2014-12-10",
        "rechtsform": null,
        "sitz": null,
        "url": "https://www.handelsregisterbekanntmachungen.de/en/skripte/hrb.php?rb_id=251892&land_abk=hh"
    },
    "parsed": {
        "officers": [
            {
                "class": "AppointedManagingDirector",
                "payload": {
                    "city": "Frankfurt am Main",
                    "dob": "1965-03-27",
                    "flag": "vertretungsberechtigt gemäß allgemeiner Vertretungsregelung",
                    "lastname": "Dunke",
                    "name": "Michael"
                },
                "text": " Dunke, Michael, Frankfurt am Main, *27.03.1965, vertretungsberechtigt gemäß allgemeiner Vertretungsregelung."
            }
        ]
    }
}