{
    "orig": {
        "aktenzeichen": "HRB 103869",
        "amtsgericht": "Hamburg",
        "event_date": "2015-02-06",
        "event_type": "Veränderungen",
        "federal_state": "hh",
        "full_text": "Amtsgericht Hamburg Aktenzeichen: HRB 103869 \nBekannt gemacht am: 06.02.2015 10:11 Uhr\n\n\n\n\nIn () gesetzte Angaben der Anschrift und des Geschäftszweiges erfolgen ohne Gewähr.\nVeränderungen\n06.02.2015\n\nHRB 103869:First Property Verwaltungsgesellschaft mbH, Hamburg, Großer Burstah 45, 20457 Hamburg.Ausgeschieden Geschäftsführer: Aharoni, Royi, Gibraltar / Großbritannien, *03.04.1977. Bestellt Geschäftsführer: Belilo, Ariel, Gibraltar / Großbritannien, *17.04.1975, vertretungsberechtigt gemeinsam mit einem anderen Geschäftsführer; mit der Befugnis, im Namen der Gesellschaft mit sich im eigenen Namen oder als Vertreter eines Dritten Rechtsgeschäfte abzuschließen.",
        "gesellschafter": null,
        "inhaber": null,
        "name": "HRB 103869:First Property Verwaltungsgesellschaft mbH",
        "notice_id": "257518",
        "posted_on": "2015-02-06",
        "rechtsform": null,
        "sitz": null,
        "url": "https://www.handelsregisterbekanntmachungen.de/en/skripte/hrb.php?rb_id=257518&land_abk=hh"
    },
    "parsed": {
        "flags": [
            {
                "flag": "with the power to enter into legal transactions on behalf of the Company with itself or as a representative of a third party",
                "text": "mit\\ der\\ Befugnis\\,\\ im\\ Namen\\ der\\ Gesellschaft\\ mit\\ sich\\ im\\ eigenen\\ Namen\\ oder\\ als\\ Vertreter\\ eines\\ Dritten\\ Rechtsgesch\\äfte\\ abzuschlie\\ßen\\."
            }
        ],
        "officers": [
            {
                "class": "RetiredManagingDirector",
                "payload": {
                    "city": "Gibraltar / Großbritannien",
                    "dismissed": true,
                    "dob": "1977-04-03",
                    "lastname": "Aharoni",
                    "name": "Royi"
                },
                "text": " Aharoni, Royi, Gibraltar / Großbritannien, *03.04.1977."
            },
            {
                "class": "AppointedManagingDirector",
                "payload": {
                    "city": "Gibraltar / Großbritannien",
                    "dob": "1975-04-17",
                    "flag": "vertretungsberechtigt gemeinsam mit einem anderen Geschäftsführer",
                    "lastname": "Belilo",
                    "name": "Ariel"
                },
                "text": " Belilo, Ariel, Gibraltar / Großbritannien, *17.04.1975, vertretungsberechtigt gemeinsam mit einem anderen Geschäftsführer"
            },
            {
                "class": "AppointedManagingDirector",
                "payload": {
                    "lastname": "mit der Befugnis",
                    "name": "im Namen der Gesellschaft mit sich im eigenen Namen oder als Vertreter eines Dritten Rechtsgeschäfte abzuschließen"
                },
                "text": " mit der Befugnis, im Namen der Gesellschaft mit sich im eigenen Namen oder als Vertreter eines Dritten Rechtsgeschäfte abzuschließen."
            }
        ]
    }
}