{
    "orig": {
        "aktenzeichen": "HRB 129814",
        "amtsgericht": "Hamburg",
        "event_date": "2015-06-22",
        "event_type": "Veränderungen",
        "federal_state": "hh",
        "full_text": "Amtsgericht Hamburg Aktenzeichen: HRB 129814 \nBekannt gemacht am: 22.06.2015 19:02 Uhr\n\n\n\n\nIn () gesetzte Angaben der Anschrift und des Geschäftszweiges erfolgen ohne Gewähr.\nVeränderungen\n22.06.2015\n\nHRB 129814:2. BEMA Beteiligungs GmbH, Hamburg, New-York-Ring 6, 22297 Hamburg.Geändert (Vertretung), nun Geschäftsführer: Krümpelmann, Norbert, Schenefeld, *02.02.1965; Schröder, Christoph, Bad Vilbel, *15.01.1964, jeweils vertretungsberechtigt gemäß allgemeiner Vertretungsregelung; mit der Befugnis, im Namen der Gesellschaft mit sich als Vertreter eines Dritten Rechtsgeschäfte abzuschließen. Bei Geschäftsführerbestellungen und -abberufungen sind die Geschäftsführer vollständig von den Beschränkungen des § 181 BGB befreit. Berichtigung der Einragung vom 02.12.2014 von Amts wegen.",
        "gesellschafter": null,
        "inhaber": null,
        "name": "HRB 129814:2. BEMA Beteiligungs GmbH",
        "notice_id": "269197",
        "posted_on": "2015-06-22",
        "rechtsform": null,
        "sitz": null,
        "url": "https://www.handelsregisterbekanntmachungen.de/en/skripte/hrb.php?rb_id=269197&land_abk=hh"
    },
    "parsed": {
        "officers": [
            {
                "class": "ManagingDirector",
                "payload": {
                    "city": "Schenefeld",
                    "dob": "1965-02-02",
                    "lastname": "Krümpelmann",
                    "name": "Norbert"
                },
                "text": " Krümpelmann, Norbert, Schenefeld, *02.02.1965"
            },
            {
                "class": "ManagingDirector",
                "payload": {
                    "city": "Bad Vilbel",
                    "dob": "1964-01-15",
                    "flag": "jeweils vertretungsberechtigt gemäß allgemeiner Vertretungsregelung",
                    "lastname": "Schröder",
                    "name": "Christoph"
                },
                "text": " Schröder, Christoph, Bad Vilbel, *15.01.1964, jeweils vertretungsberechtigt gemäß allgemeiner Vertretungsregelung"
            },
            {
                "class": "ManagingDirector",
                "payload": {
                    "lastname": "mit der Befugnis",
                    "name": "im Namen der Gesellschaft mit sich als Vertreter eines Dritten Rechtsgeschäfte abzuschließen"
                },
                "text": " mit der Befugnis, im Namen der Gesellschaft mit sich als Vertreter eines Dritten Rechtsgeschäfte abzuschließen."
            }
        ]
    }
}