{
    "orig": {
        "aktenzeichen": "HRB 13366",
        "amtsgericht": "Wiesbaden",
        "event_date": "2012-02-10",
        "event_type": "Veränderungen",
        "federal_state": "he",
        "full_text": "Amtsgericht Wiesbaden Aktenzeichen: HRB 13366   \nBekannt gemacht am: 20.02.2012 22:00 Uhr\n\n\n\n\nVeröffentlichungen des Amtsgerichts Wiesbaden\r\r\rIn () gesetzte Angaben der Anschrift und des Geschäftszweiges erfolgen ohne Gewähr.\nVeränderungen\n10.02.2012\n\nAragon Grundstücksverwaltungsgesellschaft mbH, Wiesbaden, Eleonorenstraße 64, 55252 Mainz-Kastel. Ist nur ein Liquidator bestellt, so vertritt er die Gesellschaft allein. Sind mehrere Liquidatoren bestellt, so wird die Gesellschaft durch zwei Liquidatoren oder durch einen Liquidator gemeinsam mit einem Prokuristen vertreten. Jeder Liquidator ist befugt, im Namen der Gesellschaft mit sich im eigenen Namen oder als Vertreter eines Dritten Rechtsgeschäfte vorzunehmen. Nicht mehr Geschäftsführer: Born, Wolfgang, Selzen, *16.10.1951; Noll, Ralf Paul, Rockenberg, *02.02.1967. Nicht mehr Geschäftsführerin: Trapp geb. Stoll, Birgit, Friedrichsdorf, *10.05.1960. Bestellt als Liquidator: Dahlhaus, Hermann, Bingen, *05.04.1947; Momberg, Frank, Hochheim am Main, *17.04.1972, jeweils einzelvertretungsberechtigt. Prokura erloschen: Düll, Werner, Kelkheim, *02.10.1955; Höhne, Heinz Günter, Mainz, *01.05.1957. Die Gesellschaft ist aufgelöst.",
        "gesellschafter": null,
        "inhaber": null,
        "name": "Aragon Grundstücksverwaltungsgesellschaft mbH",
        "notice_id": "270561",
        "posted_on": "2012-02-20",
        "rechtsform": null,
        "sitz": null,
        "url": "https://www.handelsregisterbekanntmachungen.de/en/skripte/hrb.php?rb_id=270561&land_abk=he"
    },
    "parsed": {
        "flags": [
            {
                "flag": "CompanyClosed",
                "text": "Die\\ Gesellschaft\\ ist\\ aufgel\\öst\\."
            }
        ],
        "officers": [
            {
                "class": "DismissedManagingDirector",
                "payload": {
                    "city": "Selzen",
                    "dismissed": true,
                    "dob": "1951-10-16",
                    "lastname": "Born",
                    "name": "Wolfgang"
                },
                "text": " Born, Wolfgang, Selzen, *16.10.1951"
            },
            {
                "class": "DismissedManagingDirector",
                "payload": {
                    "city": "Friedrichsdorf",
                    "dismissed": true,
                    "dob": "1960-10-05",
                    "lastname": "Trapp",
                    "maidenname": "Stoll",
                    "name": "Birgit"
                },
                "text": " Trapp geborene Stoll, Birgit, Friedrichsdorf, *10.05.1960."
            },
            {
                "class": "Liquidator",
                "payload": {
                    "city": "Bingen",
                    "dob": "1947-05-04",
                    "lastname": "Dahlhaus",
                    "name": "Hermann"
                },
                "text": " Dahlhaus, Hermann, Bingen, *05.04.1947"
            },
            {
                "class": "ProcurationCancelled",
                "payload": {
                    "city": "Kelkheim",
                    "dismissed": true,
                    "dob": "1955-02-10",
                    "lastname": "Düll",
                    "name": "Werner"
                },
                "text": " Düll, Werner, Kelkheim, *02.10.1955"
            }
        ]
    }
}