{
    "orig": {
        "aktenzeichen": "HRB 34310",
        "amtsgericht": "Köln",
        "event_date": "2007-11-22",
        "event_type": "Veränderungen",
        "federal_state": "nw",
        "full_text": "Amtsgericht Köln Aktenzeichen: HRB 34310 \nBekannt gemacht am: 28.11.2007 12:00 Uhr\n\n\n\n\nDie in () gesetzten Angaben der Geschäftsanschrift und des Geschäftszweiges erfolgen ohne Gewähr.\nVeränderungen\n22.11.2007\n\nColonius Carrée Entwicklungsgesellschaft mbH, Köln (Siegburger Straße 241, 50679 Köln). Bestellt als Geschäftsführer: Hohwieler, Thomas, Freiburg, *07.11.1965, vertretungsberechtigt gemeinsam mit einem anderen Geschäftsführer oder einem Prokuristen. Nicht mehr Geschäftsführer: Rodehüser, Heinz-Jürgen, Köln, *24.05.1960. Zwischen der Colonius Carrée Entwicklungsgesellschaft mbH als beherrschter Gesellschaft und der STRABAG Projektentwicklung GmbH mit Sitz in Köln (Amtsgericht Köln, HRB 5740 ) besteht ein Gewinnabführungsvertrag vom 29.10.2007. Diesem Vertrag hat die Gesellschafterversammlung der Colonius Carrée Entwicklungsgesellschaft mbH durch Beschluss vom 15.11.2007 zugestimmt.",
        "gesellschafter": null,
        "inhaber": null,
        "name": "Colonius Carrée Entwicklungsgesellschaft mbH",
        "notice_id": "274891",
        "posted_on": "2007-11-28",
        "rechtsform": null,
        "sitz": null,
        "url": "https://www.handelsregisterbekanntmachungen.de/en/skripte/hrb.php?rb_id=274891&land_abk=nw"
    },
    "parsed": {
        "officers": [
            {
                "class": "AppointedManagingDirector",
                "payload": {
                    "city": "Freiburg",
                    "dob": "1965-07-11",
                    "flag": "vertretungsberechtigt gemeinsam mit einem anderen Geschäftsführer oder einem Prokuristen",
                    "lastname": "Hohwieler",
                    "name": "Thomas"
                },
                "text": " Hohwieler, Thomas, Freiburg, *07.11.1965, vertretungsberechtigt gemeinsam mit einem anderen Geschäftsführer oder einem Prokuristen."
            },
            {
                "class": "DismissedManagingDirector",
                "payload": {
                    "city": "Köln",
                    "dismissed": true,
                    "dob": "1960-05-24",
                    "lastname": "Rodehüser",
                    "name": "Heinz-Jürgen"
                },
                "text": " Rodehüser, Heinz-Jürgen, Köln, *24.05.1960."
            }
        ]
    }
}