{
    "orig": {
        "aktenzeichen": "HRB 125348",
        "amtsgericht": "Hamburg",
        "event_date": "2016-03-14",
        "event_type": "Veränderungen",
        "federal_state": "hh",
        "full_text": "Amtsgericht Hamburg Aktenzeichen: HRB 125348 \nBekannt gemacht am: 14.03.2016 09:46 Uhr\n\n\n\n\nIn () gesetzte Angaben der Anschrift und des Geschäftszweiges erfolgen ohne Gewähr.\nVeränderungen\n14.03.2016\n\nHRB 125348: Ribu Media Unternehmergesellschaft (haftungsbeschränkt), Hamburg, Albert-Schweitzer-Ring 39, 22045 Hamburg. Ist nur ein Liquidator bestellt, so vertritt er die Gesellschaft allein. Sind mehrere Liquidatoren bestellt, so wird die Gesellschaft durch die Liquidatoren gemeinsam vertreten. Geändert, nun Liquidator: Schmidt, Frank-Rüdiger, Stade OT Wipenkathen, *12.11.1961, vertretungsberechtigt gemäß allgemeiner Vertretungsregelung. Die Gesellschaft ist aufgelöst.",
        "gesellschafter": null,
        "inhaber": null,
        "name": "HRB 125348: Ribu Media Unternehmergesellschaft (haftungsbeschränkt)",
        "notice_id": "292377",
        "posted_on": "2016-03-14",
        "rechtsform": null,
        "sitz": null,
        "url": "https://www.handelsregisterbekanntmachungen.de/en/skripte/hrb.php?rb_id=292377&land_abk=hh"
    },
    "parsed": {
        "flags": [
            {
                "flag": "CompanyClosed",
                "text": "Die\\ Gesellschaft\\ ist\\ aufgel\\öst\\."
            }
        ],
        "officers": [
            {
                "class": "Liquidator",
                "payload": {
                    "city": "Stade OT Wipenkathen",
                    "dob": "1961-12-11",
                    "flag": "vertretungsberechtigt gemäß allgemeiner Vertretungsregelung",
                    "lastname": "Schmidt",
                    "name": "Frank-Rüdiger"
                },
                "text": " Schmidt, Frank-Rüdiger, Stade OT Wipenkathen, *12.11.1961, vertretungsberechtigt gemäß allgemeiner Vertretungsregelung."
            }
        ]
    }
}