{
    "orig": {
        "aktenzeichen": "HRB 131370",
        "amtsgericht": "Hamburg",
        "event_date": "2016-03-22",
        "event_type": "Veränderungen",
        "federal_state": "hh",
        "full_text": "Amtsgericht Hamburg Aktenzeichen: HRB 131370 \nBekannt gemacht am: 22.03.2016 10:19 Uhr\n\n\n\n\nIn () gesetzte Angaben der Anschrift und des Geschäftszweiges erfolgen ohne Gewähr.\nVeränderungen\n22.03.2016\n\nHRB 131370: Varo Energy Refining GmbH, Hamburg, Am Sandtorkai 77, 20457 Hamburg. Geändert, nun Geschäftsführer: Silkenath, Christian Michael, Hamburg, *14.04.1967; von Leesen, Martin, Hamburg, *01.01.1969, jeweils vertretungsberechtigt gemäß allgemeiner Vertretungsregelung; mit der Befugnis, im Namen der Gesellschaft mit sich im eigenen Namen oder als Vertreter eines Dritten Rechtsgeschäfte abzuschließen. Bestellt Geschäftsführer: Kuijl, Willem Arie, Essen, *16.11.1952, vertretungsberechtigt gemäß allgemeiner Vertretungsregelung; mit der Befugnis, im Namen der Gesellschaft mit sich im eigenen Namen oder als Vertreter eines Dritten Rechtsgeschäfte abzuschließen.",
        "gesellschafter": null,
        "inhaber": null,
        "name": "HRB 131370: Varo Energy Refining GmbH",
        "notice_id": "293132",
        "posted_on": "2016-03-22",
        "rechtsform": null,
        "sitz": null,
        "url": "https://www.handelsregisterbekanntmachungen.de/en/skripte/hrb.php?rb_id=293132&land_abk=hh"
    },
    "parsed": {
        "flags": [
            {
                "flag": "with the power to enter into legal transactions on behalf of the Company with itself or as a representative of a third party",
                "text": "mit\\ der\\ Befugnis\\,\\ im\\ Namen\\ der\\ Gesellschaft\\ mit\\ sich\\ im\\ eigenen\\ Namen\\ oder\\ als\\ Vertreter\\ eines\\ Dritten\\ Rechtsgesch\\äfte\\ abzuschlie\\ßen\\."
            },
            {
                "flag": "with the power to enter into legal transactions on behalf of the Company with itself or as a representative of a third party",
                "text": "mit\\ der\\ Befugnis\\,\\ im\\ Namen\\ der\\ Gesellschaft\\ mit\\ sich\\ im\\ eigenen\\ Namen\\ oder\\ als\\ Vertreter\\ eines\\ Dritten\\ Rechtsgesch\\äfte\\ abzuschlie\\ßen\\."
            }
        ],
        "officers": [
            {
                "class": "ManagingDirector",
                "payload": {
                    "city": "Hamburg",
                    "dob": "1967-04-14",
                    "lastname": "Silkenath",
                    "name": "Christian Michael"
                },
                "text": " Silkenath, Christian Michael, Hamburg, *14.04.1967"
            },
            {
                "class": "ManagingDirector",
                "payload": {
                    "city": "Hamburg",
                    "dob": "1969-01-01",
                    "flag": "jeweils vertretungsberechtigt gemäß allgemeiner Vertretungsregelung",
                    "lastname": "von Leesen",
                    "name": "Martin"
                },
                "text": " von Leesen, Martin, Hamburg, *01.01.1969, jeweils vertretungsberechtigt gemäß allgemeiner Vertretungsregelung"
            },
            {
                "class": "ManagingDirector",
                "payload": {
                    "lastname": "mit der Befugnis",
                    "name": "im Namen der Gesellschaft mit sich im eigenen Namen oder als Vertreter eines Dritten Rechtsgeschäfte abzuschließen"
                },
                "text": " mit der Befugnis, im Namen der Gesellschaft mit sich im eigenen Namen oder als Vertreter eines Dritten Rechtsgeschäfte abzuschließen."
            },
            {
                "class": "AppointedManagingDirector",
                "payload": {
                    "city": "Essen",
                    "dob": "1952-11-16",
                    "flag": "vertretungsberechtigt gemäß allgemeiner Vertretungsregelung",
                    "lastname": "Kuijl",
                    "name": "Willem Arie"
                },
                "text": " Kuijl, Willem Arie, Essen, *16.11.1952, vertretungsberechtigt gemäß allgemeiner Vertretungsregelung"
            },
            {
                "class": "AppointedManagingDirector",
                "payload": {
                    "lastname": "mit der Befugnis",
                    "name": "im Namen der Gesellschaft mit sich im eigenen Namen oder als Vertreter eines Dritten Rechtsgeschäfte abzuschließen"
                },
                "text": " mit der Befugnis, im Namen der Gesellschaft mit sich im eigenen Namen oder als Vertreter eines Dritten Rechtsgeschäfte abzuschließen."
            }
        ]
    }
}