{
    "orig": {
        "aktenzeichen": "HRB 60516",
        "amtsgericht": "Hamburg",
        "event_date": "2016-07-04",
        "event_type": "Veränderungen",
        "federal_state": "hh",
        "full_text": "Amtsgericht Hamburg Aktenzeichen: HRB 60516 \nBekannt gemacht am: 04.07.2016 12:47 Uhr\n\n\n\n\nIn () gesetzte Angaben der Anschrift und des Geschäftszweiges erfolgen ohne Gewähr.\nVeränderungen\n04.07.2016\n\nHRB 60516: J. J. Darboven Verwaltungs-GmbH, Hamburg, Pinkertweg 13, 22113 Hamburg. Ausgeschieden Geschäftsführer: Hilgenberg, Frank, Hamburg, *19.03.1968; Peters, Wilfried, St. Michaelisdonn, *18.10.1950. Bestellt Geschäftsführer: Brockmann, Jens Albert, Hamburg, *22.11.1967; Ziesemer, Frank, Norderstedt, *05.03.1970, jeweils vertretungsberechtigt gemeinsam mit einem anderen Geschäftsführer oder einem Prokuristen; mit der Befugnis, im Namen der Gesellschaft mit sich im eigenen Namen oder als Vertreter eines Dritten Rechtsgeschäfte abzuschließen.",
        "gesellschafter": null,
        "inhaber": null,
        "name": "HRB 60516: J. J. Darboven Verwaltungs-GmbH",
        "notice_id": "302152",
        "posted_on": "2016-07-04",
        "rechtsform": null,
        "sitz": null,
        "url": "https://www.handelsregisterbekanntmachungen.de/en/skripte/hrb.php?rb_id=302152&land_abk=hh"
    },
    "parsed": {
        "errors": [
            {
                "kls": "ParsingError",
                "text": "Cannot parse a AppointedManagingDirector from  mit der Befugnis, im Namen der Gesellschaft mit sich im eigenen Namen oder als Vertreter eines Dritten Rechtsgeschäfte abzuschließen., error text was Name is too long: im Namen der Gesellschaft mit sich im eigenen Namen oder als Vertreter eines Dritten Rechtsgeschäfte abzuschließen"
            }
        ],
        "flags": [
            {
                "flag": "with the power to enter into legal transactions on behalf of the Company with itself or as a representative of a third party",
                "text": "mit\\ der\\ Befugnis\\,\\ im\\ Namen\\ der\\ Gesellschaft\\ mit\\ sich\\ im\\ eigenen\\ Namen\\ oder\\ als\\ Vertreter\\ eines\\ Dritten\\ Rechtsgesch\\äfte\\ abzuschlie\\ßen\\."
            }
        ],
        "officers": [
            {
                "class": "RetiredManagingDirector",
                "payload": {
                    "city": "Hamburg",
                    "dismissed": true,
                    "dob": "1968-03-19",
                    "lastname": "Hilgenberg",
                    "name": "Frank"
                },
                "text": " Hilgenberg, Frank, Hamburg, *19.03.1968"
            },
            {
                "class": "RetiredManagingDirector",
                "payload": {
                    "city": "St. Michaelisdonn",
                    "dismissed": true,
                    "dob": "1950-10-18",
                    "lastname": "Peters",
                    "name": "Wilfried"
                },
                "text": " Peters, Wilfried, St. Michaelisdonn, *18.10.1950."
            },
            {
                "class": "AppointedManagingDirector",
                "payload": {
                    "city": "Hamburg",
                    "dob": "1967-11-22",
                    "lastname": "Brockmann",
                    "name": "Jens Albert"
                },
                "text": " Brockmann, Jens Albert, Hamburg, *22.11.1967"
            },
            {
                "class": "AppointedManagingDirector",
                "payload": {
                    "city": "Norderstedt",
                    "dob": "1970-03-05",
                    "flag": "jeweils vertretungsberechtigt gemeinsam mit einem anderen Geschäftsführer oder einem Prokuristen",
                    "lastname": "Ziesemer",
                    "name": "Frank"
                },
                "text": " Ziesemer, Frank, Norderstedt, *05.03.1970, jeweils vertretungsberechtigt gemeinsam mit einem anderen Geschäftsführer oder einem Prokuristen"
            }
        ]
    }
}