{
    "orig": {
        "aktenzeichen": "HRB 9760",
        "amtsgericht": "Braunschweig",
        "event_date": "2014-07-11",
        "event_type": "Veränderungen",
        "federal_state": "ni",
        "full_text": "Amtsgericht Braunschweig Aktenzeichen: HRB 9760 \nBekannt gemacht am: 11.07.2014 19:00 Uhr\n\n\n\n\nDie in () gesetzten Angaben der Geschäftsanschrift und des Unternehmensgegenstandes erfolgen ohne Gewähr.\nVeränderungen\n11.07.2014\n\nHRB 9760:HIWIG Verwaltungsgesellschaft mbH, Braunschweig, Am Denkmal 5, 38112 Braunschweig.Geschäftsanschrift: Am Denkmal 5, 38112 Braunschweig. Nicht mehr Geschäftsführer: Hinrichs, Torsten, Cremlingen, *04.09.1948. Bestellt als Geschäftsführer: Laubrich, Maic, Meinersen, *19.03.1971, vertretungsberechtigt gemeinsam mit einem anderen Geschäftsführer. Prokura erloschen: Becker, Frank, Braunschweig, *20.01.1956. Gesamtprokura gemeinsam mit dem Geschäftsführer Heinz Winkelhaus oder gemeinsam mit dem Geschäftsführer Otto Görge: Schröder, Gerhard, Peine, *29.05.1962.",
        "gesellschafter": null,
        "inhaber": null,
        "name": "HRB 9760:HIWIG Verwaltungsgesellschaft mbH",
        "notice_id": "306978",
        "posted_on": "2014-07-11",
        "rechtsform": null,
        "sitz": null,
        "url": "https://www.handelsregisterbekanntmachungen.de/en/skripte/hrb.php?rb_id=306978&land_abk=ni"
    },
    "parsed": {
        "labels": [
            {
                "label": "address",
                "text": " Am Denkmal 5, 38112 Braunschweig."
            }
        ],
        "officers": [
            {
                "class": "DismissedManagingDirector",
                "payload": {
                    "city": "Cremlingen",
                    "dismissed": true,
                    "dob": "1948-04-09",
                    "lastname": "Hinrichs",
                    "name": "Torsten"
                },
                "text": " Hinrichs, Torsten, Cremlingen, *04.09.1948."
            },
            {
                "class": "AppointedManagingDirector",
                "payload": {
                    "city": "Meinersen",
                    "dob": "1971-03-19",
                    "flag": "vertretungsberechtigt gemeinsam mit einem anderen Geschäftsführer",
                    "lastname": "Laubrich",
                    "name": "Maic"
                },
                "text": " Laubrich, Maic, Meinersen, *19.03.1971, vertretungsberechtigt gemeinsam mit einem anderen Geschäftsführer."
            },
            {
                "class": "ProcurationCancelled",
                "payload": {
                    "city": "Braunschweig",
                    "dismissed": true,
                    "dob": "1956-01-20",
                    "lastname": "Becker",
                    "name": "Frank"
                },
                "text": " Becker, Frank, Braunschweig, *20.01.1956."
            }
        ]
    }
}