{
    "orig": {
        "aktenzeichen": "HRB 5286",
        "amtsgericht": "Bad Oeynhausen",
        "event_date": "2008-04-08",
        "event_type": "Veränderungen",
        "federal_state": "nw",
        "full_text": "Amtsgericht Bad Oeynhausen Aktenzeichen: HRB 5286 \nBekannt gemacht am: 22.04.2008 22:00 Uhr\n\n\n\n\nDie in () gesetzten Angaben der Geschäftsanschrift und des Unternehmensgegenstandes erfolgen ohne Gewähr.\nVeränderungen\n08.04.2008\n\nTönsmeier Entsorgung Beteiligungs-GmbH, Porta Westfalica (An der Pforte 2, 32457 Porta Westfalica). Bestellt als Geschäftsführer: Gronlied, Wolfgang, Herford, *05.08.1950; Hachmann, Jean Michael, Gütersloh, *08.06.1968; Helmer, Lars, Rheda-Wiedenbrück, *18.08.1969, jeweils mit der Befugnis im Namen der Gesellschaft mit sich als Vertreter eines Dritten Rechtsgeschäfte abzuschließen. Nicht mehr Geschäftsführer: Balg, Jürgen, Porta Westfalica, *28.10.1957; Dipl.-Betriebswirt Gerwert, Egon, Wadersloh. Prokura erloschen: Gronlied, Wolfgang, Herford, *05.08.1950; Hachmann, Jean-Michael, Gütersloh, *08.06.1968; Helmer, Lars, Rheda-Wiedenbrück, *18.08.1969. Gesamtprokura gemeinsam mit einem Geschäftsführer oder einem anderen Prokuristen mit der Befugnis im Namen der Gesellschaft mit sich als Vertreter eines Dritten Rechtsgeschäfte abzuschließen: Brethauer, Björn, Herford, *29.11.1974.",
        "gesellschafter": null,
        "inhaber": null,
        "name": "Tönsmeier Entsorgung Beteiligungs-GmbH",
        "notice_id": "317319",
        "posted_on": "2008-04-22",
        "rechtsform": null,
        "sitz": null,
        "url": "https://www.handelsregisterbekanntmachungen.de/en/skripte/hrb.php?rb_id=317319&land_abk=nw"
    },
    "parsed": {
        "officers": [
            {
                "class": "AppointedManagingDirector",
                "payload": {
                    "city": "Herford",
                    "dob": "1950-08-05",
                    "lastname": "Gronlied",
                    "name": "Wolfgang"
                },
                "text": " Gronlied, Wolfgang, Herford, *05.08.1950"
            },
            {
                "class": "AppointedManagingDirector",
                "payload": {
                    "city": "Gütersloh",
                    "dob": "1968-06-08",
                    "lastname": "Hachmann",
                    "name": "Jean Michael"
                },
                "text": " Hachmann, Jean Michael, Gütersloh, *08.06.1968"
            },
            {
                "class": "AppointedManagingDirector",
                "payload": {
                    "city": "Rheda-Wiedenbrück",
                    "dob": "1969-08-18",
                    "flag": "jeweils mit der Befugnis im Namen der Gesellschaft mit sich als Vertreter eines Dritten Rechtsgeschäfte abzuschließen",
                    "lastname": "Helmer",
                    "name": "Lars"
                },
                "text": " Helmer, Lars, Rheda-Wiedenbrück, *18.08.1969, jeweils mit der Befugnis im Namen der Gesellschaft mit sich als Vertreter eines Dritten Rechtsgeschäfte abzuschließen."
            },
            {
                "class": "DismissedManagingDirector",
                "payload": {
                    "city": "Porta Westfalica",
                    "dismissed": true,
                    "dob": "1957-10-28",
                    "lastname": "Balg",
                    "name": "Jürgen"
                },
                "text": " Balg, Jürgen, Porta Westfalica, *28.10.1957"
            },
            {
                "class": "DismissedManagingDirector",
                "payload": {
                    "city": "Wadersloh",
                    "dismissed": true,
                    "lastname": "Dipl.-Betriebswirt Gerwert",
                    "name": "Egon"
                },
                "text": " Dipl.-Betriebswirt Gerwert, Egon, Wadersloh."
            },
            {
                "class": "ProcurationCancelled",
                "payload": {
                    "city": "Herford",
                    "dismissed": true,
                    "dob": "1950-08-05",
                    "lastname": "Gronlied",
                    "name": "Wolfgang"
                },
                "text": " Gronlied, Wolfgang, Herford, *05.08.1950"
            },
            {
                "class": "ProcurationCancelled",
                "payload": {
                    "city": "Gütersloh",
                    "dismissed": true,
                    "dob": "1968-06-08",
                    "lastname": "Hachmann",
                    "name": "Jean-Michael"
                },
                "text": " Hachmann, Jean-Michael, Gütersloh, *08.06.1968"
            },
            {
                "class": "ProcurationCancelled",
                "payload": {
                    "city": "Rheda-Wiedenbrück",
                    "dismissed": true,
                    "dob": "1969-08-18",
                    "lastname": "Helmer",
                    "name": "Lars"
                },
                "text": " Helmer, Lars, Rheda-Wiedenbrück, *18.08.1969."
            }
        ]
    }
}