{
    "orig": {
        "aktenzeichen": "HRB 89103",
        "amtsgericht": "Hamburg",
        "event_date": "2017-01-02",
        "event_type": "Veränderungen",
        "federal_state": "hh",
        "full_text": "Amtsgericht Hamburg Aktenzeichen: HRB 89103 \nBekannt gemacht am: 02.01.2017 14:31 Uhr\n\n\n\n\nIn () gesetzte Angaben der Anschrift und des Geschäftszweiges erfolgen ohne Gewähr.\nVeränderungen\n02.01.2017\n\nHRB 89103: Verwaltung \"MS Sophie\" Schifffahrtsgesellschaft mbH, Hamburg, Mattentwiete 1, 20457 Hamburg. Vertretungsbefugnis geändert, nun Geschäftsführer: Schittek, Ulrich, Hamburg, *03.04.1962, vertretungsberechtigt gemäß allgemeiner Vertretungsregelung; mit der Befugnis, im Namen der Gesellschaft mit sich im eigenen Namen oder als Vertreter eines Dritten Rechtsgeschäfte abzuschließen. Ausgeschieden Geschäftsführer: Hutt, Jürgen, Hamburg, *17.09.1976; Krämer, Christian Peter, Hamburg, *03.08.1984.",
        "gesellschafter": null,
        "inhaber": null,
        "name": "HRB 89103: Verwaltung \"MS Sophie\" Schifffahrtsgesellschaft mbH",
        "notice_id": "318242",
        "posted_on": "2017-01-02",
        "rechtsform": null,
        "sitz": null,
        "url": "https://www.handelsregisterbekanntmachungen.de/en/skripte/hrb.php?rb_id=318242&land_abk=hh"
    },
    "parsed": {
        "flags": [
            {
                "flag": "with the power to enter into legal transactions on behalf of the Company with itself or as a representative of a third party",
                "text": "mit\\ der\\ Befugnis\\,\\ im\\ Namen\\ der\\ Gesellschaft\\ mit\\ sich\\ im\\ eigenen\\ Namen\\ oder\\ als\\ Vertreter\\ eines\\ Dritten\\ Rechtsgesch\\äfte\\ abzuschlie\\ßen\\."
            }
        ],
        "officers": [
            {
                "class": "ManagingDirector",
                "payload": {
                    "city": "Hamburg",
                    "dob": "1962-04-03",
                    "flag": "vertretungsberechtigt gemäß allgemeiner Vertretungsregelung",
                    "lastname": "Schittek",
                    "name": "Ulrich"
                },
                "text": " Schittek, Ulrich, Hamburg, *03.04.1962, vertretungsberechtigt gemäß allgemeiner Vertretungsregelung"
            },
            {
                "class": "ManagingDirector",
                "payload": {
                    "lastname": "mit der Befugnis",
                    "name": "im Namen der Gesellschaft mit sich im eigenen Namen oder als Vertreter eines Dritten Rechtsgeschäfte abzuschließen"
                },
                "text": " mit der Befugnis, im Namen der Gesellschaft mit sich im eigenen Namen oder als Vertreter eines Dritten Rechtsgeschäfte abzuschließen."
            },
            {
                "class": "RetiredManagingDirector",
                "payload": {
                    "city": "Hamburg",
                    "dismissed": true,
                    "dob": "1976-09-17",
                    "lastname": "Hutt",
                    "name": "Jürgen"
                },
                "text": " Hutt, Jürgen, Hamburg, *17.09.1976"
            },
            {
                "class": "RetiredManagingDirector",
                "payload": {
                    "city": "Hamburg",
                    "dismissed": true,
                    "dob": "1984-08-03",
                    "lastname": "Krämer",
                    "name": "Christian Peter"
                },
                "text": " Krämer, Christian Peter, Hamburg, *03.08.1984."
            }
        ]
    }
}