{
    "orig": {
        "aktenzeichen": "HRB 21787",
        "amtsgericht": "Leipzig",
        "event_date": "2007-01-22",
        "event_type": "Veränderungen",
        "federal_state": "sn",
        "full_text": "Amtsgericht Leipzig Aktenzeichen: HRB 21787 \nBekannt gemacht am: 25.01.2007 12:16 Uhr\n\n\n\n\nDie in () gesetzten Angaben der Geschäftsanschrift und des Unternehmensgegenstandes erfolgen ohne Gewähr.\nVeränderungen\n22.01.2007\n\nEUTRANS - Internationale Transporte, Logistik und Nutzfahrzeugvermietung GmbH, Leipzig (Lampestr. 8, 04107 Leipzig). Ausgeschieden: Geschäftsführer: Förster, Diana, Leipzig, *13.10.1979. Bestellt: Geschäftsführer: Hartung, Jörg, Riedstadt, *08.01.1963, mit der Befugnis im Namen der Gesellschaft mit sich im eigenen Namen oder als Vertreter eines Dritten Rechtsgeschäfte abzuschließen.",
        "gesellschafter": null,
        "inhaber": null,
        "name": "EUTRANS - Internationale Transporte",
        "notice_id": "32279",
        "posted_on": "2007-01-25",
        "rechtsform": null,
        "sitz": null,
        "url": "https://www.handelsregisterbekanntmachungen.de/en/skripte/hrb.php?rb_id=32279&land_abk=sn"
    },
    "parsed": {
        "officers": [
            {
                "class": "RetiredManagingDirector",
                "payload": {
                    "city": "Leipzig",
                    "dismissed": true,
                    "dob": "1979-10-13",
                    "lastname": "Förster",
                    "name": "Diana"
                },
                "text": " Förster, Diana, Leipzig, *13.10.1979."
            },
            {
                "class": "AppointedManagingDirector",
                "payload": {
                    "city": "Riedstadt",
                    "dob": "1963-08-01",
                    "flag": "mit der Befugnis im Namen der Gesellschaft mit sich im eigenen Namen oder als Vertreter eines Dritten Rechtsgeschäfte abzuschließen",
                    "lastname": "Hartung",
                    "name": "Jörg"
                },
                "text": " Hartung, Jörg, Riedstadt, *08.01.1963, mit der Befugnis im Namen der Gesellschaft mit sich im eigenen Namen oder als Vertreter eines Dritten Rechtsgeschäfte abzuschließen."
            }
        ]
    }
}