{
    "orig": {
        "aktenzeichen": "HRB 84041",
        "amtsgericht": "Frankfurt am Main",
        "event_date": "2013-03-19",
        "event_type": "Veränderungen",
        "federal_state": "he",
        "full_text": "Amtsgericht Frankfurt am Main Aktenzeichen: HRB 84041   \nBekannt gemacht am: 22.03.2013 12:00 Uhr\n\n\n\n\nVeröffentlichungen des Amtsgerichts Frankfurt am Main\r\r\rIn () gesetzte Angaben der Anschrift und des Geschäftszweiges erfolgen ohne Gewähr.\nVeränderungen\n19.03.2013\n\nLevi Strauss Germany GmbH, Frankfurt am Main, Niddastraße 56, 60329 Frankfurt am Main. Bestellt als Geschäftsführer: Larcombe, Timothy John, Harpenden/Hertfordshire/Großbritannien, *19.02.1966. Nicht mehr Geschäftsführer: Strehler, Michael, Brüssel, Belgien, *22.08.1961; Widarzik, Torsten, Frankfurt am Main, *06.02.1968. Gesamtprokura gemeinsam mit einem Geschäftsführer oder einem anderen Prokuristen: Anthes, Michael, Mainz, *27.01.1973; Labrum, Mark, Thrapston/Northamptonshire/Großbritannien, *22.10.1973.",
        "gesellschafter": null,
        "inhaber": null,
        "name": "Levi Strauss Germany GmbH",
        "notice_id": "324038",
        "posted_on": "2013-03-22",
        "rechtsform": null,
        "sitz": null,
        "url": "https://www.handelsregisterbekanntmachungen.de/en/skripte/hrb.php?rb_id=324038&land_abk=he"
    },
    "parsed": {
        "officers": [
            {
                "class": "AppointedManagingDirector",
                "payload": {
                    "city": "Harpenden/Hertfordshire/Großbritannien",
                    "dob": "1966-02-19",
                    "lastname": "Larcombe",
                    "name": "Timothy John"
                },
                "text": " Larcombe, Timothy John, Harpenden/Hertfordshire/Großbritannien, *19.02.1966."
            },
            {
                "class": "DismissedManagingDirector",
                "payload": {
                    "city": "Belgien",
                    "dismissed": true,
                    "dob": "1961-08-22",
                    "lastname": "Strehler",
                    "name": "Michael",
                    "position": "Brüssel"
                },
                "text": " Strehler, Michael, Brüssel, Belgien, *22.08.1961"
            },
            {
                "class": "CommonProcuration",
                "payload": {
                    "city": "Mainz",
                    "dob": "1973-01-27",
                    "lastname": "Anthes",
                    "name": "Michael"
                },
                "text": " Anthes, Michael, Mainz, *27.01.1973"
            }
        ]
    }
}