{
    "orig": {
        "aktenzeichen": "HRB 143503",
        "amtsgericht": "Hamburg",
        "event_date": "2017-06-07",
        "event_type": "Veränderungen",
        "federal_state": "hh",
        "full_text": "Amtsgericht Hamburg Aktenzeichen: HRB 143503 \nBekannt gemacht am: 07.06.2017 09:18 Uhr\n\n\n\n\nIn () gesetzte Angaben der Anschrift und des Geschäftszweiges erfolgen ohne Gewähr.\nVeränderungen\n07.06.2017\n\nHRB 143503: GIANT Weilerswist g21 GmbH, Hamburg, Caffamacherreihe 8, 20355 Hamburg. Geändert, nun Geschäftsführer: Garbe, Christopher, Hamburg, *31.08.1978, vertretungsberechtigt gemäß allgemeiner Vertretungsregelung; mit der Befugnis, im Namen der Gesellschaft mit sich als Vertreter eines Dritten Rechtsgeschäfte abzuschließen. Bestellt Geschäftsführer: Daun, Jan Philipp, Hamburg, *05.01.1976; Hempel, Jan-Dietrich, Hamburg, *28.05.1964, jeweils vertretungsberechtigt gemäß allgemeiner Vertretungsregelung; mit der Befugnis, im Namen der Gesellschaft mit sich als Vertreter eines Dritten Rechtsgeschäfte abzuschließen.",
        "gesellschafter": null,
        "inhaber": null,
        "name": "HRB 143503: GIANT Weilerswist g21 GmbH",
        "notice_id": "332707",
        "posted_on": "2017-06-07",
        "rechtsform": null,
        "sitz": null,
        "url": "https://www.handelsregisterbekanntmachungen.de/en/skripte/hrb.php?rb_id=332707&land_abk=hh"
    },
    "parsed": {
        "officers": [
            {
                "class": "ManagingDirector",
                "payload": {
                    "city": "Hamburg",
                    "dob": "1978-08-31",
                    "flag": "vertretungsberechtigt gemäß allgemeiner Vertretungsregelung",
                    "lastname": "Garbe",
                    "name": "Christopher"
                },
                "text": " Garbe, Christopher, Hamburg, *31.08.1978, vertretungsberechtigt gemäß allgemeiner Vertretungsregelung"
            },
            {
                "class": "ManagingDirector",
                "payload": {
                    "lastname": "mit der Befugnis",
                    "name": "im Namen der Gesellschaft mit sich als Vertreter eines Dritten Rechtsgeschäfte abzuschließen"
                },
                "text": " mit der Befugnis, im Namen der Gesellschaft mit sich als Vertreter eines Dritten Rechtsgeschäfte abzuschließen."
            },
            {
                "class": "AppointedManagingDirector",
                "payload": {
                    "city": "Hamburg",
                    "dob": "1976-01-05",
                    "lastname": "Daun",
                    "name": "Jan Philipp"
                },
                "text": " Daun, Jan Philipp, Hamburg, *05.01.1976"
            },
            {
                "class": "AppointedManagingDirector",
                "payload": {
                    "city": "Hamburg",
                    "dob": "1964-05-28",
                    "flag": "jeweils vertretungsberechtigt gemäß allgemeiner Vertretungsregelung",
                    "lastname": "Hempel",
                    "name": "Jan-Dietrich"
                },
                "text": " Hempel, Jan-Dietrich, Hamburg, *28.05.1964, jeweils vertretungsberechtigt gemäß allgemeiner Vertretungsregelung"
            },
            {
                "class": "AppointedManagingDirector",
                "payload": {
                    "lastname": "mit der Befugnis",
                    "name": "im Namen der Gesellschaft mit sich als Vertreter eines Dritten Rechtsgeschäfte abzuschließen"
                },
                "text": " mit der Befugnis, im Namen der Gesellschaft mit sich als Vertreter eines Dritten Rechtsgeschäfte abzuschließen."
            }
        ]
    }
}