{
    "orig": {
        "aktenzeichen": "HRB 146747",
        "amtsgericht": "Hamburg",
        "event_date": "2017-06-16",
        "event_type": "Veränderungen",
        "federal_state": "hh",
        "full_text": "Amtsgericht Hamburg Aktenzeichen: HRB 146747 \nBekannt gemacht am: 16.06.2017 10:41 Uhr\n\n\n\n\nIn () gesetzte Angaben der Anschrift und des Geschäftszweiges erfolgen ohne Gewähr.\nVeränderungen\n16.06.2017\n\nHRB 146747: ANIMA Management GmbH, Hamburg, Frauenthal 15, 20149 Hamburg. Ausgeschieden Geschäftsführer: Eversmann, Moritz, Hamburg, *20.07.1962. Bestellt Geschäftsführer: Möller, Matthias Ernst Heinrich, Hamburg, *30.01.1978, vertretungsberechtigt gemäß allgemeiner Vertretungsregelung. Gesamtprokura gemeinsam mit einem Geschäftsführer oder einem anderen Prokuristen: Gieß, Tim Sebastian, Hamburg, *19.03.1987.",
        "gesellschafter": null,
        "inhaber": null,
        "name": "HRB 146747: ANIMA Management GmbH",
        "notice_id": "333700",
        "posted_on": "2017-06-16",
        "rechtsform": null,
        "sitz": null,
        "url": "https://www.handelsregisterbekanntmachungen.de/en/skripte/hrb.php?rb_id=333700&land_abk=hh"
    },
    "parsed": {
        "officers": [
            {
                "class": "RetiredManagingDirector",
                "payload": {
                    "city": "Hamburg",
                    "dismissed": true,
                    "dob": "1962-07-20",
                    "lastname": "Eversmann",
                    "name": "Moritz"
                },
                "text": " Eversmann, Moritz, Hamburg, *20.07.1962."
            },
            {
                "class": "AppointedManagingDirector",
                "payload": {
                    "city": "Hamburg",
                    "dob": "1978-01-30",
                    "flag": "vertretungsberechtigt gemäß allgemeiner Vertretungsregelung",
                    "lastname": "Möller",
                    "name": "Matthias Ernst Heinrich"
                },
                "text": " Möller, Matthias Ernst Heinrich, Hamburg, *30.01.1978, vertretungsberechtigt gemäß allgemeiner Vertretungsregelung."
            },
            {
                "class": "CommonProcuration",
                "payload": {
                    "city": "Hamburg",
                    "dob": "1987-03-19",
                    "lastname": "Gieß",
                    "name": "Tim Sebastian"
                },
                "text": " Gieß, Tim Sebastian, Hamburg, *19.03.1987."
            }
        ]
    }
}