{
    "orig": {
        "aktenzeichen": "HRB 138916",
        "amtsgericht": "Hamburg",
        "event_date": "2017-06-27",
        "event_type": "Veränderungen",
        "federal_state": "hh",
        "full_text": "Amtsgericht Hamburg Aktenzeichen: HRB 138916 \nBekannt gemacht am: 27.06.2017 15:48 Uhr\n\n\n\n\nIn () gesetzte Angaben der Anschrift und des Geschäftszweiges erfolgen ohne Gewähr.\nVeränderungen\n27.06.2017\n\nHRB 138916: WWV Management UG (haftungsbeschränkt), Hamburg, Am Stühm-Süd 98, 22175 Hamburg. Ist nur ein Liquidator bestellt, so vertritt er die Gesellschaft allein. Sind mehrere Liquidatoren bestellt, so wird die Gesellschaft durch die Liquidatoren gemeinsam vertreten. Bestellt Liquidator: Wolf, Thorsten, Lütjensee, *31.12.1964, vertretungsberechtigt gemäß allgemeiner Vertretungsregelung. Ausgeschieden Geschäftsführer: Wolf, Thorsten, Lütjensee, *31.12.1964. Die Gesellschaft ist aufgelöst.",
        "gesellschafter": null,
        "inhaber": null,
        "name": "HRB 138916: WWV Management UG (haftungsbeschränkt)",
        "notice_id": "334600",
        "posted_on": "2017-06-27",
        "rechtsform": null,
        "sitz": null,
        "url": "https://www.handelsregisterbekanntmachungen.de/en/skripte/hrb.php?rb_id=334600&land_abk=hh"
    },
    "parsed": {
        "flags": [
            {
                "flag": "CompanyClosed",
                "text": "Die\\ Gesellschaft\\ ist\\ aufgel\\öst\\."
            }
        ],
        "officers": [
            {
                "class": "Liquidator",
                "payload": {
                    "city": "Lütjensee",
                    "dob": "1964-12-31",
                    "flag": "vertretungsberechtigt gemäß allgemeiner Vertretungsregelung",
                    "lastname": "Wolf",
                    "name": "Thorsten"
                },
                "text": " Wolf, Thorsten, Lütjensee, *31.12.1964, vertretungsberechtigt gemäß allgemeiner Vertretungsregelung."
            },
            {
                "class": "RetiredManagingDirector",
                "payload": {
                    "city": "Lütjensee",
                    "dismissed": true,
                    "dob": "1964-12-31",
                    "lastname": "Wolf",
                    "name": "Thorsten"
                },
                "text": " Wolf, Thorsten, Lütjensee, *31.12.1964."
            }
        ]
    }
}