{
    "orig": {
        "aktenzeichen": "HRB 42333",
        "amtsgericht": "Düsseldorf",
        "event_date": "2008-06-25",
        "event_type": "Veränderungen",
        "federal_state": "nw",
        "full_text": "Amtsgericht Düsseldorf Aktenzeichen: HRB 42333 \nBekannt gemacht am: 01.07.2008 12:00 Uhr\n\n\n\n\nDie in () gesetzten Angaben der Geschäftsanschrift und des Geschäftszweiges erfolgen ohne Gewähr.\nVeränderungen\n25.06.2008\n\nROSOLA Grundstücks-Vermietungsgesellschaft mbH, Düsseldorf (Mercedesstr. 6, 40470 Düsseldorf). Nicht mehr Geschäftsführer: Wolters, Bernd, Düsseldorf, *15.01.1964. Bestellt als Geschäftsführer: Schmitz, Christoph, Düsseldorf, *17.04.1959, mit der Befugnis im Namen der Gesellschaft mit sich im eigenen Namen oder als Vertreter eines Dritten Rechtsgeschäfte abzuschließen. Prokura erloschen: Brandt, Thorsten, Dormagen, *11.09.1962; Woeste, Lothar, Düsseldorf, *20.05.1943. Gesamtprokura gemeinsam mit einem Geschäftsführer oder einem anderen Prokuristen mit der Befugnis im Namen der Gesellschaft mit sich im eigenen Namen oder als Vertreter eines Dritten Rechtsgeschäfte abzuschließen mit der Ermächtigung zur Veräußerung und Belastung von Grundstücken: Wolters, Bernd, Düsseldorf, *15.01.1964.",
        "gesellschafter": null,
        "inhaber": null,
        "name": "ROSOLA Grundstücks-Vermietungsgesellschaft mbH",
        "notice_id": "335832",
        "posted_on": "2008-07-01",
        "rechtsform": null,
        "sitz": null,
        "url": "https://www.handelsregisterbekanntmachungen.de/en/skripte/hrb.php?rb_id=335832&land_abk=nw"
    },
    "parsed": {
        "officers": [
            {
                "class": "DismissedManagingDirector",
                "payload": {
                    "city": "Düsseldorf",
                    "dismissed": true,
                    "dob": "1964-01-15",
                    "lastname": "Wolters",
                    "name": "Bernd"
                },
                "text": " Wolters, Bernd, Düsseldorf, *15.01.1964."
            },
            {
                "class": "AppointedManagingDirector",
                "payload": {
                    "city": "Düsseldorf",
                    "dob": "1959-04-17",
                    "flag": "mit der Befugnis im Namen der Gesellschaft mit sich im eigenen Namen oder als Vertreter eines Dritten Rechtsgeschäfte abzuschließen",
                    "lastname": "Schmitz",
                    "name": "Christoph"
                },
                "text": " Schmitz, Christoph, Düsseldorf, *17.04.1959, mit der Befugnis im Namen der Gesellschaft mit sich im eigenen Namen oder als Vertreter eines Dritten Rechtsgeschäfte abzuschließen."
            },
            {
                "class": "ProcurationCancelled",
                "payload": {
                    "city": "Dormagen",
                    "dismissed": true,
                    "dob": "1962-11-09",
                    "lastname": "Brandt",
                    "name": "Thorsten"
                },
                "text": " Brandt, Thorsten, Dormagen, *11.09.1962"
            }
        ]
    }
}