{
    "orig": {
        "aktenzeichen": "HRB 147442",
        "amtsgericht": "Hamburg",
        "event_date": "2017-07-28",
        "event_type": "Neueintragungen",
        "federal_state": "hh",
        "full_text": "Amtsgericht Hamburg Aktenzeichen: HRB 147442 \nBekannt gemacht am: 28.07.2017 10:50 Uhr\n\n\n\n\nIn () gesetzte Angaben der Anschrift und des Geschäftszweiges erfolgen ohne Gewähr.\nNeueintragungen\n28.07.2017\n\nHRB 147442: PIXELPARK GmbH, Hamburg, Gerhofstraße 1 - 3, 20354 Hamburg. Gesellschaft mit beschränkter Haftung. Gesellschaftsvertrag vom 06.12.2016 mit Änderung vom 14.02.2017. Die Gesellschafterversammlung vom 19.06.2017 hat die Änderung des Gesellschaftsvertrages in § 1 Abs. (2) (Sitz) und mit ihr die Sitzverlegung von Berlin (bisher: Amtsgericht Charlottenburg HRB 184657 B) nach Hamburg beschlossen. Geschäftsanschrift: Gerhofstraße 1 - 3, 20354 Hamburg. Gegenstand: Die Strategieberatung, die Erbringung von Agentur Services und die Entwicklung von System- und Technologielösungen im Bereich Neue Medien. Hierzu zählen insbesondere Produkte und Dienstleistungen auf den Gebieten Electronic Commerce, Electronic Finance, Intranet, Extranet sowie die Positionierung von Marken in den Neuen Medien (E-Branding) und die Erbringung von Dienstleistung sowie die Bereitstellung von Diensten auf diesen Gebieten. Die Erbringung von nach dem KWG erlaubnispflichtigen Bankgeschäften und Finanzdienstleistungen gehört nicht zum Unternehmensgegenstand. Stammkapital: 59.047.758,00 EUR. Allgemeine Vertretungsregelung: Ist nur ein Geschäftsführer bestellt, so vertritt er die Gesellschaft allein. Sind mehrere Geschäftsführer bestellt, so wird die Gesellschaft durch zwei Geschäftsführer oder durch einen Geschäftsführer gemeinsam mit einem Prokuristen vertreten. Alleinvertretungsbefugnis kann erteilt werden. Geschäftsführer können ermächtigt werden, im Namen der Gesellschaft mit sich im eigenen Namen oder als Vertreter eines Dritten Rechtsgeschäfte vorzunehmen. Geschäftsführer: Billingsley, Justin, London / Vereinigtes Königreich, *25.11.1972; Kedrowitsch, Dirk, Hamburg, *05.03.1970; Wagner, Horst, Nottensdorf, *14.01.1954, jeweils vertretungsberechtigt gemäß allgemeiner Vertretungsregelung. Gesamtprokura gemeinsam mit einem Geschäftsführer oder einem anderen Prokuristen: Berndt, Matthias, Labenz, *10.06.1968; Chemin, Nicolas, Hamburg, *10.11.1970; Jensen, Jens-Christian, Berlin, *27.08.1979; Jungbluth, Christian, Pulheim, *13.09.1974; Dr. Niemann, Ralf, Bergisch Gladbach, *10.01.1967; Pütz, Andreas, Köln, *16.10.1958; Schopp, Stefan Martin, Köln, *09.01.1975; Teege, Götz, Hamburg, *07.07.1963; Waschkies, OIav Alexander, Köln, *23.06.1970. Die Gesellschaft ist entstanden durch formwechselnde Umwandlung der PIXELPARK AG mit Sitz in Berlin (Amtsgericht Charlottenburg HRB 72163 B) auf Grund des Umwandlungsbeschlusses vom 06.12.2016; 14.02.2017. Folgende Gesellschaften sind bisher auf die Gesellschaft verschmolzen: Pixelpark Köln GmbH mit Sitz in Köln (Amtsgericht Köln HRB 28473); Elephant Seven AG mit Sitz in München (Amtsgericht München HRB 127728); Pixelpark Beteiligungs GmbH mit Sitz in Berlin (Amtsgericht Charlottenburg HRB 109710). Es besteht ein Beherrschungsvertrag mit der MMS Germany Holdings GmbH mit Sitz in Düsseldorf (Amtsgericht Düsseldorf HRB 50291), dem die Gesellschafterversammlung durch Beschluss vom 09.11.2012 zugestimmt hat.",
        "gesellschafter": null,
        "inhaber": null,
        "name": "HRB 147442: PIXELPARK GmbH",
        "notice_id": "337685",
        "posted_on": "2017-07-28",
        "rechtsform": null,
        "sitz": null,
        "url": "https://www.handelsregisterbekanntmachungen.de/en/skripte/hrb.php?rb_id=337685&land_abk=hh"
    },
    "parsed": {
        "addresses": [
            {
                "kls": "Address",
                "text": "Gerhofstraße 1 - 3, 20354 Hamburg"
            }
        ],
        "flags": [
            {
                "flag": "Company with limited liability.",
                "text": "Gesellschaft\\ mit\\ beschr\\änkter\\ Haftung\\."
            },
            {
                "flag": "If only one managing director is appointed, he represents the company alone.",
                "text": "Ist\\ nur\\ ein\\ Gesch\\äftsf\\ührer\\ bestellt\\,\\ so\\ vertritt\\ er\\ die\\ Gesellschaft\\ allein\\."
            },
            {
                "flag": "If several managing directors are appointed, then the company is represented by two managing directors or by a managing director together with an authorized officer.",
                "text": "Sind\\ mehrere\\ Gesch\\äftsf\\ührer\\ bestellt\\,\\ so\\ wird\\ die\\ Gesellschaft\\ durch\\ zwei\\ Gesch\\äftsf\\ührer\\ oder\\ durch\\ einen\\ Gesch\\äftsf\\ührer\\ gemeinsam\\ mit\\ einem\\ Prokuristen\\ vertreten\\."
            },
            {
                "flag": "Exclusive power of representation can be granted.",
                "text": "Alleinvertretungsbefugnis\\ kann\\ erteilt\\ werden\\."
            }
        ],
        "notices": [
            {
                "court": "Charlottenburg",
                "from": "Berlin",
                "hrb": "HRB 184657 B",
                "registration": "predecessor",
                "registration_conflict": true,
                "text": " von Berlin (bisher: Amtsgericht Charlottenburg HRB 184657 B) nach Hamburg beschlossen.",
                "to": "Hamburg",
                "used_regex": "court_regex, from_hrb_to_regex"
            }
        ],
        "officers": [
            {
                "class": "ManagingDirector",
                "payload": {
                    "city": "London / Vereinigtes Königreich",
                    "dob": "1972-11-25",
                    "lastname": "Billingsley",
                    "name": "Justin"
                },
                "text": " Billingsley, Justin, London / Vereinigtes Königreich, *25.11.1972"
            },
            {
                "class": "ManagingDirector",
                "payload": {
                    "city": "Hamburg",
                    "dob": "1970-03-05",
                    "lastname": "Kedrowitsch",
                    "name": "Dirk"
                },
                "text": " Kedrowitsch, Dirk, Hamburg, *05.03.1970"
            },
            {
                "class": "ManagingDirector",
                "payload": {
                    "city": "Nottensdorf",
                    "dob": "1954-01-14",
                    "flag": "jeweils vertretungsberechtigt gemäß allgemeiner Vertretungsregelung",
                    "lastname": "Wagner",
                    "name": "Horst"
                },
                "text": " Wagner, Horst, Nottensdorf, *14.01.1954, jeweils vertretungsberechtigt gemäß allgemeiner Vertretungsregelung."
            },
            {
                "class": "CommonProcuration",
                "payload": {
                    "city": "Labenz",
                    "dob": "1968-06-10",
                    "lastname": "Berndt",
                    "name": "Matthias"
                },
                "text": " Berndt, Matthias, Labenz, *10.06.1968"
            },
            {
                "class": "CommonProcuration",
                "payload": {
                    "city": "Hamburg",
                    "dob": "1970-11-10",
                    "lastname": "Chemin",
                    "name": "Nicolas"
                },
                "text": " Chemin, Nicolas, Hamburg, *10.11.1970"
            },
            {
                "class": "CommonProcuration",
                "payload": {
                    "city": "Berlin",
                    "dob": "1979-08-27",
                    "lastname": "Jensen",
                    "name": "Jens-Christian"
                },
                "text": " Jensen, Jens-Christian, Berlin, *27.08.1979"
            },
            {
                "class": "CommonProcuration",
                "payload": {
                    "city": "Pulheim",
                    "dob": "1974-09-13",
                    "lastname": "Jungbluth",
                    "name": "Christian"
                },
                "text": " Jungbluth, Christian, Pulheim, *13.09.1974"
            },
            {
                "class": "CommonProcuration",
                "payload": {
                    "city": "Bergisch Gladbach",
                    "dob": "1967-01-10",
                    "lastname": "Niemann",
                    "name": "Ralf",
                    "prof_title": "doctor"
                },
                "text": " Doctor Niemann, Ralf, Bergisch Gladbach, *10.01.1967"
            },
            {
                "class": "CommonProcuration",
                "payload": {
                    "city": "Köln",
                    "dob": "1958-10-16",
                    "lastname": "Pütz",
                    "name": "Andreas"
                },
                "text": " Pütz, Andreas, Köln, *16.10.1958"
            },
            {
                "class": "CommonProcuration",
                "payload": {
                    "city": "Köln",
                    "dob": "1975-01-09",
                    "lastname": "Schopp",
                    "name": "Stefan Martin"
                },
                "text": " Schopp, Stefan Martin, Köln, *09.01.1975"
            },
            {
                "class": "CommonProcuration",
                "payload": {
                    "city": "Hamburg",
                    "dob": "1963-07-07",
                    "lastname": "Teege",
                    "name": "Götz"
                },
                "text": " Teege, Götz, Hamburg, *07.07.1963"
            },
            {
                "class": "CommonProcuration",
                "payload": {
                    "city": "Köln",
                    "dob": "1970-06-23",
                    "lastname": "Waschkies",
                    "name": "OIav Alexander"
                },
                "text": " Waschkies, OIav Alexander, Köln, *23.06.1970."
            }
        ]
    }
}