{
    "orig": {
        "aktenzeichen": "HRB 4913",
        "amtsgericht": "Neuss",
        "event_date": "2008-07-04",
        "event_type": "Veränderungen",
        "federal_state": "nw",
        "full_text": "Amtsgericht Neuss Aktenzeichen: HRB 4913 \nBekannt gemacht am: 10.07.2008 22:00 Uhr\n\n\n\n\nDie in () gesetzten Angaben der Geschäftsanschrift und des Geschäftszweiges erfolgen ohne Gewähr.\nVeränderungen\n04.07.2008\n\nBaecker Projekt Design GmbH, Meerbusch (Sperberweg 3, 40670 Meerbusch). Ist nur ein Liquidator bestellt, so vertritt er die Gesellschaft allein. Sind mehrere Liquidatoren bestellt, so wird die Gesellschaft durch zwei Liquidatoren oder durch einen Liquidator gemeinsam mit einem Prokuristen vertreten. Nunmehr bestellt als Liquidator: Baecker, Claudia, geb. Grave, Meerbusch, *01.04.1945, einzelvertretungsberechtigt mit der Befugnis im Namen der Gesellschaft mit sich im eigenen Namen oder als Vertreter eines Dritten Rechtsgeschäfte abzuschließen. Nicht mehr Geschäftsführer: Lutz-Grave, Claudia, Meerbusch, *01.04.1945. Die Gesellschaft ist durch Gesellschafterbeschluss vom 20. Juni 2008 aufgelöst.",
        "gesellschafter": null,
        "inhaber": null,
        "name": "Baecker Projekt Design GmbH",
        "notice_id": "338697",
        "posted_on": "2008-07-10",
        "rechtsform": null,
        "sitz": null,
        "url": "https://www.handelsregisterbekanntmachungen.de/en/skripte/hrb.php?rb_id=338697&land_abk=nw"
    },
    "parsed": {
        "officers": [
            {
                "class": "Liquidator",
                "payload": {
                    "city": "Meerbusch",
                    "dob": "1945-01-04",
                    "flag": "einzelvertretungsberechtigt mit der Befugnis im Namen der Gesellschaft mit sich im eigenen Namen oder als Vertreter eines Dritten Rechtsgeschäfte abzuschließen",
                    "lastname": "Baecker",
                    "name": "Claudia geborene Grave"
                },
                "text": " Baecker, Claudia geborene Grave, Meerbusch, *01.04.1945, einzelvertretungsberechtigt mit der Befugnis im Namen der Gesellschaft mit sich im eigenen Namen oder als Vertreter eines Dritten Rechtsgeschäfte abzuschließen."
            },
            {
                "class": "DismissedManagingDirector",
                "payload": {
                    "city": "Meerbusch",
                    "dismissed": true,
                    "dob": "1945-01-04",
                    "lastname": "Lutz-Grave",
                    "name": "Claudia"
                },
                "text": " Lutz-Grave, Claudia, Meerbusch, *01.04.1945."
            }
        ]
    }
}