{
    "orig": {
        "aktenzeichen": "HRB 26613",
        "amtsgericht": "Düsseldorf",
        "event_date": "2008-07-22",
        "event_type": "Veränderungen",
        "federal_state": "nw",
        "full_text": "Amtsgericht Düsseldorf Aktenzeichen: HRB 26613 \nBekannt gemacht am: 29.07.2008 12:00 Uhr\n\n\n\n\nDie in () gesetzten Angaben der Geschäftsanschrift und des Geschäftszweiges erfolgen ohne Gewähr.\nVeränderungen\n22.07.2008\n\nMITIS Grundstücks-Vermietungsgesellschaft mbH, Düsseldorf (Uerdinger Str. 90, 40474 Düsseldorf). Nicht mehr Geschäftsführer: Graf, Ursula Anna, Mönchengladbach, *30.07.1965; Dr. Waldeyer, Hans, Düsseldorf, *01.08.1953. Bestellt als Geschäftsführer: Elbert, Bernd, Köln, *30.10.1964, mit der Befugnis im Namen der Gesellschaft mit sich im eigenen Namen oder als Vertreter eines Dritten Rechtsgeschäfte abzuschließen.",
        "gesellschafter": null,
        "inhaber": null,
        "name": "MITIS Grundstücks-Vermietungsgesellschaft mbH",
        "notice_id": "344031",
        "posted_on": "2008-07-29",
        "rechtsform": null,
        "sitz": null,
        "url": "https://www.handelsregisterbekanntmachungen.de/en/skripte/hrb.php?rb_id=344031&land_abk=nw"
    },
    "parsed": {
        "officers": [
            {
                "class": "DismissedManagingDirector",
                "payload": {
                    "city": "Mönchengladbach",
                    "dismissed": true,
                    "dob": "1965-07-30",
                    "lastname": "Graf",
                    "name": "Ursula Anna"
                },
                "text": " Graf, Ursula Anna, Mönchengladbach, *30.07.1965"
            },
            {
                "class": "AppointedManagingDirector",
                "payload": {
                    "city": "Köln",
                    "dob": "1964-10-30",
                    "flag": "mit der Befugnis im Namen der Gesellschaft mit sich im eigenen Namen oder als Vertreter eines Dritten Rechtsgeschäfte abzuschließen",
                    "lastname": "Elbert",
                    "name": "Bernd"
                },
                "text": " Elbert, Bernd, Köln, *30.10.1964, mit der Befugnis im Namen der Gesellschaft mit sich im eigenen Namen oder als Vertreter eines Dritten Rechtsgeschäfte abzuschließen."
            }
        ]
    }
}