{
    "orig": {
        "aktenzeichen": "HRB 52549",
        "amtsgericht": "Köln",
        "event_date": "2008-07-23",
        "event_type": "Veränderungen",
        "federal_state": "nw",
        "full_text": "Amtsgericht Köln Aktenzeichen: HRB 52549 \nBekannt gemacht am: 29.07.2008 22:00 Uhr\n\n\n\n\nDie in () gesetzten Angaben der Geschäftsanschrift und des Geschäftszweiges erfolgen ohne Gewähr.\nVeränderungen\n23.07.2008\n\nZucchini Deutschland GmbH, Köln (Universitätsstr. 71, 50931 Köln). Nicht mehr Geschäftsführer: Bonometti, Piergiorgio. Bestellt als Geschäftsführer: Sala, Fabio Giovanni Sebastiano, Wien/Österreich, *20.03.1960, einzelvertretungsberechtigt mit der Befugnis im Namen der Gesellschaft mit sich im eigenen Namen oder als Vertreter eines Dritten Rechtsgeschäfte abzuschließen. Einzelprokura: Remmert, Heinz-Dieter, Ense, *16.07.1955.",
        "gesellschafter": null,
        "inhaber": null,
        "name": "Zucchini Deutschland GmbH",
        "notice_id": "344456",
        "posted_on": "2008-07-29",
        "rechtsform": null,
        "sitz": null,
        "url": "https://www.handelsregisterbekanntmachungen.de/en/skripte/hrb.php?rb_id=344456&land_abk=nw"
    },
    "parsed": {
        "officers": [
            {
                "class": "DismissedManagingDirector",
                "payload": {
                    "dismissed": true,
                    "lastname": "Bonometti",
                    "name": "Piergiorgio"
                },
                "text": " Bonometti, Piergiorgio."
            },
            {
                "class": "AppointedManagingDirector",
                "payload": {
                    "city": "Wien/Österreich",
                    "dob": "1960-03-20",
                    "flag": "einzelvertretungsberechtigt mit der Befugnis im Namen der Gesellschaft mit sich im eigenen Namen oder als Vertreter eines Dritten Rechtsgeschäfte abzuschließen",
                    "lastname": "Sala",
                    "name": "Fabio Giovanni Sebastiano"
                },
                "text": " Sala, Fabio Giovanni Sebastiano, Wien/Österreich, *20.03.1960, einzelvertretungsberechtigt mit der Befugnis im Namen der Gesellschaft mit sich im eigenen Namen oder als Vertreter eines Dritten Rechtsgeschäfte abzuschließen."
            },
            {
                "class": "SingleProcuration",
                "payload": {
                    "city": "Ense",
                    "dob": "1955-07-16",
                    "lastname": "Remmert",
                    "name": "Heinz-Dieter"
                },
                "text": " Remmert, Heinz-Dieter, Ense, *16.07.1955."
            }
        ]
    }
}