{
    "orig": {
        "aktenzeichen": "HRB 28764",
        "amtsgericht": "Düsseldorf",
        "event_date": "2008-07-28",
        "event_type": "Veränderungen",
        "federal_state": "nw",
        "full_text": "Amtsgericht Düsseldorf Aktenzeichen: HRB 28764 \nBekannt gemacht am: 05.08.2008 12:00 Uhr\n\n\n\n\nDie in () gesetzten Angaben der Geschäftsanschrift und des Geschäftszweiges erfolgen ohne Gewähr.\nVeränderungen\n28.07.2008\n\nNUMERIA Grundstücks-Vermietungsgesellschaft mbH, Düsseldorf (Mercedesstr. 6, 40470 Düsseldorf). Bestellt als Geschäftsführer: Gebhardt, Stephan, Heiligenhaus, *25.11.1964; Schmitz, Christoph, Düsseldorf, *17.04.1959. Nicht mehr Geschäftsführer: Hesselmann, Hermann, kaufmännischer Angestellter, Haan, *23.03.1941; Wolters, Bernd, Düsseldorf, *15.01.1964. Prokura erloschen: Calefice, Jürgen, Neuss, *07.08.1941; Frei, Norbert, Düsseldorf, *18.05.1941; Potthast, Roland, Meerbusch, *09.12.1961; Woeste, Lothar, Düsseldorf, *20.05.1943. Gesamtprokura gemeinsam mit einem Geschäftsführer oder einem anderen Prokuristen mit der Befugnis im Namen der Gesellschaft mit sich im eigenen Namen oder als Vertreter eines Dritten Rechtsgeschäfte abzuschließen mit der Ermächtigung zur Veräußerung und Belastung von Grundstücken: Wolters, Bernd, Düsseldorf, *15.01.1964.",
        "gesellschafter": null,
        "inhaber": null,
        "name": "NUMERIA Grundstücks-Vermietungsgesellschaft mbH",
        "notice_id": "345992",
        "posted_on": "2008-08-05",
        "rechtsform": null,
        "sitz": null,
        "url": "https://www.handelsregisterbekanntmachungen.de/en/skripte/hrb.php?rb_id=345992&land_abk=nw"
    },
    "parsed": {
        "officers": [
            {
                "class": "AppointedManagingDirector",
                "payload": {
                    "city": "Heiligenhaus",
                    "dob": "1964-11-25",
                    "lastname": "Gebhardt",
                    "name": "Stephan"
                },
                "text": " Gebhardt, Stephan, Heiligenhaus, *25.11.1964"
            },
            {
                "class": "AppointedManagingDirector",
                "payload": {
                    "city": "Düsseldorf",
                    "dob": "1959-04-17",
                    "lastname": "Schmitz",
                    "name": "Christoph"
                },
                "text": " Schmitz, Christoph, Düsseldorf, *17.04.1959."
            },
            {
                "class": "DismissedManagingDirector",
                "payload": {
                    "city": "Haan",
                    "dismissed": true,
                    "dob": "1941-03-23",
                    "lastname": "Hesselmann",
                    "name": "Hermann",
                    "position": "kaufmännischer Angestellter"
                },
                "text": " Hesselmann, Hermann, kaufmännischer Angestellter, Haan, *23.03.1941"
            },
            {
                "class": "DismissedManagingDirector",
                "payload": {
                    "city": "Düsseldorf",
                    "dismissed": true,
                    "dob": "1964-01-15",
                    "lastname": "Wolters",
                    "name": "Bernd"
                },
                "text": " Wolters, Bernd, Düsseldorf, *15.01.1964."
            },
            {
                "class": "ProcurationCancelled",
                "payload": {
                    "city": "Neuss",
                    "dismissed": true,
                    "dob": "1941-08-07",
                    "lastname": "Calefice",
                    "name": "Jürgen"
                },
                "text": " Calefice, Jürgen, Neuss, *07.08.1941"
            },
            {
                "class": "ProcurationCancelled",
                "payload": {
                    "city": "Düsseldorf",
                    "dismissed": true,
                    "dob": "1941-05-18",
                    "lastname": "Frei",
                    "name": "Norbert"
                },
                "text": " Frei, Norbert, Düsseldorf, *18.05.1941"
            },
            {
                "class": "ProcurationCancelled",
                "payload": {
                    "city": "Meerbusch",
                    "dismissed": true,
                    "dob": "1961-12-09",
                    "lastname": "Potthast",
                    "name": "Roland"
                },
                "text": " Potthast, Roland, Meerbusch, *09.12.1961"
            },
            {
                "class": "ProcurationCancelled",
                "payload": {
                    "city": "Düsseldorf",
                    "dismissed": true,
                    "dob": "1943-05-20",
                    "lastname": "Woeste",
                    "name": "Lothar"
                },
                "text": " Woeste, Lothar, Düsseldorf, *20.05.1943."
            }
        ]
    }
}