{
    "orig": {
        "aktenzeichen": "HRB 41076",
        "amtsgericht": "Düsseldorf",
        "event_date": "2008-07-28",
        "event_type": "Veränderungen",
        "federal_state": "nw",
        "full_text": "Amtsgericht Düsseldorf Aktenzeichen: HRB 41076 \nBekannt gemacht am: 05.08.2008 12:00 Uhr\n\n\n\n\nDie in () gesetzten Angaben der Geschäftsanschrift und des Geschäftszweiges erfolgen ohne Gewähr.\nVeränderungen\n28.07.2008\n\nNAVISTA Schiffsbetriebsgesellschaft mbH, Düsseldorf (Mercedesstr. 6, 40470 Düsseldorf). Nicht mehr Geschäftsführer: Hesselmann, Hermann, Haan, *23.03.1941; Wolters, Bernd, Düsseldorf, *15.01.1964. Bestellt als Geschäftsführer: Schmitz, Christoph, Düsseldorf, *17.04.1959; Suchsland, Martin, Korschenbroich, *13.09.1963, jeweils mit der Befugnis im Namen der Gesellschaft mit sich im eigenen Namen oder als Vertreter eines Dritten Rechtsgeschäfte abzuschließen. Prokura erloschen: Suchsland, Martin, Korschenbroich, *13.09.1963. Gesamtprokura gemeinsam mit einem Geschäftsführer oder einem anderen Prokuristen mit der Befugnis im Namen der Gesellschaft mit sich im eigenen Namen oder als Vertreter eines Dritten Rechtsgeschäfte abzuschließen mit der Ermächtigung zur Veräußerung und Belastung von Grundstücken: Wolters, Bernd, Düsseldorf, *15.01.1964.",
        "gesellschafter": null,
        "inhaber": null,
        "name": "NAVISTA Schiffsbetriebsgesellschaft mbH",
        "notice_id": "346005",
        "posted_on": "2008-08-05",
        "rechtsform": null,
        "sitz": null,
        "url": "https://www.handelsregisterbekanntmachungen.de/en/skripte/hrb.php?rb_id=346005&land_abk=nw"
    },
    "parsed": {
        "officers": [
            {
                "class": "DismissedManagingDirector",
                "payload": {
                    "city": "Haan",
                    "dismissed": true,
                    "dob": "1941-03-23",
                    "lastname": "Hesselmann",
                    "name": "Hermann"
                },
                "text": " Hesselmann, Hermann, Haan, *23.03.1941"
            },
            {
                "class": "DismissedManagingDirector",
                "payload": {
                    "city": "Düsseldorf",
                    "dismissed": true,
                    "dob": "1964-01-15",
                    "lastname": "Wolters",
                    "name": "Bernd"
                },
                "text": " Wolters, Bernd, Düsseldorf, *15.01.1964."
            },
            {
                "class": "AppointedManagingDirector",
                "payload": {
                    "city": "Düsseldorf",
                    "dob": "1959-04-17",
                    "lastname": "Schmitz",
                    "name": "Christoph"
                },
                "text": " Schmitz, Christoph, Düsseldorf, *17.04.1959"
            },
            {
                "class": "AppointedManagingDirector",
                "payload": {
                    "city": "Korschenbroich",
                    "dob": "1963-09-13",
                    "flag": "jeweils mit der Befugnis im Namen der Gesellschaft mit sich im eigenen Namen oder als Vertreter eines Dritten Rechtsgeschäfte abzuschließen",
                    "lastname": "Suchsland",
                    "name": "Martin"
                },
                "text": " Suchsland, Martin, Korschenbroich, *13.09.1963, jeweils mit der Befugnis im Namen der Gesellschaft mit sich im eigenen Namen oder als Vertreter eines Dritten Rechtsgeschäfte abzuschließen."
            },
            {
                "class": "ProcurationCancelled",
                "payload": {
                    "city": "Korschenbroich",
                    "dismissed": true,
                    "dob": "1963-09-13",
                    "lastname": "Suchsland",
                    "name": "Martin"
                },
                "text": " Suchsland, Martin, Korschenbroich, *13.09.1963."
            }
        ]
    }
}