{
    "orig": {
        "aktenzeichen": "HRB 5197",
        "amtsgericht": "Lemgo",
        "event_date": "2008-09-03",
        "event_type": "Veränderungen",
        "federal_state": "nw",
        "full_text": "Amtsgericht Lemgo Aktenzeichen: HRB 5197 \nBekannt gemacht am: 04.09.2008 12:00 Uhr\n\n\n\n\nDie in () gesetzten Angaben der Geschäftsanschrift und des Unternehmensgegenstandes erfolgen ohne Gewähr.\nVeränderungen\n03.09.2008\n\nKoch & Siemund Geschäftsführungs GmbH, Blomberg (Gartenstr. 17, 32825 Blomberg). Nicht mehr Geschäftsführer: Koch, Fritz, Blomberg, *12.03.1938. Bestellt als Geschäftsführer: Gresens, Michael, Berg-Ettishofen, *20.02.1962, einzelvertretungsberechtigt mit der Befugnis im Namen der Gesellschaft mit sich im eigenen Namen oder als Vertreter eines Dritten Rechtsgeschäfte abzuschließen.",
        "gesellschafter": null,
        "inhaber": null,
        "name": "Koch & Siemund Geschäftsführungs GmbH",
        "notice_id": "354609",
        "posted_on": "2008-09-04",
        "rechtsform": null,
        "sitz": null,
        "url": "https://www.handelsregisterbekanntmachungen.de/en/skripte/hrb.php?rb_id=354609&land_abk=nw"
    },
    "parsed": {
        "officers": [
            {
                "class": "DismissedManagingDirector",
                "payload": {
                    "city": "Blomberg",
                    "dismissed": true,
                    "dob": "1938-03-12",
                    "lastname": "Koch",
                    "name": "Fritz"
                },
                "text": " Koch, Fritz, Blomberg, *12.03.1938."
            },
            {
                "class": "AppointedManagingDirector",
                "payload": {
                    "city": "Berg-Ettishofen",
                    "dob": "1962-02-20",
                    "flag": "einzelvertretungsberechtigt mit der Befugnis im Namen der Gesellschaft mit sich im eigenen Namen oder als Vertreter eines Dritten Rechtsgeschäfte abzuschließen",
                    "lastname": "Gresens",
                    "name": "Michael"
                },
                "text": " Gresens, Michael, Berg-Ettishofen, *20.02.1962, einzelvertretungsberechtigt mit der Befugnis im Namen der Gesellschaft mit sich im eigenen Namen oder als Vertreter eines Dritten Rechtsgeschäfte abzuschließen."
            }
        ]
    }
}