{
    "orig": {
        "aktenzeichen": "HRB 63974",
        "amtsgericht": "Saarbrücken",
        "event_date": "2005-09-14",
        "event_type": "Veränderungen",
        "federal_state": "sl",
        "full_text": "Amtsgericht Saarbrücken Aktenzeichen: HRB 63974 \nBekannt gemacht am: 15.09.2005 15:47 Uhr\n\n\n\n\nDie in () gesetzten Angaben der Geschäftsanschrift und des Unternehmensgegenstandes erfolgen ohne Gewähr.\nVeränderungen\n14.09.2005\n\nPizzeria \"Da Vincenzo\" GmbH, Merzig (Kanuheim, 66663 Merzig). Die Gesellschafterversammlung vom 30.08.2005 hat die Änderung des Gesellschaftsvertrages in § 13 (Bekanntmachungen) beschlossen. Nicht mehr Geschäftsführer, bestellt als Liquidator: Di Leonardis, Vincenzo, Merzig, *03.04.1956, mit der Befugnis im Namen der Gesellschaft mit sich im eigenen Namen oder als Vertreter eines Dritten Rechtsgeschäfte abzuschließen. Die Gesellschafterversammlung vom 30.08.2005 hat die Auflösung der Gesellschaft beschlossen. Als nicht eingetragen wird bekanntgemacht: Die Bekanntmachungen der Gesellschaft erfolgen im elektronischen Bundesanzeiger.",
        "gesellschafter": null,
        "inhaber": null,
        "name": "Pizzeria \"Da Vincenzo\" GmbH",
        "notice_id": "3551",
        "posted_on": "2005-09-15",
        "rechtsform": null,
        "sitz": null,
        "url": "https://www.handelsregisterbekanntmachungen.de/en/skripte/hrb.php?rb_id=3551&land_abk=sl"
    },
    "parsed": {
        "officers": [
            {
                "class": "Liquidator",
                "payload": {
                    "city": "Merzig",
                    "dob": "1956-03-04",
                    "flag": "mit der Befugnis im Namen der Gesellschaft mit sich im eigenen Namen oder als Vertreter eines Dritten Rechtsgeschäfte abzuschließen",
                    "lastname": "Di Leonardis",
                    "name": "Vincenzo"
                },
                "text": " Di Leonardis, Vincenzo, Merzig, *03.04.1956, mit der Befugnis im Namen der Gesellschaft mit sich im eigenen Namen oder als Vertreter eines Dritten Rechtsgeschäfte abzuschließen."
            }
        ]
    }
}