{
    "orig": {
        "aktenzeichen": "HRB 6323",
        "amtsgericht": "Braunschweig",
        "event_date": "2015-09-17",
        "event_type": "Veränderungen",
        "federal_state": "ni",
        "full_text": "Amtsgericht Braunschweig Aktenzeichen: HRB 6323 \nBekannt gemacht am: 17.09.2015 19:00 Uhr\n\n\n\n\nDie in () gesetzten Angaben der Geschäftsanschrift und des Unternehmensgegenstandes erfolgen ohne Gewähr.\nVeränderungen\n17.09.2015\n\nHRB 6323:INGENIEURGESELLSCHAFT Alker mbH, Salzgitter, Lange Wanne 20, 38259 Salzgitter.Durch Beschluss des Registergerichts Braunschweig vom 17.09.2015 wurde die Durchführung einer Nachtragsliquidation angeordnet. Allgemeine Vertretungsregelung: Die Gesellschaft wird durch den Nachtragsliquidator vertreten. Nicht mehr Liquidator: Alker, Helmut, Salzgitter, *15.05.1958. Aufgrund des Beschlusses des Registergerichts Braunschweig vom 17.09.2015 gerichtlich bestellt als Nachtragsliquidator: Alker, Helmut, Salzgitter, *15.05.1958, vertretungsberechtigt gemäß allgemeiner Vertretungsregelung.",
        "gesellschafter": null,
        "inhaber": null,
        "name": "HRB 6323:INGENIEURGESELLSCHAFT Alker mbH",
        "notice_id": "359927",
        "posted_on": "2015-09-17",
        "rechtsform": null,
        "sitz": null,
        "url": "https://www.handelsregisterbekanntmachungen.de/en/skripte/hrb.php?rb_id=359927&land_abk=ni"
    },
    "parsed": {
        "officers": [
            {
                "class": "NotALiquidator",
                "payload": {
                    "city": "Salzgitter",
                    "dismissed": true,
                    "dob": "1958-05-15",
                    "lastname": "Alker",
                    "name": "Helmut"
                },
                "text": ": Alker, Helmut, Salzgitter, *15.05.1958."
            },
            {
                "class": "Liquidator",
                "payload": {
                    "city": "Salzgitter",
                    "dob": "1958-05-15",
                    "flag": "vertretungsberechtigt gemäß allgemeiner Vertretungsregelung",
                    "lastname": "Alker",
                    "name": "Helmut"
                },
                "text": " Alker, Helmut, Salzgitter, *15.05.1958, vertretungsberechtigt gemäß allgemeiner Vertretungsregelung."
            }
        ]
    }
}