{
    "orig": {
        "aktenzeichen": "HRB 11035",
        "amtsgericht": "Ludwigshafen a.Rhein (Ludwigshafen)",
        "event_date": "2007-12-17",
        "event_type": "Veränderungen",
        "federal_state": "rp",
        "full_text": "Amtsgericht Ludwigshafen a.Rhein (Ludwigshafen) Aktenzeichen: HRB 11035 \nBekannt gemacht am: 21.12.2007 12:00 Uhr\n\n\n\n\nDie in () gesetzten Angaben der Geschäftsanschrift und des Unternehmensgegenstandes erfolgen ohne Gewähr.\nVeränderungen\n17.12.2007\n\nRhein - Plast GmbH, Ungstein (Altenbacher Straße 26, 67098 Bad Dürkheim). Die Gesellschafterversammlung hat am 09.11.2007 beschlossen, das Stammkapital (DEM 1.200.000,00) auf Euro umzustellen, es von dann EUR 613.550,25 um EUR 1.449,75 auf EUR 615.000,00 zu erhöhen und den Gesellschaftsvertrag in § 4 (Stammkapital) zu ändern. Weiterhin hat die Gesellschafterversammlung vom 09.11.2007 eine Änderung des Gesellschaftsvertrages in §§ 6 (Einziehung von Geschäftsanteilen und Ausschließung eines Gesellschafters), 9 (Zustimmungspflichtige Rechtsgeschäfte), 10 (Gesellschafterversammlung), 14 (Bewertung) und 16 (Bekanntmachungen der Gesellschaft) beschlossen. 615.000,00 EUR. Vertretungsbefugnis geändert: Geschäftsführer: Eisemann, Norbert, Friedelsheim, *07.03.1936; Eisemann, Hans-Georg, Ludwigshafen/Rhein, *22.02.1944, jeweils einzelvertretungsberechtigt mit der Befugnis im Namen der Gesellschaft mit sich im eigenen Namen oder als Vertreter eines Dritten Rechtsgeschäfte abzuschließen.",
        "gesellschafter": null,
        "inhaber": null,
        "name": "Rhein - Plast GmbH",
        "notice_id": "36489",
        "posted_on": "2007-12-21",
        "rechtsform": null,
        "sitz": null,
        "url": "https://www.handelsregisterbekanntmachungen.de/en/skripte/hrb.php?rb_id=36489&land_abk=rp"
    },
    "parsed": {
        "officers": [
            {
                "class": "ManagingDirector",
                "payload": {
                    "city": "Friedelsheim",
                    "dob": "1936-03-07",
                    "lastname": "Eisemann",
                    "name": "Norbert"
                },
                "text": " Eisemann, Norbert, Friedelsheim, *07.03.1936"
            },
            {
                "class": "ManagingDirector",
                "payload": {
                    "city": "Ludwigshafen/Rhein",
                    "dob": "1944-02-22",
                    "flag": "jeweils einzelvertretungsberechtigt mit der Befugnis im Namen der Gesellschaft mit sich im eigenen Namen oder als Vertreter eines Dritten Rechtsgeschäfte abzuschließen",
                    "lastname": "Eisemann",
                    "name": "Hans-Georg"
                },
                "text": " Eisemann, Hans-Georg, Ludwigshafen/Rhein, *22.02.1944, jeweils einzelvertretungsberechtigt mit der Befugnis im Namen der Gesellschaft mit sich im eigenen Namen oder als Vertreter eines Dritten Rechtsgeschäfte abzuschließen."
            }
        ]
    }
}