{
    "orig": {
        "aktenzeichen": "HRB 137357",
        "amtsgericht": "Hamburg",
        "event_date": "2018-06-14",
        "event_type": "Veränderungen",
        "federal_state": "hh",
        "full_text": "Amtsgericht Hamburg Aktenzeichen: HRB 137357 \nBekannt gemacht am: 14.06.2018 11:33 Uhr\n\n\n\n\nIn () gesetzte Angaben der Anschrift und des Geschäftszweiges erfolgen ohne Gewähr.\nVeränderungen\n14.06.2018\n\nHRB 137357: Aquila Capital Investment Verwaltungsgesellschaft IV mbH, Hamburg, Valentinskamp 70, 20355 Hamburg. Ausgeschieden Geschäftsführer: Nehrig, Fritz Günter Walter, Hannover, *19.01.1970. Geändert, nun Geschäftsführer: Büsselberg, Maren, Hamburg, *21.07.1980, vertretungsberechtigt gemäß allgemeiner Vertretungsregelung; mit der Befugnis, im Namen der Gesellschaft mit sich im eigenen Namen oder als Vertreter eines Dritten Rechtsgeschäfte abzuschließen.",
        "gesellschafter": null,
        "inhaber": null,
        "name": "HRB 137357: Aquila Capital Investment Verwaltungsgesellschaft IV mbH",
        "notice_id": "367654",
        "posted_on": "2018-06-14",
        "rechtsform": null,
        "sitz": null,
        "url": "https://www.handelsregisterbekanntmachungen.de/en/skripte/hrb.php?rb_id=367654&land_abk=hh"
    },
    "parsed": {
        "flags": [
            {
                "flag": "with the power to enter into legal transactions on behalf of the Company with itself or as a representative of a third party",
                "text": "mit\\ der\\ Befugnis\\,\\ im\\ Namen\\ der\\ Gesellschaft\\ mit\\ sich\\ im\\ eigenen\\ Namen\\ oder\\ als\\ Vertreter\\ eines\\ Dritten\\ Rechtsgesch\\äfte\\ abzuschlie\\ßen\\."
            }
        ],
        "officers": [
            {
                "class": "RetiredManagingDirector",
                "payload": {
                    "city": "Hannover",
                    "dismissed": true,
                    "dob": "1970-01-19",
                    "lastname": "Nehrig",
                    "name": "Fritz Günter Walter"
                },
                "text": " Nehrig, Fritz Günter Walter, Hannover, *19.01.1970."
            },
            {
                "class": "ManagingDirector",
                "payload": {
                    "city": "Hamburg",
                    "dob": "1980-07-21",
                    "flag": "vertretungsberechtigt gemäß allgemeiner Vertretungsregelung",
                    "lastname": "Büsselberg",
                    "name": "Maren"
                },
                "text": " Büsselberg, Maren, Hamburg, *21.07.1980, vertretungsberechtigt gemäß allgemeiner Vertretungsregelung"
            },
            {
                "class": "ManagingDirector",
                "payload": {
                    "lastname": "mit der Befugnis",
                    "name": "im Namen der Gesellschaft mit sich im eigenen Namen oder als Vertreter eines Dritten Rechtsgeschäfte abzuschließen"
                },
                "text": " mit der Befugnis, im Namen der Gesellschaft mit sich im eigenen Namen oder als Vertreter eines Dritten Rechtsgeschäfte abzuschließen."
            }
        ]
    }
}