{
    "orig": {
        "aktenzeichen": "HRA 201746",
        "amtsgericht": "Braunschweig",
        "event_date": "2015-12-11",
        "event_type": "Neueintragungen",
        "federal_state": "ni",
        "full_text": "Amtsgericht Braunschweig Aktenzeichen: HRA 201746 \nBekannt gemacht am: 11.12.2015 19:01 Uhr\n\n\n\n\nDie in () gesetzten Angaben der Geschäftsanschrift und des Unternehmensgegenstandes erfolgen ohne Gewähr.\nNeueintragungen\n11.12.2015\n\nHRA 201746: effivendo e.K. Inhaber: Henning Krause, Langelsheim, Streittorstraße 26, 38685 Langelsheim. (Gegenstand: Betrieb von Internet-Shops, Versandhandel von Waren aller Art, Betrieb von Online-Portalen im eigenen Namen und für Dritte sowie Groß- und Einzelhandel in Ladengeschäften.). Einzelkaufmann. Geschäftsanschrift: Streittorstraße 26, 38685 Langelsheim. Inhaber: Krause, Henning, Langelsheim, *19.02.1972. Der Inhaber hat das Vermögen der effivendo GmbH mit Sitz in Langelsheim (Amtsgericht Braunschweig HRB 201018) im Wege der Umwandlung durch Verschmelzung aufgrund des Verschmelzungsvertrages vom 20.08.2015 und des Zustimmungsbeschlusses der Gesellschafterversammlung vom 20.08.2015 als Ganzes übernommen. Als nicht eingetragen wird bekanntgemacht: Den Gläubigern der an der Verschmelzung beteiligten Rechtsträger ist, wenn sie binnen sechs Monaten nach dem Tag, an dem die Eintragung der Verschmelzung in das Register des Sitzes desjenigen Rechtsträgers, dessen Gläubiger sie sind, nach § 19 Abs. 3 UmwG als bekannt gemacht gilt, ihren Anspruch nach Grund und Höhe schriftlich anmelden, Sicherheit zu leisten, soweit sie nicht Befriedigung verlangen können. Dieses Recht steht den Gläubigern jedoch nur zu, wenn sie glaubhaft machen, dass durch die Verschmelzung die Erfüllung der Forderung gefährdet wird.",
        "gesellschafter": null,
        "inhaber": null,
        "name": "HRA 201746: effivendo e.K. Inhaber: Henning Krause",
        "notice_id": "370382",
        "posted_on": "2015-12-11",
        "rechtsform": "Einzelkaufmann",
        "sitz": null,
        "url": "https://www.handelsregisterbekanntmachungen.de/en/skripte/hrb.php?rb_id=370382&land_abk=ni"
    },
    "parsed": {
        "errors": [
            {
                "kls": "ParsingError",
                "text": "Cannot parse a Person from ., error text was a person without DOB, number of chunks: 1"
            }
        ],
        "flags": [
            {
                "flag": "Sole trader",
                "text": "Einzelkaufmann"
            }
        ],
        "labels": [
            {
                "label": "address",
                "text": " Streittorstraße 26, 38685 Langelsheim."
            }
        ],
        "officers": [
            {
                "class": "Owner",
                "payload": {
                    "city": "38685 Langelsheim",
                    "lastname": "Henning Krause",
                    "name": "Langelsheim",
                    "position": "Streittorstraße 26"
                },
                "text": " Henning Krause, Langelsheim, Streittorstraße 26, 38685 Langelsheim."
            },
            {
                "class": "Owner",
                "payload": {
                    "city": "Langelsheim",
                    "dob": "1972-02-19",
                    "lastname": "Krause",
                    "name": "Henning"
                },
                "text": " Krause, Henning, Langelsheim, *19.02.1972."
            }
        ]
    }
}