{
    "orig": {
        "aktenzeichen": "HRB 18341 P",
        "amtsgericht": "Potsdam",
        "event_date": "2006-03-30",
        "event_type": "Veränderungen",
        "federal_state": "br",
        "full_text": "Amtsgericht Potsdam Aktenzeichen: HRB 18341 P  \nBekannt gemacht am: 04.04.2006 16:04 Uhr\n\n\n\n\nFür die Angaben in (), die den Unternehmensgegenstand und die Anschrift betreffen, keine Gewähr. In das Handelsregister ist folgendes eingetragen worden.\nVeränderungen\n30.03.2006\n\nLIGO Grundstücks-Vermietungsgesellschaft mbH, Ludwigsfelde(Berliner Straße 1, 12529  Schönefeld). Sitz: Schönefeld. Nicht mehr Geschäftsführer: Dauer, Axel; Geschäftsführer: Schnell, Detlef, *30.03.1950, Düsseldorf. Prokura: Hue, Helmut, *11.12.1948, Brüggen; Prokura gemeinsam mit einem Geschäftsführer oder einem weiteren Prokuristen; mit der Befugnis Rechtsgeschäfte mit sich oder als Vertreter Dritter abzuschließen; mit der Befugnis zur Veräußerung und Belastung von Grundstücken; Uhr, Eilsabeth, *09.07.1964, Meerbusch; Prokura gemeinsam mit einem Geschäftsführer oder einem weiteren Prokuristen; mit der Befugnis Rechtsgeschäfte mit sich oder als Vertreter Dritter abzuschließen; mit der Befugnis zur Veräußerung und Belastung von Grundstücken Durch Beschluss der Gesellschafterversammlung vom 22.12.2005 ist der Sitz von Ludwigsfelde nach Schönefeld verlegt und der Gesellschaftsvertrag geändert in § 1 Nr. 2 (Sitz).",
        "gesellschafter": null,
        "inhaber": null,
        "name": "LIGO Grundstücks-Vermietungsgesellschaft mbH",
        "notice_id": "3766",
        "posted_on": "2006-04-04",
        "rechtsform": null,
        "sitz": null,
        "url": "https://www.handelsregisterbekanntmachungen.de/en/skripte/hrb.php?rb_id=3766&land_abk=br"
    },
    "parsed": {
        "notices": [
            {
                "court": null,
                "from": "Ludwigsfelde",
                "registration": null,
                "text": " von Ludwigsfelde nach Schönefeld verlegt und der Gesellschaftsvertrag geändert in § 1 Nr. 2 (Sitz).",
                "to": "Schönefeld",
                "used_regex": "from_regex, to_regex"
            }
        ],
        "officers": [
            {
                "class": "DismissedManagingDirector",
                "payload": {
                    "dismissed": true,
                    "lastname": "Dauer",
                    "name": "Axel"
                },
                "text": " Dauer, Axel"
            },
            {
                "class": "ManagingDirector",
                "payload": {
                    "city": "Düsseldorf",
                    "dob": "1950-03-30",
                    "lastname": "Schnell",
                    "name": "Detlef"
                },
                "text": " Schnell, Detlef, *30.03.1950, Düsseldorf."
            },
            {
                "class": "Procuration",
                "payload": {
                    "city": "Brüggen",
                    "dob": "1948-11-12",
                    "lastname": "Hue",
                    "name": "Helmut"
                },
                "text": " Hue, Helmut, *11.12.1948, Brüggen"
            }
        ]
    }
}