{
    "orig": {
        "aktenzeichen": "HRB 140549",
        "amtsgericht": "München",
        "event_date": "2005-07-07",
        "event_type": "Veränderungen",
        "federal_state": "by",
        "full_text": "Amtsgericht München Aktenzeichen: HRB 140549 \nBekannt gemacht am: 13.07.2005 11:21 Uhr\n\n\n\n\nDie in ( ) gesetzten Angaben der Geschäftsanschrift und des Geschäftszweiges erfolgen ohne Gewähr.\nVeränderungen\n07.07.2005\n\nVacanze Italiane (Deutschland) GmbH, München (Lindwurmstr. 139 a, 80337 München). Die Gesellschaft -vormals auch unter Adresse Frankfurter Ring 243 c.o. Italia Tours GmbH, 80807 München- ist durch rechtskräftige Abweisung eines Antrags auf Eröffnung des Insolvenzverfahrens mangels Masse aufgelöst (Az. 1507 IN 2927/04 Amtsgericht München). Von Amts wegen eingetragen. Die Gesellschaft wird durch den/die Liquidator/en vertreten. Geändert, nun Liquidator: Fubiani, Carlo, Lugano, Schweiz, *29.07.1962.",
        "gesellschafter": null,
        "inhaber": null,
        "name": "Vacanze Italiane (Deutschland) GmbH",
        "notice_id": "38168",
        "posted_on": "2005-07-13",
        "rechtsform": null,
        "sitz": null,
        "url": "https://www.handelsregisterbekanntmachungen.de/en/skripte/hrb.php?rb_id=38168&land_abk=by"
    },
    "parsed": {
        "officers": [
            {
                "class": "Liquidator",
                "payload": {
                    "city": "Schweiz",
                    "dob": "1962-07-29",
                    "lastname": "Fubiani",
                    "name": "Carlo",
                    "position": "Lugano"
                },
                "text": " Fubiani, Carlo, Lugano, Schweiz, *29.07.1962."
            }
        ]
    }
}