{
    "orig": {
        "aktenzeichen": "HRB 20768",
        "amtsgericht": "Duisburg",
        "event_date": "2008-12-08",
        "event_type": "Neueintragungen",
        "federal_state": "nw",
        "full_text": "Amtsgericht Duisburg Aktenzeichen: HRB 20768 \nBekannt gemacht am: 12.12.2008 22:00 Uhr\n\n\n\n\nIn () gesetzte Angaben der Anschrift und des Geschäftszweiges erfolgen ohne Gewähr.\nNeueintragungen\n08.12.2008\n\nemc Germany GmbH, Oberhausen, (Duisburger Str. 375, 46049 Oberhausen).Gesellschaft mit beschränkter Haftung. Gesellschaftsvertrag vom 15.05.2008, zuletzt geändert am 10.06.2008. Die Gesellschafterversammlung vom 17.10.2008 hat die Änderung des Gesellschaftsvertrages in § 1 Absatz (2) und mit ihr die Sitzverlegung von Düsseldorf (bisher Amtsgericht Düsseldorf, HRB 59176) nach Oberhausen beschlossen. Gegenstand: das Erbringen von Service-Leistungen aller Art in Deutschland und weltweit im Zusammenhang mit dem Engineering, der Lieferung, der Montage und der Inbetriebnahme von Komponenten von Dampf- sowie Gasturbinengeneratorenanlagen. Stammkapital: 25.000,00 EUR. Allgemeine Vertretungsregelung: Die Gesellschaft hat einen oder mehrere Geschäftsführer. Ist nur ein Geschäftsführer berufen, so vertritt dieser die Gesellschaft allein. Sind mehrere Geschäftsführer bestellt, so wird die Gesellschaft durch zwei Geschäftsführer gemeinsam oder durch einen Geschäftsführer zusammen mit einem Prokuristen vertreten. Durch Gesellschafterbeschluss kann Geschäftsführern die Befugnis erteilt werden, die Gesellschaft einzeln zu vertreten oder im Namen der Gesellschaft mit sich im eigenen Namen oder als Vertreter eines Dritten Rechtsgeschäfte vorzunehmen. Nicht mehr Geschäftsführer: Düxmann, Rolf, Geldern, *23.10.1954. Geschäftsführer: Tischler, Hans-Peter, Willich, *24.10.1963. Neu bestellt als Geschäftsführer: Saur, Wolfgang, Lünen, *15.03.1967. Gesamtprokura gemeinsam mit einem Geschäftsführer oder einem anderen Prokuristen: Brammer, Nils, Mülheim an der Ruhr, *16.07.1970; Dietz, Rainer, Düsseldorf, *11.03.1949; Forstmann, Jochen, Willich, *06.02.1963; Malicki, Margit, Duisburg, *01.08.1967; Notthoff, Klaus, Essen, *15.10.1954.",
        "gesellschafter": null,
        "inhaber": null,
        "name": "emc Germany GmbH",
        "notice_id": "381656",
        "posted_on": "2008-12-12",
        "rechtsform": null,
        "sitz": null,
        "url": "https://www.handelsregisterbekanntmachungen.de/en/skripte/hrb.php?rb_id=381656&land_abk=nw"
    },
    "parsed": {
        "flags": [
            {
                "flag": "Company with limited liability.",
                "text": "Gesellschaft\\ mit\\ beschr\\änkter\\ Haftung\\."
            }
        ],
        "notices": [
            {
                "court": "Düsseldorf",
                "from": "Düsseldorf",
                "hrb": "HRB 59176",
                "registration": "predecessor",
                "registration_conflict": true,
                "text": " von Düsseldorf (bisher Amtsgericht Düsseldorf, HRB 59176) nach Oberhausen beschlossen.",
                "to": "Oberhausen",
                "used_regex": "court_regex, from_hrb_to_regex"
            }
        ],
        "officers": [
            {
                "class": "DismissedManagingDirector",
                "payload": {
                    "city": "Geldern",
                    "dismissed": true,
                    "dob": "1954-10-23",
                    "lastname": "Düxmann",
                    "name": "Rolf"
                },
                "text": " Düxmann, Rolf, Geldern, *23.10.1954."
            },
            {
                "class": "ManagingDirector",
                "payload": {
                    "city": "Willich",
                    "dob": "1963-10-24",
                    "lastname": "Tischler",
                    "name": "Hans-Peter"
                },
                "text": " Tischler, Hans-Peter, Willich, *24.10.1963."
            },
            {
                "class": "AppointedManagingDirector",
                "payload": {
                    "city": "Lünen",
                    "dob": "1967-03-15",
                    "lastname": "Saur",
                    "name": "Wolfgang"
                },
                "text": " Saur, Wolfgang, Lünen, *15.03.1967."
            },
            {
                "class": "CommonProcuration",
                "payload": {
                    "city": "Mülheim an der Ruhr",
                    "dob": "1970-07-16",
                    "lastname": "Brammer",
                    "name": "Nils"
                },
                "text": " Brammer, Nils, Mülheim an der Ruhr, *16.07.1970"
            }
        ]
    }
}