{
    "orig": {
        "aktenzeichen": "HRB 13677",
        "amtsgericht": "Montabaur",
        "event_date": "2008-01-21",
        "event_type": "Veränderungen",
        "federal_state": "rp",
        "full_text": "Amtsgericht Montabaur Aktenzeichen: HRB 13677 \nBekannt gemacht am: 30.01.2008 12:00 Uhr\n\n\n\n\nDie in () gesetzten Angaben der Geschäftsanschrift und des Unternehmensgegenstandes erfolgen ohne Gewähr.\nVeränderungen\n21.01.2008\n\ntescho Softwareentwicklungs GmbH, Erpel (Auf¿m Rottland 3, 57577 Hamm/Sieg). Die Gesellschafterversammlung vom 23.10.2007 hat eine Änderung des Gesellschaftsvertrages in § 1 (Firma und Sitz) und mit ihr die Sitzverlegung nach Hamm/Sieg beschlossen. Hamm/Sieg. Geschäftsführer: Kostka, Mike Werner, Hövels, *06.07.1968, einzelvertretungsberechtigt mit der Befugnis im Namen der Gesellschaft mit sich im eigenen Namen oder als Vertreter eines Dritten Rechtsgeschäfte abzuschließen. Nicht mehr Geschäftsführer: Scholl, Ulrich, Softwareentwickler, Erpel, *29.01.1962; Tenbrink, Ralf, San Miguel de Salinas, *01.05.1960.",
        "gesellschafter": null,
        "inhaber": null,
        "name": "tescho Softwareentwicklungs GmbH",
        "notice_id": "38170",
        "posted_on": "2008-01-30",
        "rechtsform": null,
        "sitz": null,
        "url": "https://www.handelsregisterbekanntmachungen.de/en/skripte/hrb.php?rb_id=38170&land_abk=rp"
    },
    "parsed": {
        "officers": [
            {
                "class": "ManagingDirector",
                "payload": {
                    "city": "Hövels",
                    "dob": "1968-06-07",
                    "flag": "einzelvertretungsberechtigt mit der Befugnis im Namen der Gesellschaft mit sich im eigenen Namen oder als Vertreter eines Dritten Rechtsgeschäfte abzuschließen",
                    "lastname": "Kostka",
                    "name": "Mike Werner"
                },
                "text": " Kostka, Mike Werner, Hövels, *06.07.1968, einzelvertretungsberechtigt mit der Befugnis im Namen der Gesellschaft mit sich im eigenen Namen oder als Vertreter eines Dritten Rechtsgeschäfte abzuschließen."
            },
            {
                "class": "DismissedManagingDirector",
                "payload": {
                    "city": "Erpel",
                    "dismissed": true,
                    "dob": "1962-01-29",
                    "lastname": "Scholl",
                    "name": "Ulrich",
                    "position": "Softwareentwickler"
                },
                "text": " Scholl, Ulrich, Softwareentwickler, Erpel, *29.01.1962"
            }
        ]
    }
}