{
    "orig": {
        "aktenzeichen": "HRA 1255",
        "amtsgericht": "Traunstein",
        "event_date": "2010-01-26",
        "event_type": "Veränderungen",
        "federal_state": "by",
        "full_text": "Amtsgericht Traunstein Aktenzeichen: HRA 1255 \nBekannt gemacht am: 27.01.2010 12:00 Uhr\n\n\n\n\nIn ( ) gesetzte Angaben der Anschrift und des Geschäftszweiges erfolgen ohne Gewähr.\nVeränderungen\n26.01.2010\n\nNeimcke GmbH & Co. KG, Mühldorf am Inn, Am Industriepark 21, 84453 Mühldorf a. Inn.Vertretungsbefugnis geändert, nun: Persönlich haftender Gesellschafter: Neimcke Geschäftsführungs- und Verwaltungs GmbH, Mühldorf a. Inn (AG Traunstein HRB 6736), mit der Befugnis - auch für die jeweiligen Geschäftsführer -, im Namen der Gesellschaft mit sich im eigenen Namen oder als Vertreter eines Dritten Rechtsgeschäfte abzuschließen. Prokura erloschen: Neimcke, Jörg, Mühldorf a. Inn, *01.03.1980; Neimcke, Sven, München, *19.10.1978.",
        "gesellschafter": null,
        "inhaber": null,
        "name": "Neimcke GmbH & Co. KG",
        "notice_id": "384876",
        "posted_on": "2010-01-27",
        "rechtsform": null,
        "sitz": null,
        "url": "https://www.handelsregisterbekanntmachungen.de/en/skripte/hrb.php?rb_id=384876&land_abk=by"
    },
    "parsed": {
        "officers": [
            {
                "class": "PersonalPartner",
                "payload": {
                    "company_name": " Neimcke Geschäftsführungs- und Verwaltungs GmbH, Mühldorf a."
                },
                "text": " Neimcke Geschäftsführungs- und Verwaltungs GmbH, Mühldorf a."
            },
            {
                "class": "ProcurationCancelled",
                "payload": {
                    "city": "Mühldorf a",
                    "dismissed": true,
                    "lastname": "Neimcke",
                    "name": "Jörg"
                },
                "text": " Neimcke, Jörg, Mühldorf a."
            }
        ]
    }
}