{
    "orig": {
        "aktenzeichen": "HRB 6778",
        "amtsgericht": "Coesfeld",
        "event_date": "2009-01-15",
        "event_type": "Veränderungen",
        "federal_state": "nw",
        "full_text": "Amtsgericht Coesfeld Aktenzeichen: HRB 6778 \nBekannt gemacht am: 26.01.2009 12:00 Uhr\n\n\n\n\nIn () gesetzte Angaben der Anschrift und des Geschäftszweiges erfolgen ohne Gewähr.\nVeränderungen\n15.01.2009\n\nBRUDERHERZ Werbeagentur GmbH, Coesfeld, Borkener Straße 64 a, 48653 Coesfeld.Die Gesellschafterversammlung vom 18.11.2008 hat die Änderung des Gesellschaftsvertrages in § 4 (Stammkapital) und mit ihr die Erhöhung des Stammkapitals um 500,00 EUR beschlossen. Geschäftsanschrift: Borkener Straße 64 a, 48653 Coesfeld. 25.500,00 EUR. Vertretungsbefugnis geändert bezüglich Geschäftsführer: Arend, Alexander, Coesfeld, *31.01.1977; Arend, Aristide, Coesfeld, *15.01.1975, jeweils mit der Befugnis im Namen der Gesellschaft mit sich im eigenen Namen oder als Vertreter eines Dritten Rechtsgeschäfte abzuschließen. Bestellt als Geschäftsführer: Kanbach, Christoph, Coesfeld, *11.01.1968, mit der Befugnis im Namen der Gesellschaft mit sich im eigenen Namen oder als Vertreter eines Dritten Rechtsgeschäfte abzuschließen.",
        "gesellschafter": null,
        "inhaber": null,
        "name": "BRUDERHERZ Werbeagentur GmbH",
        "notice_id": "395514",
        "posted_on": "2009-01-26",
        "rechtsform": null,
        "sitz": null,
        "url": "https://www.handelsregisterbekanntmachungen.de/en/skripte/hrb.php?rb_id=395514&land_abk=nw"
    },
    "parsed": {
        "labels": [
            {
                "label": "address",
                "text": " Borkener Straße 64 a, 48653 Coesfeld."
            }
        ],
        "officers": [
            {
                "class": "ManagingDirector",
                "payload": {
                    "city": "Coesfeld",
                    "dob": "1977-01-31",
                    "lastname": "Arend",
                    "name": "Alexander"
                },
                "text": " Arend, Alexander, Coesfeld, *31.01.1977"
            },
            {
                "class": "ManagingDirector",
                "payload": {
                    "city": "Coesfeld",
                    "dob": "1975-01-15",
                    "flag": "jeweils mit der Befugnis im Namen der Gesellschaft mit sich im eigenen Namen oder als Vertreter eines Dritten Rechtsgeschäfte abzuschließen",
                    "lastname": "Arend",
                    "name": "Aristide"
                },
                "text": " Arend, Aristide, Coesfeld, *15.01.1975, jeweils mit der Befugnis im Namen der Gesellschaft mit sich im eigenen Namen oder als Vertreter eines Dritten Rechtsgeschäfte abzuschließen."
            },
            {
                "class": "AppointedManagingDirector",
                "payload": {
                    "city": "Coesfeld",
                    "dob": "1968-01-11",
                    "flag": "mit der Befugnis im Namen der Gesellschaft mit sich im eigenen Namen oder als Vertreter eines Dritten Rechtsgeschäfte abzuschließen",
                    "lastname": "Kanbach",
                    "name": "Christoph"
                },
                "text": " Kanbach, Christoph, Coesfeld, *11.01.1968, mit der Befugnis im Namen der Gesellschaft mit sich im eigenen Namen oder als Vertreter eines Dritten Rechtsgeschäfte abzuschließen."
            }
        ]
    }
}