{
    "orig": {
        "aktenzeichen": "HRB 6397",
        "amtsgericht": "Wetzlar",
        "event_date": "2014-08-21",
        "event_type": "Löschungen",
        "federal_state": "he",
        "full_text": "Amtsgericht Wetzlar Aktenzeichen: HRB 6397 \nBekannt gemacht am: 21.08.2014 22:01 Uhr\n\n\n\n\nVeröffentlichungen des Amtsgerichts Wetzlar\n\n\nIn () gesetzte Angaben der Anschrift und des Geschäftszweiges erfolgen ohne Gewähr.\nLöschungen\n21.08.2014\n\nHRB 6397:Willi Bremer Verwaltungs-GmbH, Bischoffen, Neue Siedlung 20, 35649 Bischoffen.Jeder Liquidator vertritt einzeln. Jeder Liquidator ist befugt, im Namen der Gesellschaft mit sich im eigenen Namen oder als Vertreter eines Dritten Rechtsgeschäfte vorzunehmen. Geändert, nun: Liquidator: Biemer, Thomas, Bischoffen, *02.11.1961; Katzer, Martin, Sinn, *27.02.1962; Richter, Andreas, Sinn, *15.04.1967, jeweils einzelvertretungsberechtigt; mit der Befugnis, im Namen der Gesellschaft mit sich im eigenen Namen oder als Vertreter eines Dritten Rechtsgeschäfte abzuschließen. Die Gesellschaft ist aufgelöst. Die Liquidation ist beendet. Die Gesellschaft ist gelöscht.",
        "gesellschafter": null,
        "inhaber": null,
        "name": "HRB 6397:Willi Bremer Verwaltungs-GmbH",
        "notice_id": "397136",
        "posted_on": "2014-08-21",
        "rechtsform": null,
        "sitz": null,
        "url": "https://www.handelsregisterbekanntmachungen.de/en/skripte/hrb.php?rb_id=397136&land_abk=he"
    },
    "parsed": {
        "errors": [
            {
                "kls": "ParsingError",
                "text": "Cannot parse a Liquidator from  mit der Befugnis, im Namen der Gesellschaft mit sich im eigenen Namen oder als Vertreter eines Dritten Rechtsgeschäfte abzuschließen., error text was Name is too long: im Namen der Gesellschaft mit sich im eigenen Namen oder als Vertreter eines Dritten Rechtsgeschäfte abzuschließen"
            }
        ],
        "flags": [
            {
                "flag": "with the power to enter into legal transactions on behalf of the Company with itself or as a representative of a third party",
                "text": "mit\\ der\\ Befugnis\\,\\ im\\ Namen\\ der\\ Gesellschaft\\ mit\\ sich\\ im\\ eigenen\\ Namen\\ oder\\ als\\ Vertreter\\ eines\\ Dritten\\ Rechtsgesch\\äfte\\ abzuschlie\\ßen\\."
            },
            {
                "flag": "CompanyClosed",
                "text": "Die\\ Gesellschaft\\ ist\\ aufgel\\öst\\."
            }
        ],
        "officers": [
            {
                "class": "Liquidator",
                "payload": {
                    "city": "Bischoffen",
                    "dob": "1961-11-02",
                    "lastname": "Biemer",
                    "name": "Thomas"
                },
                "text": ": Biemer, Thomas, Bischoffen, *02.11.1961"
            },
            {
                "class": "Liquidator",
                "payload": {
                    "city": "Sinn",
                    "dob": "1962-02-27",
                    "lastname": "Katzer",
                    "name": "Martin"
                },
                "text": " Katzer, Martin, Sinn, *27.02.1962"
            },
            {
                "class": "Liquidator",
                "payload": {
                    "city": "Sinn",
                    "dob": "1967-04-15",
                    "flag": "jeweils einzelvertretungsberechtigt",
                    "lastname": "Richter",
                    "name": "Andreas"
                },
                "text": " Richter, Andreas, Sinn, *15.04.1967, jeweils einzelvertretungsberechtigt"
            }
        ]
    }
}