{
    "orig": {
        "aktenzeichen": "HRB 67619 B",
        "amtsgericht": "Charlottenburg (Berlin)",
        "event_date": "2007-05-16",
        "event_type": "Veränderungen",
        "federal_state": "be",
        "full_text": "Amtsgericht Charlottenburg (Berlin) Aktenzeichen: HRB 67619 B  \nBekannt gemacht am: 29.05.2007 08:15 Uhr\n\n\n\n\nFür die Angaben in (), die den Unternehmensgegenstand und die Anschrift betreffen, keine Gewähr. In das Handelsregister ist folgendes eingetragen worden.\nVeränderungen\n16.05.2007\n\nLLH Ludwig Leupold Hahn Gesellschaft Beratender Ingenieure im Bauwesen mbH, Berlin(Ebereschenallee 51, 14050  Berlin). Vertretungsregelung: Die Liquidatoren vertreten gemeinschaftlich.  Änderung zu Nr. 1:; nunmehr:; Liquidator:; Leupold, Michael, Berlin, Diplom-Ingenieur; Liquidator:; 3.Hahn, Axel, *26.09.1951, Berlin Rechtsverhaeltnis: Durch Beschluss der Gesellschafterversammlung vom 25.04.2007 ist die Gesellschaft aufgelöst..",
        "gesellschafter": null,
        "inhaber": null,
        "name": "LLH Ludwig Leupold Hahn Gesellschaft Beratender Ingenieure im Bauwesen mbH",
        "notice_id": "39802",
        "posted_on": "2007-05-29",
        "rechtsform": null,
        "sitz": null,
        "url": "https://www.handelsregisterbekanntmachungen.de/en/skripte/hrb.php?rb_id=39802&land_abk=be"
    },
    "parsed": {
        "officers": [
            {
                "class": "Liquidator",
                "payload": {
                    "city": "Diplom-Ingenieur",
                    "lastname": "Leupold",
                    "name": "Michael",
                    "position": "Berlin"
                },
                "text": " Leupold, Michael, Berlin, Diplom-Ingenieur"
            },
            {
                "class": "Liquidator",
                "payload": {
                    "city": "Berlin Rechtsverhaeltnis: Durch Beschluss der Gesellschafterversammlung vom 25.04.2007 ist die Gesellschaft aufgelöst",
                    "dob": "1951-09-26",
                    "lastname": "Hahn",
                    "name": "Axel"
                },
                "text": "Hahn, Axel, *26.09.1951, Berlin Rechtsverhaeltnis: Durch Beschluss der Gesellschafterversammlung vom 25.04.2007 ist die Gesellschaft aufgelöst.."
            }
        ]
    }
}