{
    "orig": {
        "aktenzeichen": "HRB 90900",
        "amtsgericht": "Frankfurt am Main",
        "event_date": "2014-08-29",
        "event_type": "Veränderungen",
        "federal_state": "he",
        "full_text": "Amtsgericht Frankfurt am Main Aktenzeichen: HRB 90900 \nBekannt gemacht am: 29.08.2014 22:01 Uhr\n\n\n\n\nVeröffentlichungen des Amtsgerichts Frankfurt am Main\n\n\nIn () gesetzte Angaben der Anschrift und des Geschäftszweiges erfolgen ohne Gewähr.\nVeränderungen\n29.08.2014\n\nHRB 90900:MUSTANG Holding GmbH, Frankfurt am Main, Niedenau 68, 60325 Frankfurt am Main.Bestellt als Geschäftsführer: Axt, Dietmar, Hamburg, *23.07.1967, vertretungsberechtigt gemeinsam mit einem anderen Geschäftsführer oder einem Prokuristen; mit der Befugnis, im Namen der Gesellschaft mit sich als Vertreter eines Dritten Rechtsgeschäfte abzuschließen.",
        "gesellschafter": null,
        "inhaber": null,
        "name": "HRB 90900:MUSTANG Holding GmbH",
        "notice_id": "398245",
        "posted_on": "2014-08-29",
        "rechtsform": null,
        "sitz": null,
        "url": "https://www.handelsregisterbekanntmachungen.de/en/skripte/hrb.php?rb_id=398245&land_abk=he"
    },
    "parsed": {
        "officers": [
            {
                "class": "AppointedManagingDirector",
                "payload": {
                    "city": "Hamburg",
                    "dob": "1967-07-23",
                    "flag": "vertretungsberechtigt gemeinsam mit einem anderen Geschäftsführer oder einem Prokuristen",
                    "lastname": "Axt",
                    "name": "Dietmar"
                },
                "text": " Axt, Dietmar, Hamburg, *23.07.1967, vertretungsberechtigt gemeinsam mit einem anderen Geschäftsführer oder einem Prokuristen"
            }
        ]
    }
}