{
    "orig": {
        "aktenzeichen": "HRB 18194",
        "amtsgericht": "Wiesbaden",
        "event_date": "2014-09-18",
        "event_type": "Löschungen",
        "federal_state": "he",
        "full_text": "Amtsgericht Wiesbaden Aktenzeichen: HRB 18194 \nBekannt gemacht am: 18.09.2014 22:02 Uhr\n\n\n\n\nVeröffentlichungen des Amtsgerichts Wiesbaden\n\n\nIn () gesetzte Angaben der Anschrift und des Geschäftszweiges erfolgen ohne Gewähr.\nLöschungen\n18.09.2014\n\nHRB 18194:Martin Kilb, Baugeschäft GmbH, Flörsheim am Main, Untermainstraße 38, 65439 Flörsheim am Main.Geschäftsanschrift: Untermainstraße 38, 65439 Flörsheim am Main. Ist nur ein Liquidator bestellt, so vertritt er die Gesellschaft allein. Sind mehrere Liquidatoren bestellt, so wird die Gesellschaft durch die Liquidatoren gemeinsam vertreten. Geändert, nun: Liquidator: Meyer, Alfred, Maurer, Flörsheim am Main, *24.08.1951. Die Gesellschaft ist aufgelöst.",
        "gesellschafter": null,
        "inhaber": null,
        "name": "HRB 18194:Martin Kilb",
        "notice_id": "401016",
        "posted_on": "2014-09-18",
        "rechtsform": null,
        "sitz": null,
        "url": "https://www.handelsregisterbekanntmachungen.de/en/skripte/hrb.php?rb_id=401016&land_abk=he"
    },
    "parsed": {
        "flags": [
            {
                "flag": "CompanyClosed",
                "text": "Die\\ Gesellschaft\\ ist\\ aufgel\\öst\\."
            }
        ],
        "labels": [
            {
                "label": "address",
                "text": " Untermainstraße 38, 65439 Flörsheim am Main."
            }
        ],
        "officers": [
            {
                "class": "Liquidator",
                "payload": {
                    "city": "Flörsheim am Main",
                    "dob": "1951-08-24",
                    "lastname": ": Meyer",
                    "name": "Alfred",
                    "position": "Maurer"
                },
                "text": ": Meyer, Alfred, Maurer, Flörsheim am Main, *24.08.1951."
            }
        ]
    }
}