{
    "orig": {
        "aktenzeichen": "HRA 150077",
        "amtsgericht": "Oldenburg",
        "event_date": "2016-08-09",
        "event_type": "Veränderungen",
        "federal_state": "ni",
        "full_text": "Amtsgericht Oldenburg Aktenzeichen: HRA 150077 \nBekannt gemacht am: 09.08.2016 19:01 Uhr\n\n\n\n\nIn () gesetzte Angaben der Anschrift und des Geschäftszweiges erfolgen ohne Gewähr:\nVeränderungen\n09.08.2016\n\nHRA 150077: Heinz Kramer, Farben und Bilder, Cloppenburg, Osterstraße 46, 49661 Cloppenburg. Firma geändert, nun: Neue Firma: Heinz Kramer, Farben und Bilder, Inhaberin Helga Grave e.K. Geschäftsanschrift: Osterstraße 46, 49661 Cloppenburg. Nicht mehr Inhaber: Luttmer, Jürgen, Kaufmann, Cloppenburg. Eingetreten als Inhaber: Grave, Helga, Emstek/Halen, *31.01.1969. Der Übergang der in dem Betriebe des Geschäfts entstandenen Verbindlichkeiten und Forderungen ist beim Erwerb des Geschäfts durch den neuen Inhaber ausgeschlossen.",
        "gesellschafter": null,
        "inhaber": null,
        "name": "HRA 150077: Heinz Kramer",
        "notice_id": "401181",
        "posted_on": "2016-08-09",
        "rechtsform": null,
        "sitz": null,
        "url": "https://www.handelsregisterbekanntmachungen.de/en/skripte/hrb.php?rb_id=401181&land_abk=ni"
    },
    "parsed": {
        "labels": [
            {
                "label": "address",
                "text": " Osterstraße 46, 49661 Cloppenburg."
            }
        ],
        "officers": [
            {
                "class": "NotLongerOwner",
                "payload": {
                    "city": "Cloppenburg",
                    "dismissed": true,
                    "lastname": "Luttmer",
                    "name": "Jürgen",
                    "position": "Kaufmann"
                },
                "text": " Luttmer, Jürgen, Kaufmann, Cloppenburg."
            },
            {
                "class": "Owner",
                "payload": {
                    "city": "Emstek/Halen",
                    "dob": "1969-01-31",
                    "lastname": "Grave",
                    "name": "Helga"
                },
                "text": " Grave, Helga, Emstek/Halen, *31.01.1969."
            }
        ]
    }
}