{
    "orig": {
        "aktenzeichen": "HRB 252836",
        "amtsgericht": "Stuttgart",
        "event_date": "2014-02-28",
        "event_type": "Veränderungen",
        "federal_state": "bw",
        "full_text": "Amtsgericht Stuttgart Aktenzeichen: HRB 252836 \nBekannt gemacht am: 28.02.2014 16:52 Uhr\n\n\n\n\nIn () gesetzte Angaben der Anschrift und des Geschäftszweiges erfolgen ohne Gewähr:\nVeränderungen\n28.02.2014\n\nHRB 252836:Kauffmann Radsport und Spielwaren GmbH, Renningen, Leonberger Straße 8, 71272 Renningen.Allgemeine Vertretungsregelung geändert; nun: Ist nur ein Liquidator bestellt, vertritt er allein. Sind mehrere Liquidatoren bestellt, vertreten zwei gemeinsam. Liquidator: Kauffmann, Lore, Renningen, *19.02.1948, vertretungsberechtigt gemeinsam mit der Liquidatorin Frau Katrin Schmidt. Liquidator: Schmidt, Katrin, Renningen, *30.11.1976, vertretungsberechtigt gemeinsam mit der Liquidatorin Frau Lore Kauffmann. Nicht mehr Geschäftsführer: Fischbäck, Johanna, Renningen, *27.05.1952; Kauffmann, Gerhard, Renningen, *16.04.1949. Die Gesellschaft ist aufgelöst.",
        "gesellschafter": null,
        "inhaber": null,
        "name": "HRB 252836:Kauffmann Radsport und Spielwaren GmbH",
        "notice_id": "414554",
        "posted_on": "2014-02-28",
        "rechtsform": null,
        "sitz": null,
        "url": "https://www.handelsregisterbekanntmachungen.de/en/skripte/hrb.php?rb_id=414554&land_abk=bw"
    },
    "parsed": {
        "flags": [
            {
                "flag": "ignore_for_now",
                "text": "Die\\ Gesellschaft\\ ist\\ aufgel\\öst\\."
            }
        ],
        "officers": [
            {
                "class": "Liquidator",
                "payload": {
                    "city": "Renningen",
                    "dob": "1948-02-19",
                    "flag": "vertretungsberechtigt gemeinsam mit der Liquidatorin Frau Katrin Schmidt",
                    "lastname": "Kauffmann",
                    "name": "Lore"
                },
                "text": " Kauffmann, Lore, Renningen, *19.02.1948, vertretungsberechtigt gemeinsam mit der Liquidatorin Frau Katrin Schmidt."
            },
            {
                "class": "Liquidator",
                "payload": {
                    "city": "Renningen",
                    "dob": "1976-11-30",
                    "flag": "vertretungsberechtigt gemeinsam mit der Liquidatorin Frau Lore Kauffmann",
                    "lastname": "Schmidt",
                    "name": "Katrin"
                },
                "text": " Schmidt, Katrin, Renningen, *30.11.1976, vertretungsberechtigt gemeinsam mit der Liquidatorin Frau Lore Kauffmann."
            },
            {
                "class": "DismissedManagingDirector",
                "payload": {
                    "city": "Renningen",
                    "dismissed": true,
                    "dob": "1952-05-27",
                    "lastname": "Fischbäck",
                    "name": "Johanna"
                },
                "text": " Fischbäck, Johanna, Renningen, *27.05.1952"
            }
        ]
    }
}