{
    "orig": {
        "aktenzeichen": "HRA 2360",
        "amtsgericht": "Ludwigshafen a.Rhein (Ludwigshafen)",
        "event_date": "2005-08-01",
        "event_type": "Veränderungen",
        "federal_state": "rp",
        "full_text": "Amtsgericht Ludwigshafen a.Rhein (Ludwigshafen) Aktenzeichen: HRA 2360 \nBekannt gemacht am: 18.08.2005 07:27 Uhr\n\n\n\n\nDie in () gesetzten Angaben der Geschäftsanschrift und des Unternehmensgegenstandes erfolgen ohne Gewähr.\nVeränderungen\n01.08.2005\n\nKronen Apotheke Manfred Müller, Mutterstadt (Ludwigshafener Str. 10, 67112 Mutterstadt). Kronen Apotheke Dr. Heidrun Helm e.K. Inhaber: Helm, Heidrun, Mutterstadt, *24.10.1957; Nicht mehr Inhaber: Müller, Manfred, Apotheker, Mutterstadt. Der Übergang der in dem Betriebe des Geschäfts entstandenen Verbindlichkeiten und Forderungen ist beim Erwerb des Geschäfts durch den neuen Inhaber ausgeschlossen.",
        "gesellschafter": null,
        "inhaber": null,
        "name": "Kronen Apotheke Manfred Müller",
        "notice_id": "415",
        "posted_on": "2005-08-18",
        "rechtsform": null,
        "sitz": null,
        "url": "https://www.handelsregisterbekanntmachungen.de/en/skripte/hrb.php?rb_id=415&land_abk=rp"
    },
    "parsed": {
        "officers": [
            {
                "class": "Owner",
                "payload": {
                    "city": "Mutterstadt",
                    "dob": "1957-10-24",
                    "lastname": "Helm",
                    "name": "Heidrun"
                },
                "text": " Helm, Heidrun, Mutterstadt, *24.10.1957"
            },
            {
                "class": "NotLongerOwner",
                "payload": {
                    "city": "Mutterstadt",
                    "dismissed": true,
                    "lastname": "Müller",
                    "name": "Manfred",
                    "position": "Apotheker"
                },
                "text": " Müller, Manfred, Apotheker, Mutterstadt."
            }
        ]
    }
}