{
    "orig": {
        "aktenzeichen": "HRB 6135",
        "amtsgericht": "Krefeld",
        "event_date": "2009-04-14",
        "event_type": "Veränderungen",
        "federal_state": "nw",
        "full_text": "Amtsgericht Krefeld Aktenzeichen: HRB 6135 \nBekannt gemacht am: 16.04.2009 12:00 Uhr\n\n\n\n\nIn () gesetzte Angaben der Anschrift und des Geschäftszweiges erfolgen ohne Gewähr.\nVeränderungen\n14.04.2009\n\nPsion Teklogix GmbH, Willich, Jakob-Kaiser-Str. 3, 47877 Willich.Geschäftsanschrift: Jakob-Kaiser-Str. 3, 47877 Willich. Nicht mehr Geschäftsführer: Lecuivre, Jacky. Bestellt als Geschäftsführer: Nakach, Guy Franck Maurice, Abingdon/Großbritannien, *08.09.1960, einzelvertretungsberechtigt mit der Befugnis im Namen der Gesellschaft mit sich im eigenen Namen oder als Vertreter eines Dritten Rechtsgeschäfte abzuschließen. Prokura erloschen: Nakach, Guy Frank Maurice.",
        "gesellschafter": null,
        "inhaber": null,
        "name": "Psion Teklogix GmbH",
        "notice_id": "424805",
        "posted_on": "2009-04-16",
        "rechtsform": null,
        "sitz": null,
        "url": "https://www.handelsregisterbekanntmachungen.de/en/skripte/hrb.php?rb_id=424805&land_abk=nw"
    },
    "parsed": {
        "labels": [
            {
                "label": "address",
                "text": " Jakob-Kaiser-Str."
            }
        ],
        "officers": [
            {
                "class": "DismissedManagingDirector",
                "payload": {
                    "dismissed": true,
                    "lastname": "Lecuivre",
                    "name": "Jacky"
                },
                "text": " Lecuivre, Jacky."
            },
            {
                "class": "AppointedManagingDirector",
                "payload": {
                    "city": "Abingdon/Großbritannien",
                    "dob": "1960-08-09",
                    "flag": "einzelvertretungsberechtigt mit der Befugnis im Namen der Gesellschaft mit sich im eigenen Namen oder als Vertreter eines Dritten Rechtsgeschäfte abzuschließen",
                    "lastname": "Nakach",
                    "name": "Guy Franck Maurice"
                },
                "text": " Nakach, Guy Franck Maurice, Abingdon/Großbritannien, *08.09.1960, einzelvertretungsberechtigt mit der Befugnis im Namen der Gesellschaft mit sich im eigenen Namen oder als Vertreter eines Dritten Rechtsgeschäfte abzuschließen."
            },
            {
                "class": "ProcurationCancelled",
                "payload": {
                    "dismissed": true,
                    "lastname": "Nakach",
                    "name": "Guy Frank Maurice"
                },
                "text": " Nakach, Guy Frank Maurice."
            }
        ]
    }
}