{
    "orig": {
        "aktenzeichen": "HRB 211823",
        "amtsgericht": "Oldenburg",
        "event_date": "2017-02-27",
        "event_type": "Neueintragungen",
        "federal_state": "ni",
        "full_text": "Amtsgericht Oldenburg Aktenzeichen: HRB 211823 \nBekannt gemacht am: 27.02.2017 19:00 Uhr\n\n\n\n\nIn () gesetzte Angaben der Anschrift und des Geschäftszweiges erfolgen ohne Gewähr:\nNeueintragungen\n27.02.2017\n\nHRB 211823: CSB Dreizehnte Reedereiverwaltungsgesellschaft mbH, Delmenhorst, Wildeshauser Straße 27, 27753 Delmenhorst. Gesellschaft mit beschränkter Haftung. Gesellschaftsvertrag vom 11.02.2008 mit Änderung vom 07.10.2008. Die Gesellschafterversammlung vom 01.02.2017 hat die Änderung des Gesellschaftsvertrages in § 1 und mit ihr die Sitzverlegung von Moormerland-Neermoor (bisher Amtsgericht Aurich HRB 200810) nach Delmenhorst beschlossen. Geschäftsanschrift: Wildeshauser Straße 27, 27753 Delmenhorst. Gegenstand: Führung der Geschäfte in der MS \"Affo Beninga\" Reederei Bojen GmbH & Co. KG, Moormerland-Neermoor, als persönlich haftende Gesellschafterin und alle damit im Zusammenhang stehenden Geschäfte, einschließlich Bereederung der MS \"Affo Beninga\". Stammkapital: 27.000,00 EUR. Allgemeine Vertretungsregelung: Jeder Liquidator vertritt einzeln. Jeder Liquidator ist befugt, im Namen der Gesellschaft mit sich im eigenen Namen oder als Vertreter eines Dritten Rechtsgeschäfte vorzunehmen. Bestellt als Liquidator: Lundehn, Sven, Bad Zwischenahn, *08.11.1970. Nicht mehr Geschäftsführer: Bojen, Siegfried, Moormerland-Neermoor, *06.02.1939. Die Gesellschaft ist durch Gesellschafterbeschluss vom 01.02.2017 aufgelöst.",
        "gesellschafter": null,
        "inhaber": null,
        "name": "HRB 211823: CSB Dreizehnte Reedereiverwaltungsgesellschaft mbH",
        "notice_id": "427458",
        "posted_on": "2017-02-27",
        "rechtsform": null,
        "sitz": null,
        "url": "https://www.handelsregisterbekanntmachungen.de/en/skripte/hrb.php?rb_id=427458&land_abk=ni"
    },
    "parsed": {
        "flags": [
            {
                "flag": "Company with limited liability.",
                "text": "Gesellschaft\\ mit\\ beschr\\änkter\\ Haftung\\."
            }
        ],
        "labels": [
            {
                "label": "address",
                "text": " Wildeshauser Straße 27, 27753 Delmenhorst."
            }
        ],
        "notices": [
            {
                "court": "Aurich",
                "from": "Moormerland-Neermoor",
                "hrb": "HRB 200810",
                "registration": "predecessor",
                "text": " von Moormerland-Neermoor (bisher Amtsgericht Aurich HRB 200810) nach Delmenhorst beschlossen.",
                "to": "Delmenhorst",
                "used_regex": "court, from_hrb_to_regex"
            }
        ],
        "officers": [
            {
                "class": "Liquidator",
                "payload": {
                    "city": "Bad Zwischenahn",
                    "dob": "1970-08-11",
                    "lastname": "Lundehn",
                    "name": "Sven"
                },
                "text": " Lundehn, Sven, Bad Zwischenahn, *08.11.1970."
            },
            {
                "class": "DismissedManagingDirector",
                "payload": {
                    "city": "Moormerland-Neermoor",
                    "dismissed": true,
                    "dob": "1939-06-02",
                    "lastname": "Bojen",
                    "name": "Siegfried"
                },
                "text": " Bojen, Siegfried, Moormerland-Neermoor, *06.02.1939."
            }
        ]
    }
}