{
    "orig": {
        "aktenzeichen": "HRB 204850",
        "amtsgericht": "Oldenburg",
        "event_date": "2017-03-02",
        "event_type": "Veränderungen",
        "federal_state": "ni",
        "full_text": "Amtsgericht Oldenburg Aktenzeichen: HRB 204850 \nBekannt gemacht am: 02.03.2017 19:00 Uhr\n\n\n\n\nIn () gesetzte Angaben der Anschrift und des Geschäftszweiges erfolgen ohne Gewähr:\nVeränderungen\n02.03.2017\n\nHRB 204850: WangerWind Verwaltungs UG (haftungsbeschränkt), Wangerland, Mehringsburg, 26434 Wangerland. Die Gesellschafterversammlung vom 09.01.2017 hat die Neufassung des Gesellschaftsvertrages und mit ihr die Erhöhung des Stammkapitals um 24.000,00 EUR auf 25.000,00 EUR, die Änderung der Firma, des Unternehmensgegenstandes und der allgemeinen Vertretungsregelung und die Sitzverlegung nach Ovelgönne beschlossen. Die Gesellschafterversammlung vom 11.01.2017 hat eine Änderung des Gesellschaftsvertrages in Ziffer 7 (Ausübung der Gesellschafterrechte) beschlossen. Die Gesellschafterversammlung vom 14.02.2017 hat eine Änderung des Gesellschaftsvertrages in Ziffer 14 (Jahresabschluss, Ergebnisverwendung, Gründungskosten) beschlossen. Neue Firma: Linebroker Wind Geschäftsführungs-GmbH. Ovelgönne. Änderung zur Geschäftsanschrift: Hamelstraße 32, 26939 Ovelgönne. Neuer Unternehmensgegenstand: Übernahme der persönlichen Haftung sowie der Geschäftsführung bei anderen Gesellschaften. 25.000,00 EUR. Ist nur ein Geschäftsführer bestellt, so vertritt er die Gesellschaft allein. Sind mehrere Geschäftsführer bestellt, so wird die Gesellschaft durch zwei Geschäftsführer oder durch einen Geschäftsführer gemeinsam mit einem Prokuristen vertreten. Bestellt als Geschäftsführer: von Thülen, Georg, Jever, *31.10.1955, vertretungsberechtigt gemeinsam mit den Geschäftsführern Wilhelm Harken und Heinz Thomßen. Bestellt als Geschäftsführer: Harken, Wilhelm, Wangerland, *27.04.1961, vertretungsberechtigt gemeinsam mit den Geschäftsführern Georg von Thülen und Heinz Thomßen. Geändert, nun: Geschäftsführer: Thomßen, Heinz, Wangerland, *17.01.1955, vertretungsberechtigt gemeinsam mit den Geschäftsführern Georg von Thülen und Wilhelm Harken.",
        "gesellschafter": null,
        "inhaber": null,
        "name": "HRB 204850: WangerWind Verwaltungs UG (haftungsbeschränkt)",
        "notice_id": "428037",
        "posted_on": "2017-03-02",
        "rechtsform": null,
        "sitz": null,
        "url": "https://www.handelsregisterbekanntmachungen.de/en/skripte/hrb.php?rb_id=428037&land_abk=ni"
    },
    "parsed": {
        "flags": [
            {
                "flag": "If only one managing director is appointed, he represents the company alone.",
                "text": "Ist\\ nur\\ ein\\ Gesch\\äftsf\\ührer\\ bestellt\\,\\ so\\ vertritt\\ er\\ die\\ Gesellschaft\\ allein\\."
            },
            {
                "flag": "If several managing directors are appointed, then the company is represented by two managing directors or by a managing director together with an authorized officer.",
                "text": "Sind\\ mehrere\\ Gesch\\äftsf\\ührer\\ bestellt\\,\\ so\\ wird\\ die\\ Gesellschaft\\ durch\\ zwei\\ Gesch\\äftsf\\ührer\\ oder\\ durch\\ einen\\ Gesch\\äftsf\\ührer\\ gemeinsam\\ mit\\ einem\\ Prokuristen\\ vertreten\\."
            }
        ],
        "labels": [
            {
                "label": "address",
                "text": " Hamelstraße 32, 26939 Ovelgönne."
            }
        ],
        "notices": [
            {
                "court": null,
                "registration": null,
                "text": " nach Ovelgönne beschlossen.",
                "to": "Ovelgönne",
                "used_regex": "to_regex"
            }
        ],
        "officers": [
            {
                "class": "AppointedManagingDirector",
                "payload": {
                    "city": "Jever",
                    "dob": "1955-10-31",
                    "flag": "vertretungsberechtigt gemeinsam mit den Geschäftsführern Wilhelm Harken und Heinz Thomßen",
                    "lastname": "von Thülen",
                    "name": "Georg"
                },
                "text": " von Thülen, Georg, Jever, *31.10.1955, vertretungsberechtigt gemeinsam mit den Geschäftsführern Wilhelm Harken und Heinz Thomßen."
            },
            {
                "class": "AppointedManagingDirector",
                "payload": {
                    "city": "Wangerland",
                    "dob": "1961-04-27",
                    "flag": "vertretungsberechtigt gemeinsam mit den Geschäftsführern Georg von Thülen und Heinz Thomßen",
                    "lastname": "Harken",
                    "name": "Wilhelm"
                },
                "text": " Harken, Wilhelm, Wangerland, *27.04.1961, vertretungsberechtigt gemeinsam mit den Geschäftsführern Georg von Thülen und Heinz Thomßen."
            },
            {
                "class": "ManagingDirector",
                "payload": {
                    "city": "Wangerland",
                    "dob": "1955-01-17",
                    "flag": "vertretungsberechtigt gemeinsam mit den Geschäftsführern Georg von Thülen und Wilhelm Harken",
                    "lastname": "Thomßen",
                    "name": "Heinz"
                },
                "text": " Thomßen, Heinz, Wangerland, *17.01.1955, vertretungsberechtigt gemeinsam mit den Geschäftsführern Georg von Thülen und Wilhelm Harken."
            }
        ]
    }
}