{
    "orig": {
        "aktenzeichen": "HRA 6633",
        "amtsgericht": "Bad Oeynhausen",
        "event_date": "2009-04-23",
        "event_type": "Veränderungen",
        "federal_state": "nw",
        "full_text": "Amtsgericht Bad Oeynhausen Aktenzeichen: HRA 6633 \nBekannt gemacht am: 28.04.2009 12:00 Uhr\n\n\n\n\nIn () gesetzte Angaben der Anschrift und des Geschäftszweiges erfolgen ohne Gewähr.\nVeränderungen\n23.04.2009\n\nINNCONA GmbH & Co. Dreißigste Rendite Leasing KG, Herford, (Berliner Str. 17, 32052 Herford).eingetreten als Persönlich haftender Gesellschafter: Global Group for Management & Trade, Inc., Aloha, Oregon / USA (OREGON SECRETARY OF STATE Corporation Division Business Registry Nbr 323811-96). Ausgeschieden als Persönlich haftender Gesellschafter: Inncona Geschäftsführungs GmbH, Enger (AG Bad Oeynhausen HRB 6120).",
        "gesellschafter": null,
        "inhaber": null,
        "name": "INNCONA GmbH & Co. Dreißigste Rendite Leasing KG",
        "notice_id": "428487",
        "posted_on": "2009-04-28",
        "rechtsform": null,
        "sitz": null,
        "url": "https://www.handelsregisterbekanntmachungen.de/en/skripte/hrb.php?rb_id=428487&land_abk=nw"
    },
    "parsed": {
        "officers": [
            {
                "class": "PersonalPartner",
                "payload": {
                    "city": "Oregon / USA (OREGON SECRETARY OF STATE Corporation Division Business Registry Nbr 323811-96)",
                    "lastname": "Global Group for Management & Trade",
                    "name": "Inc",
                    "position": "Aloha"
                },
                "text": " Global Group for Management & Trade, Inc., Aloha, Oregon / USA (OREGON SECRETARY OF STATE Corporation Division Business Registry Nbr 323811-96)."
            },
            {
                "class": "RetiredPersonalPartner",
                "payload": {
                    "company_name": "Inncona Geschäftsführungs GmbH, Enger (AG Bad Oeynhausen HRB 6120).",
                    "dismissed": true
                },
                "text": " Inncona Geschäftsführungs GmbH, Enger (AG Bad Oeynhausen HRB 6120)."
            }
        ]
    }
}