{
    "orig": {
        "aktenzeichen": "HRB 60048",
        "amtsgericht": "Düsseldorf",
        "event_date": "2009-04-29",
        "event_type": "Veränderungen",
        "federal_state": "nw",
        "full_text": "Amtsgericht Düsseldorf Aktenzeichen: HRB 60048 \nBekannt gemacht am: 05.05.2009 12:00 Uhr\n\n\n\n\nIn () gesetzte Angaben der Anschrift und des Geschäftszweiges erfolgen ohne Gewähr.\nVeränderungen\n29.04.2009\n\nDCS Diamond Communication Systems GmbH, Düsseldorf, Stadttor 1, 40219 Düsseldorf.Nicht mehr Geschäftsführer: Salvi, Umesh Shantaram, BurDubai, Dubai, *27.04.1969. Bestellt als Geschäftsführer: Lisberg, Joern, Slagelse / Dänemark, *14.06.1952, einzelvertretungsberechtigt mit der Befugnis im Namen der Gesellschaft mit sich im eigenen Namen oder als Vertreter eines Dritten Rechtsgeschäfte abzuschließen.",
        "gesellschafter": null,
        "inhaber": null,
        "name": "DCS Diamond Communication Systems GmbH",
        "notice_id": "430276",
        "posted_on": "2009-05-05",
        "rechtsform": null,
        "sitz": null,
        "url": "https://www.handelsregisterbekanntmachungen.de/en/skripte/hrb.php?rb_id=430276&land_abk=nw"
    },
    "parsed": {
        "officers": [
            {
                "class": "DismissedManagingDirector",
                "payload": {
                    "city": "Dubai",
                    "dismissed": true,
                    "dob": "1969-04-27",
                    "lastname": "Salvi",
                    "name": "Umesh Shantaram",
                    "position": "BurDubai"
                },
                "text": " Salvi, Umesh Shantaram, BurDubai, Dubai, *27.04.1969."
            },
            {
                "class": "AppointedManagingDirector",
                "payload": {
                    "city": "Slagelse / Dänemark",
                    "dob": "1952-06-14",
                    "flag": "einzelvertretungsberechtigt mit der Befugnis im Namen der Gesellschaft mit sich im eigenen Namen oder als Vertreter eines Dritten Rechtsgeschäfte abzuschließen",
                    "lastname": "Lisberg",
                    "name": "Joern"
                },
                "text": " Lisberg, Joern, Slagelse / Dänemark, *14.06.1952, einzelvertretungsberechtigt mit der Befugnis im Namen der Gesellschaft mit sich im eigenen Namen oder als Vertreter eines Dritten Rechtsgeschäfte abzuschließen."
            }
        ]
    }
}