{
    "orig": {
        "aktenzeichen": "HRB 215045",
        "amtsgericht": "Hannover",
        "event_date": "2017-03-21",
        "event_type": "Neueintragungen",
        "federal_state": "ni",
        "full_text": "Amtsgericht Hannover Aktenzeichen: HRB 215045 \nBekannt gemacht am: 21.03.2017 19:00 Uhr\n\n\n\n\nIn () gesetzte Angaben der Anschrift und des Geschäftszweiges erfolgen ohne Gewähr:\nNeueintragungen\n21.03.2017\n\nHRB 215045: Ecolutions GmbH & Co. KGaA, Langenhagen, Mailänder Straße 2, 30539 Hannover. Kommanditgesellschaft auf Aktien. Satzung vom 05.03.2007, mehrfach geändert. Die Hauptversammlung vom 21.05.2015 hat die Änderung der Satzung in § 4 (Sitz der Gesellschaft) und mit ihr die Sitzverlegung von Frankfurt am Main (bisher Amtsgericht Frankfurt am Main HRB 79650) nach Langenhagen beschlossen. Geschäftsanschrift: Mailänder Straße 2, 30539 Hannover. Gegenstand: Abschluss von Finanzgeschäften und das Eingehen von Derivatgeschäften, die unmittelbar oder mittelbar eine Teilhabe an der Entwicklung des Wertes spezieller Emissionsberechtigungen haben, die Projektfinanzierung sowie das Halten, die Verwaltung und die Veräußerung von Beteiligungen an Private Equity Funds (Venture Capital, Buyout, Special Situations, Mezzanine) und Hedge Funds, Mehrheits- und Minderheitsbeteiligungen an privaten und börsennotierten Unternehmen (gemeinsam die \"Investitionen\") im eigenen Namen und auf eigene Rechnung. Die Gesellschaft ist des Weiteren zur Anlage des Barvermögens im eigenen Namen und für eigene Rechnung berechtigt, in Wertpapiere aller Art zu investieren. Die Gesellschaft ist berechtigt, alle Geschäfte vorzunehmen und sämtliche Maßnahmen zu ergreifen, die mit dem Gegenstand des Unternehmens zusammenhängen oder ihm unmittelbar oder mittelbar förderlich sind, mit Ausnahme solcher Geschäfte und Maßnahmen, die dazu führen, dass der Gegenstand des Unternehmens der staatlichen Genehmigung bedürfte, insbesondere mit Ausnahme des Betreibens von Bankgeschäften und der Erbringung von Finanzdienstleistungen im Sinne von § 32 Abs. (1) des Kreditwesengesetzes. Grundkapital: 28.400.000,00 EUR. Allgemeine Vertretungsregelung: Die Gesellschaft wird durch die persönlich haftende Gesellschafterin vertreten. Diese ist befugt, im Namen der Gesellschaft mit sich als Vertreter eines Dritten Rechtsgeschäfte vorzunehmen. Eingetreten als Persönlich haftender Gesellschafter: Ecolutions Management GmbH, Frankfurt am Main (Amtsgericht Frankfurt am Main HRB 79561). Das Grundkapital ist durch Beschluss der Hauptversammlung vom 08.08.2007 um bis zu 400.000,00 EUR bedingt erhöht worden (bedingtes Kapital 2007/I). Das Grundkapital ist durch Beschluss der Hauptversammlung vom 07.03.2008 um bis zu 5.000.000,00 EUR bedingt erhöht worden (bedingtes Kapital 2008/I). Das Grundkapital ist durch Beschluss der Hauptversammlung vom 25.08.2008 um bis zu 2.000.000,00 EUR bedingt erhöht worden (bedingtes Kapital 2008/II). Die persönlich haftenden Gesellschafter sind durch Beschluss der Hauptversammlung vom 19.12.2014 ermächtigt, das Grundkapital bis zum 18.12.2019 mit Zustimmung des Aufsichtsrats um bis zu 14.200.000,00 EUR gegen Bareinlage einmal oder mehrmals zu erhöhen, wobei das Bezugsrecht der Aktionäre ausgeschlossen werden kann (genehmigtes Kapital 2014/I).",
        "gesellschafter": null,
        "inhaber": null,
        "name": "HRB 215045: Ecolutions GmbH & Co. KGaA",
        "notice_id": "430613",
        "posted_on": "2017-03-21",
        "rechtsform": null,
        "sitz": null,
        "url": "https://www.handelsregisterbekanntmachungen.de/en/skripte/hrb.php?rb_id=430613&land_abk=ni"
    },
    "parsed": {
        "labels": [
            {
                "label": "address",
                "text": " Mailänder Straße 2, 30539 Hannover."
            }
        ],
        "notices": [
            {
                "from": "Frankfurt am Main",
                "hrb": "HRB 79650",
                "text": " von Frankfurt am Main (bisher Amtsgericht Frankfurt am Main HRB 79650) nach Langenhagen beschlossen.",
                "to": "Langenhagen",
                "used_regex": "from_hrb_to_regex"
            }
        ],
        "officers": [
            {
                "class": "PersonalPartner",
                "payload": {
                    "company_name": "Ecolutions Management GmbH, Frankfurt am Main (Amtsgericht Frankfurt am Main HRB 79561)."
                },
                "text": " Ecolutions Management GmbH, Frankfurt am Main (Amtsgericht Frankfurt am Main HRB 79561)."
            }
        ]
    }
}