{
    "orig": {
        "aktenzeichen": "HRA 3966",
        "amtsgericht": "Friedberg",
        "event_date": "2015-07-29",
        "event_type": "Veränderungen",
        "federal_state": "he",
        "full_text": "Amtsgericht Friedberg Aktenzeichen: HRA 3966 \nBekannt gemacht am: 29.07.2015 22:00 Uhr\n\n\n\n\nVeröffentlichungen des Amtsgerichts Friedberg (Hessen)\n\n\nIn () gesetzte Angaben der Anschrift und des Geschäftszweiges erfolgen ohne Gewähr.\nVeränderungen\n29.07.2015\n\nHRA 3966: Schütz Group GmbH & Co. KG, Rosbach v. d. Höhe, Dieselstraße 5, 61191 Rosbach v. d. Höhe. Jeder Liquidator vertritt einzeln. Geändert, nun: Liquidator und Persönlich haftender Gesellschafter: Schütz Group Verwaltungsgesellschaft mbH, Rosbach v.d.Höhe (Amtsgericht Friedberg (Hessen) HRB 6051). Prokura erloschen: Ballnus, Sandra, Butzbach, *07.09.1976; Kohler, Jasmin, Ober-Mörlen, *30.09.1979; Witt, Thomas, Bad Homburg, *26.02.1969. Die Gesellschaft ist aufgelöst.",
        "gesellschafter": null,
        "inhaber": null,
        "name": "HRA 3966: Schütz Group GmbH & Co. KG",
        "notice_id": "445109",
        "posted_on": "2015-07-29",
        "rechtsform": null,
        "sitz": null,
        "url": "https://www.handelsregisterbekanntmachungen.de/en/skripte/hrb.php?rb_id=445109&land_abk=he"
    },
    "parsed": {
        "flags": [
            {
                "flag": "CompanyClosed",
                "text": "Die\\ Gesellschaft\\ ist\\ aufgel\\öst\\."
            }
        ],
        "officers": [
            {
                "class": "PersonalPartner",
                "payload": {
                    "company_name": "Schütz Group Verwaltungsgesellschaft mbH, Rosbach v.d.Höhe (Amtsgericht Friedberg (Hessen) HRB 6051)."
                },
                "text": " Schütz Group Verwaltungsgesellschaft mbH, Rosbach v.d.Höhe (Amtsgericht Friedberg (Hessen) HRB 6051)."
            },
            {
                "class": "ProcurationCancelled",
                "payload": {
                    "city": "Butzbach",
                    "dismissed": true,
                    "dob": "1976-09-07",
                    "lastname": "Ballnus",
                    "name": "Sandra"
                },
                "text": " Ballnus, Sandra, Butzbach, *07.09.1976"
            },
            {
                "class": "ProcurationCancelled",
                "payload": {
                    "city": "Ober-Mörlen",
                    "dismissed": true,
                    "dob": "1979-09-30",
                    "lastname": "Kohler",
                    "name": "Jasmin"
                },
                "text": " Kohler, Jasmin, Ober-Mörlen, *30.09.1979"
            },
            {
                "class": "ProcurationCancelled",
                "payload": {
                    "city": "Bad Homburg",
                    "dismissed": true,
                    "dob": "1969-02-26",
                    "lastname": "Witt",
                    "name": "Thomas"
                },
                "text": " Witt, Thomas, Bad Homburg, *26.02.1969."
            }
        ]
    }
}