{
    "orig": {
        "aktenzeichen": "HRB 206782",
        "amtsgericht": "Hannover",
        "event_date": "2017-08-11",
        "event_type": "Veränderungen",
        "federal_state": "ni",
        "full_text": "Amtsgericht Hannover Aktenzeichen: HRB 206782 \nBekannt gemacht am: 11.08.2017 19:00 Uhr\n\n\n\n\nIn () gesetzte Angaben der Anschrift und des Geschäftszweiges erfolgen ohne Gewähr:\nVeränderungen\n11.08.2017\n\nHRB 206782: Europharma Company GmbH, Hannover, Rotenburger Straße 9, 30659 Hannover. Die Gesellschafterversammlung vom 06.07.2017 hat eine Änderung des Gesellschaftsvertrages in § 1 (Firma und Sitz) und mit ihr die Änderung der Firma sowie die Änderung des § 2 (Gegenstand des Unternehmens) und mit ihr die Änderung des Unternehmensgegenstandes beschlossen. Neue Firma: Rapco Invest GmbH. Änderung zur Geschäftsanschrift: Rotenburger Straße 13-15, 30659 Hannover. Neuer Unternehmensgegenstand: Investitionen in Produktionsanlagen und Beteiligungen sowie der Im- und Export und der Vertrieb von genehmigungsfreien Waren aller Art ohne ausgeprägten Schwerpunkt, insbesondere Lebensmittel. Bestellt als Geschäftsführer: Gharaati Rahmatollah, Massoud, Teheran / Islamische Republik Iran, *23.08.1965; Mohammadi Hojatollah, Mehdi, Teheran / Islamische Republik Iran, *21.04.1982; Tabesh Alireza, Ehsan, Bousher/Muscat/Alozaibe / Oman, *28.07.1978, jeweils einzelvertretungsberechtigt; mit der Befugnis, im Namen der Gesellschaft mit sich im eigenen Namen oder als Vertreter eines Dritten Rechtsgeschäfte abzuschließen.",
        "gesellschafter": null,
        "inhaber": null,
        "name": "HRB 206782: Europharma Company GmbH",
        "notice_id": "447131",
        "posted_on": "2017-08-11",
        "rechtsform": null,
        "sitz": null,
        "url": "https://www.handelsregisterbekanntmachungen.de/en/skripte/hrb.php?rb_id=447131&land_abk=ni"
    },
    "parsed": {
        "errors": [
            {
                "kls": "ParsingError",
                "text": "Cannot parse a AppointedManagingDirector from  mit der Befugnis, im Namen der Gesellschaft mit sich im eigenen Namen oder als Vertreter eines Dritten Rechtsgeschäfte abzuschließen., error text was Name is too long: im Namen der Gesellschaft mit sich im eigenen Namen oder als Vertreter eines Dritten Rechtsgeschäfte abzuschließen"
            }
        ],
        "flags": [
            {
                "flag": "with the power to enter into legal transactions on behalf of the Company with itself or as a representative of a third party",
                "text": "mit\\ der\\ Befugnis\\,\\ im\\ Namen\\ der\\ Gesellschaft\\ mit\\ sich\\ im\\ eigenen\\ Namen\\ oder\\ als\\ Vertreter\\ eines\\ Dritten\\ Rechtsgesch\\äfte\\ abzuschlie\\ßen\\."
            }
        ],
        "labels": [
            {
                "label": "address",
                "text": " Rotenburger Straße 13-15, 30659 Hannover."
            }
        ],
        "officers": [
            {
                "class": "AppointedManagingDirector",
                "payload": {
                    "city": "Teheran / Islamische Republik Iran",
                    "dob": "1965-08-23",
                    "lastname": "Gharaati Rahmatollah",
                    "name": "Massoud"
                },
                "text": " Gharaati Rahmatollah, Massoud, Teheran / Islamische Republik Iran, *23.08.1965"
            },
            {
                "class": "AppointedManagingDirector",
                "payload": {
                    "city": "Teheran / Islamische Republik Iran",
                    "dob": "1982-04-21",
                    "lastname": "Mohammadi Hojatollah",
                    "name": "Mehdi"
                },
                "text": " Mohammadi Hojatollah, Mehdi, Teheran / Islamische Republik Iran, *21.04.1982"
            },
            {
                "class": "AppointedManagingDirector",
                "payload": {
                    "city": "Bousher/Muscat/Alozaibe / Oman",
                    "dob": "1978-07-28",
                    "flag": "jeweils einzelvertretungsberechtigt",
                    "lastname": "Tabesh Alireza",
                    "name": "Ehsan"
                },
                "text": " Tabesh Alireza, Ehsan, Bousher/Muscat/Alozaibe / Oman, *28.07.1978, jeweils einzelvertretungsberechtigt"
            }
        ]
    }
}