{
    "orig": {
        "aktenzeichen": "HRB 36801",
        "amtsgericht": "Bielefeld",
        "event_date": "2009-07-03",
        "event_type": "Veränderungen",
        "federal_state": "nw",
        "full_text": "Amtsgericht Bielefeld Aktenzeichen: HRB 36801 \nBekannt gemacht am: 08.07.2009 12:00 Uhr\n\n\n\n\nIn () gesetzte Angaben der Anschrift und des Geschäftszweiges erfolgen ohne Gewähr.\nVeränderungen\n03.07.2009\n\nBIOGAS NORD Anlagenbau GmbH, Bielefeld, Werningshof 2-4, 33719 Bielefeld.Geschäftsanschrift: Werningshof 2-4, 33719 Bielefeld. Geschäftsführer: Drouianov, Asnat, Kfar Sava, *09.07.1956, mit der Befugnis im Namen der Gesellschaft mit sich im eigenen Namen oder als Vertreter eines Dritten Rechtsgeschäfte abzuschließen. Nicht mehr Geschäftsführer: Kubat, Matthias, Tegernheim, *17.10.1965. Nicht mehr Geschäftsführer: Feuchte, Rudolf, LR Rijswijk/Niederlande, *16.05.1951, mit der Befugnis im Namen der Gesellschaft mit sich im eigenen Namen oder als Vertreter eines Dritten Rechtsgeschäfte abzuschließen.",
        "gesellschafter": null,
        "inhaber": null,
        "name": "BIOGAS NORD Anlagenbau GmbH",
        "notice_id": "448670",
        "posted_on": "2009-07-08",
        "rechtsform": null,
        "sitz": null,
        "url": "https://www.handelsregisterbekanntmachungen.de/en/skripte/hrb.php?rb_id=448670&land_abk=nw"
    },
    "parsed": {
        "addresses": [
            {
                "kls": "Address",
                "text": "Werningshof 2-4, 33719 Bielefeld"
            }
        ],
        "officers": [
            {
                "class": "ManagingDirector",
                "payload": {
                    "city": "Kfar Sava",
                    "dob": "1956-07-09",
                    "flag": "mit der Befugnis im Namen der Gesellschaft mit sich im eigenen Namen oder als Vertreter eines Dritten Rechtsgeschäfte abzuschließen",
                    "lastname": "Drouianov",
                    "name": "Asnat"
                },
                "text": " Drouianov, Asnat, Kfar Sava, *09.07.1956, mit der Befugnis im Namen der Gesellschaft mit sich im eigenen Namen oder als Vertreter eines Dritten Rechtsgeschäfte abzuschließen."
            },
            {
                "class": "DismissedManagingDirector",
                "payload": {
                    "city": "Tegernheim",
                    "dismissed": true,
                    "dob": "1965-10-17",
                    "lastname": "Kubat",
                    "name": "Matthias"
                },
                "text": " Kubat, Matthias, Tegernheim, *17.10.1965."
            },
            {
                "class": "DismissedManagingDirector",
                "payload": {
                    "city": "LR Rijswijk/Niederlande",
                    "dismissed": true,
                    "dob": "1951-05-16",
                    "flag": "mit der Befugnis im Namen der Gesellschaft mit sich im eigenen Namen oder als Vertreter eines Dritten Rechtsgeschäfte abzuschließen",
                    "lastname": "Feuchte",
                    "name": "Rudolf"
                },
                "text": " Feuchte, Rudolf, LR Rijswijk/Niederlande, *16.05.1951, mit der Befugnis im Namen der Gesellschaft mit sich im eigenen Namen oder als Vertreter eines Dritten Rechtsgeschäfte abzuschließen."
            }
        ]
    }
}