{
    "orig": {
        "aktenzeichen": "HRB 81983",
        "amtsgericht": "Hamburg",
        "event_date": "2008-02-04",
        "event_type": "Veränderungen",
        "federal_state": "hh",
        "full_text": "Amtsgericht Hamburg Aktenzeichen: HRB 81983 \nBekannt gemacht am: 05.02.2008 12:00 Uhr\n\n\n\n\nDie in () gesetzten Angaben der Geschäftsanschrift und des Geschäftszweiges erfolgen ohne Gewähr.\nVeränderungen\n04.02.2008\n\nnextevolution management consulting GmbH, Hamburg (Am Sandtorkai 74, 20457 Hamburg). Ausgeschieden Geschäftsführer: Kosyk, Frank, Bad Tölz, *12.06.1977; Dr. Schomann, Marc, Hamburg, *24.08.1966. Bestellt Geschäftsführer: Tensing, Markus, Zürich, *02.02.1972, vertretungsberechtigt gemeinsam mit einem anderen Geschäftsführer oder einem Prokuristen. Gesamtprokura gemeinsam mit einem Geschäftsführer oder einem anderen Prokuristen: Manegold, Nils, Dreieich, *19.12.1971.",
        "gesellschafter": null,
        "inhaber": null,
        "name": "nextevolution management consulting GmbH",
        "notice_id": "44931",
        "posted_on": "2008-02-05",
        "rechtsform": null,
        "sitz": null,
        "url": "https://www.handelsregisterbekanntmachungen.de/en/skripte/hrb.php?rb_id=44931&land_abk=hh"
    },
    "parsed": {
        "officers": [
            {
                "class": "RetiredManagingDirector",
                "payload": {
                    "city": "Bad Tölz",
                    "dismissed": true,
                    "dob": "1977-12-06",
                    "lastname": "Kosyk",
                    "name": "Frank"
                },
                "text": " Kosyk, Frank, Bad Tölz, *12.06.1977"
            },
            {
                "class": "AppointedManagingDirector",
                "payload": {
                    "city": "Zürich",
                    "dob": "1972-02-02",
                    "flag": "vertretungsberechtigt gemeinsam mit einem anderen Geschäftsführer oder einem Prokuristen",
                    "lastname": "Tensing",
                    "name": "Markus"
                },
                "text": " Tensing, Markus, Zürich, *02.02.1972, vertretungsberechtigt gemeinsam mit einem anderen Geschäftsführer oder einem Prokuristen."
            },
            {
                "class": "CommonProcuration",
                "payload": {
                    "city": "Dreieich",
                    "dob": "1971-12-19",
                    "lastname": "Manegold",
                    "name": "Nils"
                },
                "text": " Manegold, Nils, Dreieich, *19.12.1971."
            }
        ]
    }
}