{
    "orig": {
        "aktenzeichen": "HRB 47559",
        "amtsgericht": "Düsseldorf",
        "event_date": "2009-07-29",
        "event_type": "Veränderungen",
        "federal_state": "nw",
        "full_text": "Amtsgericht Düsseldorf Aktenzeichen: HRB 47559 \nBekannt gemacht am: 04.08.2009 12:00 Uhr\n\n\n\n\nIn () gesetzte Angaben der Anschrift und des Geschäftszweiges erfolgen ohne Gewähr.\nVeränderungen\n29.07.2009\n\nSIEBTE PAXAS Treuhand- und Beteiligungsgesellschaft mbH, Düsseldorf, Königsallee 106, 40215 Düsseldorf.Geschäftsanschrift: Königsallee 106, 40215 Düsseldorf. Nicht mehr Geschäftsführer: vor dem Esche, Hans-Bernd, Meerbusch, *10.11.1947. Bestellt als Geschäftsführer: Schmidt, Ronald Hans, Tönisvorst, *28.09.1963, mit der Befugnis im Namen der Gesellschaft mit sich im eigenen Namen oder als Vertreter eines Dritten Rechtsgeschäfte abzuschließen.",
        "gesellschafter": null,
        "inhaber": null,
        "name": "SIEBTE PAXAS Treuhand- und Beteiligungsgesellschaft mbH",
        "notice_id": "457776",
        "posted_on": "2009-08-04",
        "rechtsform": null,
        "sitz": null,
        "url": "https://www.handelsregisterbekanntmachungen.de/en/skripte/hrb.php?rb_id=457776&land_abk=nw"
    },
    "parsed": {
        "labels": [
            {
                "label": "address",
                "text": " Königsallee 106, 40215 Düsseldorf."
            }
        ],
        "officers": [
            {
                "class": "DismissedManagingDirector",
                "payload": {
                    "city": "Meerbusch",
                    "dismissed": true,
                    "dob": "1947-10-11",
                    "lastname": "vor dem Esche",
                    "name": "Hans-Bernd"
                },
                "text": " vor dem Esche, Hans-Bernd, Meerbusch, *10.11.1947."
            },
            {
                "class": "AppointedManagingDirector",
                "payload": {
                    "city": "Tönisvorst",
                    "dob": "1963-09-28",
                    "flag": "mit der Befugnis im Namen der Gesellschaft mit sich im eigenen Namen oder als Vertreter eines Dritten Rechtsgeschäfte abzuschließen",
                    "lastname": "Schmidt",
                    "name": "Ronald Hans"
                },
                "text": " Schmidt, Ronald Hans, Tönisvorst, *28.09.1963, mit der Befugnis im Namen der Gesellschaft mit sich im eigenen Namen oder als Vertreter eines Dritten Rechtsgeschäfte abzuschließen."
            }
        ]
    }
}