{
    "orig": {
        "aktenzeichen": "HRA 4572 P",
        "amtsgericht": "Potsdam",
        "event_date": "2010-04-16",
        "event_type": "Veränderungen",
        "federal_state": "br",
        "full_text": "Amtsgericht Potsdam Aktenzeichen: HRA 4572 P  \nBekannt gemacht am: 20.04.2010 22:00 Uhr\n\n\n\n\nIn () gesetzte Angaben der Anschrift und des Geschäftszweiges erfolgen ohne Gewähr.\nVeränderungen\n16.04.2010\n\nPHI - 3. Projekt GmbH & Co. KG, Kleinmachnow, Erlenweg 33, 14532 Kleinmachnow. Nicht mehr Persönlich haftender Gesellschafter: 1. GSKR Vermögensverwaltung GmbH; Persönlich haftender Gesellschafter: 2. PHI Grundbesitz AG, Kleinmachnow (Amtsgericht Potsdam, HRB 19030 P); mit der für sich sowie ihren Vorstand geltenden Befugnis Rechtsgeschäfte mit sich selbst oder als Vertreter Dritter abzuschließen.",
        "gesellschafter": null,
        "inhaber": null,
        "name": "PHI - 3. Projekt GmbH & Co. KG",
        "notice_id": "47148",
        "posted_on": "2010-04-20",
        "rechtsform": null,
        "sitz": null,
        "url": "https://www.handelsregisterbekanntmachungen.de/en/skripte/hrb.php?rb_id=47148&land_abk=br"
    },
    "parsed": {
        "officers": [
            {
                "class": "PersonalPartner",
                "payload": {
                    "company_name": " GSKR Vermögensverwaltung GmbH"
                },
                "text": " GSKR Vermögensverwaltung GmbH"
            },
            {
                "class": "PersonalPartner",
                "payload": {
                    "city": "HRB 19030 P)",
                    "lastname": "PHI Grundbesitz AG",
                    "name": "Kleinmachnow (Amtsgericht Potsdam"
                },
                "text": " PHI Grundbesitz AG, Kleinmachnow (Amtsgericht Potsdam, HRB 19030 P)"
            }
        ]
    }
}