{
    "orig": {
        "aktenzeichen": "HRA 724350",
        "amtsgericht": "Ulm",
        "event_date": "2015-02-02",
        "event_type": "Neueintragungen",
        "federal_state": "bw",
        "full_text": "Amtsgericht Ulm Aktenzeichen: HRA 724350 \nBekannt gemacht am: 02.02.2015 15:55 Uhr\n\n\n\n\nIn () gesetzte Angaben der Anschrift und des Geschäftszweiges erfolgen ohne Gewähr:\nNeueintragungen\n02.02.2015\n\nHRA 724350:Apotheke im Spital, Inh. Alexander Franze e.K., Ravensburg, Bachstraße 51, 88214 Ravensburg.Einzelkaufmann. Geschäftsanschrift: Bachstraße 51, 88214 Ravensburg. Zweigniederlassung unter der Firma: Löwen-Apotheke, Filialapotheke der Apotheke im Spital, Inh. Alexander Franze e.K., 88214 Ravensburg, Geschäftsanschrift: Bachstraße 22, 88214 Ravensburg. Inhaber: Franze, Alexander, Ravensburg, *16.06.1982. Der Geschäftsbetrieb des bisher als Zweigniederlassung unter der Fima \"Apotheke im Spital, Filialapotheke der Löwen-Apotheke Ravensburg, Inh. Josef Franze e.K., Ravensburg (Amtsgericht Ulm HRA 550190), geführten Unternehmens ist mit dem Recht zur Fortführung der Firma auf den Inhaber übergegangen, der es als Hauptniederlassung fortführt. Der Geschäftsbetrieb des bisher als Hautpniederlassung unter der Firma \"Löwen-Apotheke Ravensburg Inh. Josef Franze e.K.\", Ravensburg (Amtsgericht Ulm HRA 550190) geführten Unternehmens ist mit dem Recht zur Fortführung der Firma auf den Inhaber übergangen, der es als Zweigniederlassung forführt.",
        "gesellschafter": null,
        "inhaber": null,
        "name": "HRA 724350:Apotheke im Spital",
        "notice_id": "471822",
        "posted_on": "2015-02-02",
        "rechtsform": "Einzelkaufmann",
        "sitz": null,
        "url": "https://www.handelsregisterbekanntmachungen.de/en/skripte/hrb.php?rb_id=471822&land_abk=bw"
    },
    "parsed": {
        "flags": [
            {
                "flag": "Sole trader",
                "text": "Einzelkaufmann"
            }
        ],
        "labels": [
            {
                "label": "address",
                "text": " Bachstraße 51, 88214 Ravensburg."
            },
            {
                "label": "address",
                "text": " Bachstraße 22, 88214 Ravensburg."
            }
        ],
        "officers": [
            {
                "class": "Owner",
                "payload": {
                    "city": "Ravensburg",
                    "dob": "1982-06-16",
                    "lastname": "Franze",
                    "name": "Alexander"
                },
                "text": " Franze, Alexander, Ravensburg, *16.06.1982."
            }
        ]
    }
}