{
    "orig": {
        "aktenzeichen": "HRB 103315",
        "amtsgericht": "Frankfurt am Main",
        "event_date": "2016-02-02",
        "event_type": "Veränderungen",
        "federal_state": "he",
        "full_text": "Amtsgericht Frankfurt am Main Aktenzeichen: HRB 103315 \nBekannt gemacht am: 02.02.2016 22:01 Uhr\n\n\n\n\nVeröffentlichungen des Amtsgerichts Frankfurt am Main\n\n\nIn () gesetzte Angaben der Anschrift und des Geschäftszweiges erfolgen ohne Gewähr.\nVeränderungen\n02.02.2016\n\nHRB 103315: Blitz F15-323 GmbH, Frankfurt am Main, c/o Blitzstart Holding AG, Theresienhöhe 30, 80339 München. Geändert, nun: Geschäftsanschrift: Kohlenhofstraße 10, 67663 Kaiserslautern. Nicht mehr Geschäftsführerin: Gogalla, Katja, München, *11.04.1968; Selnes, Randi Mette, München, *02.03.1978. Bestellt als Geschäftsführer: Hassam, Shan, Birmingham / Vereinigtes Königreich, *05.03.1985; Kanani, Abbas, Birmingham / Vereinigtes Königreich, *07.05.1984, jeweils einzelvertretungsberechtigt; mit der Befugnis, im Namen der Gesellschaft mit sich im eigenen Namen oder als Vertreter eines Dritten Rechtsgeschäfte abzuschließen.",
        "gesellschafter": null,
        "inhaber": null,
        "name": "HRB 103315: Blitz F15-323 GmbH",
        "notice_id": "472490",
        "posted_on": "2016-02-02",
        "rechtsform": null,
        "sitz": null,
        "url": "https://www.handelsregisterbekanntmachungen.de/en/skripte/hrb.php?rb_id=472490&land_abk=he"
    },
    "parsed": {
        "flags": [
            {
                "flag": "with the power to enter into legal transactions on behalf of the Company with itself or as a representative of a third party",
                "text": "mit\\ der\\ Befugnis\\,\\ im\\ Namen\\ der\\ Gesellschaft\\ mit\\ sich\\ im\\ eigenen\\ Namen\\ oder\\ als\\ Vertreter\\ eines\\ Dritten\\ Rechtsgesch\\äfte\\ abzuschlie\\ßen\\."
            }
        ],
        "labels": [
            {
                "label": "address",
                "text": " Kohlenhofstraße 10, 67663 Kaiserslautern."
            }
        ],
        "officers": [
            {
                "class": "DismissedManagingDirector",
                "payload": {
                    "city": "München",
                    "dismissed": true,
                    "dob": "1968-04-11",
                    "lastname": "Gogalla",
                    "name": "Katja"
                },
                "text": " Gogalla, Katja, München, *11.04.1968"
            },
            {
                "class": "DismissedManagingDirector",
                "payload": {
                    "city": "München",
                    "dismissed": true,
                    "dob": "1978-03-02",
                    "lastname": "Selnes",
                    "name": "Randi Mette"
                },
                "text": " Selnes, Randi Mette, München, *02.03.1978."
            },
            {
                "class": "AppointedManagingDirector",
                "payload": {
                    "city": "Birmingham / Vereinigtes Königreich",
                    "dob": "1985-03-05",
                    "lastname": "Hassam",
                    "name": "Shan"
                },
                "text": " Hassam, Shan, Birmingham / Vereinigtes Königreich, *05.03.1985"
            },
            {
                "class": "AppointedManagingDirector",
                "payload": {
                    "city": "Birmingham / Vereinigtes Königreich",
                    "dob": "1984-05-07",
                    "flag": "jeweils einzelvertretungsberechtigt",
                    "lastname": "Kanani",
                    "name": "Abbas"
                },
                "text": " Kanani, Abbas, Birmingham / Vereinigtes Königreich, *07.05.1984, jeweils einzelvertretungsberechtigt"
            },
            {
                "class": "AppointedManagingDirector",
                "payload": {
                    "lastname": "mit der Befugnis",
                    "name": "im Namen der Gesellschaft mit sich im eigenen Namen oder als Vertreter eines Dritten Rechtsgeschäfte abzuschließen"
                },
                "text": " mit der Befugnis, im Namen der Gesellschaft mit sich im eigenen Namen oder als Vertreter eines Dritten Rechtsgeschäfte abzuschließen."
            }
        ]
    }
}