{
    "orig": {
        "aktenzeichen": "HRB 5221",
        "amtsgericht": "Mainz",
        "event_date": "2008-10-23",
        "event_type": "Veränderungen",
        "federal_state": "rp",
        "full_text": "Amtsgericht Mainz Aktenzeichen: HRB 5221 \nBekannt gemacht am: 27.10.2008 12:00 Uhr\n\n\n\n\nDie in () gesetzten Angaben der Geschäftsanschrift und des Unternehmensgegenstandes erfolgen ohne Gewähr.\nVeränderungen\n23.10.2008\n\nLias Grundstücksverwaltungsgesellschaft mbH, Mainz (Wilhelm-Theodor-Römheld-Str. 30, 55130 Mainz). Ist nur ein Liquidator bestellt, so vertritt er die Gesellschaft allein. Sind mehrere Liquidatoren bestellt, so wird die Gesellschaft durch die Liquidatoren gemeinsam vertreten. Bestellt als Liquidator: Dahlhaus, Hermann, Bingen am Rhein, *05.04.1947; Momberg, Frank, Wiesbaden, *17.04.1972, jeweils einzelvertretungsberechtigt mit der Befugnis im Namen der Gesellschaft mit sich im eigenen Namen oder als Vertreter eines Dritten Rechtsgeschäfte abzuschließen. Nicht mehr Geschäftsführer: Butsch, Mainz; Stolz, Heribert, Wiesbaden, *25.09.1956. Prokura erloschen: Hagenguth, Peter Heinz, Mainz, *15.02.1952; Höhne, Heinz Günter, Mainz, *01.05.1957; Wessollek, Manfred Horst, Bad Kreuznach, *12.08.1955. Die Gesellschaft ist aufgelöst.",
        "gesellschafter": null,
        "inhaber": null,
        "name": "Lias Grundstücksverwaltungsgesellschaft mbH",
        "notice_id": "49906",
        "posted_on": "2008-10-27",
        "rechtsform": null,
        "sitz": null,
        "url": "https://www.handelsregisterbekanntmachungen.de/en/skripte/hrb.php?rb_id=49906&land_abk=rp"
    },
    "parsed": {
        "flags": [
            {
                "flag": "CompanyClosed",
                "text": "Die\\ Gesellschaft\\ ist\\ aufgel\\öst\\."
            }
        ],
        "officers": [
            {
                "class": "Liquidator",
                "payload": {
                    "city": "Bingen am Rhein",
                    "dob": "1947-04-05",
                    "lastname": "Dahlhaus",
                    "name": "Hermann"
                },
                "text": " Dahlhaus, Hermann, Bingen am Rhein, *05.04.1947"
            },
            {
                "class": "Liquidator",
                "payload": {
                    "city": "Wiesbaden",
                    "dob": "1972-04-17",
                    "flag": "jeweils einzelvertretungsberechtigt mit der Befugnis im Namen der Gesellschaft mit sich im eigenen Namen oder als Vertreter eines Dritten Rechtsgeschäfte abzuschließen",
                    "lastname": "Momberg",
                    "name": "Frank"
                },
                "text": " Momberg, Frank, Wiesbaden, *17.04.1972, jeweils einzelvertretungsberechtigt mit der Befugnis im Namen der Gesellschaft mit sich im eigenen Namen oder als Vertreter eines Dritten Rechtsgeschäfte abzuschließen."
            },
            {
                "class": "DismissedManagingDirector",
                "payload": {
                    "dismissed": true,
                    "lastname": "Butsch",
                    "name": "Mainz"
                },
                "text": " Butsch, Mainz"
            },
            {
                "class": "DismissedManagingDirector",
                "payload": {
                    "city": "Wiesbaden",
                    "dismissed": true,
                    "dob": "1956-09-25",
                    "lastname": "Stolz",
                    "name": "Heribert"
                },
                "text": " Stolz, Heribert, Wiesbaden, *25.09.1956."
            },
            {
                "class": "ProcurationCancelled",
                "payload": {
                    "city": "Mainz",
                    "dismissed": true,
                    "dob": "1952-02-15",
                    "lastname": "Hagenguth",
                    "name": "Peter Heinz"
                },
                "text": " Hagenguth, Peter Heinz, Mainz, *15.02.1952"
            },
            {
                "class": "ProcurationCancelled",
                "payload": {
                    "city": "Mainz",
                    "dismissed": true,
                    "dob": "1957-05-01",
                    "lastname": "Höhne",
                    "name": "Heinz Günter"
                },
                "text": " Höhne, Heinz Günter, Mainz, *01.05.1957"
            },
            {
                "class": "ProcurationCancelled",
                "payload": {
                    "city": "Bad Kreuznach",
                    "dismissed": true,
                    "dob": "1955-08-12",
                    "lastname": "Wessollek",
                    "name": "Manfred Horst"
                },
                "text": " Wessollek, Manfred Horst, Bad Kreuznach, *12.08.1955."
            }
        ]
    }
}