{
    "orig": {
        "aktenzeichen": "HRA 96805",
        "amtsgericht": "München",
        "event_date": "2011-04-13",
        "event_type": "Veränderungen",
        "federal_state": "by",
        "full_text": "Amtsgericht München Aktenzeichen: HRA 96805 \nBekannt gemacht am: 20.04.2011 12:00 Uhr\n\n\n\n\nIn ( ) gesetzte Angaben der Anschrift und des Geschäftszweiges erfolgen ohne Gewähr.\nVeränderungen\n13.04.2011\n\nTODOROVI OHG, Eitting, Landkreis Erding, Fliederweg 7, 85462 Eitting. Je eingetreten: Persönlich haftender Gesellschafter: Dimitrov, Tsvetomir, München, *31.03.1981; Dobrev, Diyan Dragnev, München, *31.03.1965; Ivanov, Dimitar Aleksandrov, München, *05.01.1969; Mihaylov, Mihail Vasilev, München, *26.08.1973; Pavlov, Angel Iliev, München, *21.11.1978; Petkov, Ivan Mihaylov, München, *18.02.1968, jeweils von der Vertretung ausgeschlossen.",
        "gesellschafter": null,
        "inhaber": null,
        "name": "TODOROVI OHG",
        "notice_id": "499261",
        "posted_on": "2011-04-20",
        "rechtsform": null,
        "sitz": null,
        "url": "https://www.handelsregisterbekanntmachungen.de/en/skripte/hrb.php?rb_id=499261&land_abk=by"
    },
    "parsed": {
        "officers": [
            {
                "class": "PersonalPartner",
                "payload": {
                    "city": "München",
                    "dob": "1981-03-31",
                    "lastname": "Dimitrov",
                    "name": "Tsvetomir"
                },
                "text": " Dimitrov, Tsvetomir, München, *31.03.1981"
            },
            {
                "class": "PersonalPartner",
                "payload": {
                    "city": "München",
                    "dob": "1965-03-31",
                    "lastname": "Dobrev",
                    "name": "Diyan Dragnev"
                },
                "text": " Dobrev, Diyan Dragnev, München, *31.03.1965"
            },
            {
                "class": "PersonalPartner",
                "payload": {
                    "city": "München",
                    "dob": "1969-01-05",
                    "lastname": "Ivanov",
                    "name": "Dimitar Aleksandrov"
                },
                "text": " Ivanov, Dimitar Aleksandrov, München, *05.01.1969"
            },
            {
                "class": "PersonalPartner",
                "payload": {
                    "city": "München",
                    "dob": "1973-08-26",
                    "lastname": "Mihaylov",
                    "name": "Mihail Vasilev"
                },
                "text": " Mihaylov, Mihail Vasilev, München, *26.08.1973"
            },
            {
                "class": "PersonalPartner",
                "payload": {
                    "city": "München",
                    "dob": "1978-11-21",
                    "lastname": "Pavlov",
                    "name": "Angel Iliev"
                },
                "text": " Pavlov, Angel Iliev, München, *21.11.1978"
            },
            {
                "class": "PersonalPartner",
                "payload": {
                    "city": "München",
                    "dob": "1968-02-18",
                    "flag": "jeweils von der Vertretung ausgeschlossen",
                    "lastname": "Petkov",
                    "name": "Ivan Mihaylov"
                },
                "text": " Petkov, Ivan Mihaylov, München, *18.02.1968, jeweils von der Vertretung ausgeschlossen."
            }
        ]
    }
}