{
    "orig": {
        "aktenzeichen": "HRA 15496",
        "amtsgericht": "Leipzig",
        "event_date": "2008-02-29",
        "event_type": "Neueintragungen",
        "federal_state": "sn",
        "full_text": "Amtsgericht Leipzig Aktenzeichen: HRA 15496 \nBekannt gemacht am: 06.03.2008 22:00 Uhr\n\n\n\n\nDie in () gesetzten Angaben der Geschäftsanschrift und des Unternehmensgegenstandes erfolgen ohne Gewähr.\nNeueintragungen\n29.02.2008\n\nHöffner Möbelgesellschaft GmbH & Co. KG, Taucha (Leipziger Str. 131, 04425 Taucha, Einzelhandel mit Möbeln und anderen Einrichtungsgegenständen). Kommanditgesellschaft. Jeder persönlich haftende Gesellschafter vertritt einzeln. Jeder persönlich haftende Gesellschafter sowie dessen jeweilige Geschäftsführer sind befugt, im Namen der Gesellschaft mit sich im eigenen Namen oder als Vertreter eines Dritten Rechtsgeschäfte vorzunehmen. Persönlich haftender Gesellschafter: Höffner Möbelgesellschaft Beteiligungs-GmbH, Taucha (Amtsgericht Leipzig HRB 23875). Eingetreten: Persönlich haftender Gesellschafter: Rotter, Thomas, Berlin, *27.05.1970, von der Vertretung ausgeschlossen. Entstanden durch formwechselnde Umwandlung der Höffner Möbelgesellschaft Taucha GmbH mit dem Sitz in Taucha (Amtsgericht Leipzig HRB 22684). Als nicht eingetragen wird veröffentlicht: Den Gläubigern der an der Umwandlung beteiligten Rechtsträgern ist, wenn sie binnen sechs Monaten nach dem Tag, an dem die Eintragung der Umwandlung in das Register des Sitzes desjenigen Rechträgers, dessen Gläubiger sie sind, nach § 19 Abs. 3 UmwG als bekannt gemacht gilt, ihren Anspruch nach Grund und Höhe schriftlich anmelden, Sicherheit zu leisten, soweit sie nicht Befriedigung verlangen können. Dieses Recht steht den Gläubigern jedoch nur zu, wenn sie glaubhaft machen, dass durch die Umwandlung die Erfüllung der Forderung gefährdet wird.",
        "gesellschafter": null,
        "inhaber": null,
        "name": "Höffner Möbelgesellschaft GmbH & Co. KG",
        "notice_id": "50276",
        "posted_on": "2008-03-06",
        "rechtsform": null,
        "sitz": null,
        "url": "https://www.handelsregisterbekanntmachungen.de/en/skripte/hrb.php?rb_id=50276&land_abk=sn"
    },
    "parsed": {
        "flags": [
            {
                "flag": "Limited partnership.",
                "text": "Kommanditgesellschaft\\."
            }
        ],
        "officers": [
            {
                "class": "PersonalPartner",
                "payload": {
                    "lastname": "Höffner Möbelgesellschaft Beteiligungs-GmbH",
                    "name": "Taucha (Amtsgericht Leipzig HRB 23875)"
                },
                "text": " Höffner Möbelgesellschaft Beteiligungs-GmbH, Taucha (Amtsgericht Leipzig HRB 23875)."
            },
            {
                "class": "PersonalPartner",
                "payload": {
                    "city": "Berlin",
                    "dob": "1970-05-27",
                    "flag": "von der Vertretung ausgeschlossen",
                    "lastname": "Rotter",
                    "name": "Thomas"
                },
                "text": " Rotter, Thomas, Berlin, *27.05.1970, von der Vertretung ausgeschlossen."
            }
        ]
    }
}