{
    "orig": {
        "aktenzeichen": "HRB 10613",
        "amtsgericht": "Wiesbaden",
        "event_date": "2016-10-11",
        "event_type": "Veränderungen",
        "federal_state": "he",
        "full_text": "Amtsgericht Wiesbaden Aktenzeichen: HRB 10613 \nBekannt gemacht am: 11.10.2016 22:02 Uhr\n\n\n\n\nVeröffentlichungen des Amtsgerichts Wiesbaden\n\n\nIn () gesetzte Angaben der Anschrift und des Geschäftszweiges erfolgen ohne Gewähr.\nVeränderungen\n11.10.2016\n\nHRB 10613: Kalle Auslandsbeteiligungen GmbH, Wiesbaden, Rheingaustraße 190-196, 65203 Wiesbaden. Bestellt als Geschäftsführer: Burgheim, Johannes, Frankfurt am Main, *13.08.1978; Weidenfeld, Jörg, Ruhpolding, *26.09.1976, jeweils einzelvertretungsberechtigt; mit der Befugnis, im Namen der Gesellschaft mit sich als Vertreter eines Dritten Rechtsgeschäfte abzuschließen. Nicht mehr Geschäftsführer: Graf Haller von Hallerstein, Lorenz, Bad Homburg, *26.10.1959.",
        "gesellschafter": null,
        "inhaber": null,
        "name": "HRB 10613: Kalle Auslandsbeteiligungen GmbH",
        "notice_id": "507907",
        "posted_on": "2016-10-11",
        "rechtsform": null,
        "sitz": null,
        "url": "https://www.handelsregisterbekanntmachungen.de/en/skripte/hrb.php?rb_id=507907&land_abk=he"
    },
    "parsed": {
        "errors": [
            {
                "kls": "ParsingError",
                "text": "Cannot parse a AppointedManagingDirector from  mit der Befugnis, im Namen der Gesellschaft mit sich als Vertreter eines Dritten Rechtsgeschäfte abzuschließen., error text was Name is too long: im Namen der Gesellschaft mit sich als Vertreter eines Dritten Rechtsgeschäfte abzuschließen"
            }
        ],
        "officers": [
            {
                "class": "AppointedManagingDirector",
                "payload": {
                    "city": "Frankfurt am Main",
                    "dob": "1978-08-13",
                    "lastname": "Burgheim",
                    "name": "Johannes"
                },
                "text": " Burgheim, Johannes, Frankfurt am Main, *13.08.1978"
            },
            {
                "class": "AppointedManagingDirector",
                "payload": {
                    "city": "Ruhpolding",
                    "dob": "1976-09-26",
                    "flag": "jeweils einzelvertretungsberechtigt",
                    "lastname": "Weidenfeld",
                    "name": "Jörg"
                },
                "text": " Weidenfeld, Jörg, Ruhpolding, *26.09.1976, jeweils einzelvertretungsberechtigt"
            },
            {
                "class": "DismissedManagingDirector",
                "payload": {
                    "city": "Bad Homburg",
                    "dismissed": true,
                    "dob": "1959-10-26",
                    "lastname": "Graf Haller von Hallerstein",
                    "name": "Lorenz"
                },
                "text": " Graf Haller von Hallerstein, Lorenz, Bad Homburg, *26.10.1959."
            }
        ]
    }
}