{
    "orig": {
        "aktenzeichen": "HRB 41438",
        "amtsgericht": "Darmstadt",
        "event_date": "2016-10-13",
        "event_type": "Veränderungen",
        "federal_state": "he",
        "full_text": "Amtsgericht Darmstadt Aktenzeichen: HRB 41438 \nBekannt gemacht am: 13.10.2016 22:01 Uhr\n\n\n\n\nVeröffentlichungen des Amtsgerichts Darmstadt\n\n\nIn () gesetzte Angaben der Anschrift und des Geschäftszweiges erfolgen ohne Gewähr.\nVeränderungen\n13.10.2016\n\nHRB 41438: Centre for Pharmaceutical Research GmbH, Mörlenbach, Groß-Breitenbach 60, 69509 Mörlenbach. Geschäftsanschrift: Groß-Breitenbach 60, 69509 Mörlenbach. Nicht mehr Geschäftsführer: Kreissl, Hans-Jürgen, Herisau, Schweiz, *01.08.1956. Bestellt als Geschäftsführerin: Glas, Barbara, Pfäffikon / Schweiz, *11.09.1968, einzelvertretungsberechtigt; mit der Befugnis, im Namen der Gesellschaft mit sich im eigenen Namen oder als Vertreter eines Dritten Rechtsgeschäfte abzuschließen.",
        "gesellschafter": null,
        "inhaber": null,
        "name": "HRB 41438: Centre for Pharmaceutical Research GmbH",
        "notice_id": "508261",
        "posted_on": "2016-10-13",
        "rechtsform": null,
        "sitz": null,
        "url": "https://www.handelsregisterbekanntmachungen.de/en/skripte/hrb.php?rb_id=508261&land_abk=he"
    },
    "parsed": {
        "flags": [
            {
                "flag": "with the power to enter into legal transactions on behalf of the Company with itself or as a representative of a third party",
                "text": "mit\\ der\\ Befugnis\\,\\ im\\ Namen\\ der\\ Gesellschaft\\ mit\\ sich\\ im\\ eigenen\\ Namen\\ oder\\ als\\ Vertreter\\ eines\\ Dritten\\ Rechtsgesch\\äfte\\ abzuschlie\\ßen\\."
            }
        ],
        "labels": [
            {
                "label": "address",
                "text": " Groß-Breitenbach 60, 69509 Mörlenbach."
            }
        ],
        "officers": [
            {
                "class": "DismissedManagingDirector",
                "payload": {
                    "city": "Schweiz",
                    "dismissed": true,
                    "dob": "1956-08-01",
                    "lastname": "Kreissl",
                    "name": "Hans-Jürgen",
                    "position": "Herisau"
                },
                "text": " Kreissl, Hans-Jürgen, Herisau, Schweiz, *01.08.1956."
            },
            {
                "class": "ManagingDirector",
                "payload": {
                    "city": "Pfäffikon / Schweiz",
                    "dob": "1968-09-11",
                    "flag": "sole representation",
                    "lastname": "Glas",
                    "name": "Barbara"
                },
                "text": " Glas, Barbara, Pfäffikon / Schweiz, *11.09.1968, einzelvertretungsberechtigt"
            },
            {
                "class": "ManagingDirector",
                "payload": {
                    "lastname": "mit der Befugnis",
                    "name": "im Namen der Gesellschaft mit sich im eigenen Namen oder als Vertreter eines Dritten Rechtsgeschäfte abzuschließen"
                },
                "text": " mit der Befugnis, im Namen der Gesellschaft mit sich im eigenen Namen oder als Vertreter eines Dritten Rechtsgeschäfte abzuschließen."
            }
        ]
    }
}