{
    "orig": {
        "aktenzeichen": "HRB 14327",
        "amtsgericht": "Frankfurt am Main",
        "event_date": "2007-07-25",
        "event_type": "Veränderungen",
        "federal_state": "he",
        "full_text": "Amtsgericht Frankfurt am Main Aktenzeichen: HRB 14327 \nBekannt gemacht am: 30.07.2007 08:16 Uhr\n\n\n\n\nVeröffentlichungen des Amtsgerichts Frankfurt am Main\r\r\rDie in () gesetzten Angaben der Geschäftsanschrift und des Geschäftszweiges erfolgen ohne Gewähr.\nVeränderungen\n25.07.2007\n\nWitt Gesellschaft mit beschränkter Haftung, Kriftel (Gartenstraße 1, 65830 Kriftel). Nicht mehr Geschäftsführer: Witt, Johannes, Kaufmann, Kriftel. Bestellt als Geschäftsführer: Adam, Patrick, Paris/ Frankreich, *26.01.1955, einzelvertretungsberechtigt; mit der Befugnis, im Namen der Gesellschaft mit sich im eigenen Namen oder als Vertreter eines Dritten Rechtsgeschäfte abzuschließen. Gesamtprokura gemeinsam mit einem Geschäftsführer oder einem anderen Prokuristen: Roger-Kouyoumdjan, Johann Georges Stéphane, Versailles/ Frankreich, *21.11.1974.",
        "gesellschafter": null,
        "inhaber": null,
        "name": "Witt Gesellschaft mit beschränkter Haftung",
        "notice_id": "51244",
        "posted_on": "2007-07-30",
        "rechtsform": null,
        "sitz": null,
        "url": "https://www.handelsregisterbekanntmachungen.de/en/skripte/hrb.php?rb_id=51244&land_abk=he"
    },
    "parsed": {
        "flags": [
            {
                "flag": "with the power to enter into legal transactions on behalf of the Company with itself or as a representative of a third party",
                "text": "mit\\ der\\ Befugnis\\,\\ im\\ Namen\\ der\\ Gesellschaft\\ mit\\ sich\\ im\\ eigenen\\ Namen\\ oder\\ als\\ Vertreter\\ eines\\ Dritten\\ Rechtsgesch\\äfte\\ abzuschlie\\ßen\\."
            }
        ],
        "officers": [
            {
                "class": "DismissedManagingDirector",
                "payload": {
                    "city": "Kriftel",
                    "dismissed": true,
                    "lastname": "Witt",
                    "name": "Johannes",
                    "position": "Kaufmann"
                },
                "text": " Witt, Johannes, Kaufmann, Kriftel."
            },
            {
                "class": "AppointedManagingDirector",
                "payload": {
                    "city": "Paris/ Frankreich",
                    "dob": "1955-01-26",
                    "flag": "sole representation",
                    "lastname": "Adam",
                    "name": "Patrick"
                },
                "text": " Adam, Patrick, Paris/ Frankreich, *26.01.1955, einzelvertretungsberechtigt"
            },
            {
                "class": "AppointedManagingDirector",
                "payload": {
                    "lastname": "mit der Befugnis",
                    "name": "im Namen der Gesellschaft mit sich im eigenen Namen oder als Vertreter eines Dritten Rechtsgeschäfte abzuschließen"
                },
                "text": " mit der Befugnis, im Namen der Gesellschaft mit sich im eigenen Namen oder als Vertreter eines Dritten Rechtsgeschäfte abzuschließen."
            },
            {
                "class": "CommonProcuration",
                "payload": {
                    "city": "Versailles/ Frankreich",
                    "dob": "1974-11-21",
                    "lastname": "Roger-Kouyoumdjan",
                    "name": "Johann Georges Stéphane"
                },
                "text": " Roger-Kouyoumdjan, Johann Georges Stéphane, Versailles/ Frankreich, *21.11.1974."
            }
        ]
    }
}