{
    "orig": {
        "aktenzeichen": "HRB 36649",
        "amtsgericht": "Düsseldorf",
        "event_date": "2010-01-14",
        "event_type": "Veränderungen",
        "federal_state": "nw",
        "full_text": "Amtsgericht Düsseldorf Aktenzeichen: HRB 36649 \nBekannt gemacht am: 19.01.2010 12:00 Uhr\n\n\n\n\nIn () gesetzte Angaben der Anschrift und des Geschäftszweiges erfolgen ohne Gewähr.\nVeränderungen\n14.01.2010\n\nTARES Beteiligungsgesellschaft mbH, Düsseldorf, Königsallee 106, 40215 Düsseldorf.Nicht mehr Geschäftsführer: Seck, Klauspeter, Erkrath, *11.04.1960. Bestellt als Geschäftsführer: Rosendahl, Harald, Düsseldorf, *30.05.1962, mit der Befugnis im Namen der Gesellschaft mit sich im eigenen Namen oder als Vertreter eines Dritten Rechtsgeschäfte abzuschließen. Gesamtprokura gemeinsam mit einem Geschäftsführer oder einem anderen Prokuristen mit der Befugnis im Namen der Gesellschaft mit sich im eigenen Namen oder als Vertreter eines Dritten Rechtsgeschäfte abzuschließen mit der Ermächtigung zur Veräußerung und Belastung von Grundstücken: Seck, Klauspeter, Erkrath, *11.04.1960.",
        "gesellschafter": null,
        "inhaber": null,
        "name": "TARES Beteiligungsgesellschaft mbH",
        "notice_id": "512977",
        "posted_on": "2010-01-19",
        "rechtsform": null,
        "sitz": null,
        "url": "https://www.handelsregisterbekanntmachungen.de/en/skripte/hrb.php?rb_id=512977&land_abk=nw"
    },
    "parsed": {
        "officers": [
            {
                "class": "DismissedManagingDirector",
                "payload": {
                    "city": "Erkrath",
                    "dismissed": true,
                    "dob": "1960-11-04",
                    "lastname": "Seck",
                    "name": "Klauspeter"
                },
                "text": " Seck, Klauspeter, Erkrath, *11.04.1960."
            },
            {
                "class": "AppointedManagingDirector",
                "payload": {
                    "city": "Düsseldorf",
                    "dob": "1962-05-30",
                    "flag": "mit der Befugnis im Namen der Gesellschaft mit sich im eigenen Namen oder als Vertreter eines Dritten Rechtsgeschäfte abzuschließen",
                    "lastname": "Rosendahl",
                    "name": "Harald"
                },
                "text": " Rosendahl, Harald, Düsseldorf, *30.05.1962, mit der Befugnis im Namen der Gesellschaft mit sich im eigenen Namen oder als Vertreter eines Dritten Rechtsgeschäfte abzuschließen."
            }
        ]
    }
}