{
    "orig": {
        "aktenzeichen": "HRB 6133",
        "amtsgericht": "Recklinghausen",
        "event_date": "2010-03-24",
        "event_type": "Veränderungen",
        "federal_state": "nw",
        "full_text": "Amtsgericht Recklinghausen Aktenzeichen: HRB 6133 \nBekannt gemacht am: 26.03.2010 12:00 Uhr\n\n\n\n\nIn () gesetzte Angaben der Anschrift und des Geschäftszweiges erfolgen ohne Gewähr.\nVeränderungen\n24.03.2010\n\nAD GETRIEBESERVICE & REPARATUR GmbH, Recklinghausen, Carl-Still-Str. 8, 45659 Recklinghausen.Neu bestellt. Geschäftsführer: Koenig, Olaf, Mülheim, *27.04.1944, einzelvertretungsberechtigt mit der Befugnis im Namen der Gesellschaft mit sich im eigenen Namen oder als Vertreter eines Dritten Rechtsgeschäfte abzuschließen. Nicht mehr Geschäftsführer: Lübeck, Marlis, Dessau-Roßlau, *12.05.1954; Schumacher, Stefan, Bochum, *05.09.1967.",
        "gesellschafter": null,
        "inhaber": null,
        "name": "AD GETRIEBESERVICE & REPARATUR GmbH",
        "notice_id": "537506",
        "posted_on": "2010-03-26",
        "rechtsform": null,
        "sitz": null,
        "url": "https://www.handelsregisterbekanntmachungen.de/en/skripte/hrb.php?rb_id=537506&land_abk=nw"
    },
    "parsed": {
        "officers": [
            {
                "class": "ManagingDirector",
                "payload": {
                    "city": "Mülheim",
                    "dob": "1944-04-27",
                    "flag": "einzelvertretungsberechtigt mit der Befugnis im Namen der Gesellschaft mit sich im eigenen Namen oder als Vertreter eines Dritten Rechtsgeschäfte abzuschließen",
                    "lastname": "Koenig",
                    "name": "Olaf"
                },
                "text": " Koenig, Olaf, Mülheim, *27.04.1944, einzelvertretungsberechtigt mit der Befugnis im Namen der Gesellschaft mit sich im eigenen Namen oder als Vertreter eines Dritten Rechtsgeschäfte abzuschließen."
            },
            {
                "class": "DismissedManagingDirector",
                "payload": {
                    "city": "Dessau-Roßlau",
                    "dismissed": true,
                    "dob": "1954-12-05",
                    "lastname": "Lübeck",
                    "name": "Marlis"
                },
                "text": " Lübeck, Marlis, Dessau-Roßlau, *12.05.1954"
            }
        ]
    }
}