{
    "orig": {
        "aktenzeichen": "HRB 5567",
        "amtsgericht": "Siegburg",
        "event_date": "2010-04-08",
        "event_type": "Veränderungen",
        "federal_state": "nw",
        "full_text": "Amtsgericht Siegburg Aktenzeichen: HRB 5567 \nBekannt gemacht am: 12.04.2010 12:00 Uhr\n\n\n\n\nIn () gesetzte Angaben der Anschrift und des Geschäftszweiges erfolgen ohne Gewähr.\nVeränderungen\n08.04.2010\n\nHamacher Industriebedarf GmbH, Neunkirchen-Seelscheid, Hamsterweg 7, 53819 Neunkirchen-Seelscheid.Ist nur ein Liquidator bestellt, so vertritt er die Gesellschaft allein. Sind mehrere Liquidatoren bestellt, so wird die Gesellschaft durch zwei Liquidatoren gemeinschaftlich vertreten. Nicht mehr Geschäftsführer, nunmehr Liquidator: Hamacher, Klaus, Neunkirchen-Seelscheid, *17.05.1940, einzelvertretungsberechtigt mit der Befugnis im Namen der Gesellschaft mit sich im eigenen Namen oder als Vertreter eines Dritten Rechtsgeschäfte abzuschließen. Die Gesellschaft ist durch Gesellschafterbeschluss vom 10.03.2010 mit Wirkung zum 31.03.2010 aufgelöst.",
        "gesellschafter": null,
        "inhaber": null,
        "name": "Hamacher Industriebedarf GmbH",
        "notice_id": "541277",
        "posted_on": "2010-04-12",
        "rechtsform": null,
        "sitz": null,
        "url": "https://www.handelsregisterbekanntmachungen.de/en/skripte/hrb.php?rb_id=541277&land_abk=nw"
    },
    "parsed": {
        "officers": [
            {
                "class": "Liquidator",
                "payload": {
                    "city": "Neunkirchen-Seelscheid",
                    "dob": "1940-05-17",
                    "flag": "einzelvertretungsberechtigt mit der Befugnis im Namen der Gesellschaft mit sich im eigenen Namen oder als Vertreter eines Dritten Rechtsgeschäfte abzuschließen",
                    "lastname": "Hamacher",
                    "name": "Klaus"
                },
                "text": " Hamacher, Klaus, Neunkirchen-Seelscheid, *17.05.1940, einzelvertretungsberechtigt mit der Befugnis im Namen der Gesellschaft mit sich im eigenen Namen oder als Vertreter eines Dritten Rechtsgeschäfte abzuschließen."
            }
        ]
    }
}