{
    "orig": {
        "aktenzeichen": "HRB 11695",
        "amtsgericht": "Bad Oeynhausen",
        "event_date": "2010-04-09",
        "event_type": "Veränderungen",
        "federal_state": "nw",
        "full_text": "Amtsgericht Bad Oeynhausen Aktenzeichen: HRB 11695 \nBekannt gemacht am: 12.04.2010 12:00 Uhr\n\n\n\n\nIn () gesetzte Angaben der Anschrift und des Geschäftszweiges erfolgen ohne Gewähr.\nVeränderungen\n09.04.2010\n\nBachhotel GmbH, Porta Westfalica, Zur Porta 14, 32457 Porta Westfalica.Geschäftsführer: Hayat, Nazir, Fulda, *02.08.1971, einzelvertretungsberechtigt mit der Befugnis im Namen der Gesellschaft mit sich im eigenen Namen oder als Vertreter eines Dritten Rechtsgeschäfte abzuschließen. Nicht mehr Geschäftsführer: Kubiak, Carsten, Fulda, *08.01.1977. Einzelprokura: Heuer, Kirsten, Bad Salzuflen, *16.01.1961.",
        "gesellschafter": null,
        "inhaber": null,
        "name": "Bachhotel GmbH",
        "notice_id": "541401",
        "posted_on": "2010-04-12",
        "rechtsform": null,
        "sitz": null,
        "url": "https://www.handelsregisterbekanntmachungen.de/en/skripte/hrb.php?rb_id=541401&land_abk=nw"
    },
    "parsed": {
        "flags": [
            {
                "flag": "Single procuration",
                "text": "Einzelprokura"
            }
        ],
        "officers": [
            {
                "class": "ManagingDirector",
                "payload": {
                    "city": "Fulda",
                    "dob": "1971-02-08",
                    "flag": "einzelvertretungsberechtigt mit der Befugnis im Namen der Gesellschaft mit sich im eigenen Namen oder als Vertreter eines Dritten Rechtsgeschäfte abzuschließen",
                    "lastname": "Hayat",
                    "name": "Nazir"
                },
                "text": " Hayat, Nazir, Fulda, *02.08.1971, einzelvertretungsberechtigt mit der Befugnis im Namen der Gesellschaft mit sich im eigenen Namen oder als Vertreter eines Dritten Rechtsgeschäfte abzuschließen."
            },
            {
                "class": "DismissedManagingDirector",
                "payload": {
                    "city": "Fulda",
                    "dismissed": true,
                    "dob": "1977-08-01",
                    "lastname": "Kubiak",
                    "name": "Carsten"
                },
                "text": " Kubiak, Carsten, Fulda, *08.01.1977."
            },
            {
                "class": "SingleProcuration",
                "payload": {
                    "city": "Bad Salzuflen",
                    "dob": "1961-01-16",
                    "lastname": "Heuer",
                    "name": "Kirsten"
                },
                "text": " Heuer, Kirsten, Bad Salzuflen, *16.01.1961."
            }
        ]
    }
}