{
    "orig": {
        "aktenzeichen": "HRB 714503",
        "amtsgericht": "Freiburg",
        "event_date": "2016-03-31",
        "event_type": "Neueintragungen",
        "federal_state": "bw",
        "full_text": "Amtsgericht Freiburg Aktenzeichen: HRB 714503 \nBekannt gemacht am: 31.03.2016 10:03 Uhr\n\n\n\n\nIn () gesetzte Angaben der Anschrift und des Geschäftszweiges erfolgen ohne Gewähr:\nNeueintragungen\n31.03.2016\n\nHRB 714503: Tranter GmbH, Schopfheim, Hohe-Flum-Straße 31, 79650 Schopfheim. Gesellschaft mit beschränkter Haftung. Gesellschaftsvertrag vom 01.04.2009 mit Änderung vom 20.11.2012. Die Gesellschafterversammlung vom 01.12.2015 hat die Änderung des Gesellschaftsvertrages in § 1 (Firma und Sitz) beschlossen. Der Sitz ist von Artern (Amtsgericht Jena HRB 504017) nach Schopfheim verlegt. Geschäftsanschrift: Hohe-Flum-Straße 31, 79650 Schopfheim. Zweigniederlassung unter gleicher Firma mit Zusatz: Zweigniederlassung Hildesheim, 31135 Hildesheim, Geschäftsanschrift: Steven 6, 31135 Hildesheim. Aufgehoben als Zweigniederlassung: 79650 Schopfheim, Geschäftsanschrift: Hohe-Flum-Straße 31, 79650 Schopfheim. Gegenstand: Die Herstellung und der Vertrieb von Wärmetauschern und Erzeugnissen der Blechverarbeitung aus Edelstahl. Stammkapital: 300.000,00 EUR. Allgemeine Vertretungsregelung: Ist nur ein Geschäftsführer bestellt, vertritt er allein. Sind mehrere Geschäftsführer bestellt, vertreten zwei gemeinsam oder ein Geschäftsführer mit einem Prokuristen. Einzelvertretungsbefugnis kann erteilt werden. Die Geschäftsführer können von den Beschränkungen des § 181 BGB allgemein befreit werden. Geschäftsführer: Lantz, Torbjörn Bertil, Upplands Väsby / Schweden, *04.11.1965, einzelvertretungsberechtigt mit der Befugnis, im Namen der Gesellschaft mit sich im eigenen Namen oder als Vertreter eines Dritten Rechtsgeschäfte abzuschließen. Gesamtprokura gemeinsam mit einem Geschäftsführer oder einem anderen Prokuristen: Hierholzer, Werner, Steinen, *18.01.1961; Kettner, Jürgen, Schopfheim, *04.07.1955; Maierhofer, Manfred, Guntramsdorf / Österreich, *10.04.1966; Schroeder, Gustavo Alexander, Särö / Schweden, *30.03.1960; Traulsen, Jörg-Michael, Hannover, *24.04.1963. Gesamtprokura gemeinsam mit einem Geschäftsführer oder einem anderen Prokuristen mit der Befugnis, im Namen der Gesellschaft mit sich im eigenen Namen oder als Vertreter eines Dritten Rechtsgeschäfte abzuschließen: Dr. Schiller, Johann, Aumühle, *29.08.1949. Die Gesellschaft hat am 28.10.2009 mit der \"Alfa Laval Holding GmbH\", Glinde (Amtsgericht Lübeck HRB 3134 RE) als herrschender Gesellschaft einen Gewinnabführungsvertrag geschlossen. Die Gesellschafterversammlung hat mit Beschluss vom 28.10.2009 zugestimmt.",
        "gesellschafter": null,
        "inhaber": null,
        "name": "HRB 714503: Tranter GmbH",
        "notice_id": "543360",
        "posted_on": "2016-03-31",
        "rechtsform": null,
        "sitz": null,
        "url": "https://www.handelsregisterbekanntmachungen.de/en/skripte/hrb.php?rb_id=543360&land_abk=bw"
    },
    "parsed": {
        "addresses": [
            {
                "kls": "Address",
                "text": "Hohe-Flum-Straße 31, 79650 Schopfheim"
            },
            {
                "kls": "Address",
                "text": "Steven 6, 31135 Hildesheim"
            },
            {
                "kls": "Address",
                "text": "Hohe-Flum-Straße 31, 79650 Schopfheim"
            }
        ],
        "flags": [
            {
                "flag": "Company with limited liability.",
                "text": "Gesellschaft\\ mit\\ beschr\\änkter\\ Haftung\\."
            },
            {
                "flag": "with the power to enter into legal transactions on behalf of the Company with itself or as a representative of a third party",
                "text": "mit\\ der\\ Befugnis\\,\\ im\\ Namen\\ der\\ Gesellschaft\\ mit\\ sich\\ im\\ eigenen\\ Namen\\ oder\\ als\\ Vertreter\\ eines\\ Dritten\\ Rechtsgesch\\äfte\\ abzuschlie\\ßen\\."
            }
        ],
        "notices": [
            {
                "court": "Jena",
                "from": "Artern",
                "hrb": "HRB 504017",
                "registration": "predecessor",
                "registration_fuzzy": true,
                "text": " ist von Artern (Amtsgericht Jena HRB 504017) nach Schopfheim verlegt.",
                "to": "Schopfheim",
                "used_regex": "from_regex, hrb_regex, to_regex, court_regex"
            }
        ],
        "officers": [
            {
                "class": "ManagingDirector",
                "payload": {
                    "city": "Upplands Väsby / Schweden",
                    "dob": "1965-11-04",
                    "flag": "einzelvertretungsberechtigt mit der Befugnis im Namen der Gesellschaft mit sich im eigenen Namen oder als Vertreter eines Dritten Rechtsgeschäfte abzuschließen",
                    "lastname": "Lantz",
                    "name": "Torbjörn Bertil"
                },
                "text": " Lantz, Torbjörn Bertil, Upplands Väsby / Schweden, *04.11.1965, einzelvertretungsberechtigt mit der Befugnis, im Namen der Gesellschaft mit sich im eigenen Namen oder als Vertreter eines Dritten Rechtsgeschäfte abzuschließen."
            },
            {
                "class": "CommonProcuration",
                "payload": {
                    "city": "Steinen",
                    "dob": "1961-01-18",
                    "lastname": "Hierholzer",
                    "name": "Werner"
                },
                "text": " Hierholzer, Werner, Steinen, *18.01.1961"
            },
            {
                "class": "CommonProcuration",
                "payload": {
                    "city": "Schopfheim",
                    "dob": "1955-07-04",
                    "lastname": "Kettner",
                    "name": "Jürgen"
                },
                "text": " Kettner, Jürgen, Schopfheim, *04.07.1955"
            },
            {
                "class": "CommonProcuration",
                "payload": {
                    "city": "Guntramsdorf / Österreich",
                    "dob": "1966-04-10",
                    "lastname": "Maierhofer",
                    "name": "Manfred"
                },
                "text": " Maierhofer, Manfred, Guntramsdorf / Österreich, *10.04.1966"
            },
            {
                "class": "CommonProcuration",
                "payload": {
                    "city": "Särö / Schweden",
                    "dob": "1960-03-30",
                    "lastname": "Schroeder",
                    "name": "Gustavo Alexander"
                },
                "text": " Schroeder, Gustavo Alexander, Särö / Schweden, *30.03.1960"
            },
            {
                "class": "CommonProcuration",
                "payload": {
                    "city": "Hannover",
                    "dob": "1963-04-24",
                    "lastname": "Traulsen",
                    "name": "Jörg-Michael"
                },
                "text": " Traulsen, Jörg-Michael, Hannover, *24.04.1963."
            }
        ]
    }
}