{
    "orig": {
        "aktenzeichen": "HRB 1185",
        "amtsgericht": "Ansbach",
        "event_date": "2011-11-24",
        "event_type": "Veränderungen",
        "federal_state": "by",
        "full_text": "Amtsgericht Ansbach Aktenzeichen: HRB 1185   \nBekannt gemacht am: 01.12.2011 12:00 Uhr\n\n\n\n\nIn ( ) gesetzte Angaben der Anschrift und des Geschäftszweiges erfolgen ohne Gewähr.\nVeränderungen\n24.11.2011\n\nJeremias GmbH Fachgroßhandel für Schornsteinbedarf, Wassertrüdingen, Opfenrieder Straße 12, 91717 Wassertrüdingen. Bestellt: Geschäftsführer: Geiser, Wolfgang, Herzogenaurach, *11.04.1963; Wissmüller, Christoph, Gunzenhausen, *30.10.1978, jeweils einzelvertretungsberechtigt; mit der Befugnis, im Namen der Gesellschaft mit sich im eigenen Namen oder als Vertreter eines Dritten Rechtsgeschäfte abzuschließen. Prokura erloschen: Geiser, Wolfgang, Herzogenaurach, *11.04.1963. Einzelprokura mit der Befugnis, im Namen der Gesellschaft mit sich im eigenen Namen oder als Vertreter eines Dritten Rechtsgeschäfte abzuschließen: Wening, Alexander, Ansbach, *17.11.1981.",
        "gesellschafter": null,
        "inhaber": null,
        "name": "Jeremias GmbH Fachgroßhandel für Schornsteinbedarf",
        "notice_id": "554487",
        "posted_on": "2011-12-01",
        "rechtsform": null,
        "sitz": null,
        "url": "https://www.handelsregisterbekanntmachungen.de/en/skripte/hrb.php?rb_id=554487&land_abk=by"
    },
    "parsed": {
        "flags": [
            {
                "flag": "with the power to enter into legal transactions on behalf of the Company with itself or as a representative of a third party",
                "text": "mit\\ der\\ Befugnis\\,\\ im\\ Namen\\ der\\ Gesellschaft\\ mit\\ sich\\ im\\ eigenen\\ Namen\\ oder\\ als\\ Vertreter\\ eines\\ Dritten\\ Rechtsgesch\\äfte\\ abzuschlie\\ßen\\."
            },
            {
                "flag": "Single procuration",
                "text": "Einzelprokura"
            }
        ],
        "officers": [
            {
                "class": "AppointedManagingDirector",
                "payload": {
                    "city": "Herzogenaurach",
                    "dob": "1963-04-11",
                    "lastname": "Geiser",
                    "name": "Wolfgang"
                },
                "text": " Geiser, Wolfgang, Herzogenaurach, *11.04.1963"
            },
            {
                "class": "AppointedManagingDirector",
                "payload": {
                    "city": "Gunzenhausen",
                    "dob": "1978-10-30",
                    "flag": "jeweils einzelvertretungsberechtigt",
                    "lastname": "Wissmüller",
                    "name": "Christoph"
                },
                "text": " Wissmüller, Christoph, Gunzenhausen, *30.10.1978, jeweils einzelvertretungsberechtigt"
            },
            {
                "class": "AppointedManagingDirector",
                "payload": {
                    "lastname": "mit der Befugnis",
                    "name": "im Namen der Gesellschaft mit sich im eigenen Namen oder als Vertreter eines Dritten Rechtsgeschäfte abzuschließen"
                },
                "text": " mit der Befugnis, im Namen der Gesellschaft mit sich im eigenen Namen oder als Vertreter eines Dritten Rechtsgeschäfte abzuschließen."
            },
            {
                "class": "ProcurationCancelled",
                "payload": {
                    "city": "Herzogenaurach",
                    "dismissed": true,
                    "dob": "1963-04-11",
                    "lastname": "Geiser",
                    "name": "Wolfgang"
                },
                "text": " Geiser, Wolfgang, Herzogenaurach, *11.04.1963."
            }
        ]
    }
}