{
    "orig": {
        "aktenzeichen": "HRB 15223",
        "amtsgericht": "Duisburg",
        "event_date": "2010-06-17",
        "event_type": "Veränderungen",
        "federal_state": "nw",
        "full_text": "Amtsgericht Duisburg Aktenzeichen: HRB 15223 \nBekannt gemacht am: 18.06.2010 12:00 Uhr\n\n\n\n\nIn () gesetzte Angaben der Anschrift und des Geschäftszweiges erfolgen ohne Gewähr.\nVeränderungen\n17.06.2010\n\nGlobudent O-Dent-O Deutschland GmbH, Mülheim an der Ruhr, Schenkendorfstraße 29, 45472 Mülheim an der Ruhr.Geschäftsanschrift: Schenkendorfstraße 29, 45472 Mülheim an der Ruhr. Ist nur ein Liquidator bestellt, so vertritt er die Gesellschaft allein. Sind mehrere Liquidatoren bestellt, können die Gesellschafter Einzelvertretungsbefugnis erteilen, im übrigen wird die Gesellschaft durch zwei Liquidatoren gemeinsam oder einen Liquidator gemeinsam mit einem Prokuristen vertreten. Nicht mehr Geschäftsführer: Mamisch, Omar John, Essen, *30.04.1975. Neu bestellt als Liquidator: Sommerwerck, Joachim, Tönisvorst, *05.11.1960, mit der Befugnis im Namen der Gesellschaft mit sich im eigenen Namen oder als Vertreter eines Dritten Rechtsgeschäfte abzuschließen. Die Gesellschaft ist aufgelöst.",
        "gesellschafter": null,
        "inhaber": null,
        "name": "Globudent O-Dent-O Deutschland GmbH",
        "notice_id": "562626",
        "posted_on": "2010-06-18",
        "rechtsform": null,
        "sitz": null,
        "url": "https://www.handelsregisterbekanntmachungen.de/en/skripte/hrb.php?rb_id=562626&land_abk=nw"
    },
    "parsed": {
        "flags": [
            {
                "flag": "ignore_for_now",
                "text": "Die\\ Gesellschaft\\ ist\\ aufgel\\öst\\."
            }
        ],
        "labels": [
            {
                "label": "address",
                "text": " Schenkendorfstraße 29, 45472 Mülheim an der Ruhr."
            }
        ],
        "officers": [
            {
                "class": "DismissedManagingDirector",
                "payload": {
                    "city": "Essen",
                    "dismissed": true,
                    "dob": "1975-04-30",
                    "lastname": "Mamisch",
                    "name": "Omar John"
                },
                "text": " Mamisch, Omar John, Essen, *30.04.1975."
            },
            {
                "class": "Liquidator",
                "payload": {
                    "city": "Tönisvorst",
                    "dob": "1960-05-11",
                    "flag": "mit der Befugnis im Namen der Gesellschaft mit sich im eigenen Namen oder als Vertreter eines Dritten Rechtsgeschäfte abzuschließen",
                    "lastname": "Sommerwerck",
                    "name": "Joachim"
                },
                "text": " Sommerwerck, Joachim, Tönisvorst, *05.11.1960, mit der Befugnis im Namen der Gesellschaft mit sich im eigenen Namen oder als Vertreter eines Dritten Rechtsgeschäfte abzuschließen."
            }
        ]
    }
}