{
    "orig": {
        "aktenzeichen": "HRB 48571",
        "amtsgericht": "Offenbach am Main",
        "event_date": "2017-10-30",
        "event_type": "Veränderungen",
        "federal_state": "he",
        "full_text": "Amtsgericht Offenbach am Main Aktenzeichen: HRB 48571 \nBekannt gemacht am: 30.10.2017 22:00 Uhr\n\n\n\n\nVeröffentlichungen des Amtsgerichts Offenbach am Main\n\n\nIn () gesetzte Angaben der Anschrift und des Geschäftszweiges erfolgen ohne Gewähr.\nVeränderungen\n30.10.2017\n\nHRB 48571: Jiang Yu GmbH, Dreieich, Oberdorf 4, 56348 Bornich. Allgemeine Vertretungsregelung von Amts wegen berichtigt, nun: Die Gesellschaft wird durch den/die Liquidator/en vertreten. Personenbezogene Daten von Amts wegen berichtigt, nun: Liquidator: Yang, Yie, Urumqi, Xinjiang / China, *15.01.1973; Zhu, Zhu, Tianjin / China, *10.03.1981. Die Gesellschaft ist aufgrund Eröffnung des Insolvenzverfahrens aufgelöst.",
        "gesellschafter": null,
        "inhaber": null,
        "name": "HRB 48571: Jiang Yu GmbH",
        "notice_id": "563673",
        "posted_on": "2017-10-30",
        "rechtsform": null,
        "sitz": null,
        "url": "https://www.handelsregisterbekanntmachungen.de/en/skripte/hrb.php?rb_id=563673&land_abk=he"
    },
    "parsed": {
        "officers": [
            {
                "class": "Liquidator",
                "payload": {
                    "city": "Xinjiang / China",
                    "dob": "1973-01-15",
                    "lastname": "Yang",
                    "name": "Yie",
                    "position": "Urumqi"
                },
                "text": " Yang, Yie, Urumqi, Xinjiang / China, *15.01.1973"
            }
        ]
    }
}