{
    "orig": {
        "aktenzeichen": "HRB 13864",
        "amtsgericht": "Saarbrücken",
        "event_date": "2016-03-21",
        "event_type": "Veränderungen",
        "federal_state": "sl",
        "full_text": "Amtsgericht Saarbrücken Aktenzeichen: HRB 13864 \nBekannt gemacht am: 21.03.2016 15:44 Uhr\n\n\n\n\nIn () gesetzte Angaben der Anschrift und des Geschäftszweiges erfolgen ohne Gewähr.\nVeränderungen\n21.03.2016\n\nHRB 13864: StahlDesign Koch GmbH, Völklingen, Hochstraße 29, 66292 Riegelsberg. Ist nur ein Liquidator bestellt, so vertritt er die Gesellschaft allein. Sind mehrere Liquidatoren bestellt, so wird die Gesellschaft durch zwei Liquidatoren oder durch einen Liquidator gemeinsam mit einem Prokuristen vertreten. Nicht mehr Geschäftsführer, nun: Liquidator: Koch, Rolf, Riegelsberg, *01.05.1968, einzelvertretungsberechtigt mit der Befugnis im Namen der Gesellschaft mit sich im eigenen Namen oder als Vertreter eines Dritten Rechtsgeschäfte abzuschließen. Die Gesellschafterversammlung vom 17.03.2016 hat die Auflösung der Gesellschaft beschlossen. Änderung zur Geschäftsanschrift: Hochstraße 29, 66292 Riegelsberg.",
        "gesellschafter": null,
        "inhaber": null,
        "name": "HRB 13864: StahlDesign Koch GmbH",
        "notice_id": "56492",
        "posted_on": "2016-03-21",
        "rechtsform": null,
        "sitz": null,
        "url": "https://www.handelsregisterbekanntmachungen.de/en/skripte/hrb.php?rb_id=56492&land_abk=sl"
    },
    "parsed": {
        "labels": [
            {
                "label": "address",
                "text": " Hochstraße 29 , 66292 Riegelsberg ."
            }
        ],
        "officers": [
            {
                "class": "Liquidator",
                "payload": {
                    "city": "Riegelsberg",
                    "dob": "1968-01-05",
                    "flag": "einzelvertretungsberechtigt mit der Befugnis im Namen der Gesellschaft mit sich im eigenen Namen oder als Vertreter eines Dritten Rechtsgeschäfte abzuschließen",
                    "lastname": "Koch",
                    "name": "Rolf"
                },
                "text": " Koch , Rolf , Riegelsberg , * 01.05.1968 , einzelvertretungsberechtigt mit der Befugnis im Namen der Gesellschaft mit sich im eigenen Namen oder als Vertreter eines Dritten Rechtsgeschäfte abzuschließen ."
            }
        ]
    }
}