{
    "orig": {
        "aktenzeichen": "HRB 15404",
        "amtsgericht": "Saarbrücken",
        "event_date": "2016-03-31",
        "event_type": "Veränderungen",
        "federal_state": "sl",
        "full_text": "Amtsgericht Saarbrücken Aktenzeichen: HRB 15404 \nBekannt gemacht am: 31.03.2016 14:14 Uhr\n\n\n\n\nIn () gesetzte Angaben der Anschrift und des Geschäftszweiges erfolgen ohne Gewähr.\nVeränderungen\n31.03.2016\n\nHRB 15404: Atec GmbH, Merzig, Zum Gipsberg 21, 66663 Merzig. Allgemeine Vertretungsregelung: Ist nur ein Liquidator bestellt, so vertritt er die Gesellschaft allein. Sind mehrere Liquidatoren bestellt, so wird die Gesellschaft durch zwei Liquidatoren oder durch einen Liquidator gemeinsam mit einem Prokuristen vertreten. Nicht mehr Geschäftsführer, nun: Liquidator: Grawinkel, Hans-Peter, Merzig, *27.03.1964, einzelvertretungsberechtigt mit der Befugnis im Namen der Gesellschaft mit sich im eigenen Namen oder als Vertreter eines Dritten Rechtsgeschäfte abzuschließen. Die Gesellschafterversammlung vom 21.03.2016 hat die Auflösung der Gesellschaft beschlossen. Geschäftsanschrift: Zum Gipsberg 21, 66663 Merzig.",
        "gesellschafter": null,
        "inhaber": null,
        "name": "HRB 15404: Atec GmbH",
        "notice_id": "56580",
        "posted_on": "2016-03-31",
        "rechtsform": null,
        "sitz": null,
        "url": "https://www.handelsregisterbekanntmachungen.de/en/skripte/hrb.php?rb_id=56580&land_abk=sl"
    },
    "parsed": {
        "addresses": [
            {
                "kls": "Address",
                "text": "Zum Gipsberg 21, 66663 Merzig"
            }
        ],
        "officers": [
            {
                "class": "Liquidator",
                "payload": {
                    "city": "Merzig",
                    "dob": "1964-03-27",
                    "flag": "einzelvertretungsberechtigt mit der Befugnis im Namen der Gesellschaft mit sich im eigenen Namen oder als Vertreter eines Dritten Rechtsgeschäfte abzuschließen",
                    "lastname": "Grawinkel",
                    "name": "Hans-Peter"
                },
                "text": " Grawinkel, Hans-Peter, Merzig, *27.03.1964, einzelvertretungsberechtigt mit der Befugnis im Namen der Gesellschaft mit sich im eigenen Namen oder als Vertreter eines Dritten Rechtsgeschäfte abzuschließen."
            }
        ]
    }
}