{
    "orig": {
        "aktenzeichen": "HRB 15645",
        "amtsgericht": "Augsburg",
        "event_date": "2012-04-30",
        "event_type": "Veränderungen",
        "federal_state": "by",
        "full_text": "Amtsgericht Augsburg Aktenzeichen: HRB 15645   \nBekannt gemacht am: 02.05.2012 12:00 Uhr\n\n\n\n\nIn ( ) gesetzte Angaben der Anschrift und des Geschäftszweiges erfolgen ohne Gewähr.\nVeränderungen\n30.04.2012\n\nZaunbau Echter GmbH, Affing, Von-Grafenreuth-Straße 18, 86444 Affing. Je bestellt: Geschäftsführer: Echter, Alfons, Gersthofen, *02.09.1974; Koller, Eva, Gersthofen, *12.02.1968; jeweils einzelvertretungsberechtigt, mit der Befugnis, im Namen der Gesellschaft mit sich im eigenen Namen oder als Vertreter eines Dritten Rechtsgeschäfte abzuschließen. Ausgeschieden: Geschäftsführer: Echter, Alfons, Schlosser, Affing, *01.03.1943.",
        "gesellschafter": null,
        "inhaber": null,
        "name": "Zaunbau Echter GmbH",
        "notice_id": "594959",
        "posted_on": "2012-05-02",
        "rechtsform": null,
        "sitz": null,
        "url": "https://www.handelsregisterbekanntmachungen.de/en/skripte/hrb.php?rb_id=594959&land_abk=by"
    },
    "parsed": {
        "flags": [
            {
                "flag": "with the power to enter into legal transactions on behalf of the Company with itself or as a representative of a third party",
                "text": "mit\\ der\\ Befugnis\\,\\ im\\ Namen\\ der\\ Gesellschaft\\ mit\\ sich\\ im\\ eigenen\\ Namen\\ oder\\ als\\ Vertreter\\ eines\\ Dritten\\ Rechtsgesch\\äfte\\ abzuschlie\\ßen\\."
            }
        ],
        "officers": [
            {
                "class": "AppointedManagingDirector",
                "payload": {
                    "city": "Gersthofen",
                    "dob": "1974-09-02",
                    "lastname": "Echter",
                    "name": "Alfons"
                },
                "text": " Echter, Alfons, Gersthofen, *02.09.1974"
            },
            {
                "class": "AppointedManagingDirector",
                "payload": {
                    "city": "Gersthofen",
                    "dob": "1968-02-12",
                    "lastname": "Koller",
                    "name": "Eva"
                },
                "text": " Koller, Eva, Gersthofen, *12.02.1968"
            },
            {
                "class": "AppointedManagingDirector",
                "payload": {
                    "city": "im Namen der Gesellschaft mit sich im eigenen Namen oder als Vertreter eines Dritten Rechtsgeschäfte abzuschließen",
                    "lastname": "jeweils einzelvertretungsberechtigt",
                    "name": "mit der Befugnis"
                },
                "text": " jeweils einzelvertretungsberechtigt, mit der Befugnis, im Namen der Gesellschaft mit sich im eigenen Namen oder als Vertreter eines Dritten Rechtsgeschäfte abzuschließen."
            },
            {
                "class": "RetiredManagingDirector",
                "payload": {
                    "city": "Affing",
                    "dismissed": true,
                    "dob": "1943-03-01",
                    "lastname": "Echter",
                    "name": "Alfons",
                    "position": "Schlosser"
                },
                "text": " Echter, Alfons, Schlosser, Affing, *01.03.1943."
            }
        ]
    }
}