{
    "orig": {
        "aktenzeichen": "HRB 14118",
        "amtsgericht": "Montabaur",
        "event_date": "2009-05-14",
        "event_type": "Veränderungen",
        "federal_state": "rp",
        "full_text": "Amtsgericht Montabaur Aktenzeichen: HRB 14118 \nBekannt gemacht am: 25.05.2009 12:00 Uhr\n\n\n\n\nDie in () gesetzten Angaben der Anschrift und des Geschäftszweiges erfolgen ohne Gewähr.\nVeränderungen\n14.05.2009\n\nPexim GmbH, Neuwied, Gönnersdorferstr. 1, 56567 Neuwied.Geschäftsanschrift: Gönnersdorferstr. 1, 56567 Neuwied. Ist nur ein Liquidator bestellt, so vertritt er die Gesellschaft allein. Sind mehrere Liquidatoren bestellt, so wird die Gesellschaft durch zwei Liquidatoren oder durch einen Liquidator gemeinsam mit einem Prokuristen vertreten. Bestellt als Liquidator: Kutschki, Linda Ursula, Andernach, *08.06.1968, mit der Befugnis im Namen der Gesellschaft mit sich im eigenen Namen oder als Vertreter eines Dritten Rechtsgeschäfte abzuschließen.",
        "gesellschafter": null,
        "inhaber": null,
        "name": "Pexim GmbH",
        "notice_id": "60203",
        "posted_on": "2009-05-25",
        "rechtsform": null,
        "sitz": null,
        "url": "https://www.handelsregisterbekanntmachungen.de/en/skripte/hrb.php?rb_id=60203&land_abk=rp"
    },
    "parsed": {
        "labels": [
            {
                "label": "address",
                "text": " Gönnersdorferstr."
            }
        ],
        "officers": [
            {
                "class": "Liquidator",
                "payload": {
                    "city": "Andernach",
                    "dob": "1968-08-06",
                    "flag": "mit der Befugnis im Namen der Gesellschaft mit sich im eigenen Namen oder als Vertreter eines Dritten Rechtsgeschäfte abzuschließen",
                    "lastname": "Kutschki",
                    "name": "Linda Ursula"
                },
                "text": " Kutschki, Linda Ursula, Andernach, *08.06.1968, mit der Befugnis im Namen der Gesellschaft mit sich im eigenen Namen oder als Vertreter eines Dritten Rechtsgeschäfte abzuschließen."
            }
        ]
    }
}