{
    "orig": {
        "aktenzeichen": "HRB 760335",
        "amtsgericht": "Stuttgart",
        "event_date": "2017-03-22",
        "event_type": "Neueintragungen",
        "federal_state": "bw",
        "full_text": "Amtsgericht Stuttgart Aktenzeichen: HRB 760335 \nBekannt gemacht am: 22.03.2017 14:14 Uhr\n\n\n\n\nIn () gesetzte Angaben der Anschrift und des Geschäftszweiges erfolgen ohne Gewähr:\nNeueintragungen\n22.03.2017\n\nHRB 760335: GETEV FS GmbH, Esslingen am Neckar, Weilstraße 227, 73733 Esslingen am Neckar. Gesellschaft mit beschränkter Haftung. Gesellschaftsvertrag vom 24.10.2003. Die Gesellschafterversammlung vom 13.02.2017 hat die Neufassung des Gesellschaftsvertrages beschlossen. Der Sitz ist von Ichenhausen (Amtsgericht Memmingen HRB 11977) nach Esslingen am Neckar verlegt. Firma geändert; nun: Sitz verlegt; nun: Neue Geschäftsanschrift: Weilstraße 227, 73733 Esslingen am Neckar. Gegenstand geändert; nun: Gegenstand: Verwaltung eigenen Vermögens, Erwerb und Verwaltung von Beteiligungen sowie Übernahme der persönlichen Haftung und Geschäftsführung bei Handelsgesellschaften, insbesondere die Beteiligung als persönlich haftende Gesellschafterin an der WD Finanzvermittlungs GmbH & Co KG sowie Erbringung von Dienstleistungen auf dem Gebiet der Gebäudereinigungen, Sonderreinigungen, Unterhaltsreinigungen, Glasreinigungen, Fassadenreinigungen, Winterdienst sowie Handel mit Waren aller Art, soweit hierfür nicht eine besondere Erlaubnis erforderlich ist, insbesondere mit Reinigungs- und Sportartikeln. Stammkapital: 25.000,00 EUR. Allgemeine Vertretungsregelung: Ist nur ein Geschäftsführer bestellt, vertritt er allein. Sind mehrere Geschäftsführer bestellt, vertreten zwei gemeinsam oder ein Geschäftsführer mit einem Prokuristen. Geschäftsführer: Danzl, Michael, Offingen, *04.09.1967; Wenger, Werner, Wittislingen, *27.09.1963. Bestellt als Geschäftsführer: Münz, Axel, Ulm, *19.05.1963, einzelvertretungsberechtigt.",
        "gesellschafter": null,
        "inhaber": null,
        "name": "HRB 760335: GETEV FS GmbH",
        "notice_id": "605305",
        "posted_on": "2017-03-22",
        "rechtsform": null,
        "sitz": null,
        "url": "https://www.handelsregisterbekanntmachungen.de/en/skripte/hrb.php?rb_id=605305&land_abk=bw"
    },
    "parsed": {
        "flags": [
            {
                "flag": "Company with limited liability.",
                "text": "Gesellschaft\\ mit\\ beschr\\änkter\\ Haftung\\."
            }
        ],
        "labels": [
            {
                "label": "address",
                "text": " Weilstraße 227, 73733 Esslingen am Neckar."
            }
        ],
        "notices": [
            {
                "court": "Memmingen",
                "from": "Ichenhausen",
                "hrb": "HRB 11977",
                "registration": "predecessor",
                "registration_fuzzy": true,
                "text": " ist von Ichenhausen (Amtsgericht Memmingen HRB 11977) nach Esslingen am Neckar verlegt.",
                "to": "Esslingen am Neckar",
                "used_regex": "from_regex, hrb_regex, to_regex, court_regex"
            },
            {
                "court": null,
                "registration": null,
                "text": "",
                "used_regex": ""
            }
        ],
        "officers": [
            {
                "class": "ManagingDirector",
                "payload": {
                    "city": "Offingen",
                    "dob": "1967-09-04",
                    "lastname": "Danzl",
                    "name": "Michael"
                },
                "text": " Danzl, Michael, Offingen, *04.09.1967"
            },
            {
                "class": "ManagingDirector",
                "payload": {
                    "city": "Wittislingen",
                    "dob": "1963-09-27",
                    "lastname": "Wenger",
                    "name": "Werner"
                },
                "text": " Wenger, Werner, Wittislingen, *27.09.1963."
            },
            {
                "class": "AppointedManagingDirector",
                "payload": {
                    "city": "Ulm",
                    "dob": "1963-05-19",
                    "flag": "sole representation",
                    "lastname": "Münz",
                    "name": "Axel"
                },
                "text": " Münz, Axel, Ulm, *19.05.1963, einzelvertretungsberechtigt."
            }
        ]
    }
}