{
    "orig": {
        "aktenzeichen": "HRB 49025",
        "amtsgericht": "Düsseldorf",
        "event_date": "2010-10-27",
        "event_type": "Veränderungen",
        "federal_state": "nw",
        "full_text": "Amtsgericht Düsseldorf Aktenzeichen: HRB 49025 \nBekannt gemacht am: 02.11.2010 12:00 Uhr\n\n\n\n\nIn () gesetzte Angaben der Anschrift und des Geschäftszweiges erfolgen ohne Gewähr.\nVeränderungen\n27.10.2010\n\nLingea GmbH, Düsseldorf, Goethestr. 7, 40237 Düsseldorf. Die Gesellschaft ist aufgelöst. Ist nur ein Liquidator bestellt, so vertritt er die Gesellschaft allein. Sind mehrere Liquidatoren bestellt, so vertreten sie die Gesellschaft gemeinsam. Jedem Liquidator kann Einzelvertretungsbefugnis und/oder Befreiung von den Beschränkungen des § 181 BGB erteilt werden. Bestellt als Liquidator: Poppek, Reinhold, Düsseldorf, *13.07.1950; Sevecek, Pavel, Brno/Tschechische Republik, *12.06.1965, jeweils einzelvertretungsberechtigt mit der Befugnis im Namen der Gesellschaft mit sich im eigenen Namen oder als Vertreter eines Dritten Rechtsgeschäfte abzuschließen.",
        "gesellschafter": null,
        "inhaber": null,
        "name": "Lingea GmbH",
        "notice_id": "606797",
        "posted_on": "2010-11-02",
        "rechtsform": null,
        "sitz": null,
        "url": "https://www.handelsregisterbekanntmachungen.de/en/skripte/hrb.php?rb_id=606797&land_abk=nw"
    },
    "parsed": {
        "flags": [
            {
                "flag": "CompanyClosed",
                "text": "Die\\ Gesellschaft\\ ist\\ aufgel\\öst\\."
            }
        ],
        "officers": [
            {
                "class": "Liquidator",
                "payload": {
                    "city": "Düsseldorf",
                    "dob": "1950-07-13",
                    "lastname": "Poppek",
                    "name": "Reinhold"
                },
                "text": " Poppek, Reinhold, Düsseldorf, *13.07.1950"
            },
            {
                "class": "Liquidator",
                "payload": {
                    "city": "Brno/Tschechische Republik",
                    "dob": "1965-06-12",
                    "flag": "jeweils einzelvertretungsberechtigt mit der Befugnis im Namen der Gesellschaft mit sich im eigenen Namen oder als Vertreter eines Dritten Rechtsgeschäfte abzuschließen",
                    "lastname": "Sevecek",
                    "name": "Pavel"
                },
                "text": " Sevecek, Pavel, Brno/Tschechische Republik, *12.06.1965, jeweils einzelvertretungsberechtigt mit der Befugnis im Namen der Gesellschaft mit sich im eigenen Namen oder als Vertreter eines Dritten Rechtsgeschäfte abzuschließen."
            }
        ]
    }
}