{
    "orig": {
        "aktenzeichen": "HRB 8344",
        "amtsgericht": "Kleve",
        "event_date": "2010-11-23",
        "event_type": "Veränderungen",
        "federal_state": "nw",
        "full_text": "Amtsgericht Kleve Aktenzeichen: HRB 8344 \nBekannt gemacht am: 26.11.2010 12:00 Uhr\n\n\n\n\nIn () gesetzte Angaben der Anschrift und des Geschäftszweiges erfolgen ohne Gewähr.\nVeränderungen\n23.11.2010\n\nLC Niederrhein Holding GmbH, Kamp-Lintfort, Saalhoffer Straße 327, 47475 Kamp-Lintfort. Bestellt als Geschäftsführer: Lehmbrock, Heinrich - genannt Heiner -, Kamp-Lintfort, *09.09.1959, einzelvertretungsberechtigt mit der Befugnis im Namen der Gesellschaft mit sich im eigenen Namen oder als Vertreter eines Dritten Rechtsgeschäfte abzuschließen. Nicht mehr Geschäftsführer: Cornelißen, Eckhardt, Rheinberg, *07.07.1961.",
        "gesellschafter": null,
        "inhaber": null,
        "name": "LC Niederrhein Holding GmbH",
        "notice_id": "614509",
        "posted_on": "2010-11-26",
        "rechtsform": null,
        "sitz": null,
        "url": "https://www.handelsregisterbekanntmachungen.de/en/skripte/hrb.php?rb_id=614509&land_abk=nw"
    },
    "parsed": {
        "officers": [
            {
                "class": "AppointedManagingDirector",
                "payload": {
                    "city": "Kamp-Lintfort",
                    "dob": "1959-09-09",
                    "flag": "einzelvertretungsberechtigt mit der Befugnis im Namen der Gesellschaft mit sich im eigenen Namen oder als Vertreter eines Dritten Rechtsgeschäfte abzuschließen",
                    "lastname": "Lehmbrock",
                    "name": "Heinrich - genannt Heiner -"
                },
                "text": " Lehmbrock, Heinrich - genannt Heiner -, Kamp-Lintfort, *09.09.1959, einzelvertretungsberechtigt mit der Befugnis im Namen der Gesellschaft mit sich im eigenen Namen oder als Vertreter eines Dritten Rechtsgeschäfte abzuschließen."
            },
            {
                "class": "DismissedManagingDirector",
                "payload": {
                    "city": "Rheinberg",
                    "dismissed": true,
                    "dob": "1961-07-07",
                    "lastname": "Cornelißen",
                    "name": "Eckhardt"
                },
                "text": " Cornelißen, Eckhardt, Rheinberg, *07.07.1961."
            }
        ]
    }
}