{
    "orig": {
        "aktenzeichen": "HRB 9117",
        "amtsgericht": "Kleve",
        "event_date": "2011-01-17",
        "event_type": "Veränderungen",
        "federal_state": "nw",
        "full_text": "Amtsgericht Kleve Aktenzeichen: HRB 9117 \nBekannt gemacht am: 21.01.2011 12:00 Uhr\n\n\n\n\nIn () gesetzte Angaben der Anschrift und des Geschäftszweiges erfolgen ohne Gewähr.\nVeränderungen\n17.01.2011\n\nTerrazoo gemeinnützige GmbH, Rheinberg, Melkweg 7, 47495 Rheinberg. Durch Beschluss der Gesellschafterversammlung vom 21.12.2010 ist die Gesellschaft aufgelöst. Ist nur ein Liquidator bestellt, vertritt dieser die Gesellschaft allein. Sind mehrere Liquidatoren bestellt, so vertreten sie die Gesellschaft gemeinschaftlich. Die Gesellschafterversammlung kann auch bei Vorhandensein mehrerer Liquidatoren Alleinvertretungsbefugnis erteilen. Dem Liquidator kann Befreiung von § 181 BGB erteilt werden. Nunmehr bestellt als Liquidator: Kahlen, Isabella, Rheinberg, *11.09.1972, einzelvertretungsberechtigt mit der Befugnis im Namen der Gesellschaft mit sich im eigenen Namen oder als Vertreter eines Dritten Rechtsgeschäfte abzuschließen. Gemäß § 3 EGGmbHG von Amts wegen ergänzt als Geschäftsanschrift: Melkweg 7, 47495 Rheinberg.",
        "gesellschafter": null,
        "inhaber": null,
        "name": "Terrazoo gemeinnützige GmbH",
        "notice_id": "634020",
        "posted_on": "2011-01-21",
        "rechtsform": null,
        "sitz": null,
        "url": "https://www.handelsregisterbekanntmachungen.de/en/skripte/hrb.php?rb_id=634020&land_abk=nw"
    },
    "parsed": {
        "labels": [
            {
                "label": "address",
                "text": " Melkweg 7, 47495 Rheinberg."
            }
        ],
        "officers": [
            {
                "class": "Liquidator",
                "payload": {
                    "city": "Rheinberg",
                    "dob": "1972-09-11",
                    "flag": "einzelvertretungsberechtigt mit der Befugnis im Namen der Gesellschaft mit sich im eigenen Namen oder als Vertreter eines Dritten Rechtsgeschäfte abzuschließen",
                    "lastname": "Kahlen",
                    "name": "Isabella"
                },
                "text": " Kahlen, Isabella, Rheinberg, *11.09.1972, einzelvertretungsberechtigt mit der Befugnis im Namen der Gesellschaft mit sich im eigenen Namen oder als Vertreter eines Dritten Rechtsgeschäfte abzuschließen."
            }
        ]
    }
}