{
    "orig": {
        "aktenzeichen": "HRB 101458",
        "amtsgericht": "Saarbrücken",
        "event_date": "2017-11-02",
        "event_type": "Veränderungen",
        "federal_state": "sl",
        "full_text": "Amtsgericht Saarbrücken Aktenzeichen: HRB 101458 \nBekannt gemacht am: 02.11.2017 09:42 Uhr\n\n\n\n\nIn () gesetzte Angaben der Anschrift und des Geschäftszweiges erfolgen ohne Gewähr.\nVeränderungen\n02.11.2017\n\nHRB 101458: T.R.I.O. Tower GmbH, Saarbrücken, Neumühler Weg 14, 66130 Saarbrücken. Die Gesellschafterversammlung vom 06.10.2017 hat eine Änderung des Gesellschaftsvertrages in § 1 (Firma, Sitz) und mit ihr die Sitzverlegung nach St. Ingbert beschlossen. Bestellt als Geschäftsführer: Ritter, Christian, Kaiserslautern, *13.02.1980, einzelvertretungsberechtigt mit der Befugnis im Namen der Gesellschaft mit sich im eigenen Namen oder als Vertreter eines Dritten Rechtsgeschäfte abzuschließen. Nicht mehr Geschäftsführer: Schmeer, Torsten, Saarbrücken, *22.06.1974. Neuer Sitz: St. Ingbert. Geschäftsanschrift: Elversberger Straße 40a, 66386 St. Ingbert.",
        "gesellschafter": null,
        "inhaber": null,
        "name": "HRB 101458: T.R.I.O. Tower GmbH",
        "notice_id": "64551",
        "posted_on": "2017-11-02",
        "rechtsform": null,
        "sitz": null,
        "url": "https://www.handelsregisterbekanntmachungen.de/en/skripte/hrb.php?rb_id=64551&land_abk=sl"
    },
    "parsed": {
        "labels": [
            {
                "label": "address",
                "text": " Elversberger Straße 40a, 66386 St. Ingbert."
            }
        ],
        "notices": [
            {
                "text": " nach St. Ingbert beschlossen.",
                "to": "St. Ingbert",
                "used_regex": "to_regex"
            }
        ],
        "officers": [
            {
                "class": "AppointedManagingDirector",
                "payload": {
                    "city": "Kaiserslautern",
                    "dob": "1980-02-13",
                    "flag": "einzelvertretungsberechtigt mit der Befugnis im Namen der Gesellschaft mit sich im eigenen Namen oder als Vertreter eines Dritten Rechtsgeschäfte abzuschließen",
                    "lastname": "Ritter",
                    "name": "Christian"
                },
                "text": " Ritter, Christian, Kaiserslautern, *13.02.1980, einzelvertretungsberechtigt mit der Befugnis im Namen der Gesellschaft mit sich im eigenen Namen oder als Vertreter eines Dritten Rechtsgeschäfte abzuschließen."
            },
            {
                "class": "DismissedManagingDirector",
                "payload": {
                    "city": "Saarbrücken",
                    "dismissed": true,
                    "dob": "1974-06-22",
                    "lastname": "Schmeer",
                    "name": "Torsten"
                },
                "text": " Schmeer, Torsten, Saarbrücken, *22.06.1974."
            }
        ]
    }
}