{
    "orig": {
        "aktenzeichen": "HRB 799",
        "amtsgericht": "Saarbrücken",
        "event_date": "2017-11-06",
        "event_type": "Veränderungen",
        "federal_state": "sl",
        "full_text": "Amtsgericht Saarbrücken Aktenzeichen: HRB 799 \nBekannt gemacht am: 06.11.2017 13:42 Uhr\n\n\n\n\nIn () gesetzte Angaben der Anschrift und des Geschäftszweiges erfolgen ohne Gewähr.\nVeränderungen\n06.11.2017\n\nHRB 799: Reisebüro Helmut Goetz GmbH, Sulzbach, Sulzbachtalstraße 62, 66280 Sulzbach. Ist nur ein Liquidator bestellt, so vertritt er die Gesellschaft allein. Sind mehrere Liquidatoren bestellt, so wird die Gesellschaft durch die Liquidatoren gemeinsam vertreten. Nicht mehr Geschäftsführer, nun: Liquidator: Färber, Jürgen, Tholey-Scheuern, *11.07.1937, einzelvertretungsberechtigt mit der Befugnis im Namen der Gesellschaft mit sich im eigenen Namen oder als Vertreter eines Dritten Rechtsgeschäfte abzuschließen. Die Gesellschafterversammlung vom 25.07.2017 bzw. 31.07.2017 hat die Auflösung der Gesellschaft beschlossen. Geschäftsanschrift: Sulzbachtalstraße 62, 66280 Sulzbach.",
        "gesellschafter": null,
        "inhaber": null,
        "name": "HRB 799: Reisebüro Helmut Goetz GmbH",
        "notice_id": "64601",
        "posted_on": "2017-11-06",
        "rechtsform": null,
        "sitz": null,
        "url": "https://www.handelsregisterbekanntmachungen.de/en/skripte/hrb.php?rb_id=64601&land_abk=sl"
    },
    "parsed": {
        "addresses": [
            {
                "kls": "Address",
                "text": "Sulzbachtalstraße 62, 66280 Sulzbach"
            }
        ],
        "officers": [
            {
                "class": "Liquidator",
                "payload": {
                    "city": "Tholey-Scheuern",
                    "dob": "1937-07-11",
                    "flag": "einzelvertretungsberechtigt mit der Befugnis im Namen der Gesellschaft mit sich im eigenen Namen oder als Vertreter eines Dritten Rechtsgeschäfte abzuschließen",
                    "lastname": "Färber",
                    "name": "Jürgen"
                },
                "text": " Färber, Jürgen, Tholey-Scheuern, *11.07.1937, einzelvertretungsberechtigt mit der Befugnis im Namen der Gesellschaft mit sich im eigenen Namen oder als Vertreter eines Dritten Rechtsgeschäfte abzuschließen."
            }
        ]
    }
}