{
    "orig": {
        "aktenzeichen": "HRB 19040",
        "amtsgericht": "Duisburg",
        "event_date": "2011-03-18",
        "event_type": "Veränderungen",
        "federal_state": "nw",
        "full_text": "Amtsgericht Duisburg Aktenzeichen: HRB 19040 \nBekannt gemacht am: 25.03.2011 12:00 Uhr\n\n\n\n\nIn () gesetzte Angaben der Anschrift und des Geschäftszweiges erfolgen ohne Gewähr.\nVeränderungen\n18.03.2011\n\nglückspalast GmbH, Duisburg, Schlachthofstraße 7, 47167 Duisburg. Geschäftsanschrift: Schlachthofstraße 7, 47167 Duisburg. Die Gesellschaft hat einen oder mehrere Liquidatoren. Ist nur ein Liquidator bestellt, so vertritt dieser die Gesellschaft allein. Sind mehrere Liquidatoren bestellt, so wird die Gesellschaft durch zwei Liquidatoren gemeinsam vertreten. Durch Gesellschafterbeschluss kann Liquidatoren die Befugnis erteilt werden, die Gesellschaft einzeln zu vertreten oder im Namen der Gesellschaft mit sich im eigenen Namen oder als Vertreter eines Dritten Rechtsgeschäfte vorzunehmen. Nicht mehr Geschäftsführer, nunmehr bestellt als Liquidator: Gürses, Tamer, Dorsten, *06.06.1969, mit der Befugnis im Namen der Gesellschaft mit sich im eigenen Namen oder als Vertreter eines Dritten Rechtsgeschäfte abzuschließen. Prokura erloschen: Geyik, Hüseyin, Essen, *05.10.1964. Die Gesellschaft ist aufgelöst.",
        "gesellschafter": null,
        "inhaber": null,
        "name": "glückspalast GmbH",
        "notice_id": "657301",
        "posted_on": "2011-03-25",
        "rechtsform": null,
        "sitz": null,
        "url": "https://www.handelsregisterbekanntmachungen.de/en/skripte/hrb.php?rb_id=657301&land_abk=nw"
    },
    "parsed": {
        "flags": [
            {
                "flag": "ignore_for_now",
                "text": "Die\\ Gesellschaft\\ ist\\ aufgel\\öst\\."
            }
        ],
        "labels": [
            {
                "label": "address",
                "text": " Schlachthofstraße 7, 47167 Duisburg."
            }
        ],
        "officers": [
            {
                "class": "Liquidator",
                "payload": {
                    "city": "Dorsten",
                    "dob": "1969-06-06",
                    "flag": "mit der Befugnis im Namen der Gesellschaft mit sich im eigenen Namen oder als Vertreter eines Dritten Rechtsgeschäfte abzuschließen",
                    "lastname": "Gürses",
                    "name": "Tamer"
                },
                "text": " Gürses, Tamer, Dorsten, *06.06.1969, mit der Befugnis im Namen der Gesellschaft mit sich im eigenen Namen oder als Vertreter eines Dritten Rechtsgeschäfte abzuschließen."
            },
            {
                "class": "ProcurationCancelled",
                "payload": {
                    "city": "Essen",
                    "dismissed": true,
                    "dob": "1964-05-10",
                    "lastname": "Geyik",
                    "name": "Hüseyin"
                },
                "text": " Geyik, Hüseyin, Essen, *05.10.1964."
            }
        ]
    }
}