{
    "orig": {
        "aktenzeichen": "HRB 16045",
        "amtsgericht": "Neuss",
        "event_date": "2011-04-05",
        "event_type": "Veränderungen",
        "federal_state": "nw",
        "full_text": "Amtsgericht Neuss Aktenzeichen: HRB 16045 \nBekannt gemacht am: 07.04.2011 22:00 Uhr\n\n\n\n\nIn () gesetzte Angaben der Anschrift und des Geschäftszweiges erfolgen ohne Gewähr.\nVeränderungen\n05.04.2011\n\nA & R Stage GmbH, Meerbusch, In der Loh 34c, 40668 Meerbusch. Die Gesellschafterversammlung vom 31. März 2011 hat eine Änderung des Gesellschaftsvertrages in § 1 (Firma, Sitz) und mit ihr die Änderung der Firma beschlossen. Neue Firma: AMA Stage GmbH. Bestellt als Geschäftsführer: Brancusi, Andrei Bogdan, Bukarest/ Rumänien, *10.12.1984, einzelvertretungsberechtigt mit der Befugnis im Namen der Gesellschaft mit sich im eigenen Namen oder als Vertreter eines Dritten Rechtsgeschäfte abzuschließen. Nicht mehr Geschäftsführer: Bilali, Ardijan, Moers, *18.06.1978.",
        "gesellschafter": null,
        "inhaber": null,
        "name": "A & R Stage GmbH",
        "notice_id": "662049",
        "posted_on": "2011-04-07",
        "rechtsform": null,
        "sitz": null,
        "url": "https://www.handelsregisterbekanntmachungen.de/en/skripte/hrb.php?rb_id=662049&land_abk=nw"
    },
    "parsed": {
        "officers": [
            {
                "class": "AppointedManagingDirector",
                "payload": {
                    "city": "Bukarest/ Rumänien",
                    "dob": "1984-10-12",
                    "flag": "einzelvertretungsberechtigt mit der Befugnis im Namen der Gesellschaft mit sich im eigenen Namen oder als Vertreter eines Dritten Rechtsgeschäfte abzuschließen",
                    "lastname": "Brancusi",
                    "name": "Andrei Bogdan"
                },
                "text": " Brancusi, Andrei Bogdan, Bukarest/ Rumänien, *10.12.1984, einzelvertretungsberechtigt mit der Befugnis im Namen der Gesellschaft mit sich im eigenen Namen oder als Vertreter eines Dritten Rechtsgeschäfte abzuschließen."
            },
            {
                "class": "DismissedManagingDirector",
                "payload": {
                    "city": "Moers",
                    "dismissed": true,
                    "dob": "1978-06-18",
                    "lastname": "Bilali",
                    "name": "Ardijan"
                },
                "text": " Bilali, Ardijan, Moers, *18.06.1978."
            }
        ]
    }
}