{
    "orig": {
        "aktenzeichen": "HRB 1931",
        "amtsgericht": "Duisburg",
        "event_date": "2011-05-13",
        "event_type": "Veränderungen",
        "federal_state": "nw",
        "full_text": "Amtsgericht Duisburg Aktenzeichen: HRB 1931 \nBekannt gemacht am: 20.05.2011 12:00 Uhr\n\n\n\n\nIn () gesetzte Angaben der Anschrift und des Geschäftszweiges erfolgen ohne Gewähr.\nVeränderungen\n13.05.2011\n\nBiBA Gesellschaft mit beschränkter Haftung, Duisburg, Daimlerstraße 3, 47167 Duisburg. Nach Änderung des Vornamens und der besonderen Vertretungsbefugnis weiterhin Geschäftsführer: Grünwald, Beatrice Monika, Mülheim an der Ruhr, *18.08.1966, vertretungsberechtigt gemeinsam mit dem Geschäftsführer Oliver Kessel. Nach Änderung der besonderen Vertretungsbefugnis weiterhin Geschäftsführer: von Lonski, Norbert, Kehl, *12.11.1962, vertretungsberechtigt gemeinsam mit dem Geschäftsführer Oliver Kessel.",
        "gesellschafter": null,
        "inhaber": null,
        "name": "BiBA Gesellschaft mit beschränkter Haftung",
        "notice_id": "675780",
        "posted_on": "2011-05-20",
        "rechtsform": null,
        "sitz": null,
        "url": "https://www.handelsregisterbekanntmachungen.de/en/skripte/hrb.php?rb_id=675780&land_abk=nw"
    },
    "parsed": {
        "officers": [
            {
                "class": "ManagingDirector",
                "payload": {
                    "city": "Mülheim an der Ruhr",
                    "dob": "1966-08-18",
                    "flag": "vertretungsberechtigt gemeinsam mit dem Geschäftsführer Oliver Kessel",
                    "lastname": "Grünwald",
                    "name": "Beatrice Monika"
                },
                "text": " Grünwald, Beatrice Monika, Mülheim an der Ruhr, *18.08.1966, vertretungsberechtigt gemeinsam mit dem Geschäftsführer Oliver Kessel."
            },
            {
                "class": "ManagingDirector",
                "payload": {
                    "city": "Kehl",
                    "dob": "1962-12-11",
                    "flag": "vertretungsberechtigt gemeinsam mit dem Geschäftsführer Oliver Kessel",
                    "lastname": "von Lonski",
                    "name": "Norbert"
                },
                "text": " von Lonski, Norbert, Kehl, *12.11.1962, vertretungsberechtigt gemeinsam mit dem Geschäftsführer Oliver Kessel."
            }
        ]
    }
}