{
    "orig": {
        "aktenzeichen": "HRB 9921",
        "amtsgericht": "Bad Oeynhausen",
        "event_date": "2011-05-20",
        "event_type": "Veränderungen",
        "federal_state": "nw",
        "full_text": "Amtsgericht Bad Oeynhausen Aktenzeichen: HRB 9921 \nBekannt gemacht am: 01.06.2011 22:00 Uhr\n\n\n\n\nIn () gesetzte Angaben der Anschrift und des Geschäftszweiges erfolgen ohne Gewähr.\nVeränderungen\n20.05.2011\n\nEDEKA Minden-Hannover An- und Vermietungs GmbH, Minden, Wittelsbacherallee 61, 32427 Minden. Bestellt als Geschäftsführer: Lackner, Ellen, Hamburg, *30.04.1959, mit der Befugnis im Namen der Gesellschaft mit sich im eigenen Namen oder als Vertreter eines Dritten Rechtsgeschäfte abzuschließen. Gesamtprokura gemeinsam mit einem Geschäftsführer mit der Befugnis im Namen der Gesellschaft mit sich als Vertreter eines Dritten Rechtsgeschäfte abzuschließen: Bruns, Bernd, Minden, *29.11.1960. Prokura erloschen: Koschany, Thomas, Minden, *27.11.1950.",
        "gesellschafter": null,
        "inhaber": null,
        "name": "EDEKA Minden-Hannover An- und Vermietungs GmbH",
        "notice_id": "679540",
        "posted_on": "2011-06-01",
        "rechtsform": null,
        "sitz": null,
        "url": "https://www.handelsregisterbekanntmachungen.de/en/skripte/hrb.php?rb_id=679540&land_abk=nw"
    },
    "parsed": {
        "officers": [
            {
                "class": "AppointedManagingDirector",
                "payload": {
                    "city": "Hamburg",
                    "dob": "1959-04-30",
                    "flag": "mit der Befugnis im Namen der Gesellschaft mit sich im eigenen Namen oder als Vertreter eines Dritten Rechtsgeschäfte abzuschließen",
                    "lastname": "Lackner",
                    "name": "Ellen"
                },
                "text": " Lackner, Ellen, Hamburg, *30.04.1959, mit der Befugnis im Namen der Gesellschaft mit sich im eigenen Namen oder als Vertreter eines Dritten Rechtsgeschäfte abzuschließen."
            },
            {
                "class": "ProcurationCancelled",
                "payload": {
                    "city": "Minden",
                    "dismissed": true,
                    "dob": "1950-11-27",
                    "lastname": "Koschany",
                    "name": "Thomas"
                },
                "text": " Koschany, Thomas, Minden, *27.11.1950."
            }
        ]
    }
}