{
    "orig": {
        "aktenzeichen": "HRB 51903",
        "amtsgericht": "München",
        "event_date": "2013-05-24",
        "event_type": "Veränderungen",
        "federal_state": "by",
        "full_text": "Amtsgericht München Aktenzeichen: HRB 51903   \nBekannt gemacht am: 29.05.2013 12:00 Uhr\n\n\n\n\nIn ( ) gesetzte Angaben der Anschrift und des Geschäftszweiges erfolgen ohne Gewähr.\nVeränderungen\n24.05.2013\n\nBöhm & Meinl GmbH, Geretsried, Landkreis Bad Tölz-Wolfratshausen, Isardamm 133, 82538 Geretsried. Ausgeschieden: Geschäftsführer: Meinl, Gerhard, technischer Angestellter, Wolfratshausen. Bestellt: Geschäftsführer: Merold, Andrea, Wolfratshausen, *02.11.1961, einzelvertretungsberechtigt; mit der Befugnis, im Namen der Gesellschaft mit sich im eigenen Namen oder als Vertreter eines Dritten Rechtsgeschäfte abzuschließen.",
        "gesellschafter": null,
        "inhaber": null,
        "name": "Böhm & Meinl GmbH",
        "notice_id": "693470",
        "posted_on": "2013-05-29",
        "rechtsform": null,
        "sitz": null,
        "url": "https://www.handelsregisterbekanntmachungen.de/en/skripte/hrb.php?rb_id=693470&land_abk=by"
    },
    "parsed": {
        "flags": [
            {
                "flag": "with the power to enter into legal transactions on behalf of the Company with itself or as a representative of a third party",
                "text": "mit\\ der\\ Befugnis\\,\\ im\\ Namen\\ der\\ Gesellschaft\\ mit\\ sich\\ im\\ eigenen\\ Namen\\ oder\\ als\\ Vertreter\\ eines\\ Dritten\\ Rechtsgesch\\äfte\\ abzuschlie\\ßen\\."
            }
        ],
        "officers": [
            {
                "class": "RetiredManagingDirector",
                "payload": {
                    "city": "Wolfratshausen",
                    "dismissed": true,
                    "lastname": "Meinl",
                    "name": "Gerhard",
                    "position": "technischer Angestellter"
                },
                "text": " Meinl, Gerhard, technischer Angestellter, Wolfratshausen."
            },
            {
                "class": "AppointedManagingDirector",
                "payload": {
                    "city": "Wolfratshausen",
                    "dob": "1961-11-02",
                    "flag": "sole representation",
                    "lastname": "Merold",
                    "name": "Andrea"
                },
                "text": " Merold, Andrea, Wolfratshausen, *02.11.1961, einzelvertretungsberechtigt"
            },
            {
                "class": "AppointedManagingDirector",
                "payload": {
                    "lastname": "mit der Befugnis",
                    "name": "im Namen der Gesellschaft mit sich im eigenen Namen oder als Vertreter eines Dritten Rechtsgeschäfte abzuschließen"
                },
                "text": " mit der Befugnis, im Namen der Gesellschaft mit sich im eigenen Namen oder als Vertreter eines Dritten Rechtsgeschäfte abzuschließen."
            }
        ]
    }
}