{
    "orig": {
        "aktenzeichen": "HRB 101576",
        "amtsgericht": "Hildesheim",
        "event_date": "2009-01-15",
        "event_type": "Veränderungen",
        "federal_state": "ni",
        "full_text": "Amtsgericht Hildesheim Aktenzeichen: HRB 101576 \nBekannt gemacht am: 21.01.2009 12:00 Uhr\n\n\n\n\nIn () gesetzte Angaben der Anschrift und des Geschäftszweiges erfolgen ohne Gewähr.\nVeränderungen\n15.01.2009\n\nWindstrom Projekt GmbH, Edemissen, Am Torfstich 11, 31234 Edemissen.Geschäftsanschrift: Am Torfstich 11, 31234 Edemissen. Nicht mehr Geschäftsführer: Buß-Lissek, Gerold, Diepholz, *01.08.1954; Glander, Wilfried, Hannover, *03.10.1955; Rieken, Rolf, Edemissen, *14.10.1961; Schmidt, Ralf, Müden, *23.10.1960. Geändert, nun: Geschäftsführer: Mrotzek, Joachim, Großenkneten, *30.10.1960; Warneboldt, Steffen, Adenbüttel, *06.07.1967, jeweils einzelvertretungsberechtigt; mit der Befugnis, im Namen der Gesellschaft mit sich im eigenen Namen oder als Vertreter eines Dritten Rechtsgeschäfte abzuschließen.",
        "gesellschafter": null,
        "inhaber": null,
        "name": "Windstrom Projekt GmbH",
        "notice_id": "72935",
        "posted_on": "2009-01-21",
        "rechtsform": null,
        "sitz": null,
        "url": "https://www.handelsregisterbekanntmachungen.de/en/skripte/hrb.php?rb_id=72935&land_abk=ni"
    },
    "parsed": {
        "addresses": [
            {
                "kls": "Address",
                "text": "Am Torfstich 11, 31234 Edemissen"
            }
        ],
        "errors": [
            {
                "kls": "ParsingError",
                "text": "Cannot parse a ManagingDirector from  mit der Befugnis, im Namen der Gesellschaft mit sich im eigenen Namen oder als Vertreter eines Dritten Rechtsgeschäfte abzuschließen., error text was Name is too long: im Namen der Gesellschaft mit sich im eigenen Namen oder als Vertreter eines Dritten Rechtsgeschäfte abzuschließen"
            }
        ],
        "flags": [
            {
                "flag": "with the power to enter into legal transactions on behalf of the Company with itself or as a representative of a third party",
                "text": "mit\\ der\\ Befugnis\\,\\ im\\ Namen\\ der\\ Gesellschaft\\ mit\\ sich\\ im\\ eigenen\\ Namen\\ oder\\ als\\ Vertreter\\ eines\\ Dritten\\ Rechtsgesch\\äfte\\ abzuschlie\\ßen\\."
            }
        ],
        "officers": [
            {
                "class": "DismissedManagingDirector",
                "payload": {
                    "city": "Diepholz",
                    "dismissed": true,
                    "dob": "1954-08-01",
                    "lastname": "Buß-Lissek",
                    "name": "Gerold"
                },
                "text": " Buß-Lissek, Gerold, Diepholz, *01.08.1954"
            },
            {
                "class": "DismissedManagingDirector",
                "payload": {
                    "city": "Hannover",
                    "dismissed": true,
                    "dob": "1955-10-03",
                    "lastname": "Glander",
                    "name": "Wilfried"
                },
                "text": " Glander, Wilfried, Hannover, *03.10.1955"
            },
            {
                "class": "DismissedManagingDirector",
                "payload": {
                    "city": "Edemissen",
                    "dismissed": true,
                    "dob": "1961-10-14",
                    "lastname": "Rieken",
                    "name": "Rolf"
                },
                "text": " Rieken, Rolf, Edemissen, *14.10.1961"
            },
            {
                "class": "DismissedManagingDirector",
                "payload": {
                    "city": "Müden",
                    "dismissed": true,
                    "dob": "1960-10-23",
                    "lastname": "Schmidt",
                    "name": "Ralf"
                },
                "text": " Schmidt, Ralf, Müden, *23.10.1960."
            },
            {
                "class": "ManagingDirector",
                "payload": {
                    "city": "Großenkneten",
                    "dob": "1960-10-30",
                    "lastname": "Mrotzek",
                    "name": "Joachim"
                },
                "text": " Mrotzek, Joachim, Großenkneten, *30.10.1960"
            },
            {
                "class": "ManagingDirector",
                "payload": {
                    "city": "Adenbüttel",
                    "dob": "1967-07-06",
                    "flag": "jeweils einzelvertretungsberechtigt",
                    "lastname": "Warneboldt",
                    "name": "Steffen"
                },
                "text": " Warneboldt, Steffen, Adenbüttel, *06.07.1967, jeweils einzelvertretungsberechtigt"
            }
        ]
    }
}