{
    "orig": {
        "aktenzeichen": "HRB 2455",
        "amtsgericht": "Coesfeld",
        "event_date": "2012-05-10",
        "event_type": "Löschungen von Amts wegen",
        "federal_state": "nw",
        "full_text": "Amtsgericht Coesfeld Aktenzeichen: HRB 2455   \nBekannt gemacht am: 16.05.2012 22:00 Uhr\n\n\n\n\nIn () gesetzte Angaben der Anschrift und des Geschäftszweiges erfolgen ohne Gewähr.\nLöschungen von Amts wegen\n10.05.2012\n\nPries Bedachungen GmbH, Nottuln, Wellstraße 4, 48301 Nottuln. Bestellt als Geschäftsführer: Pries, Winfried, Nottuln, *15.01.1963, einzelvertretungsberechtigt mit der Befugnis im Namen der Gesellschaft mit sich im eigenen Namen oder als Vertreter eines Dritten Rechtsgeschäfte abzuschließen. Die Gesellschaft ist gemäß § 394 Absatz 1 FamFG wegen Vermögenslosigkeit von Amts wegen gelöscht.",
        "gesellschafter": null,
        "inhaber": null,
        "name": "Pries Bedachungen GmbH",
        "notice_id": "796245",
        "posted_on": "2012-05-16",
        "rechtsform": null,
        "sitz": null,
        "url": "https://www.handelsregisterbekanntmachungen.de/en/skripte/hrb.php?rb_id=796245&land_abk=nw"
    },
    "parsed": {
        "officers": [
            {
                "class": "AppointedManagingDirector",
                "payload": {
                    "city": "Nottuln",
                    "dob": "1963-01-15",
                    "flag": "einzelvertretungsberechtigt mit der Befugnis im Namen der Gesellschaft mit sich im eigenen Namen oder als Vertreter eines Dritten Rechtsgeschäfte abzuschließen",
                    "lastname": "Pries",
                    "name": "Winfried"
                },
                "text": " Pries, Winfried, Nottuln, *15.01.1963, einzelvertretungsberechtigt mit der Befugnis im Namen der Gesellschaft mit sich im eigenen Namen oder als Vertreter eines Dritten Rechtsgeschäfte abzuschließen."
            }
        ]
    }
}