{
    "orig": {
        "aktenzeichen": "HRB 9238",
        "amtsgericht": "Bad Oeynhausen",
        "event_date": "2012-07-19",
        "event_type": "Veränderungen",
        "federal_state": "nw",
        "full_text": "Amtsgericht Bad Oeynhausen Aktenzeichen: HRB 9238   \nBekannt gemacht am: 09.08.2012 12:00 Uhr\n\n\n\n\nIn () gesetzte Angaben der Anschrift und des Geschäftszweiges erfolgen ohne Gewähr.\nVeränderungen\n19.07.2012\n\nJCW Autovermietungs GmbH, Stemwede, Scshröttinghauser Str. 23, 32351 Stemwede-Levern. Berichtigung von Amts wegen zur Geschäftsanschrift: Schröttinghauser Str. 23, 32351 Stemwede. Bestellt als Geschäftsführer: Weitkamp, Jan Christoph, Bad Essen, *20.07.1974, einzelvertretungsberechtigt mit der Befugnis im Namen der Gesellschaft mit sich im eigenen Namen oder als Vertreter eines Dritten Rechtsgeschäfte abzuschließen. Nicht mehr Geschäftsführer: Clamor, Angelika, Kaufmännische Angestellte, Stemwede.",
        "gesellschafter": null,
        "inhaber": null,
        "name": "JCW Autovermietungs GmbH",
        "notice_id": "822380",
        "posted_on": "2012-08-09",
        "rechtsform": null,
        "sitz": null,
        "url": "https://www.handelsregisterbekanntmachungen.de/en/skripte/hrb.php?rb_id=822380&land_abk=nw"
    },
    "parsed": {
        "labels": [
            {
                "label": "address",
                "text": " Schröttinghauser Str."
            }
        ],
        "officers": [
            {
                "class": "AppointedManagingDirector",
                "payload": {
                    "city": "Bad Essen",
                    "dob": "1974-07-20",
                    "flag": "einzelvertretungsberechtigt mit der Befugnis im Namen der Gesellschaft mit sich im eigenen Namen oder als Vertreter eines Dritten Rechtsgeschäfte abzuschließen",
                    "lastname": "Weitkamp",
                    "name": "Jan Christoph"
                },
                "text": " Weitkamp, Jan Christoph, Bad Essen, *20.07.1974, einzelvertretungsberechtigt mit der Befugnis im Namen der Gesellschaft mit sich im eigenen Namen oder als Vertreter eines Dritten Rechtsgeschäfte abzuschließen."
            },
            {
                "class": "DismissedManagingDirector",
                "payload": {
                    "city": "Stemwede",
                    "dismissed": true,
                    "lastname": "Clamor",
                    "name": "Angelika",
                    "position": "Kaufmännische Angestellte"
                },
                "text": " Clamor, Angelika, Kaufmännische Angestellte, Stemwede."
            }
        ]
    }
}