{
    "orig": {
        "aktenzeichen": "HRB 20397",
        "amtsgericht": "Chemnitz",
        "event_date": "2005-07-04",
        "event_type": "Veränderungen",
        "federal_state": "sn",
        "full_text": "Amtsgericht Chemnitz Aktenzeichen: HRB 20397 \nBekannt gemacht am: 07.07.2005 09:14 Uhr\n\n\n\n\nDie in () gesetzten Angaben der Geschäftsanschrift und des  Unternehmensgegenstandes erfolgen ohne Gewähr.\nVeränderungen\n04.07.2005\n\nFrischdienst Union Siebenlehn Vertriebsgesellschaft für Fleisch- und Wurstwaren GmbH, Siebenlehn (Nordstr. 4, 09634 Siebenlehn). Ausgeschieden: Geschäftsführer: Lützow, Siegmund, Burg Stargard, *18.10.1944. Bestellt als Geschäftsführer: Bick, Hartmut, Porta Westfalica, *05.09.1951, mit der Befugnis im Namen der Gesellschaft mit sich im eigenen Namen oder als Vertreter eines Dritten Rechtsgeschäfte abzuschließen.",
        "gesellschafter": null,
        "inhaber": null,
        "name": "Frischdienst Union Siebenlehn Vertriebsgesellschaft für Fleisch- und Wurstwaren GmbH",
        "notice_id": "8232",
        "posted_on": "2005-07-07",
        "rechtsform": null,
        "sitz": null,
        "url": "https://www.handelsregisterbekanntmachungen.de/en/skripte/hrb.php?rb_id=8232&land_abk=sn"
    },
    "parsed": {
        "officers": [
            {
                "class": "RetiredManagingDirector",
                "payload": {
                    "city": "Burg Stargard",
                    "dismissed": true,
                    "dob": "1944-10-18",
                    "lastname": "Lützow",
                    "name": "Siegmund"
                },
                "text": " Lützow, Siegmund, Burg Stargard, *18.10.1944."
            },
            {
                "class": "AppointedManagingDirector",
                "payload": {
                    "city": "Porta Westfalica",
                    "dob": "1951-05-09",
                    "flag": "mit der Befugnis im Namen der Gesellschaft mit sich im eigenen Namen oder als Vertreter eines Dritten Rechtsgeschäfte abzuschließen",
                    "lastname": "Bick",
                    "name": "Hartmut"
                },
                "text": " Bick, Hartmut, Porta Westfalica, *05.09.1951, mit der Befugnis im Namen der Gesellschaft mit sich im eigenen Namen oder als Vertreter eines Dritten Rechtsgeschäfte abzuschließen."
            }
        ]
    }
}