{
    "orig": {
        "aktenzeichen": "HRB 11756",
        "amtsgericht": "Montabaur",
        "event_date": "2010-08-02",
        "event_type": "Veränderungen",
        "federal_state": "rp",
        "full_text": "Amtsgericht Montabaur Aktenzeichen: HRB 11756 \nBekannt gemacht am: 19.08.2010 22:00 Uhr\n\n\n\n\nDie in () gesetzten Angaben der Anschrift und des Geschäftszweiges erfolgen ohne Gewähr.\nVeränderungen\n02.08.2010\n\nHerz Gesellschaft mit beschränkter Haftung Bedachungsartikel und Elektrogeräte-Großhandel, Neuwied, Stadtteil Engers, Neuwieder Str. 27, 56566 Neuwied.Nach Änderung der Vertretungsmacht, jetzt: Geschäftsführer: Herz, Martina, Neuwied, *28.03.1973, einzelvertretungsberechtigt mit der Befugnis im Namen der Gesellschaft mit sich im eigenen Namen oder als Vertreter eines Dritten Rechtsgeschäfte abzuschließen.",
        "gesellschafter": null,
        "inhaber": null,
        "name": "Herz Gesellschaft mit beschränkter Haftung Bedachungsartikel und Elektrogeräte-Großhandel",
        "notice_id": "83593",
        "posted_on": "2010-08-19",
        "rechtsform": null,
        "sitz": null,
        "url": "https://www.handelsregisterbekanntmachungen.de/en/skripte/hrb.php?rb_id=83593&land_abk=rp"
    },
    "parsed": {
        "officers": [
            {
                "class": "ManagingDirector",
                "payload": {
                    "city": "Neuwied",
                    "dob": "1973-03-28",
                    "flag": "einzelvertretungsberechtigt mit der Befugnis im Namen der Gesellschaft mit sich im eigenen Namen oder als Vertreter eines Dritten Rechtsgeschäfte abzuschließen",
                    "lastname": "Herz",
                    "name": "Martina"
                },
                "text": " Herz, Martina, Neuwied, *28.03.1973, einzelvertretungsberechtigt mit der Befugnis im Namen der Gesellschaft mit sich im eigenen Namen oder als Vertreter eines Dritten Rechtsgeschäfte abzuschließen."
            }
        ]
    }
}