{
    "orig": {
        "aktenzeichen": "HRB 56432",
        "amtsgericht": "Köln",
        "event_date": "2005-11-28",
        "event_type": "Veränderungen",
        "federal_state": "nw",
        "full_text": "Amtsgericht Köln Aktenzeichen: HRB 56432 \nBekannt gemacht am: 01.12.2005 11:13 Uhr\n\n\n\n\nDie in () gesetzten Angaben der Geschäftsanschrift und des Geschäftszweiges erfolgen ohne Gewähr.\nVeränderungen\n28.11.2005\n\nKristall 29. GmbH, Köln (c/o Linklaters Oppenhoff & Rädler, Börsenplatz 1, 50667 Köln). Nicht mehr Geschäftsführer: Borcherdt, Antje. Bestellt als Geschäftsführer: Hahr, Andrea, Zürich / Schweiz, *08.12.1972; Kesselring, Daniel, Zürich / Schweiz, *14.05.1964, jeweils einzelvertretungsberechtigt mit der Befugnis im Namen der Gesellschaft mit sich im eigenen Namen oder als Vertreter eines Dritten Rechtsgeschäfte abzuschließen.",
        "gesellschafter": null,
        "inhaber": null,
        "name": "Kristall 29. GmbH",
        "notice_id": "84295",
        "posted_on": "2005-12-01",
        "rechtsform": null,
        "sitz": null,
        "url": "https://www.handelsregisterbekanntmachungen.de/en/skripte/hrb.php?rb_id=84295&land_abk=nw"
    },
    "parsed": {
        "officers": [
            {
                "class": "DismissedManagingDirector",
                "payload": {
                    "dismissed": true,
                    "lastname": "Borcherdt",
                    "name": "Antje"
                },
                "text": " Borcherdt, Antje."
            },
            {
                "class": "AppointedManagingDirector",
                "payload": {
                    "city": "Zürich / Schweiz",
                    "dob": "1972-12-08",
                    "lastname": "Hahr",
                    "name": "Andrea"
                },
                "text": " Hahr, Andrea, Zürich / Schweiz, *08.12.1972"
            },
            {
                "class": "AppointedManagingDirector",
                "payload": {
                    "city": "Zürich / Schweiz",
                    "dob": "1964-05-14",
                    "flag": "jeweils einzelvertretungsberechtigt mit der Befugnis im Namen der Gesellschaft mit sich im eigenen Namen oder als Vertreter eines Dritten Rechtsgeschäfte abzuschließen",
                    "lastname": "Kesselring",
                    "name": "Daniel"
                },
                "text": " Kesselring, Daniel, Zürich / Schweiz, *14.05.1964, jeweils einzelvertretungsberechtigt mit der Befugnis im Namen der Gesellschaft mit sich im eigenen Namen oder als Vertreter eines Dritten Rechtsgeschäfte abzuschließen."
            }
        ]
    }
}