{
    "orig": {
        "aktenzeichen": "HRB 87665",
        "amtsgericht": "Hamburg",
        "event_date": "2009-06-22",
        "event_type": "Veränderungen",
        "federal_state": "hh",
        "full_text": "Amtsgericht Hamburg Aktenzeichen: HRB 87665 \nBekannt gemacht am: 23.06.2009 12:00 Uhr\n\n\n\n\nIn () gesetzte Angaben der Anschrift und des Geschäftszweiges erfolgen ohne Gewähr.\nVeränderungen\n22.06.2009\n\nVerwaltung MS \"SAN ANTONIO\" Schifffahrtsgesellschaft mbH, Hamburg, Van-der-Smissen-Str. 9, 22767 Hamburg.Ausgeschieden Geschäftsführer: Wiebel, Markus, Hamburg, *23.06.1972. Geändert, nun Geschäftsführer: Echevarria von Gusovius, Roberto, Hamburg, *27.11.1960; Rößler, Dirk, Hamburg, *12.03.1971, jeweils vertretungsberechtigt gemeinsam mit einem der Geschäftsführer Michael F. Seidel oder Joachim van Grieken; mit der Befugnis, im Namen der Gesellschaft mit sich im eigenen Namen oder als Vertreter eines Dritten Rechtsgeschäfte abzuschließen.",
        "gesellschafter": null,
        "inhaber": null,
        "name": "Verwaltung MS \"SAN ANTONIO\" Schifffahrtsgesellschaft mbH",
        "notice_id": "84302",
        "posted_on": "2009-06-23",
        "rechtsform": null,
        "sitz": null,
        "url": "https://www.handelsregisterbekanntmachungen.de/en/skripte/hrb.php?rb_id=84302&land_abk=hh"
    },
    "parsed": {
        "flags": [
            {
                "flag": "with the power to enter into legal transactions on behalf of the Company with itself or as a representative of a third party",
                "text": "mit\\ der\\ Befugnis\\,\\ im\\ Namen\\ der\\ Gesellschaft\\ mit\\ sich\\ im\\ eigenen\\ Namen\\ oder\\ als\\ Vertreter\\ eines\\ Dritten\\ Rechtsgesch\\äfte\\ abzuschlie\\ßen\\."
            }
        ],
        "officers": [
            {
                "class": "RetiredManagingDirector",
                "payload": {
                    "city": "Hamburg",
                    "dismissed": true,
                    "dob": "1972-06-23",
                    "lastname": "Wiebel",
                    "name": "Markus"
                },
                "text": " Wiebel, Markus, Hamburg, *23.06.1972."
            },
            {
                "class": "ManagingDirector",
                "payload": {
                    "city": "Hamburg",
                    "dob": "1960-11-27",
                    "lastname": "Echevarria von Gusovius",
                    "name": "Roberto"
                },
                "text": " Echevarria von Gusovius, Roberto, Hamburg, *27.11.1960"
            },
            {
                "class": "ManagingDirector",
                "payload": {
                    "city": "Hamburg",
                    "dob": "1971-03-12",
                    "flag": "jeweils vertretungsberechtigt gemeinsam mit einem der Geschäftsführer Michael F. Seidel oder Joachim van Grieken",
                    "lastname": "Rößler",
                    "name": "Dirk"
                },
                "text": " Rößler, Dirk, Hamburg, *12.03.1971, jeweils vertretungsberechtigt gemeinsam mit einem der Geschäftsführer Michael F. Seidel oder Joachim van Grieken"
            },
            {
                "class": "ManagingDirector",
                "payload": {
                    "lastname": "mit der Befugnis",
                    "name": "im Namen der Gesellschaft mit sich im eigenen Namen oder als Vertreter eines Dritten Rechtsgeschäfte abzuschließen"
                },
                "text": " mit der Befugnis, im Namen der Gesellschaft mit sich im eigenen Namen oder als Vertreter eines Dritten Rechtsgeschäfte abzuschließen."
            }
        ]
    }
}