{
    "orig": {
        "aktenzeichen": "HRB 19119 B",
        "amtsgericht": "Charlottenburg (Berlin)",
        "event_date": "2009-01-05",
        "event_type": "Veränderungen",
        "federal_state": "be",
        "full_text": "Amtsgericht Charlottenburg (Berlin) Aktenzeichen: HRB 19119 B  \nBekannt gemacht am: 07.01.2009 12:00 Uhr\n\n\n\n\nFür die Angaben in (), die den Unternehmensgegenstand und die Anschrift betreffen, keine Gewähr. In das Handelsregister ist folgendes eingetragen worden.\nVeränderungen\n05.01.2009\n\nIngenieurbüro für Bauwesen Professor Polonyi und Fink GmbH, Berlin(Schlüterstr. 42, 10707 Berlin). Vertretungsregelung: Ist ein Liquidator bestellt, vertritt er die Gesellschaft allein. Sind mehrere Liquidatoren bestellt, vertreten sie die Gesellschaft gemeinsam. Änderung zu Nr. 1:; Liquidator:; Fink, Herbert, *27.09.1935, Berlin, Diplom-Ingenieur Rechtsverhaeltnis: Durch Beschluss der Gesellschafterversammlung vom 02.12.2008 ist die Gesellschaft zum 01.01.2009 aufgelöst..",
        "gesellschafter": null,
        "inhaber": null,
        "name": "Ingenieurbüro für Bauwesen Professor Polonyi und Fink GmbH",
        "notice_id": "84842",
        "posted_on": "2009-01-07",
        "rechtsform": null,
        "sitz": null,
        "url": "https://www.handelsregisterbekanntmachungen.de/en/skripte/hrb.php?rb_id=84842&land_abk=be"
    },
    "parsed": {
        "officers": [
            {
                "class": "Liquidator",
                "payload": {
                    "city": "Berlin",
                    "dob": "1935-09-27",
                    "flag": "Diplom-Ingenieur Rechtsverhaeltnis: Durch Beschluss der Gesellschafterversammlung vom 02.12.2008 ist die Gesellschaft zum 01.01.2009 aufgelöst",
                    "lastname": "Fink",
                    "name": "Herbert"
                },
                "text": " Fink, Herbert, *27.09.1935, Berlin, Diplom-Ingenieur Rechtsverhaeltnis: Durch Beschluss der Gesellschafterversammlung vom 02.12.2008 ist die Gesellschaft zum 01.01.2009 aufgelöst.."
            }
        ]
    }
}