{
    "orig": {
        "aktenzeichen": "HRB 13673",
        "amtsgericht": "Dortmund",
        "event_date": "2012-12-19",
        "event_type": "Veränderungen",
        "federal_state": "nw",
        "full_text": "Amtsgericht Dortmund Aktenzeichen: HRB 13673   \nBekannt gemacht am: 21.12.2012 12:00 Uhr\n\n\n\n\nIn () gesetzte Angaben der Anschrift und des Geschäftszweiges erfolgen ohne Gewähr.\nVeränderungen\n19.12.2012\n\nDr. Peters Geschäftsführungs-GmbH, Dortmund, Stockholmer Allee 53, 44269 Dortmund. Nicht mehr Geschäftsführer: Salamon, Jürgen, Dorsten, *02.10.1947. Wohnort und Vertretungsbefugnis geändert, weiterhin Geschäftsführer: Gehling, Anselm, Lüdinghausen, *10.10.1967, einzelvertretungsberechtigt mit der Befugnis im Namen der Gesellschaft mit sich im eigenen Namen oder als Vertreter eines Dritten Rechtsgeschäfte abzuschließen.",
        "gesellschafter": null,
        "inhaber": null,
        "name": "Dr. Peters Geschäftsführungs-GmbH",
        "notice_id": "865113",
        "posted_on": "2012-12-21",
        "rechtsform": null,
        "sitz": null,
        "url": "https://www.handelsregisterbekanntmachungen.de/en/skripte/hrb.php?rb_id=865113&land_abk=nw"
    },
    "parsed": {
        "officers": [
            {
                "class": "DismissedManagingDirector",
                "payload": {
                    "city": "Dorsten",
                    "dismissed": true,
                    "dob": "1947-02-10",
                    "lastname": "Salamon",
                    "name": "Jürgen"
                },
                "text": " Salamon, Jürgen, Dorsten, *02.10.1947."
            },
            {
                "class": "ManagingDirector",
                "payload": {
                    "city": "Lüdinghausen",
                    "dob": "1967-10-10",
                    "flag": "einzelvertretungsberechtigt mit der Befugnis im Namen der Gesellschaft mit sich im eigenen Namen oder als Vertreter eines Dritten Rechtsgeschäfte abzuschließen",
                    "lastname": "Gehling",
                    "name": "Anselm"
                },
                "text": " Gehling, Anselm, Lüdinghausen, *10.10.1967, einzelvertretungsberechtigt mit der Befugnis im Namen der Gesellschaft mit sich im eigenen Namen oder als Vertreter eines Dritten Rechtsgeschäfte abzuschließen."
            }
        ]
    }
}