{
    "orig": {
        "aktenzeichen": "HRB 50318",
        "amtsgericht": "Düsseldorf",
        "event_date": "2013-01-03",
        "event_type": "Veränderungen",
        "federal_state": "nw",
        "full_text": "Amtsgericht Düsseldorf Aktenzeichen: HRB 50318   \nBekannt gemacht am: 08.01.2013 12:00 Uhr\n\n\n\n\nIn () gesetzte Angaben der Anschrift und des Geschäftszweiges erfolgen ohne Gewähr.\nVeränderungen\n03.01.2013\n\nInfrastrukturentwicklungsgesellschaft Hilden mbH, Hilden, Am Rathaus 1, 40721 Hilden. Die Gesellschafterversammlung vom 19.12.2012 hat eine Änderung des Gesellschaftsvertrages in § 2 und damit des Unternehmensgegenstandes und des § 6 bisher 8 ( Geschäftsführung und Vertretung ) beschlossen. Der Gesellschaftsvertrag ist insgesamt neu gefasst. Neuer Unternehmensgegenstand: Der notwendige bzw. zweckmäßige Erwerb, die Verwaltung, die Baureifmachung von Grundstücken und der Bau und die Vermietung von Infrastruktureinrichtungen in Hilden. Nicht mehr Geschäftsführer: Ellendt, Sabine, Düsseldorf, *17.11.1964; Lange, Thomas, Siegburg, *20.06.1963. Bestellt als Geschäftsführer: Klausgrete, Heinrich, Hilden, *15.08.1955; Schneider, Hans-Ullrich, Hilden, *10.08.1965, jeweils mit der Befugnis im Namen der Gesellschaft mit sich im eigenen Namen oder als Vertreter eines Dritten Rechtsgeschäfte abzuschließen.",
        "gesellschafter": null,
        "inhaber": null,
        "name": "Infrastrukturentwicklungsgesellschaft Hilden mbH",
        "notice_id": "869036",
        "posted_on": "2013-01-08",
        "rechtsform": null,
        "sitz": null,
        "url": "https://www.handelsregisterbekanntmachungen.de/en/skripte/hrb.php?rb_id=869036&land_abk=nw"
    },
    "parsed": {
        "officers": [
            {
                "class": "DismissedManagingDirector",
                "payload": {
                    "city": "Düsseldorf",
                    "dismissed": true,
                    "dob": "1964-11-17",
                    "lastname": "Ellendt",
                    "name": "Sabine"
                },
                "text": " Ellendt, Sabine, Düsseldorf, *17.11.1964"
            },
            {
                "class": "DismissedManagingDirector",
                "payload": {
                    "city": "Siegburg",
                    "dismissed": true,
                    "dob": "1963-06-20",
                    "lastname": "Lange",
                    "name": "Thomas"
                },
                "text": " Lange, Thomas, Siegburg, *20.06.1963."
            },
            {
                "class": "AppointedManagingDirector",
                "payload": {
                    "city": "Hilden",
                    "dob": "1955-08-15",
                    "lastname": "Klausgrete",
                    "name": "Heinrich"
                },
                "text": " Klausgrete, Heinrich, Hilden, *15.08.1955"
            },
            {
                "class": "AppointedManagingDirector",
                "payload": {
                    "city": "Hilden",
                    "dob": "1965-08-10",
                    "flag": "jeweils mit der Befugnis im Namen der Gesellschaft mit sich im eigenen Namen oder als Vertreter eines Dritten Rechtsgeschäfte abzuschließen",
                    "lastname": "Schneider",
                    "name": "Hans-Ullrich"
                },
                "text": " Schneider, Hans-Ullrich, Hilden, *10.08.1965, jeweils mit der Befugnis im Namen der Gesellschaft mit sich im eigenen Namen oder als Vertreter eines Dritten Rechtsgeschäfte abzuschließen."
            }
        ]
    }
}