{
    "orig": {
        "aktenzeichen": "HRB 5364",
        "amtsgericht": "Dresden",
        "event_date": "2010-04-13",
        "event_type": "Veränderungen",
        "federal_state": "sn",
        "full_text": "Amtsgericht Dresden Aktenzeichen: HRB 5364 \nBekannt gemacht am: 15.04.2010 12:00 Uhr\n\n\n\n\nDie in () gesetzten Angaben der Geschäftsanschrift und des  Unternehmensgegenstandes erfolgen ohne Gewähr.\nVeränderungen\n13.04.2010\n\nMAINMETALL Großhandelsgesellschaft m. b. H. Bretnig, Bretnig, Gewerbering Nord 3, 01900 Bretnig.Geschäftsanschrift: Gewerbering Nord 3, 01900 Bretnig. Geburtsdatum von Amts wegen ergänzt, nun: Geschäftsführer: Leeger, Thomas, Miltenberg, *01.08.1966; Leeger, Andreas, Miltenberg, *09.04.1958, jeweils einzelvertretungsberechtigt; mit der Befugnis im Namen der Gesellschaft mit sich im eigenen Namen oder als Vertreter eines Dritten Rechtsgeschäfte abzuschließen. Gesamtprokura gemeinsam mit einem Geschäftsführer oder einem anderen Prokuristen: Hartmann, Dirk, Neukirch, *05.01.1976; Stupp, Norbert, Flieden, *17.02.1957.",
        "gesellschafter": null,
        "inhaber": null,
        "name": "MAINMETALL Großhandelsgesellschaft m. b. H. Bretnig",
        "notice_id": "88237",
        "posted_on": "2010-04-15",
        "rechtsform": null,
        "sitz": null,
        "url": "https://www.handelsregisterbekanntmachungen.de/en/skripte/hrb.php?rb_id=88237&land_abk=sn"
    },
    "parsed": {
        "errors": [
            {
                "kls": "ParsingError",
                "text": "Cannot parse a ManagingDirector from  mit der Befugnis im Namen der Gesellschaft mit sich im eigenen Namen oder als Vertreter eines Dritten Rechtsgeschäfte abzuschließen., error text was a person without DOB, number of chunks: 1"
            }
        ],
        "labels": [
            {
                "label": "address",
                "text": " Gewerbering Nord 3, 01900 Bretnig."
            }
        ],
        "officers": [
            {
                "class": "ManagingDirector",
                "payload": {
                    "city": "Miltenberg",
                    "dob": "1966-08-01",
                    "lastname": "Leeger",
                    "name": "Thomas"
                },
                "text": " Leeger, Thomas, Miltenberg, *01.08.1966"
            },
            {
                "class": "ManagingDirector",
                "payload": {
                    "city": "Miltenberg",
                    "dob": "1958-04-09",
                    "flag": "jeweils einzelvertretungsberechtigt",
                    "lastname": "Leeger",
                    "name": "Andreas"
                },
                "text": " Leeger, Andreas, Miltenberg, *09.04.1958, jeweils einzelvertretungsberechtigt"
            },
            {
                "class": "CommonProcuration",
                "payload": {
                    "city": "Neukirch",
                    "dob": "1976-01-05",
                    "lastname": "Hartmann",
                    "name": "Dirk"
                },
                "text": " Hartmann, Dirk, Neukirch, *05.01.1976"
            },
            {
                "class": "CommonProcuration",
                "payload": {
                    "city": "Flieden",
                    "dob": "1957-02-17",
                    "lastname": "Stupp",
                    "name": "Norbert"
                },
                "text": " Stupp, Norbert, Flieden, *17.02.1957."
            }
        ]
    }
}