{
    "orig": {
        "aktenzeichen": "HRB 5238",
        "amtsgericht": "Ludwigshafen a.Rhein (Ludwigshafen)",
        "event_date": "2011-01-10",
        "event_type": "Veränderungen",
        "federal_state": "rp",
        "full_text": "Amtsgericht Ludwigshafen a.Rhein (Ludwigshafen) Aktenzeichen: HRB 5238 \nBekannt gemacht am: 14.01.2011 12:00 Uhr\n\n\n\n\nDie in () gesetzten Angaben der Anschrift und des Geschäftszweiges erfolgen ohne Gewähr.\nVeränderungen\n10.01.2011\n\nAlmatis Holdings GmbH, Ludwigshafen/Rh., Giulinistraße 2, 67065 Ludwigshafen. Nicht mehr Geschäftsführer: Herlinger, Charles, RG10 9TL Hare Hatch, *05.11.1955. Bestellt als Geschäftsführer: Stams, Henning, Friedrichsdorf, *03.06.1963, einzelvertretungsberechtigt mit der Befugnis im Namen der Gesellschaft mit sich im eigenen Namen oder als Vertreter eines Dritten Rechtsgeschäfte abzuschließen.",
        "gesellschafter": null,
        "inhaber": null,
        "name": "Almatis Holdings GmbH",
        "notice_id": "91808",
        "posted_on": "2011-01-14",
        "rechtsform": null,
        "sitz": null,
        "url": "https://www.handelsregisterbekanntmachungen.de/en/skripte/hrb.php?rb_id=91808&land_abk=rp"
    },
    "parsed": {
        "officers": [
            {
                "class": "DismissedManagingDirector",
                "payload": {
                    "city": "RG10 9TL Hare Hatch",
                    "dismissed": true,
                    "dob": "1955-05-11",
                    "lastname": "Herlinger",
                    "name": "Charles"
                },
                "text": " Herlinger, Charles, RG10 9TL Hare Hatch, *05.11.1955."
            },
            {
                "class": "AppointedManagingDirector",
                "payload": {
                    "city": "Friedrichsdorf",
                    "dob": "1963-03-06",
                    "flag": "einzelvertretungsberechtigt mit der Befugnis im Namen der Gesellschaft mit sich im eigenen Namen oder als Vertreter eines Dritten Rechtsgeschäfte abzuschließen",
                    "lastname": "Stams",
                    "name": "Henning"
                },
                "text": " Stams, Henning, Friedrichsdorf, *03.06.1963, einzelvertretungsberechtigt mit der Befugnis im Namen der Gesellschaft mit sich im eigenen Namen oder als Vertreter eines Dritten Rechtsgeschäfte abzuschließen."
            }
        ]
    }
}