{
    "orig": {
        "aktenzeichen": "HRB 12390",
        "amtsgericht": "Siegburg",
        "event_date": "2013-12-23",
        "event_type": "Veränderungen",
        "federal_state": "nw",
        "full_text": "Amtsgericht Siegburg Aktenzeichen: HRB 12390 \nBekannt gemacht am: 23.12.2013 19:59 Uhr\n\n\n\n\nIn () gesetzte Angaben der Anschrift und des Geschäftszweiges erfolgen ohne Gewähr.\nVeränderungen\n23.12.2013\n\nHRB 12390:SFG Projekt Verwaltungs-GmbH, Sankt Augustin, Hirschbergweg 8, 53757 Sankt Augustin.Die Gesellschafterversammlung vom 03.12.2013 hat die Änderung des Gesellschaftsvertrages in § 1 Absatz 2 (Sitz) und mit ihr die Sitzverlegung von Sankt Augustin nach Hennef beschlossen. Neuer Sitz: Hennef. Änderung zur Geschäftsanschrift: Allnerhof 1, 53773 Hennef. Geschäftsführer: Dr. Krutisch, Dominic, Wallerfangen, *06.01.1973, einzelvertretungsberechtigt mit der Befugnis im Namen der Gesellschaft mit sich im eigenen Namen oder als Vertreter eines Dritten Rechtsgeschäfte abzuschließen. Nicht mehr Geschäftsführer: Seitz-Friedrich, Heike, Sankt Augustin, *31.07.1963.",
        "gesellschafter": null,
        "inhaber": null,
        "name": "HRB 12390:SFG Projekt Verwaltungs-GmbH",
        "notice_id": "986515",
        "posted_on": "2013-12-23",
        "rechtsform": null,
        "sitz": null,
        "url": "https://www.handelsregisterbekanntmachungen.de/en/skripte/hrb.php?rb_id=986515&land_abk=nw"
    },
    "parsed": {
        "addresses": [
            {
                "kls": "Address",
                "text": "Allnerhof 1, 53773 Hennef"
            }
        ],
        "notices": [
            {
                "court": null,
                "from": "Sankt Augustin",
                "registration": null,
                "text": " von Sankt Augustin nach Hennef beschlossen.",
                "to": "Hennef",
                "used_regex": "from, to_regex"
            }
        ],
        "officers": [
            {
                "class": "ManagingDirector",
                "payload": {
                    "city": "Wallerfangen",
                    "dob": "1973-01-06",
                    "flag": "einzelvertretungsberechtigt mit der Befugnis im Namen der Gesellschaft mit sich im eigenen Namen oder als Vertreter eines Dritten Rechtsgeschäfte abzuschließen",
                    "lastname": "Krutisch",
                    "name": "Dominic",
                    "prof_title": "doctor"
                },
                "text": " Doctor Krutisch, Dominic, Wallerfangen, *06.01.1973, einzelvertretungsberechtigt mit der Befugnis im Namen der Gesellschaft mit sich im eigenen Namen oder als Vertreter eines Dritten Rechtsgeschäfte abzuschließen."
            },
            {
                "class": "DismissedManagingDirector",
                "payload": {
                    "city": "Sankt Augustin",
                    "dismissed": true,
                    "dob": "1963-07-31",
                    "lastname": "Seitz-Friedrich",
                    "name": "Heike"
                },
                "text": " Seitz-Friedrich, Heike, Sankt Augustin, *31.07.1963."
            }
        ]
    }
}