{
    "orig": {
        "aktenzeichen": "HRB 7127",
        "amtsgericht": "Gütersloh",
        "event_date": "2013-12-23",
        "event_type": "Veränderungen",
        "federal_state": "nw",
        "full_text": "Amtsgericht Gütersloh Aktenzeichen: HRB 7127 \nBekannt gemacht am: 23.12.2013 20:01 Uhr\n\n\n\n\nIn () gesetzte Angaben der Anschrift und des Geschäftszweiges erfolgen ohne Gewähr.\nVeränderungen\n23.12.2013\n\nHRB 7127:Alternative Capital Invest Vertriebs- & Service GmbH, Gütersloh, Berliner Str. 7, 33330 Gütersloh.Änderung zur Geschäftsanschrift: Siegfriedstr. 9, 33332 Gütersloh. Bestellt als Liquidator: Lohmann, Wilma, Gütersloh, *26.05.1947, mit der Befugnis im Namen der Gesellschaft mit sich im eigenen Namen oder als Vertreter eines Dritten Rechtsgeschäfte abzuschließen. Nicht mehr Liquidator: Lohmann, Hanns-Uwe, Gütersloh, *14.12.1944.",
        "gesellschafter": null,
        "inhaber": null,
        "name": "HRB 7127:Alternative Capital Invest Vertriebs- & Service GmbH",
        "notice_id": "986926",
        "posted_on": "2013-12-23",
        "rechtsform": null,
        "sitz": null,
        "url": "https://www.handelsregisterbekanntmachungen.de/en/skripte/hrb.php?rb_id=986926&land_abk=nw"
    },
    "parsed": {
        "labels": [
            {
                "label": "address",
                "text": " Siegfriedstr."
            }
        ],
        "officers": [
            {
                "class": "Liquidator",
                "payload": {
                    "city": "Gütersloh",
                    "dob": "1947-05-26",
                    "flag": "mit der Befugnis im Namen der Gesellschaft mit sich im eigenen Namen oder als Vertreter eines Dritten Rechtsgeschäfte abzuschließen",
                    "lastname": "Lohmann",
                    "name": "Wilma"
                },
                "text": " Lohmann, Wilma, Gütersloh, *26.05.1947, mit der Befugnis im Namen der Gesellschaft mit sich im eigenen Namen oder als Vertreter eines Dritten Rechtsgeschäfte abzuschließen."
            },
            {
                "class": "NotALiquidator",
                "payload": {
                    "city": "Gütersloh",
                    "dismissed": true,
                    "dob": "1944-12-14",
                    "lastname": ": Lohmann",
                    "name": "Hanns-Uwe"
                },
                "text": ": Lohmann, Hanns-Uwe, Gütersloh, *14.12.1944."
            }
        ]
    }
}