{
    "orig": {
        "aktenzeichen": "HRA 26313",
        "amtsgericht": "Köln",
        "event_date": "2013-12-27",
        "event_type": "Veränderungen",
        "federal_state": "nw",
        "full_text": "Amtsgericht Köln Aktenzeichen: HRA 26313 \nBekannt gemacht am: 27.12.2013 20:00 Uhr\n\n\n\n\nIn () gesetzte Angaben der Anschrift und des Geschäftszweiges erfolgen ohne Gewähr.\nVeränderungen\n27.12.2013\n\nHRA 26313:Metzgerei Matthias Schmidt e.K., Köln, Merowingerstraße 32, 50677 Köln.Nunmehr: Offene Handelsgesellschaft. Nach Änderung der Firma nunmehr METZGEREI MATTHIAS SCHMIDT OHG. Jeder persönlich haftende Gesellschafter vertritt einzeln. Bestellt als Persönlich haftender Gesellschafter: Schmidt, Pascal, Köln, *28.03.1982, mit der Befugnis im Namen der Gesellschaft mit sich im eigenen Namen oder als Vertreter eines Dritten Rechtsgeschäfte abzuschließen. Nicht mehr Inhaber nunmehr Persönlich haftender Gesellschafter: Schmidt, Jakob, Köln, *25.09.1953, mit der Befugnis im Namen der Gesellschaft mit sich im eigenen Namen oder als Vertreter eines Dritten Rechtsgeschäfte abzuschließen.",
        "gesellschafter": null,
        "inhaber": null,
        "name": "HRA 26313:Metzgerei Matthias Schmidt e.K.",
        "notice_id": "987376",
        "posted_on": "2013-12-27",
        "rechtsform": null,
        "sitz": null,
        "url": "https://www.handelsregisterbekanntmachungen.de/en/skripte/hrb.php?rb_id=987376&land_abk=nw"
    },
    "parsed": {
        "officers": [
            {
                "class": "PersonalPartner",
                "payload": {
                    "city": "Köln",
                    "dob": "1982-03-28",
                    "flag": "mit der Befugnis im Namen der Gesellschaft mit sich im eigenen Namen oder als Vertreter eines Dritten Rechtsgeschäfte abzuschließen",
                    "lastname": "Schmidt",
                    "name": "Pascal"
                },
                "text": " Schmidt, Pascal, Köln, *28.03.1982, mit der Befugnis im Namen der Gesellschaft mit sich im eigenen Namen oder als Vertreter eines Dritten Rechtsgeschäfte abzuschließen."
            },
            {
                "class": "PersonalPartner",
                "payload": {
                    "city": "Köln",
                    "dob": "1953-09-25",
                    "flag": "mit der Befugnis im Namen der Gesellschaft mit sich im eigenen Namen oder als Vertreter eines Dritten Rechtsgeschäfte abzuschließen",
                    "lastname": "Schmidt",
                    "name": "Jakob"
                },
                "text": " Schmidt, Jakob, Köln, *25.09.1953, mit der Befugnis im Namen der Gesellschaft mit sich im eigenen Namen oder als Vertreter eines Dritten Rechtsgeschäfte abzuschließen."
            }
        ]
    }
}