{
    "orig": {
        "aktenzeichen": "HRB 1757",
        "amtsgericht": "Duisburg",
        "event_date": "2014-01-03",
        "event_type": "Veränderungen",
        "federal_state": "nw",
        "full_text": "Amtsgericht Duisburg Aktenzeichen: HRB 1757 \nBekannt gemacht am: 03.01.2014 20:00 Uhr\n\n\n\n\nIn () gesetzte Angaben der Anschrift und des Geschäftszweiges erfolgen ohne Gewähr.\nVeränderungen\n03.01.2014\n\nHRB 1757:Autohaus Nagel GmbH, Duisburg, Kulturstr. 49, 47055 Duisburg.Ist nur ein Liquidator berufen, so vertritt dieser die Gesellschaft allein. Sind mehrere Liquidatoren bestellt, so wird die Gesellschaft durch zwei Liquidatoren gemeinsam vertreten. Geändert, nunmehr Liquidator: Mühleib, Elke, Duisburg, *10.11.1963, mit der Befugnis im Namen der Gesellschaft mit sich im eigenen Namen oder als Vertreter eines Dritten Rechtsgeschäfte abzuschließen. Die Gesellschaft ist aufgelöst.",
        "gesellschafter": null,
        "inhaber": null,
        "name": "HRB 1757:Autohaus Nagel GmbH",
        "notice_id": "989114",
        "posted_on": "2014-01-03",
        "rechtsform": null,
        "sitz": null,
        "url": "https://www.handelsregisterbekanntmachungen.de/en/skripte/hrb.php?rb_id=989114&land_abk=nw"
    },
    "parsed": {
        "flags": [
            {
                "flag": "ignore_for_now",
                "text": "Die\\ Gesellschaft\\ ist\\ aufgel\\öst\\."
            }
        ],
        "officers": [
            {
                "class": "Liquidator",
                "payload": {
                    "city": "Duisburg",
                    "dob": "1963-10-11",
                    "flag": "mit der Befugnis im Namen der Gesellschaft mit sich im eigenen Namen oder als Vertreter eines Dritten Rechtsgeschäfte abzuschließen",
                    "lastname": "Mühleib",
                    "name": "Elke"
                },
                "text": " Mühleib, Elke, Duisburg, *10.11.1963, mit der Befugnis im Namen der Gesellschaft mit sich im eigenen Namen oder als Vertreter eines Dritten Rechtsgeschäfte abzuschließen."
            }
        ]
    }
}