{
    "orig": {
        "aktenzeichen": "HRB 11139",
        "amtsgericht": "Gelsenkirchen",
        "event_date": "2014-01-08",
        "event_type": "Veränderungen",
        "federal_state": "nw",
        "full_text": "Amtsgericht Gelsenkirchen Aktenzeichen: HRB 11139 \nBekannt gemacht am: 08.01.2014 20:00 Uhr\n\n\n\n\nIn () gesetzte Angaben der Anschrift und des Geschäftszweiges erfolgen ohne Gewähr.\nVeränderungen\n08.01.2014\n\nHRB 11139:CMI Cash Management Innovation GmbH, Bottrop, Industriestraße 40a, 46240 Bottrop.Die Gesellschafterversammlung vom 31.10.2013 hat eine Änderung des Gesellschaftsvertrages in § 1 und mit ihr die Änderung der Firma beschlossen. Die Gesellschafterversammlung vom 31.10.2013 hat eine Änderung des Gesellschaftsvertrages in § 4 (Stammkapital, Stammeinlagen) beschlossen. Neue Firma: Bally Wulff Cash Management GmbH. Nicht mehr Geschäftsführer: Böttcher, Birgit, Bottrop, *16.07.1967; Potokar, Manfred, Bottrop, *02.12.1957. Bestellt als Geschäftsführer: Blodau, Sascha, Berlin, *30.04.1969; Günther, Andreas, Schüttorf, *29.06.1969, jeweils einzelvertretungsberechtigt mit der Befugnis im Namen der Gesellschaft mit sich im eigenen Namen oder als Vertreter eines Dritten Rechtsgeschäfte abzuschließen.",
        "gesellschafter": null,
        "inhaber": null,
        "name": "HRB 11139:CMI Cash Management Innovation GmbH",
        "notice_id": "990832",
        "posted_on": "2014-01-08",
        "rechtsform": null,
        "sitz": null,
        "url": "https://www.handelsregisterbekanntmachungen.de/en/skripte/hrb.php?rb_id=990832&land_abk=nw"
    },
    "parsed": {
        "officers": [
            {
                "class": "DismissedManagingDirector",
                "payload": {
                    "city": "Bottrop",
                    "dismissed": true,
                    "dob": "1967-07-16",
                    "lastname": "Böttcher",
                    "name": "Birgit"
                },
                "text": " Böttcher, Birgit, Bottrop, *16.07.1967"
            },
            {
                "class": "DismissedManagingDirector",
                "payload": {
                    "city": "Bottrop",
                    "dismissed": true,
                    "dob": "1957-12-02",
                    "lastname": "Potokar",
                    "name": "Manfred"
                },
                "text": " Potokar, Manfred, Bottrop, *02.12.1957."
            },
            {
                "class": "AppointedManagingDirector",
                "payload": {
                    "city": "Berlin",
                    "dob": "1969-04-30",
                    "lastname": "Blodau",
                    "name": "Sascha"
                },
                "text": " Blodau, Sascha, Berlin, *30.04.1969"
            },
            {
                "class": "AppointedManagingDirector",
                "payload": {
                    "city": "Schüttorf",
                    "dob": "1969-06-29",
                    "flag": "jeweils einzelvertretungsberechtigt mit der Befugnis im Namen der Gesellschaft mit sich im eigenen Namen oder als Vertreter eines Dritten Rechtsgeschäfte abzuschließen",
                    "lastname": "Günther",
                    "name": "Andreas"
                },
                "text": " Günther, Andreas, Schüttorf, *29.06.1969, jeweils einzelvertretungsberechtigt mit der Befugnis im Namen der Gesellschaft mit sich im eigenen Namen oder als Vertreter eines Dritten Rechtsgeschäfte abzuschließen."
            }
        ]
    }
}