{
    "orig": {
        "aktenzeichen": "HRA 503909",
        "amtsgericht": "Jena",
        "event_date": "2016-09-27",
        "event_type": "Löschungen",
        "federal_state": "th",
        "full_text": "Amtsgericht Jena Aktenzeichen: HRA 503909 \nBekannt gemacht am: 27.09.2016 12:30 Uhr\n\n\n\n\nDie in () gesetzten Angaben der Geschäftsanschrift und des Unternehmensgegenstandes erfolgen ohne Gewähr.\nLöschungen\n27.09.2016\n\nHRA 503909: Jens Schüller e.K., Erfurt, Blumenstraße 70, 99092 Erfurt. Das von dem Einzelkaufmann Schüller, Jens, Riethnordhausen, *22.05.1966 unter der Firma Jens Schüller e.K. mit dem Sitz in Erfurt betriebene Unternehmen hat Teile des Vermögens gemäß Ausgliederungserklärung vom 10.08.2016 auf die neu gegründete Jens Schüller GmbH Heizung Sanitär mit dem Sitz in Erfurt (Amtsgericht Jena HRB 512709) ausgegliedert. Die Firma ist erloschen. Nicht eingetragen: Den Gläubigern der an der Ausgliederung beteiligten Rechtsträger, ist wenn sie binnen sechs Monaten nach dem Tag, an dem die Eintragung der Ausgliederung in das Register des Sitzes desjenigen Rechtsträgers, dessen Gläubiger sie sind, nach §§125, 19 Abs. 3 UmwG als bekanntgemacht gilt, ihren Anspruch nach Grund und Höhe schriftlich anmelden, Sicherheit zu leisten, soweit sie nicht Befriedigung verlangen können. Dieses Recht steht ihnen jedoch nur zu, wenn sie glaubhaft machen, daß durch die Ausgliederung die Erfüllung ihrer Forderung gefährdet wird.",
        "gesellschafter": null,
        "inhaber": null,
        "name": "HRA 503909: Jens Schüller e.K.",
        "notice_id": "99348",
        "posted_on": "2016-09-27",
        "rechtsform": "Einzelkaufmann",
        "sitz": null,
        "url": "https://www.handelsregisterbekanntmachungen.de/en/skripte/hrb.php?rb_id=99348&land_abk=th"
    },
    "parsed": {
        "flags": [
            {
                "flag": "Sole trader",
                "text": "Einzelkaufmann"
            }
        ],
        "officers": [
            {
                "class": "Person",
                "payload": {
                    "city": "Riethnordhausen",
                    "dob": "1966-05-22",
                    "lastname": "Schüller",
                    "name": "Jens"
                },
                "text": " Schüller, Jens, Riethnordhausen, *22.05.1966 unter der Firma Jens Schüller e.K."
            }
        ]
    }
}